Workbook

Sheet TB-Jan
A1: Republic of the Philippines
A2: PROVINCE OF AGUSAN DEL SUR
A3: Gov. Democrito O. Plaza Government Center, Prosperidad
A5: TRUST FUND
A6: TRIAL BALANCE
A7: As of January 31, 2011
E9: =A7 -> As of January 31, 2011 | G9: Check Disbursement | I9: Cash Disbursement | K9: Cash Receipts | M9: General Journal
A11: Account Title | B11: Account Code | C11: Debit | D11: Credit | E11: Debit | F11: Credit | G11: Debit | H11: Credit | I11: Debit | J11: Credit | K11: Debit | L11: Credit | M11: Debit | N11: Credit
A13: Cash in Vault | B13: 101 | C13: =E13-F13 -> 0 | E13: =SUM(G13,I13,K13,M13) -> 0 | F13: =SUM(H13,J13,L13,N13) -> 0
A14: Cash - Collecting Officers | B14: 102 | C14: =E14-F14 -> 0 | E14: =SUM(G14,I14,K14,M14) -> 0 | F14: =SUM(H14,J14,L14,N14) -> 0
A15: Cash Disbursing Officers | B15: 103 | C15: =E15-F15 -> 0 | E15: =SUM(G15,I15,K15,M15) -> 0 | F15: =SUM(H15,J15,L15,N15) -> 0
A16: Petty Cash Fund | B16: 104 | C16: =E16-F16 -> 0 | E16: =SUM(G16,I16,K16,M16) -> 0 | F16: =SUM(H16,J16,L16,N16) -> 0
A17: Payroll Fund | B17: 106 | C17: =E17-F17 -> 0 | E17: =SUM(G17,I17,K17,M17) -> 0 | F17: =SUM(H17,J17,L17,N17) -> 0
A18: Cash - Bangko Sentral ng Pilipinas | B18: 110 | C18: =E18-F18 -> 0 | E18: =SUM(G18,I18,K18,M18) -> 0 | F18: =SUM(H18,J18,L18,N18) -> 0
A19: Cash in Bank - Local Currency, Current Account | B19: 111 | C19: =E19-F19 -> 0 | E19: =SUM(G19,I19,K19,M19) -> 0 | F19: =SUM(H19,J19,L19,N19) -> 0
A20: Cash in Bank - Local Currency, SavingsAccount | B20: 112 | C20: =E20-F20 -> 0 | E20: =SUM(G20,I20,K20,M20) -> 0 | F20: =SUM(H20,J20,L20,N20) -> 0
A21: Cash in Bank - Local Currency, Time Deposits | B21: 113 | C21: =E21-F21 -> 0 | E21: =SUM(G21,I21,K21,M21) -> 0 | F21: =SUM(H21,J21,L21,N21) -> 0
A22: Cash - Bangko Sentral ng Pilipinas | B22: 114 | C22: =E22-F22 -> 0 | E22: =SUM(G22,I22,K22,M22) -> 0 | F22: =SUM(H22,J22,L22,N22) -> 0
A23: Cash in Bank - Foreign Currency, Current Account | B23: 115 | C23: =E23-F23 -> 0 | E23: =SUM(G23,I23,K23,M23) -> 0 | F23: =SUM(H23,J23,L23,N23) -> 0
A24: Cash in Bank - Foreign Currency, Savings Account | B24: 116 | C24: =E24-F24 -> 0 | E24: =SUM(G24,I24,K24,M24) -> 0 | F24: =SUM(H24,J24,L24,N24) -> 0
A25: Cash in Bank - Foreign Currency, Time Deposits | B25: 117 | C25: =E25-F25 -> 0 | E25: =SUM(G25,I25,K25,M25) -> 0 | F25: =SUM(H25,J25,L25,N25) -> 0
A26: Accounts Receivable | B26: 121 | C26: =E26-F26 -> 0 | E26: =SUM(G26,I26,K26,M26) -> 0 | F26: =SUM(H26,J26,L26,N26) -> 0
A27: Allowance for Doubtful Accounts | B27: 301 | C27: =E27-F27 -> 0 | E27: =SUM(G27,I27,K27,M27) -> 0 | F27: =SUM(H27,J27,L27,N27) -> 0
A28: Notes Receivable | B28: 122 | C28: =E28-F28 -> 0 | E28: =SUM(G28,I28,K28,M28) -> 0 | F28: =SUM(H28,J28,L28,N28) -> 0
A29: Due from Officers and Employees | B29: 123 | C29: =E29-F29 -> 0 | E29: =SUM(G29,I29,K29,M29) -> 0 | F29: =SUM(H29,J29,L29,N29) -> 0
A30: Loans Receivable - GOCCs | B30: 124 | C30: =E30-F30 -> 0 | E30: =SUM(G30,I30,K30,M30) -> 0 | F30: =SUM(H30,J30,L30,N30) -> 0
A31: Loans Receivable - LGUs | B31: 125 | C31: =E31-F31 -> 0 | E31: =SUM(G31,I31,K31,M31) -> 0 | F31: =SUM(H31,J31,L31,N31) -> 0
A32: Loans Receivable - Others | B32: 126 | C32: =E32-F32 -> 0 | E32: =SUM(G32,I32,K32,M32) -> 0 | F32: =SUM(H32,J32,L32,N32) -> 0
A33: Real Property Tax Receivable | B33: 127 | C33: =E33-F33 -> 0 | E33: =SUM(G33,I33,K33,M33) -> 0 | F33: =SUM(H33,J33,L33,N33) -> 0
A34: Special Education Tax Receivable | B34: 128 | C34: =E34-F34 -> 0 | E34: =SUM(G34,I34,K34,M34) -> 0 | F34: =SUM(H34,J34,L34,N34) -> 0
A35: Interests Receivable | B35: 129 | C35: =E35-F35 -> 0 | E35: =SUM(G35,I35,K35,M35) -> 0 | F35: =SUM(H35,J35,L35,N35) -> 0
... A37: Due from GOCCs | B37: 137 | C37: =E37-F37 -> 0 | E37: =SUM(G37,I37,K37,M37) -> 0 | F37: =SUM(H37,J37,L37,N37) -> 0
A38: Due from LGUs | B38: 138 | C38: =E38-F38 -> 0 | E38: =SUM(G38,I38,K38,M38) -> 0 | F38: =SUM(H38,J38,L38,N38) -> 0
A39: Due from NGOs/POs | B39: 139 | C39: =E39-F39 -> 0 | E39: =SUM(G39,I39,K39,M39) -> 0 | F39: =SUM(H39,J39,L39,N39) -> 0
A40: Due from Other Funds | B40: 144 | C40: =E40-F40 -> 0 | E40: =SUM(G40,I40,K40,M40) -> 0 | F40: =SUM(H40,J40,L40,N40) -> 0
A41: Receivables - Disallowances/Charges | B41: 146 | C41: =E41-F41 -> 0 | E41: =SUM(G41,I41,K41,M41) -> 0 | F41: =SUM(H41,J41,L41,N41) -> 0
A42: Advances to Officers and Employees | B42: 148 | C42: =E42-F42 -> 0 | E42: =SUM(G42,I42,K42,M42) -> 0 | F42: =SUM(H42,J42,L42,N42) -> 0
A43: Other Receivables | B43: 149 | C43: =E43-F43 -> 0 | E43: =SUM(G43,I43,K43,M43) -> 0 | F43: =SUM(H43,J43,L43,N43) -> 0
A44: Raw Materials Inventory | B44: 151 | C44: =E44-F44 -> 0 | E44: =SUM(G44,I44,K44,M44) -> 0 | F44: =SUM(H44,J44,L44,N44) -> 0
A45: Work-In-Process Inventory | B45: 152 | C45: =E45-F45 -> 0 | E45: =SUM(G45,I45,K45,M45) -> 0 | F45: =SUM(H45,J45,L45,N45) -> 0
A46: Finished Goods Inventory | B46: 153 | C46: =E46-F46 -> 0 | E46: =SUM(G46,I46,K46,M46) -> 0 | F46: =SUM(H46,J46,L46,N46) -> 0
A47: Merchandise Inventory | B47: 154 | C47: =E47-F47 -> 0 | E47: =SUM(G47,I47,K47,M47) -> 0 | F47: =SUM(H47,J47,L47,N47) -> 0
A48: Office Supplies Inventory | B48: 155 | C48: =E48-F48 -> 0 | E48: =SUM(G48,I48,K48,M48) -> 0 | F48: =SUM(H48,J48,L48,N48) -> 0
A49: Accountable Forms Inventory | B49: 156 | C49: =E49-F49 -> 0 | E49: =SUM(G49,I49,K49,M49) -> 0 | F49: =SUM(H49,J49,L49,N49) -> 0
A50: Animal/Zoological Supplies Inventory | B50: 157 | C50: =E50-F50 -> 0 | E50: =SUM(G50,I50,K50,M50) -> 0 | F50: =SUM(H50,J50,L50,N50) -> 0
A51: Food Supplies Inventory | B51: 158 | C51: =E51-F51 -> 0 | E51: =SUM(G51,I51,K51,M51) -> 0 | F51: =SUM(H51,J51,L51,N51) -> 0
A52: Drugs and Medicines Inventory | B52: 159 | C52: =E52-F52 -> 0 | E52: =SUM(G52,I52,K52,M52) -> 0 | F52: =SUM(H52,J52,L52,N52) -> 0
... A57: Military and Police Supplies Inventory | B57: 164 | C57: =E57-F57 -> 0 | E57: =SUM(G57,I57,K57,M57) -> 0 | F57: =SUM(H57,J57,L57,N57) -> 0
A58: Other Supplies Inventory | B58: 165 | C58: =E58-F58 -> 0 | E58: =SUM(G58,I58,K58,M58) -> 0 | F58: =SUM(H58,J58,L58,N58) -> 0
A59: Confiscated/Abandoned/Seized Goods Inventory | B59: 166 | C59: =E59-F59 -> 0 | E59: =SUM(G59,I59,K59,M59) -> 0 | F59: =SUM(H59,J59,L59,N59) -> 0
A60: Spare Parts Inventory | B60: 167 | C60: =E60-F60 -> 0 | E60: =SUM(G60,I60,K60,M60) -> 0 | F60: =SUM(H60,J60,L60,N60) -> 0
A61: Construction Materials Inventory | B61: 168 | C61: =E61-F61 -> 0 | E61: =SUM(G61,I61,K61,M61) -> 0 | F61: =SUM(H61,J61,L61,N61) -> 0
A62: Livestock Inventory | B62: 169 | C62: =E62-F62 -> 0 | E62: =SUM(G62,I62,K62,M62) -> 0 | F62: =SUM(H62,J62,L62,N62) -> 0
A63: Crops and Fruits Inventory | B63: 170 | C63: =E63-F63 -> 0 | E63: =SUM(G63,I63,K63,M63) -> 0 | F63: =SUM(H63,J63,L63,N63) -> 0
A64: Other Agricultural, Fishery and Forestry Products Inventory | B64: 176 | C64: =E64-F64 -> 0 | E64: =SUM(G64,I64,K64,M64) -> 0 | F64: =SUM(H64,J64,L64,N64) -> 0
A65: Prepaid Rent | B65: 177 | C65: =E65-F65 -> 0 | E65: =SUM(G65,I65,K65,M65) -> 0 | F65: =SUM(H65,J65,L65,N65) -> 0
A66: Prepaid Insurance | B66: 178 | C66: =E66-F66 -> 0 | E66: =SUM(G66,I66,K66,M66) -> 0 | F66: =SUM(H66,J66,L66,N66) -> 0
A67: Prepaid Interest | B67: 179 | C67: =E67-F67 -> 0 | E67: =SUM(G67,I67,K67,M67) -> 0 | F67: =SUM(H67,J67,L67,N67) -> 0
A68: Deposit on Letters of Credit | B68: 180 | C68: =E68-F68 -> 0 | E68: =SUM(G68,I68,K68,M68) -> 0 | F68: =SUM(H68,J68,L68,N68) -> 0
A69: Advances to Contractors | B69: 181 | C69: =E69-F69 -> 0 | E69: =SUM(G69,I69,K69,M69) -> 0 | F69: =SUM(H69,J69,L69,N69) -> 0
A70: Deferred Charges | B70: 182 | C70: =E70-F70 -> 0 | E70: =SUM(G70,I70,K70,M70) -> 0 | F70: =SUM(H70,J70,L70,N70) -> 0
A71: Other Prepaid Expenses | B71: 185 | C71: =E71-F71 -> 0 | E71: =SUM(G71,I71,K71,M71) -> 0 | F71: =SUM(H71,J71,L71,N71) -> 0
A72: Guaranty Deposits | B72: 186 | C72: =E72-F72 -> 0 | E72: =SUM(G72,I72,K72,M72) -> 0 | F72: =SUM(H72,J72,L72,N72) -> 0
A73: Other Current Assets | B73: 189 | C73: =E73-F73 -> 0 | E73: =SUM(G73,I73,K73,M73) -> 0 | F73: =SUM(H73,J73,L73,N73) -> 0
A74: Investments in Treasury Bills | B74: 191 | C74: =E74-F74 -> 0 | E74: =SUM(G74,I74,K74,M74) -> 0 | F74: =SUM(H74,J74,L74,N74) -> 0
A75: Investments in Stocks | B75: 192 | C75: =E75-F75 -> 0 | E75: =SUM(G75,I75,K75,M75) -> 0 | F75: =SUM(H75,J75,L75,N75) -> 0
A76: Investments in Bonds | B76: 193 | C76: =E76-F76 -> 0 | E76: =SUM(G76,I76,K76,M76) -> 0 | F76: =SUM(H76,J76,L76,N76) -> 0
A77: Other Investments and Marketable Securities | B77: 197 | C77: =E77-F77 -> 0 | E77: =SUM(G77,I77,K77,M77) -> 0 | F77: =SUM(H77,J77,L77,N77) -> 0
A78: Sinking Fund | B78: 198 | C78: =E78-F78 -> 0 | E78: =SUM(G78,I78,K78,M78) -> 0 | F78: =SUM(H78,J78,L78,N78) -> 0
A79: Land | B79: 201 | C79: =E79-F79 -> 0 | E79: =SUM(G79,I79,K79,M79) -> 0 | F79: =SUM(H79,J79,L79,N79) -> 0
A80: Land Improvements | B80: 202 | C80: =E80-F80 -> 0 | E80: =SUM(G80,I80,K80,M80) -> 0 | F80: =SUM(H80,J80,L80,N80) -> 0
A81: Accumulated Depreciation – Land Improvements | B81: 302 | D81: =F81-E81 -> 0 | E81: =SUM(G81,I81,K81,M81) -> 0 | F81: =SUM(H81,J81,L81,N81) -> 0
A82: Runways/Taxiways | B82: 203 | C82: =E82-F82 -> 0 | E82: =SUM(G82,I82,K82,M82) -> 0 | F82: =SUM(H82,J82,L82,N82) -> 0
A83: Accumulated Depreciation - Runways/Taxiways | B83: 303 | D83: =F83-E83 -> 0 | E83: =SUM(G83,I83,K83,M83) -> 0 | F83: =SUM(H83,J83,L83,N83) -> 0
A84: Railways | B84: 204 | C84: =E84-F84 -> 0 | E84: =SUM(G84,I84,K84,M84) -> 0 | F84: =SUM(H84,J84,L84,N84) -> 0
A85: Accumulated Depreciation - Railways | B85: 304 | D85: =F85-E85 -> 0 | E85: =SUM(G85,I85,K85,M85) -> 0 | F85: =SUM(H85,J85,L85,N85) -> 0
A86: Electrification, Power and Energy Structures | B86: 205 | C86: =E86-F86 -> 0 | E86: =SUM(G86,I86,K86,M86) -> 0 | F86: =SUM(H86,J86,L86,N86) -> 0
A87: Accumulated Depreciation - Electrification, Power and Energy | B87: 305 | D87: =F87-E87 -> 0 | E87: =SUM(G87,I87,K87,M87) -> 0 | F87: =SUM(H87,J87,L87,N87) -> 0
A88: Office Buildings | B88: 211 | C88: =E88-F88 -> 0 | E88: =SUM(G88,I88,K88,M88) -> 0 | F88: =SUM(H88,J88,L88,N88) -> 0
A89: Accumulated Depreciation - Office Buildings | B89: 311 | D89: =F89-E89 -> 0 | E89: =SUM(G89,I89,K89,M89) -> 0 | F89: =SUM(H89,J89,L89,N89) -> 0
A90: School Buildings | B90: 212 | C90: =E90-F90 -> 0 | E90: =SUM(G90,I90,K90,M90) -> 0 | F90: =SUM(H90,J90,L90,N90) -> 0
A91: Accumulated Depreciation - School Buildings | B91: 312 | D91: =F91-E91 -> 0 | E91: =SUM(G91,I91,K91,M91) -> 0 | F91: =SUM(H91,J91,L91,N91) -> 0
A92: Hospitals and Health Centers | B92: 213 | C92: =E92-F92 -> 0 | E92: =SUM(G92,I92,K92,M92) -> 0 | F92: =SUM(H92,J92,L92,N92) -> 0
A93: Accumulated Depreciation - Hospitals and Health Centers | B93: 313 | D93: =F93-E93 -> 0 | E93: =SUM(G93,I93,K93,M93) -> 0 | F93: =SUM(H93,J93,L93,N93) -> 0
A94: Markets and Slaughterhouses | B94: 214 | C94: =E94-F94 -> 0 | E94: =SUM(G94,I94,K94,M94) -> 0 | F94: =SUM(H94,J94,L94,N94) -> 0
A95: Accumulated Depreciation - Markets and Slaughterhouses | B95: 314 | D95: =F95-E95 -> 0 | E95: =SUM(G95,I95,K95,M95) -> 0 | F95: =SUM(H95,J95,L95,N95) -> 0
A96: Other Structures | B96: 215 | C96: =E96-F96 -> 0 | E96: =SUM(G96,I96,K96,M96) -> 0 | F96: =SUM(H96,J96,L96,N96) -> 0
A97: Accumulated Depreciation - Other Structures | B97: 315 | D97: =F97-E97 -> 0 | E97: =SUM(G97,I97,K97,M97) -> 0 | F97: =SUM(H97,J97,L97,N97) -> 0
A98: Leasehold Improvements, Land | B98: 218 | C98: =E98-F98 -> 0 | E98: =SUM(G98,I98,K98,M98) -> 0 | F98: =SUM(H98,J98,L98,N98) -> 0
A99: Accumulated Depreciation - Leasehold Improvements, Land | B99: 318 | D99: =F99-E99 -> 0 | E99: =SUM(G99,I99,K99,M99) -> 0 | F99: =SUM(H99,J99,L99,N99) -> 0
A100: Leasehold Improvements, Buildings | B100: 219 | C100: =E100-F100 -> 0 | E100: =SUM(G100,I100,K100,M100) -> 0 | F100: =SUM(H100,J100,L100,N100) -> 0
A101: Accumulated Depreciation - Leasehold Improvements, Buildings | B101: 319 | D101: =F101-E101 -> 0 | E101: =SUM(G101,I101,K101,M101) -> 0 | F101: =SUM(H101,J101,L101,N101) -> 0
A102: Other Leasehold Improvements | B102: 220 | C102: =E102-F102 -> 0 | E102: =SUM(G102,I102,K102,M102) -> 0 | F102: =SUM(H102,J102,L102,N102) -> 0
A103: Accumulated Depreciation - Other Leasehold Improvements | B103: 320 | D103: =F103-E103 -> 0 | E103: =SUM(G103,I103,K103,M103) -> 0 | F103: =SUM(H103,J103,L103,N103) -> 0
A104: Office Equipment | B104: 221 | C104: =E104-F104 -> 0 | E104: =SUM(G104,I104,K104,M104) -> 0 | F104: =SUM(H104,J104,L104,N104) -> 0
A105: Accumulated Depreciation - Office Equipment | B105: 321 | D105: =F105-E105 -> 0 | E105: =SUM(G105,I105,K105,M105) -> 0 | F105: =SUM(H105,J105,L105,N105) -> 0
A106: Furniture and Fixtures | B106: 222 | C106: =E106-F106 -> 0 | E106: =SUM(G106,I106,K106,M106) -> 0 | F106: =SUM(H106,J106,L106,N106) -> 0
A107: Accumulated Depreciation - Furniture and Fixtures | B107: 322 | D107: =F107-E107 -> 0 | E107: =SUM(G107,I107,K107,M107) -> 0 | F107: =SUM(H107,J107,L107,N107) -> 0
A108: IT Equipment and Software | B108: 223 | C108: =E108-F108 -> 0 | E108: =SUM(G108,I108,K108,M108) -> 0 | F108: =SUM(H108,J108,L108,N108) -> 0
A109: Accumulated Depreciation - IT Equipment | B109: 323 | D109: =F109-E109 -> 0 | E109: =SUM(G109,I109,K109,M109) -> 0 | F109: =SUM(H109,J109,L109,N109) -> 0
...

Sheet TB-Feb
A1: Republic of the Philippines
A2: PROVINCE OF AGUSAN DEL SUR
A3: Gov. Democrito O. Plaza Government Center, Prosperidad
A5: TRUST FUND
A6: TRIAL BALANCE
A7: As of February 28, 2011
E9: =A7 -> As of February 28, 2011 | G9: Check Disbursement | I9: Cash Disbursement | K9: Cash Receipts | M9: General Journal
A11: Account Title | B11: Account Code | C11: Debit | D11: Credit | E11: Debit | F11: Credit | G11: Debit | H11: Credit | I11: Debit | J11: Credit | K11: Debit | L11: Credit | M11: Debit | N11: Credit
A13: Cash in Vault | B13: 101 | C13: =E13-F13 -> 0 | E13: =SUM(G13,I13,K13,M13) -> 0 | F13: =SUM(H13,J13,L13,N13) -> 0
A14: Cash - Collecting Officers | B14: 102 | C14: =E14-F14 -> 0 | E14: =SUM(G14,I14,K14,M14) -> 0 | F14: =SUM(H14,J14,L14,N14) -> 0
A15: Cash Disbursing Officers | B15: 103 | C15: =E15-F15 -> 0 | E15: =SUM(G15,I15,K15,M15) -> 0 | F15: =SUM(H15,J15,L15,N15) -> 0
A16: Petty Cash Fund | B16: 104 | C16: =E16-F16 -> 0 | E16: =SUM(G16,I16,K16,M16) -> 0 | F16: =SUM(H16,J16,L16,N16) -> 0
A17: Payroll Fund | B17: 106 | C17: =E17-F17 -> 0 | E17: =SUM(G17,I17,K17,M17) -> 0 | F17: =SUM(H17,J17,L17,N17) -> 0
A18: Cash - Bangko Sentral ng Pilipinas | B18: 110 | C18: =E18-F18 -> 0 | E18: =SUM(G18,I18,K18,M18) -> 0 | F18: =SUM(H18,J18,L18,N18) -> 0
A19: Cash in Bank - Local Currency, Current Account | B19: 111 | C19: =E19-F19 -> 0 | E19: =SUM(G19,I19,K19,M19) -> 0 | F19: =SUM(H19,J19,L19,N19) -> 0
A20: Cash in Bank - Local Currency, SavingsAccount | B20: 112 | C20: =E20-F20 -> 0 | E20: =SUM(G20,I20,K20,M20) -> 0 | F20: =SUM(H20,J20,L20,N20) -> 0
A21: Cash in Bank - Local Currency, Time Deposits | B21: 113 | C21: =E21-F21 -> 0 | E21: =SUM(G21,I21,K21,M21) -> 0 | F21: =SUM(H21,J21,L21,N21) -> 0
A22: Cash - Bangko Sentral ng Pilipinas | B22: 114 | C22: =E22-F22 -> 0 | E22: =SUM(G22,I22,K22,M22) -> 0 | F22: =SUM(H22,J22,L22,N22) -> 0
A23: Cash in Bank - Foreign Currency, Current Account | B23: 115 | C23: =E23-F23 -> 0 | E23: =SUM(G23,I23,K23,M23) -> 0 | F23: =SUM(H23,J23,L23,N23) -> 0
A24: Cash in Bank - Foreign Currency, Savings Account | B24: 116 | C24: =E24-F24 -> 0 | E24: =SUM(G24,I24,K24,M24) -> 0 | F24: =SUM(H24,J24,L24,N24) -> 0
A25: Cash in Bank - Foreign Currency, Time Deposits | B25: 117 | C25: =E25-F25 -> 0 | E25: =SUM(G25,I25,K25,M25) -> 0 | F25: =SUM(H25,J25,L25,N25) -> 0
A26: Accounts Receivable | B26: 121 | C26: =E26-F26 -> 0 | E26: =SUM(G26,I26,K26,M26) -> 0 | F26: =SUM(H26,J26,L26,N26) -> 0
A27: Allowance for Doubtful Accounts | B27: 301 | C27: =E27-F27 -> 0 | E27: =SUM(G27,I27,K27,M27) -> 0 | F27: =SUM(H27,J27,L27,N27) -> 0
A28: Notes Receivable | B28: 122 | C28: =E28-F28 -> 0 | E28: =SUM(G28,I28,K28,M28) -> 0 | F28: =SUM(H28,J28,L28,N28) -> 0
A29: Due from Officers and Employees | B29: 123 | C29: =E29-F29 -> 0 | E29: =SUM(G29,I29,K29,M29) -> 0 | F29: =SUM(H29,J29,L29,N29) -> 0
A30: Loans Receivable - GOCCs | B30: 124 | C30: =E30-F30 -> 0 | E30: =SUM(G30,I30,K30,M30) -> 0 | F30: =SUM(H30,J30,L30,N30) -> 0
A31: Loans Receivable - LGUs | B31: 125 | C31: =E31-F31 -> 0 | E31: =SUM(G31,I31,K31,M31) -> 0 | F31: =SUM(H31,J31,L31,N31) -> 0
A32: Loans Receivable - Others | B32: 126 | C32: =E32-F32 -> 0 | E32: =SUM(G32,I32,K32,M32) -> 0 | F32: =SUM(H32,J32,L32,N32) -> 0
A33: Real Property Tax Receivable | B33: 127 | C33: =E33-F33 -> 0 | E33: =SUM(G33,I33,K33,M33) -> 0 | F33: =SUM(H33,J33,L33,N33) -> 0
A34: Special Education Tax Receivable | B34: 128 | C34: =E34-F34 -> 0 | E34: =SUM(G34,I34,K34,M34) -> 0 | F34: =SUM(H34,J34,L34,N34) -> 0
A35: Interests Receivable | B35: 129 | C35: =E35-F35 -> 0 | E35: =SUM(G35,I35,K35,M35) -> 0 | F35: =SUM(H35,J35,L35,N35) -> 0
... A37: Due from GOCCs | B37: 137 | C37: =E37-F37 -> 0 | E37: =SUM(G37,I37,K37,M37) -> 0 | F37: =SUM(H37,J37,L37,N37) -> 0
A38: Due from LGUs | B38: 138 | C38: =E38-F38 -> 0 | E38: =SUM(G38,I38,K38,M38) -> 0 | F38: =SUM(H38,J38,L38,N38) -> 0
A39: Due from NGOs/POs | B39: 139 | C39: =E39-F39 -> 0 | E39: =SUM(G39,I39,K39,M39) -> 0 | F39: =SUM(H39,J39,L39,N39) -> 0
A40: Due from Other Funds | B40: 144 | C40: =E40-F40 -> 0 | E40: =SUM(G40,I40,K40,M40) -> 0 | F40: =SUM(H40,J40,L40,N40) -> 0
A41: Receivables - Disallowances/Charges | B41: 146 | C41: =E41-F41 -> 0 | E41: =SUM(G41,I41,K41,M41) -> 0 | F41: =SUM(H41,J41,L41,N41) -> 0
A42: Advances to Officers and Employees | B42: 148 | C42: =E42-F42 -> 0 | E42: =SUM(G42,I42,K42,M42) -> 0 | F42: =SUM(H42,J42,L42,N42) -> 0
A43: Other Receivables | B43: 149 | C43: =E43-F43 -> 0 | E43: =SUM(G43,I43,K43,M43) -> 0 | F43: =SUM(H43,J43,L43,N43) -> 0
A44: Raw Materials Inventory | B44: 151 | C44: =E44-F44 -> 0 | E44: =SUM(G44,I44,K44,M44) -> 0 | F44: =SUM(H44,J44,L44,N44) -> 0
A45: Work-In-Process Inventory | B45: 152 | C45: =E45-F45 -> 0 | E45: =SUM(G45,I45,K45,M45) -> 0 | F45: =SUM(H45,J45,L45,N45) -> 0
A46: Finished Goods Inventory | B46: 153 | C46: =E46-F46 -> 0 | E46: =SUM(G46,I46,K46,M46) -> 0 | F46: =SUM(H46,J46,L46,N46) -> 0
A47: Merchandise Inventory | B47: 154 | C47: =E47-F47 -> 0 | E47: =SUM(G47,I47,K47,M47) -> 0 | F47: =SUM(H47,J47,L47,N47) -> 0
A48: Office Supplies Inventory | B48: 155 | C48: =E48-F48 -> 0 | E48: =SUM(G48,I48,K48,M48) -> 0 | F48: =SUM(H48,J48,L48,N48) -> 0
A49: Accountable Forms Inventory | B49: 156 | C49: =E49-F49 -> 0 | E49: =SUM(G49,I49,K49,M49) -> 0 | F49: =SUM(H49,J49,L49,N49) -> 0
A50: Animal/Zoological Supplies Inventory | B50: 157 | C50: =E50-F50 -> 0 | E50: =SUM(G50,I50,K50,M50) -> 0 | F50: =SUM(H50,J50,L50,N50) -> 0
A51: Food Supplies Inventory | B51: 158 | C51: =E51-F51 -> 0 | E51: =SUM(G51,I51,K51,M51) -> 0 | F51: =SUM(H51,J51,L51,N51) -> 0
A52: Drugs and Medicines Inventory | B52: 159 | C52: =E52-F52 -> 0 | E52: =SUM(G52,I52,K52,M52) -> 0 | F52: =SUM(H52,J52,L52,N52) -> 0
... A57: Military and Police Supplies Inventory | B57: 164 | C57: =E57-F57 -> 0 | E57: =SUM(G57,I57,K57,M57) -> 0 | F57: =SUM(H57,J57,L57,N57) -> 0
A58: Other Supplies Inventory | B58: 165 | C58: =E58-F58 -> 0 | E58: =SUM(G58,I58,K58,M58) -> 0 | F58: =SUM(H58,J58,L58,N58) -> 0
A59: Confiscated/Abandoned/Seized Goods Inventory | B59: 166 | C59: =E59-F59 -> 0 | E59: =SUM(G59,I59,K59,M59) -> 0 | F59: =SUM(H59,J59,L59,N59) -> 0
A60: Spare Parts Inventory | B60: 167 | C60: =E60-F60 -> 0 | E60: =SUM(G60,I60,K60,M60) -> 0 | F60: =SUM(H60,J60,L60,N60) -> 0
A61: Construction Materials Inventory | B61: 168 | C61: =E61-F61 -> 0 | E61: =SUM(G61,I61,K61,M61) -> 0 | F61: =SUM(H61,J61,L61,N61) -> 0
A62: Livestock Inventory | B62: 169 | C62: =E62-F62 -> 0 | E62: =SUM(G62,I62,K62,M62) -> 0 | F62: =SUM(H62,J62,L62,N62) -> 0
A63: Crops and Fruits Inventory | B63: 170 | C63: =E63-F63 -> 0 | E63: =SUM(G63,I63,K63,M63) -> 0 | F63: =SUM(H63,J63,L63,N63) -> 0
A64: Other Agricultural, Fishery and Forestry Products Inventory | B64: 176 | C64: =E64-F64 -> 0 | E64: =SUM(G64,I64,K64,M64) -> 0 | F64: =SUM(H64,J64,L64,N64) -> 0
A65: Prepaid Rent | B65: 177 | C65: =E65-F65 -> 0 | E65: =SUM(G65,I65,K65,M65) -> 0 | F65: =SUM(H65,J65,L65,N65) -> 0
A66: Prepaid Insurance | B66: 178 | C66: =E66-F66 -> 0 | E66: =SUM(G66,I66,K66,M66) -> 0 | F66: =SUM(H66,J66,L66,N66) -> 0
A67: Prepaid Interest | B67: 179 | C67: =E67-F67 -> 0 | E67: =SUM(G67,I67,K67,M67) -> 0 | F67: =SUM(H67,J67,L67,N67) -> 0
A68: Deposit on Letters of Credit | B68: 180 | C68: =E68-F68 -> 0 | E68: =SUM(G68,I68,K68,M68) -> 0 | F68: =SUM(H68,J68,L68,N68) -> 0
A69: Advances to Contractors | B69: 181 | C69: =E69-F69 -> 0 | E69: =SUM(G69,I69,K69,M69) -> 0 | F69: =SUM(H69,J69,L69,N69) -> 0
A70: Deferred Charges | B70: 182 | C70: =E70-F70 -> 0 | E70: =SUM(G70,I70,K70,M70) -> 0 | F70: =SUM(H70,J70,L70,N70) -> 0
A71: Other Prepaid Expenses | B71: 185 | C71: =E71-F71 -> 0 | E71: =SUM(G71,I71,K71,M71) -> 0 | F71: =SUM(H71,J71,L71,N71) -> 0
A72: Guaranty Deposits | B72: 186 | C72: =E72-F72 -> 0 | E72: =SUM(G72,I72,K72,M72) -> 0 | F72: =SUM(H72,J72,L72,N72) -> 0
A73: Other Current Assets | B73: 189 | C73: =E73-F73 -> 0 | E73: =SUM(G73,I73,K73,M73) -> 0 | F73: =SUM(H73,J73,L73,N73) -> 0
A74: Investments in Treasury Bills | B74: 191 | C74: =E74-F74 -> 0 | E74: =SUM(G74,I74,K74,M74) -> 0 | F74: =SUM(H74,J74,L74,N74) -> 0
A75: Investments in Stocks | B75: 192 | C75: =E75-F75 -> 0 | E75: =SUM(G75,I75,K75,M75) -> 0 | F75: =SUM(H75,J75,L75,N75) -> 0
A76: Investments in Bonds | B76: 193 | C76: =E76-F76 -> 0 | E76: =SUM(G76,I76,K76,M76) -> 0 | F76: =SUM(H76,J76,L76,N76) -> 0
A77: Other Investments and Marketable Securities | B77: 197 | C77: =E77-F77 -> 0 | E77: =SUM(G77,I77,K77,M77) -> 0 | F77: =SUM(H77,J77,L77,N77) -> 0
A78: Sinking Fund | B78: 198 | C78: =E78-F78 -> 0 | E78: =SUM(G78,I78,K78,M78) -> 0 | F78: =SUM(H78,J78,L78,N78) -> 0
A79: Land | B79: 201 | C79: =E79-F79 -> 0 | E79: =SUM(G79,I79,K79,M79) -> 0 | F79: =SUM(H79,J79,L79,N79) -> 0
A80: Land Improvements | B80: 202 | C80: =E80-F80 -> 0 | E80: =SUM(G80,I80,K80,M80) -> 0 | F80: =SUM(H80,J80,L80,N80) -> 0
A81: Accumulated Depreciation – Land Improvements | B81: 302 | D81: =F81-E81 -> 0 | E81: =SUM(G81,I81,K81,M81) -> 0 | F81: =SUM(H81,J81,L81,N81) -> 0
A82: Runways/Taxiways | B82: 203 | C82: =E82-F82 -> 0 | E82: =SUM(G82,I82,K82,M82) -> 0 | F82: =SUM(H82,J82,L82,N82) -> 0
A83: Accumulated Depreciation - Runways/Taxiways | B83: 303 | D83: =F83-E83 -> 0 | E83: =SUM(G83,I83,K83,M83) -> 0 | F83: =SUM(H83,J83,L83,N83) -> 0
A84: Railways | B84: 204 | C84: =E84-F84 -> 0 | E84: =SUM(G84,I84,K84,M84) -> 0 | F84: =SUM(H84,J84,L84,N84) -> 0
A85: Accumulated Depreciation - Railways | B85: 304 | D85: =F85-E85 -> 0 | E85: =SUM(G85,I85,K85,M85) -> 0 | F85: =SUM(H85,J85,L85,N85) -> 0
A86: Electrification, Power and Energy Structures | B86: 205 | C86: =E86-F86 -> 0 | E86: =SUM(G86,I86,K86,M86) -> 0 | F86: =SUM(H86,J86,L86,N86) -> 0
A87: Accumulated Depreciation - Electrification, Power and Energy | B87: 305 | D87: =F87-E87 -> 0 | E87: =SUM(G87,I87,K87,M87) -> 0 | F87: =SUM(H87,J87,L87,N87) -> 0
A88: Office Buildings | B88: 211 | C88: =E88-F88 -> 0 | E88: =SUM(G88,I88,K88,M88) -> 0 | F88: =SUM(H88,J88,L88,N88) -> 0
A89: Accumulated Depreciation - Office Buildings | B89: 311 | D89: =F89-E89 -> 0 | E89: =SUM(G89,I89,K89,M89) -> 0 | F89: =SUM(H89,J89,L89,N89) -> 0
A90: School Buildings | B90: 212 | C90: =E90-F90 -> 0 | E90: =SUM(G90,I90,K90,M90) -> 0 | F90: =SUM(H90,J90,L90,N90) -> 0
A91: Accumulated Depreciation - School Buildings | B91: 312 | D91: =F91-E91 -> 0 | E91: =SUM(G91,I91,K91,M91) -> 0 | F91: =SUM(H91,J91,L91,N91) -> 0
A92: Hospitals and Health Centers | B92: 213 | C92: =E92-F92 -> 0 | E92: =SUM(G92,I92,K92,M92) -> 0 | F92: =SUM(H92,J92,L92,N92) -> 0
A93: Accumulated Depreciation - Hospitals and Health Centers | B93: 313 | D93: =F93-E93 -> 0 | E93: =SUM(G93,I93,K93,M93) -> 0 | F93: =SUM(H93,J93,L93,N93) -> 0
A94: Markets and Slaughterhouses | B94: 214 | C94: =E94-F94 -> 0 | E94: =SUM(G94,I94,K94,M94) -> 0 | F94: =SUM(H94,J94,L94,N94) -> 0
A95: Accumulated Depreciation - Markets and Slaughterhouses | B95: 314 | D95: =F95-E95 -> 0 | E95: =SUM(G95,I95,K95,M95) -> 0 | F95: =SUM(H95,J95,L95,N95) -> 0
A96: Other Structures | B96: 215 | C96: =E96-F96 -> 0 | E96: =SUM(G96,I96,K96,M96) -> 0 | F96: =SUM(H96,J96,L96,N96) -> 0
A97: Accumulated Depreciation - Other Structures | B97: 315 | D97: =F97-E97 -> 0 | E97: =SUM(G97,I97,K97,M97) -> 0 | F97: =SUM(H97,J97,L97,N97) -> 0
A98: Leasehold Improvements, Land | B98: 218 | C98: =E98-F98 -> 0 | E98: =SUM(G98,I98,K98,M98) -> 0 | F98: =SUM(H98,J98,L98,N98) -> 0
A99: Accumulated Depreciation - Leasehold Improvements, Land | B99: 318 | D99: =F99-E99 -> 0 | E99: =SUM(G99,I99,K99,M99) -> 0 | F99: =SUM(H99,J99,L99,N99) -> 0
A100: Leasehold Improvements, Buildings | B100: 219 | C100: =E100-F100 -> 0 | E100: =SUM(G100,I100,K100,M100) -> 0 | F100: =SUM(H100,J100,L100,N100) -> 0
A101: Accumulated Depreciation - Leasehold Improvements, Buildings | B101: 319 | D101: =F101-E101 -> 0 | E101: =SUM(G101,I101,K101,M101) -> 0 | F101: =SUM(H101,J101,L101,N101) -> 0
A102: Other Leasehold Improvements | B102: 220 | C102: =E102-F102 -> 0 | E102: =SUM(G102,I102,K102,M102) -> 0 | F102: =SUM(H102,J102,L102,N102) -> 0
A103: Accumulated Depreciation - Other Leasehold Improvements | B103: 320 | D103: =F103-E103 -> 0 | E103: =SUM(G103,I103,K103,M103) -> 0 | F103: =SUM(H103,J103,L103,N103) -> 0
A104: Office Equipment | B104: 221 | C104: =E104-F104 -> 0 | E104: =SUM(G104,I104,K104,M104) -> 0 | F104: =SUM(H104,J104,L104,N104) -> 0
A105: Accumulated Depreciation - Office Equipment | B105: 321 | D105: =F105-E105 -> 0 | E105: =SUM(G105,I105,K105,M105) -> 0 | F105: =SUM(H105,J105,L105,N105) -> 0
A106: Furniture and Fixtures | B106: 222 | C106: =E106-F106 -> 0 | E106: =SUM(G106,I106,K106,M106) -> 0 | F106: =SUM(H106,J106,L106,N106) -> 0
A107: Accumulated Depreciation - Furniture and Fixtures | B107: 322 | D107: =F107-E107 -> 0 | E107: =SUM(G107,I107,K107,M107) -> 0 | F107: =SUM(H107,J107,L107,N107) -> 0
A108: IT Equipment and Software | B108: 223 | C108: =E108-F108 -> 0 | E108: =SUM(G108,I108,K108,M108) -> 0 | F108: =SUM(H108,J108,L108,N108) -> 0
A109: Accumulated Depreciation - IT Equipment | B109: 323 | D109: =F109-E109 -> 0 | E109: =SUM(G109,I109,K109,M109) -> 0 | F109: =SUM(H109,J109,L109,N109) -> 0
...

Sheet TB-Mar
A1: Republic of the Philippines
A2: PROVINCE OF AGUSAN DEL SUR
A3: Gov. Democrito O. Plaza Government Center, Prosperidad
A5: TRUST FUND
A6: TRIAL BALANCE
A7: As of March 31, 2011
E9: =A7 -> As of March 31, 2011 | G9: Check Disbursement | I9: Cash Disbursement | K9: Cash Receipts | M9: General Journal
A11: Account Title | B11: Account Code | C11: Debit | D11: Credit | E11: Debit | F11: Credit | G11: Debit | H11: Credit | I11: Debit | J11: Credit | K11: Debit | L11: Credit | M11: Debit | N11: Credit
A13: Cash in Vault | B13: 101 | C13: =E13-F13 -> 0 | E13: =SUM(G13,I13,K13,M13) -> 0 | F13: =SUM(H13,J13,L13,N13) -> 0
A14: Cash - Collecting Officers | B14: 102 | C14: =E14-F14 -> 0 | E14: =SUM(G14,I14,K14,M14) -> 0 | F14: =SUM(H14,J14,L14,N14) -> 0
A15: Cash Disbursing Officers | B15: 103 | C15: =E15-F15 -> 0 | E15: =SUM(G15,I15,K15,M15) -> 0 | F15: =SUM(H15,J15,L15,N15) -> 0
A16: Petty Cash Fund | B16: 104 | C16: =E16-F16 -> 0 | E16: =SUM(G16,I16,K16,M16) -> 0 | F16: =SUM(H16,J16,L16,N16) -> 0
A17: Payroll Fund | B17: 106 | C17: =E17-F17 -> 0 | E17: =SUM(G17,I17,K17,M17) -> 0 | F17: =SUM(H17,J17,L17,N17) -> 0
A18: Cash - Bangko Sentral ng Pilipinas | B18: 110 | C18: =E18-F18 -> 0 | E18: =SUM(G18,I18,K18,M18) -> 0 | F18: =SUM(H18,J18,L18,N18) -> 0
A19: Cash in Bank - Local Currency, Current Account | B19: 111 | C19: =E19-F19 -> 0 | E19: =SUM(G19,I19,K19,M19) -> 0 | F19: =SUM(H19,J19,L19,N19) -> 0
A20: Cash in Bank - Local Currency, SavingsAccount | B20: 112 | C20: =E20-F20 -> 0 | E20: =SUM(G20,I20,K20,M20) -> 0 | F20: =SUM(H20,J20,L20,N20) -> 0
A21: Cash in Bank - Local Currency, Time Deposits | B21: 113 | C21: =E21-F21 -> 0 | E21: =SUM(G21,I21,K21,M21) -> 0 | F21: =SUM(H21,J21,L21,N21) -> 0
A22: Cash - Bangko Sentral ng Pilipinas | B22: 114 | C22: =E22-F22 -> 0 | E22: =SUM(G22,I22,K22,M22) -> 0 | F22: =SUM(H22,J22,L22,N22) -> 0
A23: Cash in Bank - Foreign Currency, Current Account | B23: 115 | C23: =E23-F23 -> 0 | E23: =SUM(G23,I23,K23,M23) -> 0 | F23: =SUM(H23,J23,L23,N23) -> 0
A24: Cash in Bank - Foreign Currency, Savings Account | B24: 116 | C24: =E24-F24 -> 0 | E24: =SUM(G24,I24,K24,M24) -> 0 | F24: =SUM(H24,J24,L24,N24) -> 0
A25: Cash in Bank - Foreign Currency, Time Deposits | B25: 117 | C25: =E25-F25 -> 0 | E25: =SUM(G25,I25,K25,M25) -> 0 | F25: =SUM(H25,J25,L25,N25) -> 0
A26: Accounts Receivable | B26: 121 | C26: =E26-F26 -> 0 | E26: =SUM(G26,I26,K26,M26) -> 0 | F26: =SUM(H26,J26,L26,N26) -> 0
A27: Allowance for Doubtful Accounts | B27: 301 | C27: =E27-F27 -> 0 | E27: =SUM(G27,I27,K27,M27) -> 0 | F27: =SUM(H27,J27,L27,N27) -> 0
A28: Notes Receivable | B28: 122 | C28: =E28-F28 -> 0 | E28: =SUM(G28,I28,K28,M28) -> 0 | F28: =SUM(H28,J28,L28,N28) -> 0
A29: Due from Officers and Employees | B29: 123 | C29: =E29-F29 -> 0 | E29: =SUM(G29,I29,K29,M29) -> 0 | F29: =SUM(H29,J29,L29,N29) -> 0
A30: Loans Receivable - GOCCs | B30: 124 | C30: =E30-F30 -> 0 | E30: =SUM(G30,I30,K30,M30) -> 0 | F30: =SUM(H30,J30,L30,N30) -> 0
A31: Loans Receivable - LGUs | B31: 125 | C31: =E31-F31 -> 0 | E31: =SUM(G31,I31,K31,M31) -> 0 | F31: =SUM(H31,J31,L31,N31) -> 0
A32: Loans Receivable - Others | B32: 126 | C32: =E32-F32 -> 0 | E32: =SUM(G32,I32,K32,M32) -> 0 | F32: =SUM(H32,J32,L32,N32) -> 0
A33: Real Property Tax Receivable | B33: 127 | C33: =E33-F33 -> 0 | E33: =SUM(G33,I33,K33,M33) -> 0 | F33: =SUM(H33,J33,L33,N33) -> 0
A34: Special Education Tax Receivable | B34: 128 | C34: =E34-F34 -> 0 | E34: =SUM(G34,I34,K34,M34) -> 0 | F34: =SUM(H34,J34,L34,N34) -> 0
A35: Interests Receivable | B35: 129 | C35: =E35-F35 -> 0 | E35: =SUM(G35,I35,K35,M35) -> 0 | F35: =SUM(H35,J35,L35,N35) -> 0
... A37: Due from GOCCs | B37: 137 | C37: =E37-F37 -> 0 | E37: =SUM(G37,I37,K37,M37) -> 0 | F37: =SUM(H37,J37,L37,N37) -> 0
A38: Due from LGUs | B38: 138 | C38: =E38-F38 -> 0 | E38: =SUM(G38,I38,K38,M38) -> 0 | F38: =SUM(H38,J38,L38,N38) -> 0
A39: Due from NGOs/POs | B39: 139 | C39: =E39-F39 -> 0 | E39: =SUM(G39,I39,K39,M39) -> 0 | F39: =SUM(H39,J39,L39,N39) -> 0
A40: Due from Other Funds | B40: 144 | C40: =E40-F40 -> 0 | E40: =SUM(G40,I40,K40,M40) -> 0 | F40: =SUM(H40,J40,L40,N40) -> 0
A41: Receivables - Disallowances/Charges | B41: 146 | C41: =E41-F41 -> 0 | E41: =SUM(G41,I41,K41,M41) -> 0 | F41: =SUM(H41,J41,L41,N41) -> 0
A42: Advances to Officers and Employees | B42: 148 | C42: =E42-F42 -> 0 | E42: =SUM(G42,I42,K42,M42) -> 0 | F42: =SUM(H42,J42,L42,N42) -> 0
A43: Other Receivables | B43: 149 | C43: =E43-F43 -> 0 | E43: =SUM(G43,I43,K43,M43) -> 0 | F43: =SUM(H43,J43,L43,N43) -> 0
A44: Raw Materials Inventory | B44: 151 | C44: =E44-F44 -> 0 | E44: =SUM(G44,I44,K44,M44) -> 0 | F44: =SUM(H44,J44,L44,N44) -> 0
A45: Work-In-Process Inventory | B45: 152 | C45: =E45-F45 -> 0 | E45: =SUM(G45,I45,K45,M45) -> 0 | F45: =SUM(H45,J45,L45,N45) -> 0
A46: Finished Goods Inventory | B46: 153 | C46: =E46-F46 -> 0 | E46: =SUM(G46,I46,K46,M46) -> 0 | F46: =SUM(H46,J46,L46,N46) -> 0
A47: Merchandise Inventory | B47: 154 | C47: =E47-F47 -> 0 | E47: =SUM(G47,I47,K47,M47) -> 0 | F47: =SUM(H47,J47,L47,N47) -> 0
A48: Office Supplies Inventory | B48: 155 | C48: =E48-F48 -> 0 | E48: =SUM(G48,I48,K48,M48) -> 0 | F48: =SUM(H48,J48,L48,N48) -> 0
A49: Accountable Forms Inventory | B49: 156 | C49: =E49-F49 -> 0 | E49: =SUM(G49,I49,K49,M49) -> 0 | F49: =SUM(H49,J49,L49,N49) -> 0
A50: Animal/Zoological Supplies Inventory | B50: 157 | C50: =E50-F50 -> 0 | E50: =SUM(G50,I50,K50,M50) -> 0 | F50: =SUM(H50,J50,L50,N50) -> 0
A51: Food Supplies Inventory | B51: 158 | C51: =E51-F51 -> 0 | E51: =SUM(G51,I51,K51,M51) -> 0 | F51: =SUM(H51,J51,L51,N51) -> 0
A52: Drugs and Medicines Inventory | B52: 159 | C52: =E52-F52 -> 0 | E52: =SUM(G52,I52,K52,M52) -> 0 | F52: =SUM(H52,J52,L52,N52) -> 0
... A57: Military and Police Supplies Inventory | B57: 164 | C57: =E57-F57 -> 0 | E57: =SUM(G57,I57,K57,M57) -> 0 | F57: =SUM(H57,J57,L57,N57) -> 0
A58: Other Supplies Inventory | B58: 165 | C58: =E58-F58 -> 0 | E58: =SUM(G58,I58,K58,M58) -> 0 | F58: =SUM(H58,J58,L58,N58) -> 0
A59: Confiscated/Abandoned/Seized Goods Inventory | B59: 166 | C59: =E59-F59 -> 0 | E59: =SUM(G59,I59,K59,M59) -> 0 | F59: =SUM(H59,J59,L59,N59) -> 0
A60: Spare Parts Inventory | B60: 167 | C60: =E60-F60 -> 0 | E60: =SUM(G60,I60,K60,M60) -> 0 | F60: =SUM(H60,J60,L60,N60) -> 0
A61: Construction Materials Inventory | B61: 168 | C61: =E61-F61 -> 0 | E61: =SUM(G61,I61,K61,M61) -> 0 | F61: =SUM(H61,J61,L61,N61) -> 0
A62: Livestock Inventory | B62: 169 | C62: =E62-F62 -> 0 | E62: =SUM(G62,I62,K62,M62) -> 0 | F62: =SUM(H62,J62,L62,N62) -> 0
A63: Crops and Fruits Inventory | B63: 170 | C63: =E63-F63 -> 0 | E63: =SUM(G63,I63,K63,M63) -> 0 | F63: =SUM(H63,J63,L63,N63) -> 0
A64: Other Agricultural, Fishery and Forestry Products Inventory | B64: 176 | C64: =E64-F64 -> 0 | E64: =SUM(G64,I64,K64,M64) -> 0 | F64: =SUM(H64,J64,L64,N64) -> 0
A65: Prepaid Rent | B65: 177 | C65: =E65-F65 -> 0 | E65: =SUM(G65,I65,K65,M65) -> 0 | F65: =SUM(H65,J65,L65,N65) -> 0
A66: Prepaid Insurance | B66: 178 | C66: =E66-F66 -> 0 | E66: =SUM(G66,I66,K66,M66) -> 0 | F66: =SUM(H66,J66,L66,N66) -> 0
A67: Prepaid Interest | B67: 179 | C67: =E67-F67 -> 0 | E67: =SUM(G67,I67,K67,M67) -> 0 | F67: =SUM(H67,J67,L67,N67) -> 0
A68: Deposit on Letters of Credit | B68: 180 | C68: =E68-F68 -> 0 | E68: =SUM(G68,I68,K68,M68) -> 0 | F68: =SUM(H68,J68,L68,N68) -> 0
A69: Advances to Contractors | B69: 181 | C69: =E69-F69 -> 0 | E69: =SUM(G69,I69,K69,M69) -> 0 | F69: =SUM(H69,J69,L69,N69) -> 0
A70: Deferred Charges | B70: 182 | C70: =E70-F70 -> 0 | E70: =SUM(G70,I70,K70,M70) -> 0 | F70: =SUM(H70,J70,L70,N70) -> 0
A71: Other Prepaid Expenses | B71: 185 | C71: =E71-F71 -> 0 | E71: =SUM(G71,I71,K71,M71) -> 0 | F71: =SUM(H71,J71,L71,N71) -> 0
A72: Guaranty Deposits | B72: 186 | C72: =E72-F72 -> 0 | E72: =SUM(G72,I72,K72,M72) -> 0 | F72: =SUM(H72,J72,L72,N72) -> 0
A73: Other Current Assets | B73: 189 | C73: =E73-F73 -> 0 | E73: =SUM(G73,I73,K73,M73) -> 0 | F73: =SUM(H73,J73,L73,N73) -> 0
A74: Investments in Treasury Bills | B74: 191 | C74: =E74-F74 -> 0 | E74: =SUM(G74,I74,K74,M74) -> 0 | F74: =SUM(H74,J74,L74,N74) -> 0
A75: Investments in Stocks | B75: 192 | C75: =E75-F75 -> 0 | E75: =SUM(G75,I75,K75,M75) -> 0 | F75: =SUM(H75,J75,L75,N75) -> 0
A76: Investments in Bonds | B76: 193 | C76: =E76-F76 -> 0 | E76: =SUM(G76,I76,K76,M76) -> 0 | F76: =SUM(H76,J76,L76,N76) -> 0
A77: Other Investments and Marketable Securities | B77: 197 | C77: =E77-F77 -> 0 | E77: =SUM(G77,I77,K77,M77) -> 0 | F77: =SUM(H77,J77,L77,N77) -> 0
A78: Sinking Fund | B78: 198 | C78: =E78-F78 -> 0 | E78: =SUM(G78,I78,K78,M78) -> 0 | F78: =SUM(H78,J78,L78,N78) -> 0
A79: Land | B79: 201 | C79: =E79-F79 -> 0 | E79: =SUM(G79,I79,K79,M79) -> 0 | F79: =SUM(H79,J79,L79,N79) -> 0
A80: Land Improvements | B80: 202 | C80: =E80-F80 -> 0 | E80: =SUM(G80,I80,K80,M80) -> 0 | F80: =SUM(H80,J80,L80,N80) -> 0
A81: Accumulated Depreciation – Land Improvements | B81: 302 | D81: =F81-E81 -> 0 | E81: =SUM(G81,I81,K81,M81) -> 0 | F81: =SUM(H81,J81,L81,N81) -> 0
A82: Runways/Taxiways | B82: 203 | C82: =E82-F82 -> 0 | E82: =SUM(G82,I82,K82,M82) -> 0 | F82: =SUM(H82,J82,L82,N82) -> 0
A83: Accumulated Depreciation - Runways/Taxiways | B83: 303 | D83: =F83-E83 -> 0 | E83: =SUM(G83,I83,K83,M83) -> 0 | F83: =SUM(H83,J83,L83,N83) -> 0
A84: Railways | B84: 204 | C84: =E84-F84 -> 0 | E84: =SUM(G84,I84,K84,M84) -> 0 | F84: =SUM(H84,J84,L84,N84) -> 0
A85: Accumulated Depreciation - Railways | B85: 304 | D85: =F85-E85 -> 0 | E85: =SUM(G85,I85,K85,M85) -> 0 | F85: =SUM(H85,J85,L85,N85) -> 0
A86: Electrification, Power and Energy Structures | B86: 205 | C86: =E86-F86 -> 0 | E86: =SUM(G86,I86,K86,M86) -> 0 | F86: =SUM(H86,J86,L86,N86) -> 0
A87: Accumulated Depreciation - Electrification, Power and Energy | B87: 305 | D87: =F87-E87 -> 0 | E87: =SUM(G87,I87,K87,M87) -> 0 | F87: =SUM(H87,J87,L87,N87) -> 0
A88: Office Buildings | B88: 211 | C88: =E88-F88 -> 0 | E88: =SUM(G88,I88,K88,M88) -> 0 | F88: =SUM(H88,J88,L88,N88) -> 0
A89: Accumulated Depreciation - Office Buildings | B89: 311 | D89: =F89-E89 -> 0 | E89: =SUM(G89,I89,K89,M89) -> 0 | F89: =SUM(H89,J89,L89,N89) -> 0
A90: School Buildings | B90: 212 | C90: =E90-F90 -> 0 | E90: =SUM(G90,I90,K90,M90) -> 0 | F90: =SUM(H90,J90,L90,N90) -> 0
A91: Accumulated Depreciation - School Buildings | B91: 312 | D91: =F91-E91 -> 0 | E91: =SUM(G91,I91,K91,M91) -> 0 | F91: =SUM(H91,J91,L91,N91) -> 0
A92: Hospitals and Health Centers | B92: 213 | C92: =E92-F92 -> 0 | E92: =SUM(G92,I92,K92,M92) -> 0 | F92: =SUM(H92,J92,L92,N92) -> 0
A93: Accumulated Depreciation - Hospitals and Health Centers | B93: 313 | D93: =F93-E93 -> 0 | E93: =SUM(G93,I93,K93,M93) -> 0 | F93: =SUM(H93,J93,L93,N93) -> 0
A94: Markets and Slaughterhouses | B94: 214 | C94: =E94-F94 -> 0 | E94: =SUM(G94,I94,K94,M94) -> 0 | F94: =SUM(H94,J94,L94,N94) -> 0
A95: Accumulated Depreciation - Markets and Slaughterhouses | B95: 314 | D95: =F95-E95 -> 0 | E95: =SUM(G95,I95,K95,M95) -> 0 | F95: =SUM(H95,J95,L95,N95) -> 0
A96: Other Structures | B96: 215 | C96: =E96-F96 -> 0 | E96: =SUM(G96,I96,K96,M96) -> 0 | F96: =SUM(H96,J96,L96,N96) -> 0
A97: Accumulated Depreciation - Other Structures | B97: 315 | D97: =F97-E97 -> 0 | E97: =SUM(G97,I97,K97,M97) -> 0 | F97: =SUM(H97,J97,L97,N97) -> 0
A98: Leasehold Improvements, Land | B98: 218 | C98: =E98-F98 -> 0 | E98: =SUM(G98,I98,K98,M98) -> 0 | F98: =SUM(H98,J98,L98,N98) -> 0
A99: Accumulated Depreciation - Leasehold Improvements, Land | B99: 318 | D99: =F99-E99 -> 0 | E99: =SUM(G99,I99,K99,M99) -> 0 | F99: =SUM(H99,J99,L99,N99) -> 0
A100: Leasehold Improvements, Buildings | B100: 219 | C100: =E100-F100 -> 0 | E100: =SUM(G100,I100,K100,M100) -> 0 | F100: =SUM(H100,J100,L100,N100) -> 0
A101: Accumulated Depreciation - Leasehold Improvements, Buildings | B101: 319 | D101: =F101-E101 -> 0 | E101: =SUM(G101,I101,K101,M101) -> 0 | F101: =SUM(H101,J101,L101,N101) -> 0
A102: Other Leasehold Improvements | B102: 220 | C102: =E102-F102 -> 0 | E102: =SUM(G102,I102,K102,M102) -> 0 | F102: =SUM(H102,J102,L102,N102) -> 0
A103: Accumulated Depreciation - Other Leasehold Improvements | B103: 320 | D103: =F103-E103 -> 0 | E103: =SUM(G103,I103,K103,M103) -> 0 | F103: =SUM(H103,J103,L103,N103) -> 0
A104: Office Equipment | B104: 221 | C104: =E104-F104 -> 0 | E104: =SUM(G104,I104,K104,M104) -> 0 | F104: =SUM(H104,J104,L104,N104) -> 0
A105: Accumulated Depreciation - Office Equipment | B105: 321 | D105: =F105-E105 -> 0 | E105: =SUM(G105,I105,K105,M105) -> 0 | F105: =SUM(H105,J105,L105,N105) -> 0
A106: Furniture and Fixtures | B106: 222 | C106: =E106-F106 -> 0 | E106: =SUM(G106,I106,K106,M106) -> 0 | F106: =SUM(H106,J106,L106,N106) -> 0
A107: Accumulated Depreciation - Furniture and Fixtures | B107: 322 | D107: =F107-E107 -> 0 | E107: =SUM(G107,I107,K107,M107) -> 0 | F107: =SUM(H107,J107,L107,N107) -> 0
A108: IT Equipment and Software | B108: 223 | C108: =E108-F108 -> 0 | E108: =SUM(G108,I108,K108,M108) -> 0 | F108: =SUM(H108,J108,L108,N108) -> 0
A109: Accumulated Depreciation - IT Equipment | B109: 323 | D109: =F109-E109 -> 0 | E109: =SUM(G109,I109,K109,M109) -> 0 | F109: =SUM(H109,J109,L109,N109) -> 0
...

Sheet TB-Apr
A1: Republic of the Philippines
A2: PROVINCE OF AGUSAN DEL SUR
A3: Gov. Democrito O. Plaza Government Center, Prosperidad
A5: TRUST FUND
A6: TRIAL BALANCE
A7: As of April 30, 2011
E9: =A7 -> As of April 30, 2011 | G9: TB for April | I9: Cash Disbursement | K9: Cash Receipts | M9: General Journal
A11: Account Title | B11: Account Code | C11: Debit | D11: Credit | E11: Debit | F11: Credit | G11: Debit | H11: Credit | I11: Debit | J11: Credit | K11: Debit | L11: Credit | M11: Debit | N11: Credit
A13: Cash in Vault | B13: 101 | C13: =E13-F13 -> 0 | E13: =SUM(G13,I13,K13,M13) -> 0 | F13: =SUM(H13,J13,L13,N13) -> 0
A14: Cash - Collecting Officers | B14: 102 | C14: =E14-F14 -> 0 | E14: =SUM(G14,I14,K14,M14) -> 0 | F14: =SUM(H14,J14,L14,N14) -> 0
A15: Cash Disbursing Officers | B15: 103 | C15: =E15-F15 -> 0 | E15: =SUM(G15,I15,K15,M15) -> 0 | F15: =SUM(H15,J15,L15,N15) -> 0
A16: Petty Cash Fund | B16: 104 | C16: =E16-F16 -> 50000 | E16: =SUM(G16,I16,K16,M16) -> 50000 | F16: =SUM(H16,J16,L16,N16) -> 0 | G16: 50000
A17: Payroll Fund | B17: 106 | C17: =E17-F17 -> 4876.62 | E17: =SUM(G17,I17,K17,M17) -> 4876.62 | F17: =SUM(H17,J17,L17,N17) -> 0 | G17: 4876.62
A18: Cash - Bangko Sentral ng Pilipinas | B18: 110 | C18: =E18-F18 -> 0 | E18: =SUM(G18,I18,K18,M18) -> 0 | F18: =SUM(H18,J18,L18,N18) -> 0
A19: Cash in Bank - Local Currency, Current Account | B19: 111 | C19: =E19-F19 -> 75809618 | E19: =SUM(G19,I19,K19,M19) -> 75809618 | F19: =SUM(H19,J19,L19,N19) -> 0 | G19: 75809618
A20: Cash in Bank - Local Currency, SavingsAccount | B20: 112 | C20: =E20-F20 -> 4335118.1 | E20: =SUM(G20,I20,K20,M20) -> 4335118.1 | F20: =SUM(H20,J20,L20,N20) -> 0 | G20: 4335118.1
A21: Cash in Bank - Local Currency, Time Deposits | B21: 113 | C21: =E21-F21 -> 0 | E21: =SUM(G21,I21,K21,M21) -> 0 | F21: =SUM(H21,J21,L21,N21) -> 0
A22: Cash - Bangko Sentral ng Pilipinas | B22: 114 | C22: =E22-F22 -> 0 | E22: =SUM(G22,I22,K22,M22) -> 0 | F22: =SUM(H22,J22,L22,N22) -> 0
A23: Cash in Bank - Foreign Currency, Current Account | B23: 115 | C23: =E23-F23 -> 0 | E23: =SUM(G23,I23,K23,M23) -> 0 | F23: =SUM(H23,J23,L23,N23) -> 0
A24: Cash in Bank - Foreign Currency, Savings Account | B24: 116 | C24: =E24-F24 -> 0 | E24: =SUM(G24,I24,K24,M24) -> 0 | F24: =SUM(H24,J24,L24,N24) -> 0
A25: Cash in Bank - Foreign Currency, Time Deposits | B25: 117 | C25: =E25-F25 -> 0 | E25: =SUM(G25,I25,K25,M25) -> 0 | F25: =SUM(H25,J25,L25,N25) -> 0
A26: Accounts Receivable | B26: 121 | C26: =E26-F26 -> 0 | E26: =SUM(G26,I26,K26,M26) -> 0 | F26: =SUM(H26,J26,L26,N26) -> 0
A27: Allowance for Doubtful Accounts | B27: 301 | C27: =E27-F27 -> 0 | E27: =SUM(G27,I27,K27,M27) -> 0 | F27: =SUM(H27,J27,L27,N27) -> 0
A28: Notes Receivable | B28: 122 | C28: =E28-F28 -> 0 | E28: =SUM(G28,I28,K28,M28) -> 0 | F28: =SUM(H28,J28,L28,N28) -> 0
A29: Due from Officers and Employees | B29: 123 | C29: =E29-F29 -> 0 | E29: =SUM(G29,I29,K29,M29) -> 0 | F29: =SUM(H29,J29,L29,N29) -> 0
A30: Loans Receivable - GOCCs | B30: 124 | C30: =E30-F30 -> 0 | E30: =SUM(G30,I30,K30,M30) -> 0 | F30: =SUM(H30,J30,L30,N30) -> 0
A31: Loans Receivable - LGUs | B31: 125 | C31: =E31-F31 -> 0 | E31: =SUM(G31,I31,K31,M31) -> 0 | F31: =SUM(H31,J31,L31,N31) -> 0
A32: Loans Receivable - Others | B32: 126 | C32: =E32-F32 -> 0 | E32: =SUM(G32,I32,K32,M32) -> 0 | F32: =SUM(H32,J32,L32,N32) -> 0
A33: Real Property Tax Receivable | B33: 127 | C33: =E33-F33 -> 0 | E33: =SUM(G33,I33,K33,M33) -> 0 | F33: =SUM(H33,J33,L33,N33) -> 0
A34: Special Education Tax Receivable | B34: 128 | C34: =E34-F34 -> 0 | E34: =SUM(G34,I34,K34,M34) -> 0 | F34: =SUM(H34,J34,L34,N34) -> 0
A35: Interests Receivable | B35: 129 | C35: =E35-F35 -> 0 | E35: =SUM(G35,I35,K35,M35) -> 0 | F35: =SUM(H35,J35,L35,N35) -> 0
... A37: Due from GOCCs | B37: 137 | C37: =E37-F37 -> 0 | E37: =SUM(G37,I37,K37,M37) -> 0 | F37: =SUM(H37,J37,L37,N37) -> 0
A38: Due from LGUs | B38: 138 | C38: =E38-F38 -> 1183464.4 | E38: =SUM(G38,I38,K38,M38) -> 1183464.4 | F38: =SUM(H38,J38,L38,N38) -> 0 | G38: 1183464.4
A39: Due from NGOs/POs | B39: 139 | C39: =E39-F39 -> 1897625 | E39: =SUM(G39,I39,K39,M39) -> 1897625 | F39: =SUM(H39,J39,L39,N39) -> 0 | G39: 1897625
A40: Due from Other Funds | B40: 144 | C40: =E40-F40 -> 0 | E40: =SUM(G40,I40,K40,M40) -> 0 | F40: =SUM(H40,J40,L40,N40) -> 0
A41: Receivables - Disallowances/Charges | B41: 146 | C41: =E41-F41 -> 0 | E41: =SUM(G41,I41,K41,M41) -> 0 | F41: =SUM(H41,J41,L41,N41) -> 0
A42: Advances to Officers and Employees | B42: 148 | C42: =E42-F42 -> 29984964 | E42: =SUM(G42,I42,K42,M42) -> 29984964 | F42: =SUM(H42,J42,L42,N42) -> 0 | G42: 29984964
A43: Other Receivables | B43: 149 | C43: =E43-F43 -> 312433.89 | E43: =SUM(G43,I43,K43,M43) -> 312433.89 | F43: =SUM(H43,J43,L43,N43) -> 0 | G43: 312433.89
A44: Raw Materials Inventory | B44: 151 | C44: =E44-F44 -> 0 | E44: =SUM(G44,I44,K44,M44) -> 0 | F44: =SUM(H44,J44,L44,N44) -> 0
A45: Work-In-Process Inventory | B45: 152 | C45: =E45-F45 -> 0 | E45: =SUM(G45,I45,K45,M45) -> 0 | F45: =SUM(H45,J45,L45,N45) -> 0
A46: Finished Goods Inventory | B46: 153 | C46: =E46-F46 -> 0 | E46: =SUM(G46,I46,K46,M46) -> 0 | F46: =SUM(H46,J46,L46,N46) -> 0
A47: Merchandise Inventory | B47: 154 | C47: =E47-F47 -> 0 | E47: =SUM(G47,I47,K47,M47) -> 0 | F47: =SUM(H47,J47,L47,N47) -> 0
A48: Office Supplies Inventory | B48: 155 | C48: =E48-F48 -> 0 | E48: =SUM(G48,I48,K48,M48) -> 0 | F48: =SUM(H48,J48,L48,N48) -> 0
A49: Accountable Forms Inventory | B49: 156 | C49: =E49-F49 -> 0 | E49: =SUM(G49,I49,K49,M49) -> 0 | F49: =SUM(H49,J49,L49,N49) -> 0
A50: Animal/Zoological Supplies Inventory | B50: 157 | C50: =E50-F50 -> 0 | E50: =SUM(G50,I50,K50,M50) -> 0 | F50: =SUM(H50,J50,L50,N50) -> 0
A51: Food Supplies Inventory | B51: 158 | C51: =E51-F51 -> 0 | E51: =SUM(G51,I51,K51,M51) -> 0 | F51: =SUM(H51,J51,L51,N51) -> 0
A52: Drugs and Medicines Inventory | B52: 159 | C52: =E52-F52 -> 2812761.9 | E52: =SUM(G52,I52,K52,M52) -> 2812761.9 | F52: =SUM(H52,J52,L52,N52) -> 0 | G52: 2812761.9
A53: Medical, Dental and Laboratory Supplies Inventory | B53: 160 | C53: =E53-F53 -> 0 | E53: =SUM(G53,I53,K53,M53) -> 0 | F53: =SUM(H53,J53,L53,N53) -> 0
A54: Gasoline, Oil and Lubricants Inventory | B54: 161 | C54: =E54-F54 -> 4202400 | E54: =SUM(G54,I54,K54,M54) -> 4202400 | F54: =SUM(H54,J54,L54,N54) -> 0 | G54: 4202400
A55: Agricultural Supplies Inventory | B55: 162 | C55: =E55-F55 -> 0 | E55: =SUM(G55,I55,K55,M55) -> 0 | F55: =SUM(H55,J55,L55,N55) -> 0
A56: Textbooks and Instructional Materials Inventory | B56: 163 | C56: =E56-F56 -> 0 | E56: =SUM(G56,I56,K56,M56) -> 0 | F56: =SUM(H56,J56,L56,N56) -> 0
A57: Military and Police Supplies Inventory | B57: 164 | C57: =E57-F57 -> 0 | E57: =SUM(G57,I57,K57,M57) -> 0 | F57: =SUM(H57,J57,L57,N57) -> 0
A58: Other Supplies Inventory | B58: 165 | C58: =E58-F58 -> 0 | E58: =SUM(G58,I58,K58,M58) -> 0 | F58: =SUM(H58,J58,L58,N58) -> 0
A59: Confiscated/Abandoned/Seized Goods Inventory | B59: 166 | C59: =E59-F59 -> 0 | E59: =SUM(G59,I59,K59,M59) -> 0 | F59: =SUM(H59,J59,L59,N59) -> 0
A60: Spare Parts Inventory | B60: 167 | C60: =E60-F60 -> 0 | E60: =SUM(G60,I60,K60,M60) -> 0 | F60: =SUM(H60,J60,L60,N60) -> 0
A61: Construction Materials Inventory | B61: 168 | C61: =E61-F61 -> 0 | E61: =SUM(G61,I61,K61,M61) -> 0 | F61: =SUM(H61,J61,L61,N61) -> 0
A62: Livestock Inventory | B62: 169 | C62: =E62-F62 -> 0 | E62: =SUM(G62,I62,K62,M62) -> 0 | F62: =SUM(H62,J62,L62,N62) -> 0
A63: Crops and Fruits Inventory | B63: 170 | C63: =E63-F63 -> 0 | E63: =SUM(G63,I63,K63,M63) -> 0 | F63: =SUM(H63,J63,L63,N63) -> 0
A64: Other Agricultural, Fishery and Forestry Products Inventory | B64: 176 | C64: =E64-F64 -> 0 | E64: =SUM(G64,I64,K64,M64) -> 0 | F64: =SUM(H64,J64,L64,N64) -> 0
A65: Prepaid Rent | B65: 177 | C65: =E65-F65 -> 0 | E65: =SUM(G65,I65,K65,M65) -> 0 | F65: =SUM(H65,J65,L65,N65) -> 0
A66: Prepaid Insurance | B66: 178 | C66: =E66-F66 -> 0 | E66: =SUM(G66,I66,K66,M66) -> 0 | F66: =SUM(H66,J66,L66,N66) -> 0
A67: Prepaid Interest | B67: 179 | C67: =E67-F67 -> 0 | E67: =SUM(G67,I67,K67,M67) -> 0 | F67: =SUM(H67,J67,L67,N67) -> 0
A68: Deposit on Letters of Credit | B68: 180 | C68: =E68-F68 -> 0 | E68: =SUM(G68,I68,K68,M68) -> 0 | F68: =SUM(H68,J68,L68,N68) -> 0
A69: Advances to Contractors | B69: 181 | C69: =E69-F69 -> 840000 | E69: =SUM(G69,I69,K69,M69) -> 840000 | F69: =SUM(H69,J69,L69,N69) -> 0 | G69: 840000
A70: Deferred Charges | B70: 182 | C70: =E70-F70 -> 0 | E70: =SUM(G70,I70,K70,M70) -> 0 | F70: =SUM(H70,J70,L70,N70) -> 0
A71: Other Prepaid Expenses | B71: 185 | C71: =E71-F71 -> 0 | E71: =SUM(G71,I71,K71,M71) -> 0 | F71: =SUM(H71,J71,L71,N71) -> 0
A72: Guaranty Deposits | B72: 186 | C72: =E72-F72 -> 0 | E72: =SUM(G72,I72,K72,M72) -> 0 | F72: =SUM(H72,J72,L72,N72) -> 0
A73: Other Current Assets | B73: 189 | C73: =E73-F73 -> 0 | E73: =SUM(G73,I73,K73,M73) -> 0 | F73: =SUM(H73,J73,L73,N73) -> 0
A74: Investments in Treasury Bills | B74: 191 | C74: =E74-F74 -> 0 | E74: =SUM(G74,I74,K74,M74) -> 0 | F74: =SUM(H74,J74,L74,N74) -> 0
A75: Investments in Stocks | B75: 192 | C75: =E75-F75 -> 0 | E75: =SUM(G75,I75,K75,M75) -> 0 | F75: =SUM(H75,J75,L75,N75) -> 0
A76: Investments in Bonds | B76: 193 | C76: =E76-F76 -> 0 | E76: =SUM(G76,I76,K76,M76) -> 0 | F76: =SUM(H76,J76,L76,N76) -> 0
A77: Other Investments and Marketable Securities | B77: 197 | C77: =E77-F77 -> 0 | E77: =SUM(G77,I77,K77,M77) -> 0 | F77: =SUM(H77,J77,L77,N77) -> 0
A78: Sinking Fund | B78: 198 | C78: =E78-F78 -> 0 | E78: =SUM(G78,I78,K78,M78) -> 0 | F78: =SUM(H78,J78,L78,N78) -> 0
A79: Land | B79: 201 | C79: =E79-F79 -> 0 | E79: =SUM(G79,I79,K79,M79) -> 0 | F79: =SUM(H79,J79,L79,N79) -> 0
A80: Land Improvements | B80: 202 | C80: =E80-F80 -> 0 | E80: =SUM(G80,I80,K80,M80) -> 0 | F80: =SUM(H80,J80,L80,N80) -> 0
A81: Accumulated Depreciation – Land Improvements | B81: 302 | D81: =F81-E81 -> 0 | E81: =SUM(G81,I81,K81,M81) -> 0 | F81: =SUM(H81,J81,L81,N81) -> 0
A82: Runways/Taxiways | B82: 203 | C82: =E82-F82 -> 0 | E82: =SUM(G82,I82,K82,M82) -> 0 | F82: =SUM(H82,J82,L82,N82) -> 0
A83: Accumulated Depreciation - Runways/Taxiways | B83: 303 | D83: =F83-E83 -> 0 | E83: =SUM(G83,I83,K83,M83) -> 0 | F83: =SUM(H83,J83,L83,N83) -> 0
A84: Railways | B84: 204 | C84: =E84-F84 -> 0 | E84: =SUM(G84,I84,K84,M84) -> 0 | F84: =SUM(H84,J84,L84,N84) -> 0
A85: Accumulated Depreciation - Railways | B85: 304 | D85: =F85-E85 -> 0 | E85: =SUM(G85,I85,K85,M85) -> 0 | F85: =SUM(H85,J85,L85,N85) -> 0
A86: Electrification, Power and Energy Structures | B86: 205 | C86: =E86-F86 -> 0 | E86: =SUM(G86,I86,K86,M86) -> 0 | F86: =SUM(H86,J86,L86,N86) -> 0
A87: Accumulated Depreciation - Electrification, Power and Energy | B87: 305 | D87: =F87-E87 -> 0 | E87: =SUM(G87,I87,K87,M87) -> 0 | F87: =SUM(H87,J87,L87,N87) -> 0
A88: Office Buildings | B88: 211 | C88: =E88-F88 -> 0 | E88: =SUM(G88,I88,K88,M88) -> 0 | F88: =SUM(H88,J88,L88,N88) -> 0
A89: Accumulated Depreciation - Office Buildings | B89: 311 | D89: =F89-E89 -> 0 | E89: =SUM(G89,I89,K89,M89) -> 0 | F89: =SUM(H89,J89,L89,N89) -> 0
A90: School Buildings | B90: 212 | C90: =E90-F90 -> 0 | E90: =SUM(G90,I90,K90,M90) -> 0 | F90: =SUM(H90,J90,L90,N90) -> 0
A91: Accumulated Depreciation - School Buildings | B91: 312 | D91: =F91-E91 -> 0 | E91: =SUM(G91,I91,K91,M91) -> 0 | F91: =SUM(H91,J91,L91,N91) -> 0
A92: Hospitals and Health Centers | B92: 213 | C92: =E92-F92 -> 0 | E92: =SUM(G92,I92,K92,M92) -> 0 | F92: =SUM(H92,J92,L92,N92) -> 0
A93: Accumulated Depreciation - Hospitals and Health Centers | B93: 313 | D93: =F93-E93 -> 0 | E93: =SUM(G93,I93,K93,M93) -> 0 | F93: =SUM(H93,J93,L93,N93) -> 0
A94: Markets and Slaughterhouses | B94: 214 | C94: =E94-F94 -> 0 | E94: =SUM(G94,I94,K94,M94) -> 0 | F94: =SUM(H94,J94,L94,N94) -> 0
A95: Accumulated Depreciation - Markets and Slaughterhouses | B95: 314 | D95: =F95-E95 -> 0 | E95: =SUM(G95,I95,K95,M95) -> 0 | F95: =SUM(H95,J95,L95,N95) -> 0
A96: Other Structures | B96: 215 | C96: =E96-F96 -> 0 | E96: =SUM(G96,I96,K96,M96) -> 0 | F96: =SUM(H96,J96,L96,N96) -> 0
A97: Accumulated Depreciation - Other Structures | B97: 315 | D97: =F97-E97 -> 0 | E97: =SUM(G97,I97,K97,M97) -> 0 | F97: =SUM(H97,J97,L97,N97) -> 0
A98: Leasehold Improvements, Land | B98: 218 | C98: =E98-F98 -> 0 | E98: =SUM(G98,I98,K98,M98) -> 0 | F98: =SUM(H98,J98,L98,N98) -> 0
A99: Accumulated Depreciation - Leasehold Improvements, Land | B99: 318 | D99: =F99-E99 -> 0 | E99: =SUM(G99,I99,K99,M99) -> 0 | F99: =SUM(H99,J99,L99,N99) -> 0
A100: Leasehold Improvements, Buildings | B100: 219 | C100: =E100-F100 -> 0 | E100: =SUM(G100,I100,K100,M100) -> 0 | F100: =SUM(H100,J100,L100,N100) -> 0
A101: Accumulated Depreciation - Leasehold Improvements, Buildings | B101: 319 | D101: =F101-E101 -> 0 | E101: =SUM(G101,I101,K101,M101) -> 0 | F101: =SUM(H101,J101,L101,N101) -> 0
A102: Other Leasehold Improvements | B102: 220 | C102: =E102-F102 -> 0 | E102: =SUM(G102,I102,K102,M102) -> 0 | F102: =SUM(H102,J102,L102,N102) -> 0
A103: Accumulated Depreciation - Other Leasehold Improvements | B103: 320 | D103: =F103-E103 -> 0 | E103: =SUM(G103,I103,K103,M103) -> 0 | F103: =SUM(H103,J103,L103,N103) -> 0
A104: Office Equipment | B104: 221 | C104: =E104-F104 -> 0 | E104: =SUM(G104,I104,K104,M104) -> 0 | F104: =SUM(H104,J104,L104,N104) -> 0
A105: Accumulated Depreciation - Office Equipment | B105: 321 | D105: =F105-E105 -> 0 | E105: =SUM(G105,I105,K105,M105) -> 0 | F105: =SUM(H105,J105,L105,N105) -> 0
...

Sheet TB-May
A1: Republic of the Philippines
A2: PROVINCE OF AGUSAN DEL SUR
A3: Gov. Democrito O. Plaza Government Center, Prosperidad
A5: TRUST FUND
A6: TRIAL BALANCE
A7: As of May 31, 2011
E9: =A7 -> As of May 31, 2011 | G9: Check Disbursement | I9: Cash Disbursement | K9: Cash Receipts | M9: General Journal
A11: Account Title | B11: Account Code | C11: Debit | D11: Credit | E11: Debit | F11: Credit | G11: Debit | H11: Credit | I11: Debit | J11: Credit | K11: Debit | L11: Credit | M11: Debit | N11: Credit
A13: Cash in Vault | B13: 101 | C13: =E13-F13 -> 0 | E13: =SUM(G13,I13,K13,M13) -> 6835876.3 | F13: =SUM(H13,J13,L13,N13) -> 6835876.3 | K13: 6835876.3 | L13: 6835876.3
A14: Cash - Collecting Officers | B14: 102 | C14: =E14-F14 -> 0 | E14: =SUM(G14,I14,K14,M14) -> 0 | F14: =SUM(H14,J14,L14,N14) -> 0
A15: Cash Disbursing Officers | B15: 103 | C15: =E15-F15 -> 0 | E15: =SUM(G15,I15,K15,M15) -> 0 | F15: =SUM(H15,J15,L15,N15) -> 0
A16: Petty Cash Fund | B16: 104 | C16: =E16-F16 -> 0 | E16: =SUM(G16,I16,K16,M16) -> 0 | F16: =SUM(H16,J16,L16,N16) -> 0
A17: Payroll Fund | B17: 106 | C17: =E17-F17 -> 3055.17 | E17: =SUM(G17,I17,K17,M17) -> 855808.91 | F17: =SUM(H17,J17,L17,N17) -> 852753.74 | G17: 855808.91 | J17: 848948.9 | L17: 3804.84
A18: Cash - Bangko Sentral ng Pilipinas | B18: 110 | C18: =E18-F18 -> 0 | E18: =SUM(G18,I18,K18,M18) -> 0 | F18: =SUM(H18,J18,L18,N18) -> 0
A19: Cash in Bank - Local Currency, Current Account | B19: 111 | C19: =E19-F19 -> 1646765.4 | E19: =SUM(G19,I19,K19,M19) -> 7473654.3 | F19: =SUM(H19,J19,L19,N19) -> 5826888.9 | H19: 5826888.9 | K19: 6835876.3 | M19: 637778
A20: Cash in Bank - Local Currency, SavingsAccount | B20: 112 | C20: =E20-F20 -> 0 | E20: =SUM(G20,I20,K20,M20) -> 0 | F20: =SUM(H20,J20,L20,N20) -> 0
A21: Cash in Bank - Local Currency, Time Deposits | B21: 113 | C21: =E21-F21 -> 0 | E21: =SUM(G21,I21,K21,M21) -> 0 | F21: =SUM(H21,J21,L21,N21) -> 0
A22: Cash - Bangko Sentral ng Pilipinas | B22: 114 | C22: =E22-F22 -> 0 | E22: =SUM(G22,I22,K22,M22) -> 0 | F22: =SUM(H22,J22,L22,N22) -> 0
A23: Cash in Bank - Foreign Currency, Current Account | B23: 115 | C23: =E23-F23 -> 0 | E23: =SUM(G23,I23,K23,M23) -> 0 | F23: =SUM(H23,J23,L23,N23) -> 0
A24: Cash in Bank - Foreign Currency, Savings Account | B24: 116 | C24: =E24-F24 -> 0 | E24: =SUM(G24,I24,K24,M24) -> 0 | F24: =SUM(H24,J24,L24,N24) -> 0
A25: Cash in Bank - Foreign Currency, Time Deposits | B25: 117 | C25: =E25-F25 -> 0 | E25: =SUM(G25,I25,K25,M25) -> 0 | F25: =SUM(H25,J25,L25,N25) -> 0
A26: Accounts Receivable | B26: 121 | C26: =E26-F26 -> 0 | E26: =SUM(G26,I26,K26,M26) -> 0 | F26: =SUM(H26,J26,L26,N26) -> 0
A27: Allowance for Doubtful Accounts | B27: 301 | C27: =E27-F27 -> 0 | E27: =SUM(G27,I27,K27,M27) -> 0 | F27: =SUM(H27,J27,L27,N27) -> 0
A28: Notes Receivable | B28: 122 | C28: =E28-F28 -> 0 | E28: =SUM(G28,I28,K28,M28) -> 0 | F28: =SUM(H28,J28,L28,N28) -> 0
A29: Due from Officers and Employees | B29: 123 | C29: =E29-F29 -> 0 | E29: =SUM(G29,I29,K29,M29) -> 0 | F29: =SUM(H29,J29,L29,N29) -> 0
A30: Loans Receivable - GOCCs | B30: 124 | C30: =E30-F30 -> 0 | E30: =SUM(G30,I30,K30,M30) -> 0 | F30: =SUM(H30,J30,L30,N30) -> 0
A31: Loans Receivable - LGUs | B31: 125 | C31: =E31-F31 -> 0 | E31: =SUM(G31,I31,K31,M31) -> 0 | F31: =SUM(H31,J31,L31,N31) -> 0
A32: Loans Receivable - Others | B32: 126 | C32: =E32-F32 -> 0 | E32: =SUM(G32,I32,K32,M32) -> 0 | F32: =SUM(H32,J32,L32,N32) -> 0
A33: Real Property Tax Receivable | B33: 127 | C33: =E33-F33 -> 0 | E33: =SUM(G33,I33,K33,M33) -> 0 | F33: =SUM(H33,J33,L33,N33) -> 0
A34: Special Education Tax Receivable | B34: 128 | C34: =E34-F34 -> 0 | E34: =SUM(G34,I34,K34,M34) -> 0 | F34: =SUM(H34,J34,L34,N34) -> 0
A35: Interests Receivable | B35: 129 | C35: =E35-F35 -> 0 | E35: =SUM(G35,I35,K35,M35) -> 0 | F35: =SUM(H35,J35,L35,N35) -> 0
... A37: Due from GOCCs | B37: 137 | C37: =E37-F37 -> 0 | E37: =SUM(G37,I37,K37,M37) -> 0 | F37: =SUM(H37,J37,L37,N37) -> 0
A38: Due from LGUs | B38: 138 | C38: =E38-F38 -> 0 | E38: =SUM(G38,I38,K38,M38) -> 0 | F38: =SUM(H38,J38,L38,N38) -> 0
A39: Due from NGOs/POs | B39: 139 | C39: =E39-F39 -> 0 | E39: =SUM(G39,I39,K39,M39) -> 0 | F39: =SUM(H39,J39,L39,N39) -> 0
A40: Due from Other Funds | B40: 144 | C40: =E40-F40 -> 0 | E40: =SUM(G40,I40,K40,M40) -> 0 | F40: =SUM(H40,J40,L40,N40) -> 0
A41: Receivables - Disallowances/Charges | B41: 146 | C41: =E41-F41 -> 0 | E41: =SUM(G41,I41,K41,M41) -> 0 | F41: =SUM(H41,J41,L41,N41) -> 0
A42: Advances to Officers and Employees | B42: 148 | C42: =E42-F42 -> 375223.52 | E42: =SUM(G42,I42,K42,M42) -> 400000 | F42: =SUM(H42,J42,L42,N42) -> 24776.48 | G42: 400000 | L42: 24776.48
A43: Other Receivables | B43: 149 | C43: =E43-F43 -> 0 | E43: =SUM(G43,I43,K43,M43) -> 0 | F43: =SUM(H43,J43,L43,N43) -> 0
A44: Raw Materials Inventory | B44: 151 | C44: =E44-F44 -> 0 | E44: =SUM(G44,I44,K44,M44) -> 0 | F44: =SUM(H44,J44,L44,N44) -> 0
A45: Work-In-Process Inventory | B45: 152 | C45: =E45-F45 -> 0 | E45: =SUM(G45,I45,K45,M45) -> 0 | F45: =SUM(H45,J45,L45,N45) -> 0
A46: Finished Goods Inventory | B46: 153 | C46: =E46-F46 -> 0 | E46: =SUM(G46,I46,K46,M46) -> 0 | F46: =SUM(H46,J46,L46,N46) -> 0
A47: Merchandise Inventory | B47: 154 | C47: =E47-F47 -> 0 | E47: =SUM(G47,I47,K47,M47) -> 0 | F47: =SUM(H47,J47,L47,N47) -> 0
A48: Office Supplies Inventory | B48: 155 | C48: =E48-F48 -> 0 | E48: =SUM(G48,I48,K48,M48) -> 0 | F48: =SUM(H48,J48,L48,N48) -> 0
A49: Accountable Forms Inventory | B49: 156 | C49: =E49-F49 -> 0 | E49: =SUM(G49,I49,K49,M49) -> 0 | F49: =SUM(H49,J49,L49,N49) -> 0
A50: Animal/Zoological Supplies Inventory | B50: 157 | C50: =E50-F50 -> 0 | E50: =SUM(G50,I50,K50,M50) -> 0 | F50: =SUM(H50,J50,L50,N50) -> 0
A51: Food Supplies Inventory | B51: 158 | C51: =E51-F51 -> 0 | E51: =SUM(G51,I51,K51,M51) -> 0 | F51: =SUM(H51,J51,L51,N51) -> 0
A52: Drugs and Medicines Inventory | B52: 159 | C52: =E52-F52 -> 99358.22 | E52: =SUM(G52,I52,K52,M52) -> 99358.22 | F52: =SUM(H52,J52,L52,N52) -> 0 | G52: 99358.22
A53: Medical, Dental and Laboratory Supplies Inventory | B53: 160 | C53: =E53-F53 -> 0 | E53: =SUM(G53,I53,K53,M53) -> 0 | F53: =SUM(H53,J53,L53,N53) -> 0
A54: Gasoline, Oil and Lubricants Inventory | B54: 161 | C54: =E54-F54 -> 890800 | E54: =SUM(G54,I54,K54,M54) -> 890800 | F54: =SUM(H54,J54,L54,N54) -> 0 | G54: 890800
A55: Agricultural Supplies Inventory | B55: 162 | C55: =E55-F55 -> 0 | E55: =SUM(G55,I55,K55,M55) -> 0 | F55: =SUM(H55,J55,L55,N55) -> 0
A56: Textbooks and Instructional Materials Inventory | B56: 163 | C56: =E56-F56 -> 0 | E56: =SUM(G56,I56,K56,M56) -> 0 | F56: =SUM(H56,J56,L56,N56) -> 0
A57: Military and Police Supplies Inventory | B57: 164 | C57: =E57-F57 -> 0 | E57: =SUM(G57,I57,K57,M57) -> 0 | F57: =SUM(H57,J57,L57,N57) -> 0
A58: Other Supplies Inventory | B58: 165 | C58: =E58-F58 -> 0 | E58: =SUM(G58,I58,K58,M58) -> 0 | F58: =SUM(H58,J58,L58,N58) -> 0
A59: Confiscated/Abandoned/Seized Goods Inventory | B59: 166 | C59: =E59-F59 -> 0 | E59: =SUM(G59,I59,K59,M59) -> 0 | F59: =SUM(H59,J59,L59,N59) -> 0
A60: Spare Parts Inventory | B60: 167 | C60: =E60-F60 -> 0 | E60: =SUM(G60,I60,K60,M60) -> 0 | F60: =SUM(H60,J60,L60,N60) -> 0
A61: Construction Materials Inventory | B61: 168 | C61: =E61-F61 -> 0 | E61: =SUM(G61,I61,K61,M61) -> 0 | F61: =SUM(H61,J61,L61,N61) -> 0
A62: Livestock Inventory | B62: 169 | C62: =E62-F62 -> 0 | E62: =SUM(G62,I62,K62,M62) -> 0 | F62: =SUM(H62,J62,L62,N62) -> 0
A63: Crops and Fruits Inventory | B63: 170 | C63: =E63-F63 -> 0 | E63: =SUM(G63,I63,K63,M63) -> 0 | F63: =SUM(H63,J63,L63,N63) -> 0
A64: Other Agricultural, Fishery and Forestry Products Inventory | B64: 176 | C64: =E64-F64 -> 0 | E64: =SUM(G64,I64,K64,M64) -> 0 | F64: =SUM(H64,J64,L64,N64) -> 0
A65: Prepaid Rent | B65: 177 | C65: =E65-F65 -> 0 | E65: =SUM(G65,I65,K65,M65) -> 0 | F65: =SUM(H65,J65,L65,N65) -> 0
A66: Prepaid Insurance | B66: 178 | C66: =E66-F66 -> 0 | E66: =SUM(G66,I66,K66,M66) -> 0 | F66: =SUM(H66,J66,L66,N66) -> 0
A67: Prepaid Interest | B67: 179 | C67: =E67-F67 -> 0 | E67: =SUM(G67,I67,K67,M67) -> 0 | F67: =SUM(H67,J67,L67,N67) -> 0
A68: Deposit on Letters of Credit | B68: 180 | C68: =E68-F68 -> 0 | E68: =SUM(G68,I68,K68,M68) -> 0 | F68: =SUM(H68,J68,L68,N68) -> 0
A69: Advances to Contractors | B69: 181 | C69: =E69-F69 -> -355923.02 | E69: =SUM(G69,I69,K69,M69) -> 0 | F69: =SUM(H69,J69,L69,N69) -> 355923.02 | H69: 355923.02
A70: Deferred Charges | B70: 182 | C70: =E70-F70 -> 0 | E70: =SUM(G70,I70,K70,M70) -> 0 | F70: =SUM(H70,J70,L70,N70) -> 0
A71: Other Prepaid Expenses | B71: 185 | C71: =E71-F71 -> 0 | E71: =SUM(G71,I71,K71,M71) -> 0 | F71: =SUM(H71,J71,L71,N71) -> 0
A72: Guaranty Deposits | B72: 186 | C72: =E72-F72 -> 0 | E72: =SUM(G72,I72,K72,M72) -> 0 | F72: =SUM(H72,J72,L72,N72) -> 0
A73: Other Current Assets | B73: 189 | C73: =E73-F73 -> 0 | E73: =SUM(G73,I73,K73,M73) -> 0 | F73: =SUM(H73,J73,L73,N73) -> 0
A74: Investments in Treasury Bills | B74: 191 | C74: =E74-F74 -> 0 | E74: =SUM(G74,I74,K74,M74) -> 0 | F74: =SUM(H74,J74,L74,N74) -> 0
A75: Investments in Stocks | B75: 192 | C75: =E75-F75 -> 0 | E75: =SUM(G75,I75,K75,M75) -> 0 | F75: =SUM(H75,J75,L75,N75) -> 0
A76: Investments in Bonds | B76: 193 | C76: =E76-F76 -> 0 | E76: =SUM(G76,I76,K76,M76) -> 0 | F76: =SUM(H76,J76,L76,N76) -> 0
A77: Other Investments and Marketable Securities | B77: 197 | C77: =E77-F77 -> 0 | E77: =SUM(G77,I77,K77,M77) -> 0 | F77: =SUM(H77,J77,L77,N77) -> 0
A78: Sinking Fund | B78: 198 | C78: =E78-F78 -> 0 | E78: =SUM(G78,I78,K78,M78) -> 0 | F78: =SUM(H78,J78,L78,N78) -> 0
A79: Land | B79: 201 | C79: =E79-F79 -> 0 | E79: =SUM(G79,I79,K79,M79) -> 0 | F79: =SUM(H79,J79,L79,N79) -> 0
A80: Land Improvements | B80: 202 | C80: =E80-F80 -> 0 | E80: =SUM(G80,I80,K80,M80) -> 0 | F80: =SUM(H80,J80,L80,N80) -> 0
A81: Accumulated Depreciation – Land Improvements | B81: 302 | D81: =F81-E81 -> 0 | E81: =SUM(G81,I81,K81,M81) -> 0 | F81: =SUM(H81,J81,L81,N81) -> 0
A82: Runways/Taxiways | B82: 203 | C82: =E82-F82 -> 0 | E82: =SUM(G82,I82,K82,M82) -> 0 | F82: =SUM(H82,J82,L82,N82) -> 0
A83: Accumulated Depreciation - Runways/Taxiways | B83: 303 | D83: =F83-E83 -> 0 | E83: =SUM(G83,I83,K83,M83) -> 0 | F83: =SUM(H83,J83,L83,N83) -> 0
A84: Railways | B84: 204 | C84: =E84-F84 -> 0 | E84: =SUM(G84,I84,K84,M84) -> 0 | F84: =SUM(H84,J84,L84,N84) -> 0
A85: Accumulated Depreciation - Railways | B85: 304 | D85: =F85-E85 -> 0 | E85: =SUM(G85,I85,K85,M85) -> 0 | F85: =SUM(H85,J85,L85,N85) -> 0
A86: Electrification, Power and Energy Structures | B86: 205 | C86: =E86-F86 -> 0 | E86: =SUM(G86,I86,K86,M86) -> 0 | F86: =SUM(H86,J86,L86,N86) -> 0
A87: Accumulated Depreciation - Electrification, Power and Energy | B87: 305 | D87: =F87-E87 -> 0 | E87: =SUM(G87,I87,K87,M87) -> 0 | F87: =SUM(H87,J87,L87,N87) -> 0
A88: Office Buildings | B88: 211 | C88: =E88-F88 -> 0 | E88: =SUM(G88,I88,K88,M88) -> 0 | F88: =SUM(H88,J88,L88,N88) -> 0
A89: Accumulated Depreciation - Office Buildings | B89: 311 | D89: =F89-E89 -> 0 | E89: =SUM(G89,I89,K89,M89) -> 0 | F89: =SUM(H89,J89,L89,N89) -> 0
A90: School Buildings | B90: 212 | C90: =E90-F90 -> 0 | E90: =SUM(G90,I90,K90,M90) -> 0 | F90: =SUM(H90,J90,L90,N90) -> 0
A91: Accumulated Depreciation - School Buildings | B91: 312 | D91: =F91-E91 -> 0 | E91: =SUM(G91,I91,K91,M91) -> 0 | F91: =SUM(H91,J91,L91,N91) -> 0
A92: Hospitals and Health Centers | B92: 213 | C92: =E92-F92 -> 0 | E92: =SUM(G92,I92,K92,M92) -> 0 | F92: =SUM(H92,J92,L92,N92) -> 0
A93: Accumulated Depreciation - Hospitals and Health Centers | B93: 313 | D93: =F93-E93 -> 0 | E93: =SUM(G93,I93,K93,M93) -> 0 | F93: =SUM(H93,J93,L93,N93) -> 0
A94: Markets and Slaughterhouses | B94: 214 | C94: =E94-F94 -> 0 | E94: =SUM(G94,I94,K94,M94) -> 0 | F94: =SUM(H94,J94,L94,N94) -> 0
A95: Accumulated Depreciation - Markets and Slaughterhouses | B95: 314 | D95: =F95-E95 -> 0 | E95: =SUM(G95,I95,K95,M95) -> 0 | F95: =SUM(H95,J95,L95,N95) -> 0
A96: Other Structures | B96: 215 | C96: =E96-F96 -> 0 | E96: =SUM(G96,I96,K96,M96) -> 0 | F96: =SUM(H96,J96,L96,N96) -> 0
A97: Accumulated Depreciation - Other Structures | B97: 315 | D97: =F97-E97 -> 0 | E97: =SUM(G97,I97,K97,M97) -> 0 | F97: =SUM(H97,J97,L97,N97) -> 0
A98: Leasehold Improvements, Land | B98: 218 | C98: =E98-F98 -> 0 | E98: =SUM(G98,I98,K98,M98) -> 0 | F98: =SUM(H98,J98,L98,N98) -> 0
A99: Accumulated Depreciation - Leasehold Improvements, Land | B99: 318 | D99: =F99-E99 -> 0 | E99: =SUM(G99,I99,K99,M99) -> 0 | F99: =SUM(H99,J99,L99,N99) -> 0
A100: Leasehold Improvements, Buildings | B100: 219 | C100: =E100-F100 -> 0 | E100: =SUM(G100,I100,K100,M100) -> 0 | F100: =SUM(H100,J100,L100,N100) -> 0
A101: Accumulated Depreciation - Leasehold Improvements, Buildings | B101: 319 | D101: =F101-E101 -> 0 | E101: =SUM(G101,I101,K101,M101) -> 0 | F101: =SUM(H101,J101,L101,N101) -> 0
A102: Other Leasehold Improvements | B102: 220 | C102: =E102-F102 -> 0 | E102: =SUM(G102,I102,K102,M102) -> 0 | F102: =SUM(H102,J102,L102,N102) -> 0
A103: Accumulated Depreciation - Other Leasehold Improvements | B103: 320 | D103: =F103-E103 -> 0 | E103: =SUM(G103,I103,K103,M103) -> 0 | F103: =SUM(H103,J103,L103,N103) -> 0
A104: Office Equipment | B104: 221 | C104: =E104-F104 -> 0 | E104: =SUM(G104,I104,K104,M104) -> 0 | F104: =SUM(H104,J104,L104,N104) -> 0
A105: Accumulated Depreciation - Office Equipment | B105: 321 | D105: =F105-E105 -> 0 | E105: =SUM(G105,I105,K105,M105) -> 0 | F105: =SUM(H105,J105,L105,N105) -> 0
...

Sheet TB-Jun
A1: Republic of the Philippines
A2: PROVINCE OF AGUSAN DEL SUR
A3: Gov. Democrito O. Plaza Government Center, Prosperidad
A5: TRUST FUND
A6: TRIAL BALANCE
A7: As of June 30, 2011
E9: =A7 -> As of June 30, 2011 | G9: Check Disbursement | I9: Cash Disbursement | K9: Cash Receipts | M9: General Journal
A11: Account Title | B11: Account Code | C11: Debit | D11: Credit | E11: Debit | F11: Credit | G11: Debit | H11: Credit | I11: Debit | J11: Credit | K11: Debit | L11: Credit | M11: Debit | N11: Credit
A13: Cash in Vault | B13: 101 | C13: =E13-F13 -> 0 | E13: =SUM(G13,I13,K13,M13) -> 7178151.9 | F13: =SUM(H13,J13,L13,N13) -> 7178151.9 | K13: 7178151.9 | L13: 7178151.9
A14: Cash - Collecting Officers | B14: 102 | C14: =E14-F14 -> 0 | E14: =SUM(G14,I14,K14,M14) -> 0 | F14: =SUM(H14,J14,L14,N14) -> 0
A15: Cash Disbursing Officers | B15: 103 | C15: =E15-F15 -> 0 | E15: =SUM(G15,I15,K15,M15) -> 0 | F15: =SUM(H15,J15,L15,N15) -> 0
A16: Petty Cash Fund | B16: 104 | C16: =E16-F16 -> 0 | E16: =SUM(G16,I16,K16,M16) -> 0 | F16: =SUM(H16,J16,L16,N16) -> 0
A17: Payroll Fund | B17: 106 | C17: =E17-F17 -> 0 | E17: =SUM(G17,I17,K17,M17) -> 729606.4 | F17: =SUM(H17,J17,L17,N17) -> 729606.4 | G17: 729606.4 | J17: 729606.4
A18: Cash - Bangko Sentral ng Pilipinas | B18: 110 | C18: =E18-F18 -> 0 | E18: =SUM(G18,I18,K18,M18) -> 0 | F18: =SUM(H18,J18,L18,N18) -> 0
A19: Cash in Bank - Local Currency, Current Account | B19: 111 | C19: =E19-F19 -> 460357.2 | E19: =SUM(G19,I19,K19,M19) -> 9117059.2 | F19: =SUM(H19,J19,L19,N19) -> 8656702 | H19: 8653202 | K19: 7178151.9 | M19: 1938907.4 | N19: 3500
A20: Cash in Bank - Local Currency, SavingsAccount | B20: 112 | C20: =E20-F20 -> 0 | E20: =SUM(G20,I20,K20,M20) -> 0 | F20: =SUM(H20,J20,L20,N20) -> 0
A21: Cash in Bank - Local Currency, Time Deposits | B21: 113 | C21: =E21-F21 -> 0 | E21: =SUM(G21,I21,K21,M21) -> 0 | F21: =SUM(H21,J21,L21,N21) -> 0
A22: Cash - Bangko Sentral ng Pilipinas | B22: 114 | C22: =E22-F22 -> 0 | E22: =SUM(G22,I22,K22,M22) -> 0 | F22: =SUM(H22,J22,L22,N22) -> 0
A23: Cash in Bank - Foreign Currency, Current Account | B23: 115 | C23: =E23-F23 -> 0 | E23: =SUM(G23,I23,K23,M23) -> 0 | F23: =SUM(H23,J23,L23,N23) -> 0
A24: Cash in Bank - Foreign Currency, Savings Account | B24: 116 | C24: =E24-F24 -> 0 | E24: =SUM(G24,I24,K24,M24) -> 0 | F24: =SUM(H24,J24,L24,N24) -> 0
A25: Cash in Bank - Foreign Currency, Time Deposits | B25: 117 | C25: =E25-F25 -> 0 | E25: =SUM(G25,I25,K25,M25) -> 0 | F25: =SUM(H25,J25,L25,N25) -> 0
A26: Accounts Receivable | B26: 121 | C26: =E26-F26 -> 0 | E26: =SUM(G26,I26,K26,M26) -> 0 | F26: =SUM(H26,J26,L26,N26) -> 0
A27: Allowance for Doubtful Accounts | B27: 301 | C27: =E27-F27 -> 0 | E27: =SUM(G27,I27,K27,M27) -> 0 | F27: =SUM(H27,J27,L27,N27) -> 0
A28: Notes Receivable | B28: 122 | C28: =E28-F28 -> 0 | E28: =SUM(G28,I28,K28,M28) -> 0 | F28: =SUM(H28,J28,L28,N28) -> 0
A29: Due from Officers and Employees | B29: 123 | C29: =E29-F29 -> 0 | E29: =SUM(G29,I29,K29,M29) -> 0 | F29: =SUM(H29,J29,L29,N29) -> 0
A30: Loans Receivable - GOCCs | B30: 124 | C30: =E30-F30 -> 0 | E30: =SUM(G30,I30,K30,M30) -> 0 | F30: =SUM(H30,J30,L30,N30) -> 0
A31: Loans Receivable - LGUs | B31: 125 | C31: =E31-F31 -> 0 | E31: =SUM(G31,I31,K31,M31) -> 0 | F31: =SUM(H31,J31,L31,N31) -> 0
A32: Loans Receivable - Others | B32: 126 | C32: =E32-F32 -> 0 | E32: =SUM(G32,I32,K32,M32) -> 0 | F32: =SUM(H32,J32,L32,N32) -> 0
A33: Real Property Tax Receivable | B33: 127 | C33: =E33-F33 -> 0 | E33: =SUM(G33,I33,K33,M33) -> 0 | F33: =SUM(H33,J33,L33,N33) -> 0
A34: Special Education Tax Receivable | B34: 128 | C34: =E34-F34 -> 0 | E34: =SUM(G34,I34,K34,M34) -> 0 | F34: =SUM(H34,J34,L34,N34) -> 0
A35: Interests Receivable | B35: 129 | C35: =E35-F35 -> 0 | E35: =SUM(G35,I35,K35,M35) -> 0 | F35: =SUM(H35,J35,L35,N35) -> 0
... A37: Due from GOCCs | B37: 137 | C37: =E37-F37 -> 0 | E37: =SUM(G37,I37,K37,M37) -> 0 | F37: =SUM(H37,J37,L37,N37) -> 0
A38: Due from LGUs | B38: 138 | C38: =E38-F38 -> 0 | E38: =SUM(G38,I38,K38,M38) -> 0 | F38: =SUM(H38,J38,L38,N38) -> 0
A39: Due from NGOs/POs | B39: 139 | C39: =E39-F39 -> 0 | E39: =SUM(G39,I39,K39,M39) -> 0 | F39: =SUM(H39,J39,L39,N39) -> 0
A40: Due from Other Funds | B40: 144 | C40: =E40-F40 -> 0 | E40: =SUM(G40,I40,K40,M40) -> 0 | F40: =SUM(H40,J40,L40,N40) -> 0
A41: Receivables - Disallowances/Charges | B41: 146 | C41: =E41-F41 -> 0 | E41: =SUM(G41,I41,K41,M41) -> 0 | F41: =SUM(H41,J41,L41,N41) -> 0
A42: Advances to Officers and Employees | B42: 148 | C42: =E42-F42 -> 28411 | E42: =SUM(G42,I42,K42,M42) -> 194920 | F42: =SUM(H42,J42,L42,N42) -> 166509 | G42: 194920 | L42: 16 | N42: 166493
A43: Other Receivables | B43: 149 | C43: =E43-F43 -> 30000 | E43: =SUM(G43,I43,K43,M43) -> 30000 | F43: =SUM(H43,J43,L43,N43) -> 0 | G43: 30000
A44: Raw Materials Inventory | B44: 151 | C44: =E44-F44 -> 0 | E44: =SUM(G44,I44,K44,M44) -> 0 | F44: =SUM(H44,J44,L44,N44) -> 0
A45: Work-In-Process Inventory | B45: 152 | C45: =E45-F45 -> 0 | E45: =SUM(G45,I45,K45,M45) -> 0 | F45: =SUM(H45,J45,L45,N45) -> 0
A46: Finished Goods Inventory | B46: 153 | C46: =E46-F46 -> 0 | E46: =SUM(G46,I46,K46,M46) -> 0 | F46: =SUM(H46,J46,L46,N46) -> 0
A47: Merchandise Inventory | B47: 154 | C47: =E47-F47 -> 0 | E47: =SUM(G47,I47,K47,M47) -> 0 | F47: =SUM(H47,J47,L47,N47) -> 0
A48: Office Supplies Inventory | B48: 155 | C48: =E48-F48 -> 0 | E48: =SUM(G48,I48,K48,M48) -> 0 | F48: =SUM(H48,J48,L48,N48) -> 0
A49: Accountable Forms Inventory | B49: 156 | C49: =E49-F49 -> 0 | E49: =SUM(G49,I49,K49,M49) -> 0 | F49: =SUM(H49,J49,L49,N49) -> 0
A50: Animal/Zoological Supplies Inventory | B50: 157 | C50: =E50-F50 -> 0 | E50: =SUM(G50,I50,K50,M50) -> 0 | F50: =SUM(H50,J50,L50,N50) -> 0
A51: Food Supplies Inventory | B51: 158 | C51: =E51-F51 -> 0 | E51: =SUM(G51,I51,K51,M51) -> 0 | F51: =SUM(H51,J51,L51,N51) -> 0
A52: Drugs and Medicines Inventory | B52: 159 | C52: =E52-F52 -> 545430 | E52: =SUM(G52,I52,K52,M52) -> 545430 | F52: =SUM(H52,J52,L52,N52) -> 0 | G52: 545430
A53: Medical, Dental and Laboratory Supplies Inventory | B53: 160 | C53: =E53-F53 -> 0 | E53: =SUM(G53,I53,K53,M53) -> 0 | F53: =SUM(H53,J53,L53,N53) -> 0
A54: Gasoline, Oil and Lubricants Inventory | B54: 161 | C54: =E54-F54 -> 616000 | E54: =SUM(G54,I54,K54,M54) -> 616000 | F54: =SUM(H54,J54,L54,N54) -> 0 | G54: 616000
A55: Agricultural Supplies Inventory | B55: 162 | C55: =E55-F55 -> 0 | E55: =SUM(G55,I55,K55,M55) -> 0 | F55: =SUM(H55,J55,L55,N55) -> 0
A56: Textbooks and Instructional Materials Inventory | B56: 163 | C56: =E56-F56 -> 0 | E56: =SUM(G56,I56,K56,M56) -> 0 | F56: =SUM(H56,J56,L56,N56) -> 0
A57: Military and Police Supplies Inventory | B57: 164 | C57: =E57-F57 -> 0 | E57: =SUM(G57,I57,K57,M57) -> 0 | F57: =SUM(H57,J57,L57,N57) -> 0
A58: Other Supplies Inventory | B58: 165 | C58: =E58-F58 -> 0 | E58: =SUM(G58,I58,K58,M58) -> 0 | F58: =SUM(H58,J58,L58,N58) -> 0
A59: Confiscated/Abandoned/Seized Goods Inventory | B59: 166 | C59: =E59-F59 -> 0 | E59: =SUM(G59,I59,K59,M59) -> 0 | F59: =SUM(H59,J59,L59,N59) -> 0
A60: Spare Parts Inventory | B60: 167 | C60: =E60-F60 -> 0 | E60: =SUM(G60,I60,K60,M60) -> 0 | F60: =SUM(H60,J60,L60,N60) -> 0
A61: Construction Materials Inventory | B61: 168 | C61: =E61-F61 -> 0 | E61: =SUM(G61,I61,K61,M61) -> 0 | F61: =SUM(H61,J61,L61,N61) -> 0
A62: Livestock Inventory | B62: 169 | C62: =E62-F62 -> 0 | E62: =SUM(G62,I62,K62,M62) -> 0 | F62: =SUM(H62,J62,L62,N62) -> 0
A63: Crops and Fruits Inventory | B63: 170 | C63: =E63-F63 -> 0 | E63: =SUM(G63,I63,K63,M63) -> 0 | F63: =SUM(H63,J63,L63,N63) -> 0
A64: Other Agricultural, Fishery and Forestry Products Inventory | B64: 176 | C64: =E64-F64 -> 0 | E64: =SUM(G64,I64,K64,M64) -> 0 | F64: =SUM(H64,J64,L64,N64) -> 0
A65: Prepaid Rent | B65: 177 | C65: =E65-F65 -> 0 | E65: =SUM(G65,I65,K65,M65) -> 0 | F65: =SUM(H65,J65,L65,N65) -> 0
A66: Prepaid Insurance | B66: 178 | C66: =E66-F66 -> 0 | E66: =SUM(G66,I66,K66,M66) -> 0 | F66: =SUM(H66,J66,L66,N66) -> 0
A67: Prepaid Interest | B67: 179 | C67: =E67-F67 -> 0 | E67: =SUM(G67,I67,K67,M67) -> 0 | F67: =SUM(H67,J67,L67,N67) -> 0
A68: Deposit on Letters of Credit | B68: 180 | C68: =E68-F68 -> 0 | E68: =SUM(G68,I68,K68,M68) -> 0 | F68: =SUM(H68,J68,L68,N68) -> 0
A69: Advances to Contractors | B69: 181 | C69: =E69-F69 -> 0 | E69: =SUM(G69,I69,K69,M69) -> 0 | F69: =SUM(H69,J69,L69,N69) -> 0
A70: Deferred Charges | B70: 182 | C70: =E70-F70 -> 0 | E70: =SUM(G70,I70,K70,M70) -> 0 | F70: =SUM(H70,J70,L70,N70) -> 0
A71: Other Prepaid Expenses | B71: 185 | C71: =E71-F71 -> 0 | E71: =SUM(G71,I71,K71,M71) -> 0 | F71: =SUM(H71,J71,L71,N71) -> 0
A72: Guaranty Deposits | B72: 186 | C72: =E72-F72 -> 0 | E72: =SUM(G72,I72,K72,M72) -> 0 | F72: =SUM(H72,J72,L72,N72) -> 0
A73: Other Current Assets | B73: 189 | C73: =E73-F73 -> 0 | E73: =SUM(G73,I73,K73,M73) -> 0 | F73: =SUM(H73,J73,L73,N73) -> 0
A74: Investments in Treasury Bills | B74: 191 | C74: =E74-F74 -> 0 | E74: =SUM(G74,I74,K74,M74) -> 0 | F74: =SUM(H74,J74,L74,N74) -> 0
A75: Investments in Stocks | B75: 192 | C75: =E75-F75 -> 0 | E75: =SUM(G75,I75,K75,M75) -> 0 | F75: =SUM(H75,J75,L75,N75) -> 0
A76: Investments in Bonds | B76: 193 | C76: =E76-F76 -> 0 | E76: =SUM(G76,I76,K76,M76) -> 0 | F76: =SUM(H76,J76,L76,N76) -> 0
A77: Other Investments and Marketable Securities | B77: 197 | C77: =E77-F77 -> 0 | E77: =SUM(G77,I77,K77,M77) -> 0 | F77: =SUM(H77,J77,L77,N77) -> 0
A78: Sinking Fund | B78: 198 | C78: =E78-F78 -> 0 | E78: =SUM(G78,I78,K78,M78) -> 0 | F78: =SUM(H78,J78,L78,N78) -> 0
A79: Land | B79: 201 | C79: =E79-F79 -> 0 | E79: =SUM(G79,I79,K79,M79) -> 0 | F79: =SUM(H79,J79,L79,N79) -> 0
A80: Land Improvements | B80: 202 | C80: =E80-F80 -> 0 | E80: =SUM(G80,I80,K80,M80) -> 0 | F80: =SUM(H80,J80,L80,N80) -> 0
A81: Accumulated Depreciation – Land Improvements | B81: 302 | D81: =F81-E81 -> 0 | E81: =SUM(G81,I81,K81,M81) -> 0 | F81: =SUM(H81,J81,L81,N81) -> 0
A82: Runways/Taxiways | B82: 203 | C82: =E82-F82 -> 0 | E82: =SUM(G82,I82,K82,M82) -> 0 | F82: =SUM(H82,J82,L82,N82) -> 0
A83: Accumulated Depreciation - Runways/Taxiways | B83: 303 | D83: =F83-E83 -> 0 | E83: =SUM(G83,I83,K83,M83) -> 0 | F83: =SUM(H83,J83,L83,N83) -> 0
A84: Railways | B84: 204 | C84: =E84-F84 -> 0 | E84: =SUM(G84,I84,K84,M84) -> 0 | F84: =SUM(H84,J84,L84,N84) -> 0
A85: Accumulated Depreciation - Railways | B85: 304 | D85: =F85-E85 -> 0 | E85: =SUM(G85,I85,K85,M85) -> 0 | F85: =SUM(H85,J85,L85,N85) -> 0
A86: Electrification, Power and Energy Structures | B86: 205 | C86: =E86-F86 -> 0 | E86: =SUM(G86,I86,K86,M86) -> 0 | F86: =SUM(H86,J86,L86,N86) -> 0
A87: Accumulated Depreciation - Electrification, Power and Energy | B87: 305 | D87: =F87-E87 -> 0 | E87: =SUM(G87,I87,K87,M87) -> 0 | F87: =SUM(H87,J87,L87,N87) -> 0
A88: Office Buildings | B88: 211 | C88: =E88-F88 -> 0 | E88: =SUM(G88,I88,K88,M88) -> 0 | F88: =SUM(H88,J88,L88,N88) -> 0
A89: Accumulated Depreciation - Office Buildings | B89: 311 | D89: =F89-E89 -> 0 | E89: =SUM(G89,I89,K89,M89) -> 0 | F89: =SUM(H89,J89,L89,N89) -> 0
A90: School Buildings | B90: 212 | C90: =E90-F90 -> 0 | E90: =SUM(G90,I90,K90,M90) -> 0 | F90: =SUM(H90,J90,L90,N90) -> 0
A91: Accumulated Depreciation - School Buildings | B91: 312 | D91: =F91-E91 -> 0 | E91: =SUM(G91,I91,K91,M91) -> 0 | F91: =SUM(H91,J91,L91,N91) -> 0
A92: Hospitals and Health Centers | B92: 213 | C92: =E92-F92 -> 0 | E92: =SUM(G92,I92,K92,M92) -> 0 | F92: =SUM(H92,J92,L92,N92) -> 0
A93: Accumulated Depreciation - Hospitals and Health Centers | B93: 313 | D93: =F93-E93 -> 0 | E93: =SUM(G93,I93,K93,M93) -> 0 | F93: =SUM(H93,J93,L93,N93) -> 0
A94: Markets and Slaughterhouses | B94: 214 | C94: =E94-F94 -> 0 | E94: =SUM(G94,I94,K94,M94) -> 0 | F94: =SUM(H94,J94,L94,N94) -> 0
A95: Accumulated Depreciation - Markets and Slaughterhouses | B95: 314 | D95: =F95-E95 -> 0 | E95: =SUM(G95,I95,K95,M95) -> 0 | F95: =SUM(H95,J95,L95,N95) -> 0
A96: Other Structures | B96: 215 | C96: =E96-F96 -> 0 | E96: =SUM(G96,I96,K96,M96) -> 0 | F96: =SUM(H96,J96,L96,N96) -> 0
A97: Accumulated Depreciation - Other Structures | B97: 315 | D97: =F97-E97 -> 0 | E97: =SUM(G97,I97,K97,M97) -> 0 | F97: =SUM(H97,J97,L97,N97) -> 0
A98: Leasehold Improvements, Land | B98: 218 | C98: =E98-F98 -> 0 | E98: =SUM(G98,I98,K98,M98) -> 0 | F98: =SUM(H98,J98,L98,N98) -> 0
A99: Accumulated Depreciation - Leasehold Improvements, Land | B99: 318 | D99: =F99-E99 -> 0 | E99: =SUM(G99,I99,K99,M99) -> 0 | F99: =SUM(H99,J99,L99,N99) -> 0
A100: Leasehold Improvements, Buildings | B100: 219 | C100: =E100-F100 -> 0 | E100: =SUM(G100,I100,K100,M100) -> 0 | F100: =SUM(H100,J100,L100,N100) -> 0
A101: Accumulated Depreciation - Leasehold Improvements, Buildings | B101: 319 | D101: =F101-E101 -> 0 | E101: =SUM(G101,I101,K101,M101) -> 0 | F101: =SUM(H101,J101,L101,N101) -> 0
A102: Other Leasehold Improvements | B102: 220 | C102: =E102-F102 -> 0 | E102: =SUM(G102,I102,K102,M102) -> 0 | F102: =SUM(H102,J102,L102,N102) -> 0
A103: Accumulated Depreciation - Other Leasehold Improvements | B103: 320 | D103: =F103-E103 -> 0 | E103: =SUM(G103,I103,K103,M103) -> 0 | F103: =SUM(H103,J103,L103,N103) -> 0
A104: Office Equipment | B104: 221 | C104: =E104-F104 -> 0 | E104: =SUM(G104,I104,K104,M104) -> 0 | F104: =SUM(H104,J104,L104,N104) -> 0
A105: Accumulated Depreciation - Office Equipment | B105: 321 | D105: =F105-E105 -> 0 | E105: =SUM(G105,I105,K105,M105) -> 0 | F105: =SUM(H105,J105,L105,N105) -> 0
...

Sheet TB-Jul
A1: Republic of the Philippines
A2: PROVINCE OF AGUSAN DEL SUR
A3: Gov. Democrito O. Plaza Government Center, Prosperidad
A5: TRUST FUND
A6: TRIAL BALANCE
A7: As of July 31, 2011
E9: =A7 -> As of July 31, 2011 | G9: Check Disbursement | I9: Cash Disbursement | K9: Cash Receipts | M9: General Journal
A11: Account Title | B11: Account Code | C11: Debit | D11: Credit | E11: Debit | F11: Credit | G11: Debit | H11: Credit | I11: Debit | J11: Credit | K11: Debit | L11: Credit | M11: Debit | N11: Credit
A13: Cash in Vault | B13: 101 | C13: =E13-F13 -> 0 | E13: =SUM(G13,I13,K13,M13) -> 5645314.5 | F13: =SUM(H13,J13,L13,N13) -> 5645314.5 | K13: 5645314.5 | L13: 5645314.5
A14: Cash - Collecting Officers | B14: 102 | C14: =E14-F14 -> 0 | E14: =SUM(G14,I14,K14,M14) -> 0 | F14: =SUM(H14,J14,L14,N14) -> 0
A15: Cash Disbursing Officers | B15: 103 | C15: =E15-F15 -> 0 | E15: =SUM(G15,I15,K15,M15) -> 0 | F15: =SUM(H15,J15,L15,N15) -> 0
A16: Petty Cash Fund | B16: 104 | C16: =E16-F16 -> 0 | E16: =SUM(G16,I16,K16,M16) -> 0 | F16: =SUM(H16,J16,L16,N16) -> 0
A17: Payroll Fund | B17: 106 | C17: =E17-F17 -> 843.3 | E17: =SUM(G17,I17,K17,M17) -> 2662222.4 | F17: =SUM(H17,J17,L17,N17) -> 2661379.1 | G17: 2662222.1 | J17: 2661379.1 | M17: 0.3
A18: Cash - Bangko Sentral ng Pilipinas | B18: 110 | C18: =E18-F18 -> 0 | E18: =SUM(G18,I18,K18,M18) -> 0 | F18: =SUM(H18,J18,L18,N18) -> 0
A19: Cash in Bank - Local Currency, Current Account | B19: 111 | C19: =E19-F19 -> -5459228.6 | E19: =SUM(G19,I19,K19,M19) -> 5911904.6 | F19: =SUM(H19,J19,L19,N19) -> 11371133 | H19: 11337173 | K19: 5678280.5 | M19: 233624.15 | N19: 33960.45
A20: Cash in Bank - Local Currency, SavingsAccount | B20: 112 | C20: =E20-F20 -> 0 | E20: =SUM(G20,I20,K20,M20) -> 0 | F20: =SUM(H20,J20,L20,N20) -> 0
A21: Cash in Bank - Local Currency, Time Deposits | B21: 113 | C21: =E21-F21 -> 0 | E21: =SUM(G21,I21,K21,M21) -> 0 | F21: =SUM(H21,J21,L21,N21) -> 0
A22: Cash - Bangko Sentral ng Pilipinas | B22: 114 | C22: =E22-F22 -> 0 | E22: =SUM(G22,I22,K22,M22) -> 0 | F22: =SUM(H22,J22,L22,N22) -> 0
A23: Cash in Bank - Foreign Currency, Current Account | B23: 115 | C23: =E23-F23 -> 0 | E23: =SUM(G23,I23,K23,M23) -> 0 | F23: =SUM(H23,J23,L23,N23) -> 0
A24: Cash in Bank - Foreign Currency, Savings Account | B24: 116 | C24: =E24-F24 -> 0 | E24: =SUM(G24,I24,K24,M24) -> 0 | F24: =SUM(H24,J24,L24,N24) -> 0
A25: Cash in Bank - Foreign Currency, Time Deposits | B25: 117 | C25: =E25-F25 -> 0 | E25: =SUM(G25,I25,K25,M25) -> 0 | F25: =SUM(H25,J25,L25,N25) -> 0
A26: Accounts Receivable | B26: 121 | C26: =E26-F26 -> 0 | E26: =SUM(G26,I26,K26,M26) -> 0 | F26: =SUM(H26,J26,L26,N26) -> 0
A27: Allowance for Doubtful Accounts | B27: 301 | C27: =E27-F27 -> 0 | E27: =SUM(G27,I27,K27,M27) -> 0 | F27: =SUM(H27,J27,L27,N27) -> 0
A28: Notes Receivable | B28: 122 | C28: =E28-F28 -> 0 | E28: =SUM(G28,I28,K28,M28) -> 0 | F28: =SUM(H28,J28,L28,N28) -> 0
A29: Due from Officers and Employees | B29: 123 | C29: =E29-F29 -> 0 | E29: =SUM(G29,I29,K29,M29) -> 0 | F29: =SUM(H29,J29,L29,N29) -> 0
A30: Loans Receivable - GOCCs | B30: 124 | C30: =E30-F30 -> 0 | E30: =SUM(G30,I30,K30,M30) -> 0 | F30: =SUM(H30,J30,L30,N30) -> 0
A31: Loans Receivable - LGUs | B31: 125 | C31: =E31-F31 -> 0 | E31: =SUM(G31,I31,K31,M31) -> 0 | F31: =SUM(H31,J31,L31,N31) -> 0
A32: Loans Receivable - Others | B32: 126 | C32: =E32-F32 -> 0 | E32: =SUM(G32,I32,K32,M32) -> 0 | F32: =SUM(H32,J32,L32,N32) -> 0
A33: Real Property Tax Receivable | B33: 127 | C33: =E33-F33 -> 0 | E33: =SUM(G33,I33,K33,M33) -> 0 | F33: =SUM(H33,J33,L33,N33) -> 0
A34: Special Education Tax Receivable | B34: 128 | C34: =E34-F34 -> 0 | E34: =SUM(G34,I34,K34,M34) -> 0 | F34: =SUM(H34,J34,L34,N34) -> 0
A35: Interests Receivable | B35: 129 | C35: =E35-F35 -> 0 | E35: =SUM(G35,I35,K35,M35) -> 0 | F35: =SUM(H35,J35,L35,N35) -> 0
... A37: Due from GOCCs | B37: 137 | C37: =E37-F37 -> 0 | E37: =SUM(G37,I37,K37,M37) -> 0 | F37: =SUM(H37,J37,L37,N37) -> 0
A38: Due from LGUs | B38: 138 | C38: =E38-F38 -> 0 | E38: =SUM(G38,I38,K38,M38) -> 0 | F38: =SUM(H38,J38,L38,N38) -> 0
A39: Due from NGOs/POs | B39: 139 | C39: =E39-F39 -> 0 | E39: =SUM(G39,I39,K39,M39) -> 0 | F39: =SUM(H39,J39,L39,N39) -> 0
A40: Due from Other Funds | B40: 144 | C40: =E40-F40 -> 0 | E40: =SUM(G40,I40,K40,M40) -> 0 | F40: =SUM(H40,J40,L40,N40) -> 0
A41: Receivables - Disallowances/Charges | B41: 146 | C41: =E41-F41 -> 0 | E41: =SUM(G41,I41,K41,M41) -> 0 | F41: =SUM(H41,J41,L41,N41) -> 0
A42: Advances to Officers and Employees | B42: 148 | C42: =E42-F42 -> 22500 | E42: =SUM(G42,I42,K42,M42) -> 22500 | F42: =SUM(H42,J42,L42,N42) -> 0 | G42: 22500
A43: Other Receivables | B43: 149 | C43: =E43-F43 -> 0 | E43: =SUM(G43,I43,K43,M43) -> 0 | F43: =SUM(H43,J43,L43,N43) -> 0
A44: Raw Materials Inventory | B44: 151 | C44: =E44-F44 -> 0 | E44: =SUM(G44,I44,K44,M44) -> 0 | F44: =SUM(H44,J44,L44,N44) -> 0
A45: Work-In-Process Inventory | B45: 152 | C45: =E45-F45 -> 0 | E45: =SUM(G45,I45,K45,M45) -> 0 | F45: =SUM(H45,J45,L45,N45) -> 0
A46: Finished Goods Inventory | B46: 153 | C46: =E46-F46 -> 0 | E46: =SUM(G46,I46,K46,M46) -> 0 | F46: =SUM(H46,J46,L46,N46) -> 0
A47: Merchandise Inventory | B47: 154 | C47: =E47-F47 -> 0 | E47: =SUM(G47,I47,K47,M47) -> 0 | F47: =SUM(H47,J47,L47,N47) -> 0
A48: Office Supplies Inventory | B48: 155 | C48: =E48-F48 -> 0 | E48: =SUM(G48,I48,K48,M48) -> 0 | F48: =SUM(H48,J48,L48,N48) -> 0
A49: Accountable Forms Inventory | B49: 156 | C49: =E49-F49 -> 0 | E49: =SUM(G49,I49,K49,M49) -> 0 | F49: =SUM(H49,J49,L49,N49) -> 0
A50: Animal/Zoological Supplies Inventory | B50: 157 | C50: =E50-F50 -> 0 | E50: =SUM(G50,I50,K50,M50) -> 0 | F50: =SUM(H50,J50,L50,N50) -> 0
A51: Food Supplies Inventory | B51: 158 | C51: =E51-F51 -> 0 | E51: =SUM(G51,I51,K51,M51) -> 0 | F51: =SUM(H51,J51,L51,N51) -> 0
A52: Drugs and Medicines Inventory | B52: 159 | C52: =E52-F52 -> 181699 | E52: =SUM(G52,I52,K52,M52) -> 181699 | F52: =SUM(H52,J52,L52,N52) -> 0 | G52: 181699
A53: Medical, Dental and Laboratory Supplies Inventory | B53: 160 | C53: =E53-F53 -> 0 | E53: =SUM(G53,I53,K53,M53) -> 0 | F53: =SUM(H53,J53,L53,N53) -> 0
A54: Gasoline, Oil and Lubricants Inventory | B54: 161 | C54: =E54-F54 -> 1207040 | E54: =SUM(G54,I54,K54,M54) -> 1207040 | F54: =SUM(H54,J54,L54,N54) -> 0 | G54: 1207040
A55: Agricultural Supplies Inventory | B55: 162 | C55: =E55-F55 -> 0 | E55: =SUM(G55,I55,K55,M55) -> 0 | F55: =SUM(H55,J55,L55,N55) -> 0
A56: Textbooks and Instructional Materials Inventory | B56: 163 | C56: =E56-F56 -> 0 | E56: =SUM(G56,I56,K56,M56) -> 0 | F56: =SUM(H56,J56,L56,N56) -> 0
A57: Military and Police Supplies Inventory | B57: 164 | C57: =E57-F57 -> 0 | E57: =SUM(G57,I57,K57,M57) -> 0 | F57: =SUM(H57,J57,L57,N57) -> 0
A58: Other Supplies Inventory | B58: 165 | C58: =E58-F58 -> 0 | E58: =SUM(G58,I58,K58,M58) -> 0 | F58: =SUM(H58,J58,L58,N58) -> 0
A59: Confiscated/Abandoned/Seized Goods Inventory | B59: 166 | C59: =E59-F59 -> 0 | E59: =SUM(G59,I59,K59,M59) -> 0 | F59: =SUM(H59,J59,L59,N59) -> 0
A60: Spare Parts Inventory | B60: 167 | C60: =E60-F60 -> 0 | E60: =SUM(G60,I60,K60,M60) -> 0 | F60: =SUM(H60,J60,L60,N60) -> 0
A61: Construction Materials Inventory | B61: 168 | C61: =E61-F61 -> 0 | E61: =SUM(G61,I61,K61,M61) -> 0 | F61: =SUM(H61,J61,L61,N61) -> 0
A62: Livestock Inventory | B62: 169 | C62: =E62-F62 -> 0 | E62: =SUM(G62,I62,K62,M62) -> 0 | F62: =SUM(H62,J62,L62,N62) -> 0
A63: Crops and Fruits Inventory | B63: 170 | C63: =E63-F63 -> 0 | E63: =SUM(G63,I63,K63,M63) -> 0 | F63: =SUM(H63,J63,L63,N63) -> 0
A64: Other Agricultural, Fishery and Forestry Products Inventory | B64: 176 | C64: =E64-F64 -> 0 | E64: =SUM(G64,I64,K64,M64) -> 0 | F64: =SUM(H64,J64,L64,N64) -> 0
A65: Prepaid Rent | B65: 177 | C65: =E65-F65 -> 0 | E65: =SUM(G65,I65,K65,M65) -> 0 | F65: =SUM(H65,J65,L65,N65) -> 0
A66: Prepaid Insurance | B66: 178 | C66: =E66-F66 -> 0 | E66: =SUM(G66,I66,K66,M66) -> 0 | F66: =SUM(H66,J66,L66,N66) -> 0
A67: Prepaid Interest | B67: 179 | C67: =E67-F67 -> 0 | E67: =SUM(G67,I67,K67,M67) -> 0 | F67: =SUM(H67,J67,L67,N67) -> 0
A68: Deposit on Letters of Credit | B68: 180 | C68: =E68-F68 -> 0 | E68: =SUM(G68,I68,K68,M68) -> 0 | F68: =SUM(H68,J68,L68,N68) -> 0
A69: Advances to Contractors | B69: 181 | C69: =E69-F69 -> -170754.75 | E69: =SUM(G69,I69,K69,M69) -> 0 | F69: =SUM(H69,J69,L69,N69) -> 170754.75 | H69: 170754.75
A70: Deferred Charges | B70: 182 | C70: =E70-F70 -> 0 | E70: =SUM(G70,I70,K70,M70) -> 0 | F70: =SUM(H70,J70,L70,N70) -> 0
A71: Other Prepaid Expenses | B71: 185 | C71: =E71-F71 -> 0 | E71: =SUM(G71,I71,K71,M71) -> 0 | F71: =SUM(H71,J71,L71,N71) -> 0
A72: Guaranty Deposits | B72: 186 | C72: =E72-F72 -> 0 | E72: =SUM(G72,I72,K72,M72) -> 0 | F72: =SUM(H72,J72,L72,N72) -> 0
A73: Other Current Assets | B73: 189 | C73: =E73-F73 -> 0 | E73: =SUM(G73,I73,K73,M73) -> 0 | F73: =SUM(H73,J73,L73,N73) -> 0
A74: Investments in Treasury Bills | B74: 191 | C74: =E74-F74 -> 0 | E74: =SUM(G74,I74,K74,M74) -> 0 | F74: =SUM(H74,J74,L74,N74) -> 0
A75: Investments in Stocks | B75: 192 | C75: =E75-F75 -> 0 | E75: =SUM(G75,I75,K75,M75) -> 0 | F75: =SUM(H75,J75,L75,N75) -> 0
A76: Investments in Bonds | B76: 193 | C76: =E76-F76 -> 0 | E76: =SUM(G76,I76,K76,M76) -> 0 | F76: =SUM(H76,J76,L76,N76) -> 0
A77: Other Investments and Marketable Securities | B77: 197 | C77: =E77-F77 -> 0 | E77: =SUM(G77,I77,K77,M77) -> 0 | F77: =SUM(H77,J77,L77,N77) -> 0
A78: Sinking Fund | B78: 198 | C78: =E78-F78 -> 0 | E78: =SUM(G78,I78,K78,M78) -> 0 | F78: =SUM(H78,J78,L78,N78) -> 0
A79: Land | B79: 201 | C79: =E79-F79 -> 0 | E79: =SUM(G79,I79,K79,M79) -> 0 | F79: =SUM(H79,J79,L79,N79) -> 0
A80: Land Improvements | B80: 202 | C80: =E80-F80 -> 0 | E80: =SUM(G80,I80,K80,M80) -> 0 | F80: =SUM(H80,J80,L80,N80) -> 0
A81: Accumulated Depreciation – Land Improvements | B81: 302 | D81: =F81-E81 -> 0 | E81: =SUM(G81,I81,K81,M81) -> 0 | F81: =SUM(H81,J81,L81,N81) -> 0
A82: Runways/Taxiways | B82: 203 | C82: =E82-F82 -> 0 | E82: =SUM(G82,I82,K82,M82) -> 0 | F82: =SUM(H82,J82,L82,N82) -> 0
A83: Accumulated Depreciation - Runways/Taxiways | B83: 303 | D83: =F83-E83 -> 0 | E83: =SUM(G83,I83,K83,M83) -> 0 | F83: =SUM(H83,J83,L83,N83) -> 0
A84: Railways | B84: 204 | C84: =E84-F84 -> 0 | E84: =SUM(G84,I84,K84,M84) -> 0 | F84: =SUM(H84,J84,L84,N84) -> 0
A85: Accumulated Depreciation - Railways | B85: 304 | D85: =F85-E85 -> 0 | E85: =SUM(G85,I85,K85,M85) -> 0 | F85: =SUM(H85,J85,L85,N85) -> 0
A86: Electrification, Power and Energy Structures | B86: 205 | C86: =E86-F86 -> 0 | E86: =SUM(G86,I86,K86,M86) -> 0 | F86: =SUM(H86,J86,L86,N86) -> 0
A87: Accumulated Depreciation - Electrification, Power and Energy | B87: 305 | D87: =F87-E87 -> 0 | E87: =SUM(G87,I87,K87,M87) -> 0 | F87: =SUM(H87,J87,L87,N87) -> 0
A88: Office Buildings | B88: 211 | C88: =E88-F88 -> 0 | E88: =SUM(G88,I88,K88,M88) -> 0 | F88: =SUM(H88,J88,L88,N88) -> 0
A89: Accumulated Depreciation - Office Buildings | B89: 311 | D89: =F89-E89 -> 0 | E89: =SUM(G89,I89,K89,M89) -> 0 | F89: =SUM(H89,J89,L89,N89) -> 0
A90: School Buildings | B90: 212 | C90: =E90-F90 -> 0 | E90: =SUM(G90,I90,K90,M90) -> 0 | F90: =SUM(H90,J90,L90,N90) -> 0
A91: Accumulated Depreciation - School Buildings | B91: 312 | D91: =F91-E91 -> 0 | E91: =SUM(G91,I91,K91,M91) -> 0 | F91: =SUM(H91,J91,L91,N91) -> 0
A92: Hospitals and Health Centers | B92: 213 | C92: =E92-F92 -> 0 | E92: =SUM(G92,I92,K92,M92) -> 0 | F92: =SUM(H92,J92,L92,N92) -> 0
A93: Accumulated Depreciation - Hospitals and Health Centers | B93: 313 | D93: =F93-E93 -> 0 | E93: =SUM(G93,I93,K93,M93) -> 0 | F93: =SUM(H93,J93,L93,N93) -> 0
A94: Markets and Slaughterhouses | B94: 214 | C94: =E94-F94 -> 0 | E94: =SUM(G94,I94,K94,M94) -> 0 | F94: =SUM(H94,J94,L94,N94) -> 0
A95: Accumulated Depreciation - Markets and Slaughterhouses | B95: 314 | D95: =F95-E95 -> 0 | E95: =SUM(G95,I95,K95,M95) -> 0 | F95: =SUM(H95,J95,L95,N95) -> 0
A96: Other Structures | B96: 215 | C96: =E96-F96 -> 0 | E96: =SUM(G96,I96,K96,M96) -> 0 | F96: =SUM(H96,J96,L96,N96) -> 0
A97: Accumulated Depreciation - Other Structures | B97: 315 | D97: =F97-E97 -> 0 | E97: =SUM(G97,I97,K97,M97) -> 0 | F97: =SUM(H97,J97,L97,N97) -> 0
A98: Leasehold Improvements, Land | B98: 218 | C98: =E98-F98 -> 0 | E98: =SUM(G98,I98,K98,M98) -> 0 | F98: =SUM(H98,J98,L98,N98) -> 0
A99: Accumulated Depreciation - Leasehold Improvements, Land | B99: 318 | D99: =F99-E99 -> 0 | E99: =SUM(G99,I99,K99,M99) -> 0 | F99: =SUM(H99,J99,L99,N99) -> 0
A100: Leasehold Improvements, Buildings | B100: 219 | C100: =E100-F100 -> 0 | E100: =SUM(G100,I100,K100,M100) -> 0 | F100: =SUM(H100,J100,L100,N100) -> 0
A101: Accumulated Depreciation - Leasehold Improvements, Buildings | B101: 319 | D101: =F101-E101 -> 0 | E101: =SUM(G101,I101,K101,M101) -> 0 | F101: =SUM(H101,J101,L101,N101) -> 0
A102: Other Leasehold Improvements | B102: 220 | C102: =E102-F102 -> 0 | E102: =SUM(G102,I102,K102,M102) -> 0 | F102: =SUM(H102,J102,L102,N102) -> 0
A103: Accumulated Depreciation - Other Leasehold Improvements | B103: 320 | D103: =F103-E103 -> 0 | E103: =SUM(G103,I103,K103,M103) -> 0 | F103: =SUM(H103,J103,L103,N103) -> 0
A104: Office Equipment | B104: 221 | C104: =E104-F104 -> 0 | E104: =SUM(G104,I104,K104,M104) -> 0 | F104: =SUM(H104,J104,L104,N104) -> 0
A105: Accumulated Depreciation - Office Equipment | B105: 321 | D105: =F105-E105 -> 0 | E105: =SUM(G105,I105,K105,M105) -> 0 | F105: =SUM(H105,J105,L105,N105) -> 0
...

Sheet TB-Aug
A1: Republic of the Philippines
A2: PROVINCE OF AGUSAN DEL SUR
A3: Gov. Democrito O. Plaza Government Center, Prosperidad
A5: TRUST FUND
A6: TRIAL BALANCE
A7: As of August 31, 2011
E9: =A7 -> As of August 31, 2011 | G9: Check Disbursement | I9: Cash Disbursement | K9: Cash Receipts | M9: General Journal
A11: Account Title | B11: Account Code | C11: Debit | D11: Credit | E11: Debit | F11: Credit | G11: Debit | H11: Credit | I11: Debit | J11: Credit | K11: Debit | L11: Credit | M11: Debit | N11: Credit
A13: Cash in Vault | B13: 101 | C13: =E13-F13 -> 0 | E13: =SUM(G13,I13,K13,M13) -> 25269350 | F13: =SUM(H13,J13,L13,N13) -> 25269350 | K13: 25269350 | L13: 25269350
A14: Cash - Collecting Officers | B14: 102 | C14: =E14-F14 -> 0 | E14: =SUM(G14,I14,K14,M14) -> 0 | F14: =SUM(H14,J14,L14,N14) -> 0
A15: Cash Disbursing Officers | B15: 103 | C15: =E15-F15 -> 0 | E15: =SUM(G15,I15,K15,M15) -> 0 | F15: =SUM(H15,J15,L15,N15) -> 0
A16: Petty Cash Fund | B16: 104 | C16: =E16-F16 -> 0 | E16: =SUM(G16,I16,K16,M16) -> 0 | F16: =SUM(H16,J16,L16,N16) -> 0
A17: Payroll Fund | B17: 106 | C17: =E17-F17 -> -0.3 | E17: =SUM(G17,I17,K17,M17) -> 408632.85 | F17: =SUM(H17,J17,L17,N17) -> 408633.15 | G17: 408632.85 | J17: 408632.85 | N17: 0.3
A18: Cash - Bangko Sentral ng Pilipinas | B18: 110 | C18: =E18-F18 -> 0 | E18: =SUM(G18,I18,K18,M18) -> 0 | F18: =SUM(H18,J18,L18,N18) -> 0
A19: Cash in Bank - Local Currency, Current Account | B19: 111 | C19: =E19-F19 -> 33125168 | E19: =SUM(G19,I19,K19,M19) -> 41795058 | F19: =SUM(H19,J19,L19,N19) -> 8669890.2 | H19: 8669890.2 | K19: 25269350 | M19: =16525707.98+0.3 -> 16525708
A20: Cash in Bank - Local Currency, SavingsAccount | B20: 112 | C20: =E20-F20 -> 0 | E20: =SUM(G20,I20,K20,M20) -> 0 | F20: =SUM(H20,J20,L20,N20) -> 0
A21: Cash in Bank - Local Currency, Time Deposits | B21: 113 | C21: =E21-F21 -> 0 | E21: =SUM(G21,I21,K21,M21) -> 0 | F21: =SUM(H21,J21,L21,N21) -> 0
A22: Cash - Bangko Sentral ng Pilipinas | B22: 114 | C22: =E22-F22 -> 0 | E22: =SUM(G22,I22,K22,M22) -> 0 | F22: =SUM(H22,J22,L22,N22) -> 0
A23: Cash in Bank - Foreign Currency, Current Account | B23: 115 | C23: =E23-F23 -> 0 | E23: =SUM(G23,I23,K23,M23) -> 0 | F23: =SUM(H23,J23,L23,N23) -> 0
A24: Cash in Bank - Foreign Currency, Savings Account | B24: 116 | C24: =E24-F24 -> 0 | E24: =SUM(G24,I24,K24,M24) -> 0 | F24: =SUM(H24,J24,L24,N24) -> 0
A25: Cash in Bank - Foreign Currency, Time Deposits | B25: 117 | C25: =E25-F25 -> 0 | E25: =SUM(G25,I25,K25,M25) -> 0 | F25: =SUM(H25,J25,L25,N25) -> 0
A26: Accounts Receivable | B26: 121 | C26: =E26-F26 -> 0 | E26: =SUM(G26,I26,K26,M26) -> 0 | F26: =SUM(H26,J26,L26,N26) -> 0
A27: Allowance for Doubtful Accounts | B27: 301 | C27: =E27-F27 -> 0 | E27: =SUM(G27,I27,K27,M27) -> 0 | F27: =SUM(H27,J27,L27,N27) -> 0
A28: Notes Receivable | B28: 122 | C28: =E28-F28 -> 0 | E28: =SUM(G28,I28,K28,M28) -> 0 | F28: =SUM(H28,J28,L28,N28) -> 0
A29: Due from Officers and Employees | B29: 123 | C29: =E29-F29 -> 0 | E29: =SUM(G29,I29,K29,M29) -> 0 | F29: =SUM(H29,J29,L29,N29) -> 0
A30: Loans Receivable - GOCCs | B30: 124 | C30: =E30-F30 -> 0 | E30: =SUM(G30,I30,K30,M30) -> 0 | F30: =SUM(H30,J30,L30,N30) -> 0
A31: Loans Receivable - LGUs | B31: 125 | C31: =E31-F31 -> 0 | E31: =SUM(G31,I31,K31,M31) -> 0 | F31: =SUM(H31,J31,L31,N31) -> 0
A32: Loans Receivable - Others | B32: 126 | C32: =E32-F32 -> 0 | E32: =SUM(G32,I32,K32,M32) -> 0 | F32: =SUM(H32,J32,L32,N32) -> 0
A33: Real Property Tax Receivable | B33: 127 | C33: =E33-F33 -> 0 | E33: =SUM(G33,I33,K33,M33) -> 0 | F33: =SUM(H33,J33,L33,N33) -> 0
A34: Special Education Tax Receivable | B34: 128 | C34: =E34-F34 -> 0 | E34: =SUM(G34,I34,K34,M34) -> 0 | F34: =SUM(H34,J34,L34,N34) -> 0
A35: Interests Receivable | B35: 129 | C35: =E35-F35 -> 0 | E35: =SUM(G35,I35,K35,M35) -> 0 | F35: =SUM(H35,J35,L35,N35) -> 0
... A37: Due from GOCCs | B37: 137 | C37: =E37-F37 -> 0 | E37: =SUM(G37,I37,K37,M37) -> 0 | F37: =SUM(H37,J37,L37,N37) -> 0
A38: Due from LGUs | B38: 138 | C38: =E38-F38 -> 0 | E38: =SUM(G38,I38,K38,M38) -> 0 | F38: =SUM(H38,J38,L38,N38) -> 0
A39: Due from NGOs/POs | B39: 139 | C39: =E39-F39 -> 0 | E39: =SUM(G39,I39,K39,M39) -> 0 | F39: =SUM(H39,J39,L39,N39) -> 0
A40: Due from Other Funds | B40: 144 | C40: =E40-F40 -> 0 | E40: =SUM(G40,I40,K40,M40) -> 0 | F40: =SUM(H40,J40,L40,N40) -> 0
A41: Receivables - Disallowances/Charges | B41: 146 | C41: =E41-F41 -> 0 | E41: =SUM(G41,I41,K41,M41) -> 0 | F41: =SUM(H41,J41,L41,N41) -> 0
A42: Advances to Officers and Employees | B42: 148 | C42: =E42-F42 -> 50000 | E42: =SUM(G42,I42,K42,M42) -> 50000 | F42: =SUM(H42,J42,L42,N42) -> 0 | G42: 50000
A43: Other Receivables | B43: 149 | C43: =E43-F43 -> 35000 | E43: =SUM(G43,I43,K43,M43) -> 35000 | F43: =SUM(H43,J43,L43,N43) -> 0 | G43: 35000
A44: Raw Materials Inventory | B44: 151 | C44: =E44-F44 -> 0 | E44: =SUM(G44,I44,K44,M44) -> 0 | F44: =SUM(H44,J44,L44,N44) -> 0
A45: Work-In-Process Inventory | B45: 152 | C45: =E45-F45 -> 0 | E45: =SUM(G45,I45,K45,M45) -> 0 | F45: =SUM(H45,J45,L45,N45) -> 0
A46: Finished Goods Inventory | B46: 153 | C46: =E46-F46 -> 0 | E46: =SUM(G46,I46,K46,M46) -> 0 | F46: =SUM(H46,J46,L46,N46) -> 0
A47: Merchandise Inventory | B47: 154 | C47: =E47-F47 -> 0 | E47: =SUM(G47,I47,K47,M47) -> 0 | F47: =SUM(H47,J47,L47,N47) -> 0
A48: Office Supplies Inventory | B48: 155 | C48: =E48-F48 -> 0 | E48: =SUM(G48,I48,K48,M48) -> 0 | F48: =SUM(H48,J48,L48,N48) -> 0
A49: Accountable Forms Inventory | B49: 156 | C49: =E49-F49 -> 0 | E49: =SUM(G49,I49,K49,M49) -> 0 | F49: =SUM(H49,J49,L49,N49) -> 0
A50: Animal/Zoological Supplies Inventory | B50: 157 | C50: =E50-F50 -> 0 | E50: =SUM(G50,I50,K50,M50) -> 0 | F50: =SUM(H50,J50,L50,N50) -> 0
A51: Food Supplies Inventory | B51: 158 | C51: =E51-F51 -> 0 | E51: =SUM(G51,I51,K51,M51) -> 0 | F51: =SUM(H51,J51,L51,N51) -> 0
A52: Drugs and Medicines Inventory | B52: 159 | C52: =E52-F52 -> 313051 | E52: =SUM(G52,I52,K52,M52) -> 313051 | F52: =SUM(H52,J52,L52,N52) -> 0 | G52: 313051
A53: Medical, Dental and Laboratory Supplies Inventory | B53: 160 | C53: =E53-F53 -> 0 | E53: =SUM(G53,I53,K53,M53) -> 0 | F53: =SUM(H53,J53,L53,N53) -> 0
A54: Gasoline, Oil and Lubricants Inventory | B54: 161 | C54: =E54-F54 -> 1255775.9 | E54: =SUM(G54,I54,K54,M54) -> 1255775.9 | F54: =SUM(H54,J54,L54,N54) -> 0 | G54: 1255775.9
A55: Agricultural Supplies Inventory | B55: 162 | C55: =E55-F55 -> 0 | E55: =SUM(G55,I55,K55,M55) -> 0 | F55: =SUM(H55,J55,L55,N55) -> 0
A56: Textbooks and Instructional Materials Inventory | B56: 163 | C56: =E56-F56 -> 0 | E56: =SUM(G56,I56,K56,M56) -> 0 | F56: =SUM(H56,J56,L56,N56) -> 0
A57: Military and Police Supplies Inventory | B57: 164 | C57: =E57-F57 -> 0 | E57: =SUM(G57,I57,K57,M57) -> 0 | F57: =SUM(H57,J57,L57,N57) -> 0
A58: Other Supplies Inventory | B58: 165 | C58: =E58-F58 -> 0 | E58: =SUM(G58,I58,K58,M58) -> 0 | F58: =SUM(H58,J58,L58,N58) -> 0
A59: Confiscated/Abandoned/Seized Goods Inventory | B59: 166 | C59: =E59-F59 -> 0 | E59: =SUM(G59,I59,K59,M59) -> 0 | F59: =SUM(H59,J59,L59,N59) -> 0
A60: Spare Parts Inventory | B60: 167 | C60: =E60-F60 -> 0 | E60: =SUM(G60,I60,K60,M60) -> 0 | F60: =SUM(H60,J60,L60,N60) -> 0
A61: Construction Materials Inventory | B61: 168 | C61: =E61-F61 -> 0 | E61: =SUM(G61,I61,K61,M61) -> 0 | F61: =SUM(H61,J61,L61,N61) -> 0
A62: Livestock Inventory | B62: 169 | C62: =E62-F62 -> 0 | E62: =SUM(G62,I62,K62,M62) -> 0 | F62: =SUM(H62,J62,L62,N62) -> 0
A63: Crops and Fruits Inventory | B63: 170 | C63: =E63-F63 -> 0 | E63: =SUM(G63,I63,K63,M63) -> 0 | F63: =SUM(H63,J63,L63,N63) -> 0
A64: Other Agricultural, Fishery and Forestry Products Inventory | B64: 176 | C64: =E64-F64 -> 0 | E64: =SUM(G64,I64,K64,M64) -> 0 | F64: =SUM(H64,J64,L64,N64) -> 0
A65: Prepaid Rent | B65: 177 | C65: =E65-F65 -> 0 | E65: =SUM(G65,I65,K65,M65) -> 0 | F65: =SUM(H65,J65,L65,N65) -> 0
A66: Prepaid Insurance | B66: 178 | C66: =E66-F66 -> 0 | E66: =SUM(G66,I66,K66,M66) -> 0 | F66: =SUM(H66,J66,L66,N66) -> 0
A67: Prepaid Interest | B67: 179 | C67: =E67-F67 -> 0 | E67: =SUM(G67,I67,K67,M67) -> 0 | F67: =SUM(H67,J67,L67,N67) -> 0
A68: Deposit on Letters of Credit | B68: 180 | C68: =E68-F68 -> 0 | E68: =SUM(G68,I68,K68,M68) -> 0 | F68: =SUM(H68,J68,L68,N68) -> 0
A69: Advances to Contractors | B69: 181 | C69: =E69-F69 -> 0 | E69: =SUM(G69,I69,K69,M69) -> 0 | F69: =SUM(H69,J69,L69,N69) -> 0
A70: Deferred Charges | B70: 182 | C70: =E70-F70 -> 0 | E70: =SUM(G70,I70,K70,M70) -> 0 | F70: =SUM(H70,J70,L70,N70) -> 0
A71: Other Prepaid Expenses | B71: 185 | C71: =E71-F71 -> 0 | E71: =SUM(G71,I71,K71,M71) -> 0 | F71: =SUM(H71,J71,L71,N71) -> 0
A72: Guaranty Deposits | B72: 186 | C72: =E72-F72 -> 0 | E72: =SUM(G72,I72,K72,M72) -> 0 | F72: =SUM(H72,J72,L72,N72) -> 0
A73: Other Current Assets | B73: 189 | C73: =E73-F73 -> 0 | E73: =SUM(G73,I73,K73,M73) -> 0 | F73: =SUM(H73,J73,L73,N73) -> 0
A74: Investments in Treasury Bills | B74: 191 | C74: =E74-F74 -> 0 | E74: =SUM(G74,I74,K74,M74) -> 0 | F74: =SUM(H74,J74,L74,N74) -> 0
A75: Investments in Stocks | B75: 192 | C75: =E75-F75 -> 0 | E75: =SUM(G75,I75,K75,M75) -> 0 | F75: =SUM(H75,J75,L75,N75) -> 0
A76: Investments in Bonds | B76: 193 | C76: =E76-F76 -> 0 | E76: =SUM(G76,I76,K76,M76) -> 0 | F76: =SUM(H76,J76,L76,N76) -> 0
A77: Other Investments and Marketable Securities | B77: 197 | C77: =E77-F77 -> 0 | E77: =SUM(G77,I77,K77,M77) -> 0 | F77: =SUM(H77,J77,L77,N77) -> 0
A78: Sinking Fund | B78: 198 | C78: =E78-F78 -> 0 | E78: =SUM(G78,I78,K78,M78) -> 0 | F78: =SUM(H78,J78,L78,N78) -> 0
A79: Land | B79: 201 | C79: =E79-F79 -> 0 | E79: =SUM(G79,I79,K79,M79) -> 0 | F79: =SUM(H79,J79,L79,N79) -> 0
A80: Land Improvements | B80: 202 | C80: =E80-F80 -> 0 | E80: =SUM(G80,I80,K80,M80) -> 0 | F80: =SUM(H80,J80,L80,N80) -> 0
A81: Accumulated Depreciation – Land Improvements | B81: 302 | D81: =F81-E81 -> 0 | E81: =SUM(G81,I81,K81,M81) -> 0 | F81: =SUM(H81,J81,L81,N81) -> 0
A82: Runways/Taxiways | B82: 203 | C82: =E82-F82 -> 0 | E82: =SUM(G82,I82,K82,M82) -> 0 | F82: =SUM(H82,J82,L82,N82) -> 0
A83: Accumulated Depreciation - Runways/Taxiways | B83: 303 | D83: =F83-E83 -> 0 | E83: =SUM(G83,I83,K83,M83) -> 0 | F83: =SUM(H83,J83,L83,N83) -> 0
A84: Railways | B84: 204 | C84: =E84-F84 -> 0 | E84: =SUM(G84,I84,K84,M84) -> 0 | F84: =SUM(H84,J84,L84,N84) -> 0
A85: Accumulated Depreciation - Railways | B85: 304 | D85: =F85-E85 -> 0 | E85: =SUM(G85,I85,K85,M85) -> 0 | F85: =SUM(H85,J85,L85,N85) -> 0
A86: Electrification, Power and Energy Structures | B86: 205 | C86: =E86-F86 -> 0 | E86: =SUM(G86,I86,K86,M86) -> 0 | F86: =SUM(H86,J86,L86,N86) -> 0
A87: Accumulated Depreciation - Electrification, Power and Energy | B87: 305 | D87: =F87-E87 -> 0 | E87: =SUM(G87,I87,K87,M87) -> 0 | F87: =SUM(H87,J87,L87,N87) -> 0
A88: Office Buildings | B88: 211 | C88: =E88-F88 -> 0 | E88: =SUM(G88,I88,K88,M88) -> 0 | F88: =SUM(H88,J88,L88,N88) -> 0
A89: Accumulated Depreciation - Office Buildings | B89: 311 | D89: =F89-E89 -> 0 | E89: =SUM(G89,I89,K89,M89) -> 0 | F89: =SUM(H89,J89,L89,N89) -> 0
A90: School Buildings | B90: 212 | C90: =E90-F90 -> 0 | E90: =SUM(G90,I90,K90,M90) -> 0 | F90: =SUM(H90,J90,L90,N90) -> 0
A91: Accumulated Depreciation - School Buildings | B91: 312 | D91: =F91-E91 -> 0 | E91: =SUM(G91,I91,K91,M91) -> 0 | F91: =SUM(H91,J91,L91,N91) -> 0
A92: Hospitals and Health Centers | B92: 213 | C92: =E92-F92 -> 0 | E92: =SUM(G92,I92,K92,M92) -> 0 | F92: =SUM(H92,J92,L92,N92) -> 0
A93: Accumulated Depreciation - Hospitals and Health Centers | B93: 313 | D93: =F93-E93 -> 0 | E93: =SUM(G93,I93,K93,M93) -> 0 | F93: =SUM(H93,J93,L93,N93) -> 0
A94: Markets and Slaughterhouses | B94: 214 | C94: =E94-F94 -> 0 | E94: =SUM(G94,I94,K94,M94) -> 0 | F94: =SUM(H94,J94,L94,N94) -> 0
A95: Accumulated Depreciation - Markets and Slaughterhouses | B95: 314 | D95: =F95-E95 -> 0 | E95: =SUM(G95,I95,K95,M95) -> 0 | F95: =SUM(H95,J95,L95,N95) -> 0
A96: Other Structures | B96: 215 | C96: =E96-F96 -> 0 | E96: =SUM(G96,I96,K96,M96) -> 0 | F96: =SUM(H96,J96,L96,N96) -> 0
A97: Accumulated Depreciation - Other Structures | B97: 315 | D97: =F97-E97 -> 0 | E97: =SUM(G97,I97,K97,M97) -> 0 | F97: =SUM(H97,J97,L97,N97) -> 0
A98: Leasehold Improvements, Land | B98: 218 | C98: =E98-F98 -> 0 | E98: =SUM(G98,I98,K98,M98) -> 0 | F98: =SUM(H98,J98,L98,N98) -> 0
A99: Accumulated Depreciation - Leasehold Improvements, Land | B99: 318 | D99: =F99-E99 -> 0 | E99: =SUM(G99,I99,K99,M99) -> 0 | F99: =SUM(H99,J99,L99,N99) -> 0
A100: Leasehold Improvements, Buildings | B100: 219 | C100: =E100-F100 -> 0 | E100: =SUM(G100,I100,K100,M100) -> 0 | F100: =SUM(H100,J100,L100,N100) -> 0
A101: Accumulated Depreciation - Leasehold Improvements, Buildings | B101: 319 | D101: =F101-E101 -> 0 | E101: =SUM(G101,I101,K101,M101) -> 0 | F101: =SUM(H101,J101,L101,N101) -> 0
A102: Other Leasehold Improvements | B102: 220 | C102: =E102-F102 -> 0 | E102: =SUM(G102,I102,K102,M102) -> 0 | F102: =SUM(H102,J102,L102,N102) -> 0
A103: Accumulated Depreciation - Other Leasehold Improvements | B103: 320 | D103: =F103-E103 -> 0 | E103: =SUM(G103,I103,K103,M103) -> 0 | F103: =SUM(H103,J103,L103,N103) -> 0
A104: Office Equipment | B104: 221 | C104: =E104-F104 -> 0 | E104: =SUM(G104,I104,K104,M104) -> 0 | F104: =SUM(H104,J104,L104,N104) -> 0
A105: Accumulated Depreciation - Office Equipment | B105: 321 | D105: =F105-E105 -> 0 | E105: =SUM(G105,I105,K105,M105) -> 0 | F105: =SUM(H105,J105,L105,N105) -> 0
...

Sheet TB-Sep
A1: Republic of the Philippines
A2: PROVINCE OF AGUSAN DEL SUR
A3: Gov. Democrito O. Plaza Government Center, Prosperidad
A5: TRUST FUND
A6: TRIAL BALANCE
A7: As of September 30, 2011
E9: =A7 -> As of September 30, 2011 | G9: Check Disbursement | I9: Cash Disbursement | K9: Cash Receipts | M9: General Journal
A11: Account Title | B11: Account Code | C11: Debit | D11: Credit | E11: Debit | F11: Credit | G11: Debit | H11: Credit | I11: Debit | J11: Credit | K11: Debit | L11: Credit | M11: Debit | N11: Credit
A13: Cash in Vault | B13: 101 | C13: =E13-F13 -> 0 | E13: =SUM(G13,I13,K13,M13) -> 0 | F13: =SUM(H13,J13,L13,N13) -> 0
A14: Cash - Collecting Officers | B14: 102 | C14: =E14-F14 -> 0 | E14: =SUM(G14,I14,K14,M14) -> 0 | F14: =SUM(H14,J14,L14,N14) -> 0
A15: Cash Disbursing Officers | B15: 103 | C15: =E15-F15 -> 0 | E15: =SUM(G15,I15,K15,M15) -> 0 | F15: =SUM(H15,J15,L15,N15) -> 0
A16: Petty Cash Fund | B16: 104 | C16: =E16-F16 -> 0 | E16: =SUM(G16,I16,K16,M16) -> 0 | F16: =SUM(H16,J16,L16,N16) -> 0
A17: Payroll Fund | B17: 106 | C17: =E17-F17 -> 0 | E17: =SUM(G17,I17,K17,M17) -> 0 | F17: =SUM(H17,J17,L17,N17) -> 0
A18: Cash - Bangko Sentral ng Pilipinas | B18: 110 | C18: =E18-F18 -> 0 | E18: =SUM(G18,I18,K18,M18) -> 0 | F18: =SUM(H18,J18,L18,N18) -> 0
A19: Cash in Bank - Local Currency, Current Account | B19: 111 | C19: =E19-F19 -> 0 | E19: =SUM(G19,I19,K19,M19) -> 0 | F19: =SUM(H19,J19,L19,N19) -> 0
A20: Cash in Bank - Local Currency, SavingsAccount | B20: 112 | C20: =E20-F20 -> 0 | E20: =SUM(G20,I20,K20,M20) -> 0 | F20: =SUM(H20,J20,L20,N20) -> 0
A21: Cash in Bank - Local Currency, Time Deposits | B21: 113 | C21: =E21-F21 -> 0 | E21: =SUM(G21,I21,K21,M21) -> 0 | F21: =SUM(H21,J21,L21,N21) -> 0
A22: Cash - Bangko Sentral ng Pilipinas | B22: 114 | C22: =E22-F22 -> 0 | E22: =SUM(G22,I22,K22,M22) -> 0 | F22: =SUM(H22,J22,L22,N22) -> 0
A23: Cash in Bank - Foreign Currency, Current Account | B23: 115 | C23: =E23-F23 -> 0 | E23: =SUM(G23,I23,K23,M23) -> 0 | F23: =SUM(H23,J23,L23,N23) -> 0
A24: Cash in Bank - Foreign Currency, Savings Account | B24: 116 | C24: =E24-F24 -> 0 | E24: =SUM(G24,I24,K24,M24) -> 0 | F24: =SUM(H24,J24,L24,N24) -> 0
A25: Cash in Bank - Foreign Currency, Time Deposits | B25: 117 | C25: =E25-F25 -> 0 | E25: =SUM(G25,I25,K25,M25) -> 0 | F25: =SUM(H25,J25,L25,N25) -> 0
A26: Accounts Receivable | B26: 121 | C26: =E26-F26 -> 0 | E26: =SUM(G26,I26,K26,M26) -> 0 | F26: =SUM(H26,J26,L26,N26) -> 0
A27: Allowance for Doubtful Accounts | B27: 301 | C27: =E27-F27 -> 0 | E27: =SUM(G27,I27,K27,M27) -> 0 | F27: =SUM(H27,J27,L27,N27) -> 0
A28: Notes Receivable | B28: 122 | C28: =E28-F28 -> 0 | E28: =SUM(G28,I28,K28,M28) -> 0 | F28: =SUM(H28,J28,L28,N28) -> 0
A29: Due from Officers and Employees | B29: 123 | C29: =E29-F29 -> 0 | E29: =SUM(G29,I29,K29,M29) -> 0 | F29: =SUM(H29,J29,L29,N29) -> 0
A30: Loans Receivable - GOCCs | B30: 124 | C30: =E30-F30 -> 0 | E30: =SUM(G30,I30,K30,M30) -> 0 | F30: =SUM(H30,J30,L30,N30) -> 0
A31: Loans Receivable - LGUs | B31: 125 | C31: =E31-F31 -> 0 | E31: =SUM(G31,I31,K31,M31) -> 0 | F31: =SUM(H31,J31,L31,N31) -> 0
A32: Loans Receivable - Others | B32: 126 | C32: =E32-F32 -> 0 | E32: =SUM(G32,I32,K32,M32) -> 0 | F32: =SUM(H32,J32,L32,N32) -> 0
A33: Real Property Tax Receivable | B33: 127 | C33: =E33-F33 -> 0 | E33: =SUM(G33,I33,K33,M33) -> 0 | F33: =SUM(H33,J33,L33,N33) -> 0
A34: Special Education Tax Receivable | B34: 128 | C34: =E34-F34 -> 0 | E34: =SUM(G34,I34,K34,M34) -> 0 | F34: =SUM(H34,J34,L34,N34) -> 0
A35: Interests Receivable | B35: 129 | C35: =E35-F35 -> 0 | E35: =SUM(G35,I35,K35,M35) -> 0 | F35: =SUM(H35,J35,L35,N35) -> 0
... A37: Due from GOCCs | B37: 137 | C37: =E37-F37 -> 0 | E37: =SUM(G37,I37,K37,M37) -> 0 | F37: =SUM(H37,J37,L37,N37) -> 0
A38: Due from LGUs | B38: 138 | C38: =E38-F38 -> 0 | E38: =SUM(G38,I38,K38,M38) -> 0 | F38: =SUM(H38,J38,L38,N38) -> 0
A39: Due from NGOs/POs | B39: 139 | C39: =E39-F39 -> 0 | E39: =SUM(G39,I39,K39,M39) -> 0 | F39: =SUM(H39,J39,L39,N39) -> 0
A40: Due from Other Funds | B40: 144 | C40: =E40-F40 -> 0 | E40: =SUM(G40,I40,K40,M40) -> 0 | F40: =SUM(H40,J40,L40,N40) -> 0
A41: Receivables - Disallowances/Charges | B41: 146 | C41: =E41-F41 -> 0 | E41: =SUM(G41,I41,K41,M41) -> 0 | F41: =SUM(H41,J41,L41,N41) -> 0
A42: Advances to Officers and Employees | B42: 148 | C42: =E42-F42 -> 0 | E42: =SUM(G42,I42,K42,M42) -> 0 | F42: =SUM(H42,J42,L42,N42) -> 0
A43: Other Receivables | B43: 149 | C43: =E43-F43 -> 0 | E43: =SUM(G43,I43,K43,M43) -> 0 | F43: =SUM(H43,J43,L43,N43) -> 0
A44: Raw Materials Inventory | B44: 151 | C44: =E44-F44 -> 0 | E44: =SUM(G44,I44,K44,M44) -> 0 | F44: =SUM(H44,J44,L44,N44) -> 0
A45: Work-In-Process Inventory | B45: 152 | C45: =E45-F45 -> 0 | E45: =SUM(G45,I45,K45,M45) -> 0 | F45: =SUM(H45,J45,L45,N45) -> 0
A46: Finished Goods Inventory | B46: 153 | C46: =E46-F46 -> 0 | E46: =SUM(G46,I46,K46,M46) -> 0 | F46: =SUM(H46,J46,L46,N46) -> 0
A47: Merchandise Inventory | B47: 154 | C47: =E47-F47 -> 0 | E47: =SUM(G47,I47,K47,M47) -> 0 | F47: =SUM(H47,J47,L47,N47) -> 0
A48: Office Supplies Inventory | B48: 155 | C48: =E48-F48 -> 0 | E48: =SUM(G48,I48,K48,M48) -> 0 | F48: =SUM(H48,J48,L48,N48) -> 0
A49: Accountable Forms Inventory | B49: 156 | C49: =E49-F49 -> 0 | E49: =SUM(G49,I49,K49,M49) -> 0 | F49: =SUM(H49,J49,L49,N49) -> 0
A50: Animal/Zoological Supplies Inventory | B50: 157 | C50: =E50-F50 -> 0 | E50: =SUM(G50,I50,K50,M50) -> 0 | F50: =SUM(H50,J50,L50,N50) -> 0
A51: Food Supplies Inventory | B51: 158 | C51: =E51-F51 -> 0 | E51: =SUM(G51,I51,K51,M51) -> 0 | F51: =SUM(H51,J51,L51,N51) -> 0
A52: Drugs and Medicines Inventory | B52: 159 | C52: =E52-F52 -> 0 | E52: =SUM(G52,I52,K52,M52) -> 0 | F52: =SUM(H52,J52,L52,N52) -> 0
... A57: Military and Police Supplies Inventory | B57: 164 | C57: =E57-F57 -> 0 | E57: =SUM(G57,I57,K57,M57) -> 0 | F57: =SUM(H57,J57,L57,N57) -> 0
A58: Other Supplies Inventory | B58: 165 | C58: =E58-F58 -> 0 | E58: =SUM(G58,I58,K58,M58) -> 0 | F58: =SUM(H58,J58,L58,N58) -> 0
A59: Confiscated/Abandoned/Seized Goods Inventory | B59: 166 | C59: =E59-F59 -> 0 | E59: =SUM(G59,I59,K59,M59) -> 0 | F59: =SUM(H59,J59,L59,N59) -> 0
A60: Spare Parts Inventory | B60: 167 | C60: =E60-F60 -> 0 | E60: =SUM(G60,I60,K60,M60) -> 0 | F60: =SUM(H60,J60,L60,N60) -> 0
A61: Construction Materials Inventory | B61: 168 | C61: =E61-F61 -> 0 | E61: =SUM(G61,I61,K61,M61) -> 0 | F61: =SUM(H61,J61,L61,N61) -> 0
A62: Livestock Inventory | B62: 169 | C62: =E62-F62 -> 0 | E62: =SUM(G62,I62,K62,M62) -> 0 | F62: =SUM(H62,J62,L62,N62) -> 0
A63: Crops and Fruits Inventory | B63: 170 | C63: =E63-F63 -> 0 | E63: =SUM(G63,I63,K63,M63) -> 0 | F63: =SUM(H63,J63,L63,N63) -> 0
A64: Other Agricultural, Fishery and Forestry Products Inventory | B64: 176 | C64: =E64-F64 -> 0 | E64: =SUM(G64,I64,K64,M64) -> 0 | F64: =SUM(H64,J64,L64,N64) -> 0
A65: Prepaid Rent | B65: 177 | C65: =E65-F65 -> 0 | E65: =SUM(G65,I65,K65,M65) -> 0 | F65: =SUM(H65,J65,L65,N65) -> 0
A66: Prepaid Insurance | B66: 178 | C66: =E66-F66 -> 0 | E66: =SUM(G66,I66,K66,M66) -> 0 | F66: =SUM(H66,J66,L66,N66) -> 0
A67: Prepaid Interest | B67: 179 | C67: =E67-F67 -> 0 | E67: =SUM(G67,I67,K67,M67) -> 0 | F67: =SUM(H67,J67,L67,N67) -> 0
A68: Deposit on Letters of Credit | B68: 180 | C68: =E68-F68 -> 0 | E68: =SUM(G68,I68,K68,M68) -> 0 | F68: =SUM(H68,J68,L68,N68) -> 0
A69: Advances to Contractors | B69: 181 | C69: =E69-F69 -> 0 | E69: =SUM(G69,I69,K69,M69) -> 0 | F69: =SUM(H69,J69,L69,N69) -> 0
A70: Deferred Charges | B70: 182 | C70: =E70-F70 -> 0 | E70: =SUM(G70,I70,K70,M70) -> 0 | F70: =SUM(H70,J70,L70,N70) -> 0
A71: Other Prepaid Expenses | B71: 185 | C71: =E71-F71 -> 0 | E71: =SUM(G71,I71,K71,M71) -> 0 | F71: =SUM(H71,J71,L71,N71) -> 0
A72: Guaranty Deposits | B72: 186 | C72: =E72-F72 -> 0 | E72: =SUM(G72,I72,K72,M72) -> 0 | F72: =SUM(H72,J72,L72,N72) -> 0
A73: Other Current Assets | B73: 189 | C73: =E73-F73 -> 0 | E73: =SUM(G73,I73,K73,M73) -> 0 | F73: =SUM(H73,J73,L73,N73) -> 0
A74: Investments in Treasury Bills | B74: 191 | C74: =E74-F74 -> 0 | E74: =SUM(G74,I74,K74,M74) -> 0 | F74: =SUM(H74,J74,L74,N74) -> 0
A75: Investments in Stocks | B75: 192 | C75: =E75-F75 -> 0 | E75: =SUM(G75,I75,K75,M75) -> 0 | F75: =SUM(H75,J75,L75,N75) -> 0
A76: Investments in Bonds | B76: 193 | C76: =E76-F76 -> 0 | E76: =SUM(G76,I76,K76,M76) -> 0 | F76: =SUM(H76,J76,L76,N76) -> 0
A77: Other Investments and Marketable Securities | B77: 197 | C77: =E77-F77 -> 0 | E77: =SUM(G77,I77,K77,M77) -> 0 | F77: =SUM(H77,J77,L77,N77) -> 0
A78: Sinking Fund | B78: 198 | C78: =E78-F78 -> 0 | E78: =SUM(G78,I78,K78,M78) -> 0 | F78: =SUM(H78,J78,L78,N78) -> 0
A79: Land | B79: 201 | C79: =E79-F79 -> 0 | E79: =SUM(G79,I79,K79,M79) -> 0 | F79: =SUM(H79,J79,L79,N79) -> 0
A80: Land Improvements | B80: 202 | C80: =E80-F80 -> 0 | E80: =SUM(G80,I80,K80,M80) -> 0 | F80: =SUM(H80,J80,L80,N80) -> 0
A81: Accumulated Depreciation – Land Improvements | B81: 302 | D81: =F81-E81 -> 0 | E81: =SUM(G81,I81,K81,M81) -> 0 | F81: =SUM(H81,J81,L81,N81) -> 0
A82: Runways/Taxiways | B82: 203 | C82: =E82-F82 -> 0 | E82: =SUM(G82,I82,K82,M82) -> 0 | F82: =SUM(H82,J82,L82,N82) -> 0
A83: Accumulated Depreciation - Runways/Taxiways | B83: 303 | D83: =F83-E83 -> 0 | E83: =SUM(G83,I83,K83,M83) -> 0 | F83: =SUM(H83,J83,L83,N83) -> 0
A84: Railways | B84: 204 | C84: =E84-F84 -> 0 | E84: =SUM(G84,I84,K84,M84) -> 0 | F84: =SUM(H84,J84,L84,N84) -> 0
A85: Accumulated Depreciation - Railways | B85: 304 | D85: =F85-E85 -> 0 | E85: =SUM(G85,I85,K85,M85) -> 0 | F85: =SUM(H85,J85,L85,N85) -> 0
A86: Electrification, Power and Energy Structures | B86: 205 | C86: =E86-F86 -> 0 | E86: =SUM(G86,I86,K86,M86) -> 0 | F86: =SUM(H86,J86,L86,N86) -> 0
A87: Accumulated Depreciation - Electrification, Power and Energy | B87: 305 | D87: =F87-E87 -> 0 | E87: =SUM(G87,I87,K87,M87) -> 0 | F87: =SUM(H87,J87,L87,N87) -> 0
A88: Office Buildings | B88: 211 | C88: =E88-F88 -> 0 | E88: =SUM(G88,I88,K88,M88) -> 0 | F88: =SUM(H88,J88,L88,N88) -> 0
A89: Accumulated Depreciation - Office Buildings | B89: 311 | D89: =F89-E89 -> 0 | E89: =SUM(G89,I89,K89,M89) -> 0 | F89: =SUM(H89,J89,L89,N89) -> 0
A90: School Buildings | B90: 212 | C90: =E90-F90 -> 0 | E90: =SUM(G90,I90,K90,M90) -> 0 | F90: =SUM(H90,J90,L90,N90) -> 0
A91: Accumulated Depreciation - School Buildings | B91: 312 | D91: =F91-E91 -> 0 | E91: =SUM(G91,I91,K91,M91) -> 0 | F91: =SUM(H91,J91,L91,N91) -> 0
A92: Hospitals and Health Centers | B92: 213 | C92: =E92-F92 -> 0 | E92: =SUM(G92,I92,K92,M92) -> 0 | F92: =SUM(H92,J92,L92,N92) -> 0
A93: Accumulated Depreciation - Hospitals and Health Centers | B93: 313 | D93: =F93-E93 -> 0 | E93: =SUM(G93,I93,K93,M93) -> 0 | F93: =SUM(H93,J93,L93,N93) -> 0
A94: Markets and Slaughterhouses | B94: 214 | C94: =E94-F94 -> 0 | E94: =SUM(G94,I94,K94,M94) -> 0 | F94: =SUM(H94,J94,L94,N94) -> 0
A95: Accumulated Depreciation - Markets and Slaughterhouses | B95: 314 | D95: =F95-E95 -> 0 | E95: =SUM(G95,I95,K95,M95) -> 0 | F95: =SUM(H95,J95,L95,N95) -> 0
A96: Other Structures | B96: 215 | C96: =E96-F96 -> 0 | E96: =SUM(G96,I96,K96,M96) -> 0 | F96: =SUM(H96,J96,L96,N96) -> 0
A97: Accumulated Depreciation - Other Structures | B97: 315 | D97: =F97-E97 -> 0 | E97: =SUM(G97,I97,K97,M97) -> 0 | F97: =SUM(H97,J97,L97,N97) -> 0
A98: Leasehold Improvements, Land | B98: 218 | C98: =E98-F98 -> 0 | E98: =SUM(G98,I98,K98,M98) -> 0 | F98: =SUM(H98,J98,L98,N98) -> 0
A99: Accumulated Depreciation - Leasehold Improvements, Land | B99: 318 | D99: =F99-E99 -> 0 | E99: =SUM(G99,I99,K99,M99) -> 0 | F99: =SUM(H99,J99,L99,N99) -> 0
A100: Leasehold Improvements, Buildings | B100: 219 | C100: =E100-F100 -> 0 | E100: =SUM(G100,I100,K100,M100) -> 0 | F100: =SUM(H100,J100,L100,N100) -> 0
A101: Accumulated Depreciation - Leasehold Improvements, Buildings | B101: 319 | D101: =F101-E101 -> 0 | E101: =SUM(G101,I101,K101,M101) -> 0 | F101: =SUM(H101,J101,L101,N101) -> 0
A102: Other Leasehold Improvements | B102: 220 | C102: =E102-F102 -> 0 | E102: =SUM(G102,I102,K102,M102) -> 0 | F102: =SUM(H102,J102,L102,N102) -> 0
A103: Accumulated Depreciation - Other Leasehold Improvements | B103: 320 | D103: =F103-E103 -> 0 | E103: =SUM(G103,I103,K103,M103) -> 0 | F103: =SUM(H103,J103,L103,N103) -> 0
A104: Office Equipment | B104: 221 | C104: =E104-F104 -> 0 | E104: =SUM(G104,I104,K104,M104) -> 0 | F104: =SUM(H104,J104,L104,N104) -> 0
A105: Accumulated Depreciation - Office Equipment | B105: 321 | D105: =F105-E105 -> 0 | E105: =SUM(G105,I105,K105,M105) -> 0 | F105: =SUM(H105,J105,L105,N105) -> 0
A106: Furniture and Fixtures | B106: 222 | C106: =E106-F106 -> 0 | E106: =SUM(G106,I106,K106,M106) -> 0 | F106: =SUM(H106,J106,L106,N106) -> 0
A107: Accumulated Depreciation - Furniture and Fixtures | B107: 322 | D107: =F107-E107 -> 0 | E107: =SUM(G107,I107,K107,M107) -> 0 | F107: =SUM(H107,J107,L107,N107) -> 0
A108: IT Equipment and Software | B108: 223 | C108: =E108-F108 -> 0 | E108: =SUM(G108,I108,K108,M108) -> 0 | F108: =SUM(H108,J108,L108,N108) -> 0
A109: Accumulated Depreciation - IT Equipment | B109: 323 | D109: =F109-E109 -> 0 | E109: =SUM(G109,I109,K109,M109) -> 0 | F109: =SUM(H109,J109,L109,N109) -> 0
...

Sheet TB-Oct
A1: Republic of the Philippines
A2: PROVINCE OF AGUSAN DEL SUR
A3: Gov. Democrito O. Plaza Government Center, Prosperidad
A5: TRUST FUND
A6: TRIAL BALANCE
A7: As of October 31, 2011
E9: =A7 -> As of October 31, 2011 | G9: Check Disbursement | I9: Cash Disbursement | K9: Cash Receipts | M9: General Journal
A11: Account Title | B11: Account Code | C11: Debit | D11: Credit | E11: Debit | F11: Credit | G11: Debit | H11: Credit | I11: Debit | J11: Credit | K11: Debit | L11: Credit | M11: Debit | N11: Credit
A13: Cash in Vault | B13: 101 | C13: =E13-F13 -> 0 | E13: =SUM(G13,I13,K13,M13) -> 0 | F13: =SUM(H13,J13,L13,N13) -> 0
A14: Cash - Collecting Officers | B14: 102 | C14: =E14-F14 -> 0 | E14: =SUM(G14,I14,K14,M14) -> 0 | F14: =SUM(H14,J14,L14,N14) -> 0
A15: Cash Disbursing Officers | B15: 103 | C15: =E15-F15 -> 0 | E15: =SUM(G15,I15,K15,M15) -> 0 | F15: =SUM(H15,J15,L15,N15) -> 0
A16: Petty Cash Fund | B16: 104 | C16: =E16-F16 -> 0 | E16: =SUM(G16,I16,K16,M16) -> 0 | F16: =SUM(H16,J16,L16,N16) -> 0
A17: Payroll Fund | B17: 106 | C17: =E17-F17 -> 0 | E17: =SUM(G17,I17,K17,M17) -> 0 | F17: =SUM(H17,J17,L17,N17) -> 0
A18: Cash - Bangko Sentral ng Pilipinas | B18: 110 | C18: =E18-F18 -> 0 | E18: =SUM(G18,I18,K18,M18) -> 0 | F18: =SUM(H18,J18,L18,N18) -> 0
A19: Cash in Bank - Local Currency, Current Account | B19: 111 | C19: =E19-F19 -> 0 | E19: =SUM(G19,I19,K19,M19) -> 0 | F19: =SUM(H19,J19,L19,N19) -> 0
A20: Cash in Bank - Local Currency, SavingsAccount | B20: 112 | C20: =E20-F20 -> 0 | E20: =SUM(G20,I20,K20,M20) -> 0 | F20: =SUM(H20,J20,L20,N20) -> 0
A21: Cash in Bank - Local Currency, Time Deposits | B21: 113 | C21: =E21-F21 -> 0 | E21: =SUM(G21,I21,K21,M21) -> 0 | F21: =SUM(H21,J21,L21,N21) -> 0
A22: Cash - Bangko Sentral ng Pilipinas | B22: 114 | C22: =E22-F22 -> 0 | E22: =SUM(G22,I22,K22,M22) -> 0 | F22: =SUM(H22,J22,L22,N22) -> 0
A23: Cash in Bank - Foreign Currency, Current Account | B23: 115 | C23: =E23-F23 -> 0 | E23: =SUM(G23,I23,K23,M23) -> 0 | F23: =SUM(H23,J23,L23,N23) -> 0
A24: Cash in Bank - Foreign Currency, Savings Account | B24: 116 | C24: =E24-F24 -> 0 | E24: =SUM(G24,I24,K24,M24) -> 0 | F24: =SUM(H24,J24,L24,N24) -> 0
A25: Cash in Bank - Foreign Currency, Time Deposits | B25: 117 | C25: =E25-F25 -> 0 | E25: =SUM(G25,I25,K25,M25) -> 0 | F25: =SUM(H25,J25,L25,N25) -> 0
A26: Accounts Receivable | B26: 121 | C26: =E26-F26 -> 0 | E26: =SUM(G26,I26,K26,M26) -> 0 | F26: =SUM(H26,J26,L26,N26) -> 0
A27: Allowance for Doubtful Accounts | B27: 301 | C27: =E27-F27 -> 0 | E27: =SUM(G27,I27,K27,M27) -> 0 | F27: =SUM(H27,J27,L27,N27) -> 0
A28: Notes Receivable | B28: 122 | C28: =E28-F28 -> 0 | E28: =SUM(G28,I28,K28,M28) -> 0 | F28: =SUM(H28,J28,L28,N28) -> 0
A29: Due from Officers and Employees | B29: 123 | C29: =E29-F29 -> 0 | E29: =SUM(G29,I29,K29,M29) -> 0 | F29: =SUM(H29,J29,L29,N29) -> 0
A30: Loans Receivable - GOCCs | B30: 124 | C30: =E30-F30 -> 0 | E30: =SUM(G30,I30,K30,M30) -> 0 | F30: =SUM(H30,J30,L30,N30) -> 0
A31: Loans Receivable - LGUs | B31: 125 | C31: =E31-F31 -> 0 | E31: =SUM(G31,I31,K31,M31) -> 0 | F31: =SUM(H31,J31,L31,N31) -> 0
A32: Loans Receivable - Others | B32: 126 | C32: =E32-F32 -> 0 | E32: =SUM(G32,I32,K32,M32) -> 0 | F32: =SUM(H32,J32,L32,N32) -> 0
A33: Real Property Tax Receivable | B33: 127 | C33: =E33-F33 -> 0 | E33: =SUM(G33,I33,K33,M33) -> 0 | F33: =SUM(H33,J33,L33,N33) -> 0
A34: Special Education Tax Receivable | B34: 128 | C34: =E34-F34 -> 0 | E34: =SUM(G34,I34,K34,M34) -> 0 | F34: =SUM(H34,J34,L34,N34) -> 0
A35: Interests Receivable | B35: 129 | C35: =E35-F35 -> 0 | E35: =SUM(G35,I35,K35,M35) -> 0 | F35: =SUM(H35,J35,L35,N35) -> 0
... A37: Due from GOCCs | B37: 137 | C37: =E37-F37 -> 0 | E37: =SUM(G37,I37,K37,M37) -> 0 | F37: =SUM(H37,J37,L37,N37) -> 0
A38: Due from LGUs | B38: 138 | C38: =E38-F38 -> 0 | E38: =SUM(G38,I38,K38,M38) -> 0 | F38: =SUM(H38,J38,L38,N38) -> 0
A39: Due from NGOs/POs | B39: 139 | C39: =E39-F39 -> 0 | E39: =SUM(G39,I39,K39,M39) -> 0 | F39: =SUM(H39,J39,L39,N39) -> 0
A40: Due from Other Funds | B40: 144 | C40: =E40-F40 -> 0 | E40: =SUM(G40,I40,K40,M40) -> 0 | F40: =SUM(H40,J40,L40,N40) -> 0
A41: Receivables - Disallowances/Charges | B41: 146 | C41: =E41-F41 -> 0 | E41: =SUM(G41,I41,K41,M41) -> 0 | F41: =SUM(H41,J41,L41,N41) -> 0
A42: Advances to Officers and Employees | B42: 148 | C42: =E42-F42 -> 0 | E42: =SUM(G42,I42,K42,M42) -> 0 | F42: =SUM(H42,J42,L42,N42) -> 0
A43: Other Receivables | B43: 149 | C43: =E43-F43 -> 0 | E43: =SUM(G43,I43,K43,M43) -> 0 | F43: =SUM(H43,J43,L43,N43) -> 0
A44: Raw Materials Inventory | B44: 151 | C44: =E44-F44 -> 0 | E44: =SUM(G44,I44,K44,M44) -> 0 | F44: =SUM(H44,J44,L44,N44) -> 0
A45: Work-In-Process Inventory | B45: 152 | C45: =E45-F45 -> 0 | E45: =SUM(G45,I45,K45,M45) -> 0 | F45: =SUM(H45,J45,L45,N45) -> 0
A46: Finished Goods Inventory | B46: 153 | C46: =E46-F46 -> 0 | E46: =SUM(G46,I46,K46,M46) -> 0 | F46: =SUM(H46,J46,L46,N46) -> 0
A47: Merchandise Inventory | B47: 154 | C47: =E47-F47 -> 0 | E47: =SUM(G47,I47,K47,M47) -> 0 | F47: =SUM(H47,J47,L47,N47) -> 0
A48: Office Supplies Inventory | B48: 155 | C48: =E48-F48 -> 0 | E48: =SUM(G48,I48,K48,M48) -> 0 | F48: =SUM(H48,J48,L48,N48) -> 0
A49: Accountable Forms Inventory | B49: 156 | C49: =E49-F49 -> 0 | E49: =SUM(G49,I49,K49,M49) -> 0 | F49: =SUM(H49,J49,L49,N49) -> 0
A50: Animal/Zoological Supplies Inventory | B50: 157 | C50: =E50-F50 -> 0 | E50: =SUM(G50,I50,K50,M50) -> 0 | F50: =SUM(H50,J50,L50,N50) -> 0
A51: Food Supplies Inventory | B51: 158 | C51: =E51-F51 -> 0 | E51: =SUM(G51,I51,K51,M51) -> 0 | F51: =SUM(H51,J51,L51,N51) -> 0
A52: Drugs and Medicines Inventory | B52: 159 | C52: =E52-F52 -> 0 | E52: =SUM(G52,I52,K52,M52) -> 0 | F52: =SUM(H52,J52,L52,N52) -> 0
... A57: Military and Police Supplies Inventory | B57: 164 | C57: =E57-F57 -> 0 | E57: =SUM(G57,I57,K57,M57) -> 0 | F57: =SUM(H57,J57,L57,N57) -> 0
A58: Other Supplies Inventory | B58: 165 | C58: =E58-F58 -> 0 | E58: =SUM(G58,I58,K58,M58) -> 0 | F58: =SUM(H58,J58,L58,N58) -> 0
A59: Confiscated/Abandoned/Seized Goods Inventory | B59: 166 | C59: =E59-F59 -> 0 | E59: =SUM(G59,I59,K59,M59) -> 0 | F59: =SUM(H59,J59,L59,N59) -> 0
A60: Spare Parts Inventory | B60: 167 | C60: =E60-F60 -> 0 | E60: =SUM(G60,I60,K60,M60) -> 0 | F60: =SUM(H60,J60,L60,N60) -> 0
A61: Construction Materials Inventory | B61: 168 | C61: =E61-F61 -> 0 | E61: =SUM(G61,I61,K61,M61) -> 0 | F61: =SUM(H61,J61,L61,N61) -> 0
A62: Livestock Inventory | B62: 169 | C62: =E62-F62 -> 0 | E62: =SUM(G62,I62,K62,M62) -> 0 | F62: =SUM(H62,J62,L62,N62) -> 0
A63: Crops and Fruits Inventory | B63: 170 | C63: =E63-F63 -> 0 | E63: =SUM(G63,I63,K63,M63) -> 0 | F63: =SUM(H63,J63,L63,N63) -> 0
A64: Other Agricultural, Fishery and Forestry Products Inventory | B64: 176 | C64: =E64-F64 -> 0 | E64: =SUM(G64,I64,K64,M64) -> 0 | F64: =SUM(H64,J64,L64,N64) -> 0
A65: Prepaid Rent | B65: 177 | C65: =E65-F65 -> 0 | E65: =SUM(G65,I65,K65,M65) -> 0 | F65: =SUM(H65,J65,L65,N65) -> 0
A66: Prepaid Insurance | B66: 178 | C66: =E66-F66 -> 0 | E66: =SUM(G66,I66,K66,M66) -> 0 | F66: =SUM(H66,J66,L66,N66) -> 0
A67: Prepaid Interest | B67: 179 | C67: =E67-F67 -> 0 | E67: =SUM(G67,I67,K67,M67) -> 0 | F67: =SUM(H67,J67,L67,N67) -> 0
A68: Deposit on Letters of Credit | B68: 180 | C68: =E68-F68 -> 0 | E68: =SUM(G68,I68,K68,M68) -> 0 | F68: =SUM(H68,J68,L68,N68) -> 0
A69: Advances to Contractors | B69: 181 | C69: =E69-F69 -> 0 | E69: =SUM(G69,I69,K69,M69) -> 0 | F69: =SUM(H69,J69,L69,N69) -> 0
A70: Deferred Charges | B70: 182 | C70: =E70-F70 -> 0 | E70: =SUM(G70,I70,K70,M70) -> 0 | F70: =SUM(H70,J70,L70,N70) -> 0
A71: Other Prepaid Expenses | B71: 185 | C71: =E71-F71 -> 0 | E71: =SUM(G71,I71,K71,M71) -> 0 | F71: =SUM(H71,J71,L71,N71) -> 0
A72: Guaranty Deposits | B72: 186 | C72: =E72-F72 -> 0 | E72: =SUM(G72,I72,K72,M72) -> 0 | F72: =SUM(H72,J72,L72,N72) -> 0
A73: Other Current Assets | B73: 189 | C73: =E73-F73 -> 0 | E73: =SUM(G73,I73,K73,M73) -> 0 | F73: =SUM(H73,J73,L73,N73) -> 0
A74: Investments in Treasury Bills | B74: 191 | C74: =E74-F74 -> 0 | E74: =SUM(G74,I74,K74,M74) -> 0 | F74: =SUM(H74,J74,L74,N74) -> 0
A75: Investments in Stocks | B75: 192 | C75: =E75-F75 -> 0 | E75: =SUM(G75,I75,K75,M75) -> 0 | F75: =SUM(H75,J75,L75,N75) -> 0
A76: Investments in Bonds | B76: 193 | C76: =E76-F76 -> 0 | E76: =SUM(G76,I76,K76,M76) -> 0 | F76: =SUM(H76,J76,L76,N76) -> 0
A77: Other Investments and Marketable Securities | B77: 197 | C77: =E77-F77 -> 0 | E77: =SUM(G77,I77,K77,M77) -> 0 | F77: =SUM(H77,J77,L77,N77) -> 0
A78: Sinking Fund | B78: 198 | C78: =E78-F78 -> 0 | E78: =SUM(G78,I78,K78,M78) -> 0 | F78: =SUM(H78,J78,L78,N78) -> 0
A79: Land | B79: 201 | C79: =E79-F79 -> 0 | E79: =SUM(G79,I79,K79,M79) -> 0 | F79: =SUM(H79,J79,L79,N79) -> 0
A80: Land Improvements | B80: 202 | C80: =E80-F80 -> 0 | E80: =SUM(G80,I80,K80,M80) -> 0 | F80: =SUM(H80,J80,L80,N80) -> 0
A81: Accumulated Depreciation – Land Improvements | B81: 302 | D81: =F81-E81 -> 0 | E81: =SUM(G81,I81,K81,M81) -> 0 | F81: =SUM(H81,J81,L81,N81) -> 0
A82: Runways/Taxiways | B82: 203 | C82: =E82-F82 -> 0 | E82: =SUM(G82,I82,K82,M82) -> 0 | F82: =SUM(H82,J82,L82,N82) -> 0
A83: Accumulated Depreciation - Runways/Taxiways | B83: 303 | D83: =F83-E83 -> 0 | E83: =SUM(G83,I83,K83,M83) -> 0 | F83: =SUM(H83,J83,L83,N83) -> 0
A84: Railways | B84: 204 | C84: =E84-F84 -> 0 | E84: =SUM(G84,I84,K84,M84) -> 0 | F84: =SUM(H84,J84,L84,N84) -> 0
A85: Accumulated Depreciation - Railways | B85: 304 | D85: =F85-E85 -> 0 | E85: =SUM(G85,I85,K85,M85) -> 0 | F85: =SUM(H85,J85,L85,N85) -> 0
A86: Electrification, Power and Energy Structures | B86: 205 | C86: =E86-F86 -> 0 | E86: =SUM(G86,I86,K86,M86) -> 0 | F86: =SUM(H86,J86,L86,N86) -> 0
A87: Accumulated Depreciation - Electrification, Power and Energy | B87: 305 | D87: =F87-E87 -> 0 | E87: =SUM(G87,I87,K87,M87) -> 0 | F87: =SUM(H87,J87,L87,N87) -> 0
A88: Office Buildings | B88: 211 | C88: =E88-F88 -> 0 | E88: =SUM(G88,I88,K88,M88) -> 0 | F88: =SUM(H88,J88,L88,N88) -> 0
A89: Accumulated Depreciation - Office Buildings | B89: 311 | D89: =F89-E89 -> 0 | E89: =SUM(G89,I89,K89,M89) -> 0 | F89: =SUM(H89,J89,L89,N89) -> 0
A90: School Buildings | B90: 212 | C90: =E90-F90 -> 0 | E90: =SUM(G90,I90,K90,M90) -> 0 | F90: =SUM(H90,J90,L90,N90) -> 0
A91: Accumulated Depreciation - School Buildings | B91: 312 | D91: =F91-E91 -> 0 | E91: =SUM(G91,I91,K91,M91) -> 0 | F91: =SUM(H91,J91,L91,N91) -> 0
A92: Hospitals and Health Centers | B92: 213 | C92: =E92-F92 -> 0 | E92: =SUM(G92,I92,K92,M92) -> 0 | F92: =SUM(H92,J92,L92,N92) -> 0
A93: Accumulated Depreciation - Hospitals and Health Centers | B93: 313 | D93: =F93-E93 -> 0 | E93: =SUM(G93,I93,K93,M93) -> 0 | F93: =SUM(H93,J93,L93,N93) -> 0
A94: Markets and Slaughterhouses | B94: 214 | C94: =E94-F94 -> 0 | E94: =SUM(G94,I94,K94,M94) -> 0 | F94: =SUM(H94,J94,L94,N94) -> 0
A95: Accumulated Depreciation - Markets and Slaughterhouses | B95: 314 | D95: =F95-E95 -> 0 | E95: =SUM(G95,I95,K95,M95) -> 0 | F95: =SUM(H95,J95,L95,N95) -> 0
A96: Other Structures | B96: 215 | C96: =E96-F96 -> 0 | E96: =SUM(G96,I96,K96,M96) -> 0 | F96: =SUM(H96,J96,L96,N96) -> 0
A97: Accumulated Depreciation - Other Structures | B97: 315 | D97: =F97-E97 -> 0 | E97: =SUM(G97,I97,K97,M97) -> 0 | F97: =SUM(H97,J97,L97,N97) -> 0
A98: Leasehold Improvements, Land | B98: 218 | C98: =E98-F98 -> 0 | E98: =SUM(G98,I98,K98,M98) -> 0 | F98: =SUM(H98,J98,L98,N98) -> 0
A99: Accumulated Depreciation - Leasehold Improvements, Land | B99: 318 | D99: =F99-E99 -> 0 | E99: =SUM(G99,I99,K99,M99) -> 0 | F99: =SUM(H99,J99,L99,N99) -> 0
A100: Leasehold Improvements, Buildings | B100: 219 | C100: =E100-F100 -> 0 | E100: =SUM(G100,I100,K100,M100) -> 0 | F100: =SUM(H100,J100,L100,N100) -> 0
A101: Accumulated Depreciation - Leasehold Improvements, Buildings | B101: 319 | D101: =F101-E101 -> 0 | E101: =SUM(G101,I101,K101,M101) -> 0 | F101: =SUM(H101,J101,L101,N101) -> 0
A102: Other Leasehold Improvements | B102: 220 | C102: =E102-F102 -> 0 | E102: =SUM(G102,I102,K102,M102) -> 0 | F102: =SUM(H102,J102,L102,N102) -> 0
A103: Accumulated Depreciation - Other Leasehold Improvements | B103: 320 | D103: =F103-E103 -> 0 | E103: =SUM(G103,I103,K103,M103) -> 0 | F103: =SUM(H103,J103,L103,N103) -> 0
A104: Office Equipment | B104: 221 | C104: =E104-F104 -> 0 | E104: =SUM(G104,I104,K104,M104) -> 0 | F104: =SUM(H104,J104,L104,N104) -> 0
A105: Accumulated Depreciation - Office Equipment | B105: 321 | D105: =F105-E105 -> 0 | E105: =SUM(G105,I105,K105,M105) -> 0 | F105: =SUM(H105,J105,L105,N105) -> 0
A106: Furniture and Fixtures | B106: 222 | C106: =E106-F106 -> 0 | E106: =SUM(G106,I106,K106,M106) -> 0 | F106: =SUM(H106,J106,L106,N106) -> 0
A107: Accumulated Depreciation - Furniture and Fixtures | B107: 322 | D107: =F107-E107 -> 0 | E107: =SUM(G107,I107,K107,M107) -> 0 | F107: =SUM(H107,J107,L107,N107) -> 0
A108: IT Equipment and Software | B108: 223 | C108: =E108-F108 -> 0 | E108: =SUM(G108,I108,K108,M108) -> 0 | F108: =SUM(H108,J108,L108,N108) -> 0
A109: Accumulated Depreciation - IT Equipment | B109: 323 | D109: =F109-E109 -> 0 | E109: =SUM(G109,I109,K109,M109) -> 0 | F109: =SUM(H109,J109,L109,N109) -> 0
...

Sheet TB-Nov
A1: Republic of the Philippines
A2: PROVINCE OF AGUSAN DEL SUR
A3: Gov. Democrito O. Plaza Government Center, Prosperidad
A5: TRUST FUND
A6: TRIAL BALANCE
A7: As of November 30, 2011
E9: =A7 -> As of November 30, 2011 | G9: Check Disbursement | I9: Cash Disbursement | K9: Cash Receipts | M9: General Journal
A11: Account Title | B11: Account Code | C11: Debit | D11: Credit | E11: Debit | F11: Credit | G11: Debit | H11: Credit | I11: Debit | J11: Credit | K11: Debit | L11: Credit | M11: Debit | N11: Credit
A13: Cash in Vault | B13: 101 | C13: =E13-F13 -> 0 | E13: =SUM(G13,I13,K13,M13) -> 0 | F13: =SUM(H13,J13,L13,N13) -> 0
A14: Cash - Collecting Officers | B14: 102 | C14: =E14-F14 -> 0 | E14: =SUM(G14,I14,K14,M14) -> 0 | F14: =SUM(H14,J14,L14,N14) -> 0
A15: Cash Disbursing Officers | B15: 103 | C15: =E15-F15 -> 0 | E15: =SUM(G15,I15,K15,M15) -> 0 | F15: =SUM(H15,J15,L15,N15) -> 0
A16: Petty Cash Fund | B16: 104 | C16: =E16-F16 -> 0 | E16: =SUM(G16,I16,K16,M16) -> 0 | F16: =SUM(H16,J16,L16,N16) -> 0
A17: Payroll Fund | B17: 106 | C17: =E17-F17 -> 0 | E17: =SUM(G17,I17,K17,M17) -> 0 | F17: =SUM(H17,J17,L17,N17) -> 0
A18: Cash - Bangko Sentral ng Pilipinas | B18: 110 | C18: =E18-F18 -> 0 | E18: =SUM(G18,I18,K18,M18) -> 0 | F18: =SUM(H18,J18,L18,N18) -> 0
A19: Cash in Bank - Local Currency, Current Account | B19: 111 | C19: =E19-F19 -> 0 | E19: =SUM(G19,I19,K19,M19) -> 0 | F19: =SUM(H19,J19,L19,N19) -> 0
A20: Cash in Bank - Local Currency, SavingsAccount | B20: 112 | C20: =E20-F20 -> 0 | E20: =SUM(G20,I20,K20,M20) -> 0 | F20: =SUM(H20,J20,L20,N20) -> 0
A21: Cash in Bank - Local Currency, Time Deposits | B21: 113 | C21: =E21-F21 -> 0 | E21: =SUM(G21,I21,K21,M21) -> 0 | F21: =SUM(H21,J21,L21,N21) -> 0
A22: Cash - Bangko Sentral ng Pilipinas | B22: 114 | C22: =E22-F22 -> 0 | E22: =SUM(G22,I22,K22,M22) -> 0 | F22: =SUM(H22,J22,L22,N22) -> 0
A23: Cash in Bank - Foreign Currency, Current Account | B23: 115 | C23: =E23-F23 -> 0 | E23: =SUM(G23,I23,K23,M23) -> 0 | F23: =SUM(H23,J23,L23,N23) -> 0
A24: Cash in Bank - Foreign Currency, Savings Account | B24: 116 | C24: =E24-F24 -> 0 | E24: =SUM(G24,I24,K24,M24) -> 0 | F24: =SUM(H24,J24,L24,N24) -> 0
A25: Cash in Bank - Foreign Currency, Time Deposits | B25: 117 | C25: =E25-F25 -> 0 | E25: =SUM(G25,I25,K25,M25) -> 0 | F25: =SUM(H25,J25,L25,N25) -> 0
A26: Accounts Receivable | B26: 121 | C26: =E26-F26 -> 0 | E26: =SUM(G26,I26,K26,M26) -> 0 | F26: =SUM(H26,J26,L26,N26) -> 0
A27: Allowance for Doubtful Accounts | B27: 301 | C27: =E27-F27 -> 0 | E27: =SUM(G27,I27,K27,M27) -> 0 | F27: =SUM(H27,J27,L27,N27) -> 0
A28: Notes Receivable | B28: 122 | C28: =E28-F28 -> 0 | E28: =SUM(G28,I28,K28,M28) -> 0 | F28: =SUM(H28,J28,L28,N28) -> 0
A29: Due from Officers and Employees | B29: 123 | C29: =E29-F29 -> 0 | E29: =SUM(G29,I29,K29,M29) -> 0 | F29: =SUM(H29,J29,L29,N29) -> 0
A30: Loans Receivable - GOCCs | B30: 124 | C30: =E30-F30 -> 0 | E30: =SUM(G30,I30,K30,M30) -> 0 | F30: =SUM(H30,J30,L30,N30) -> 0
A31: Loans Receivable - LGUs | B31: 125 | C31: =E31-F31 -> 0 | E31: =SUM(G31,I31,K31,M31) -> 0 | F31: =SUM(H31,J31,L31,N31) -> 0
A32: Loans Receivable - Others | B32: 126 | C32: =E32-F32 -> 0 | E32: =SUM(G32,I32,K32,M32) -> 0 | F32: =SUM(H32,J32,L32,N32) -> 0
A33: Real Property Tax Receivable | B33: 127 | C33: =E33-F33 -> 0 | E33: =SUM(G33,I33,K33,M33) -> 0 | F33: =SUM(H33,J33,L33,N33) -> 0
A34: Special Education Tax Receivable | B34: 128 | C34: =E34-F34 -> 0 | E34: =SUM(G34,I34,K34,M34) -> 0 | F34: =SUM(H34,J34,L34,N34) -> 0
A35: Interests Receivable | B35: 129 | C35: =E35-F35 -> 0 | E35: =SUM(G35,I35,K35,M35) -> 0 | F35: =SUM(H35,J35,L35,N35) -> 0
... A37: Due from GOCCs | B37: 137 | C37: =E37-F37 -> 0 | E37: =SUM(G37,I37,K37,M37) -> 0 | F37: =SUM(H37,J37,L37,N37) -> 0
A38: Due from LGUs | B38: 138 | C38: =E38-F38 -> 0 | E38: =SUM(G38,I38,K38,M38) -> 0 | F38: =SUM(H38,J38,L38,N38) -> 0
A39: Due from NGOs/POs | B39: 139 | C39: =E39-F39 -> 0 | E39: =SUM(G39,I39,K39,M39) -> 0 | F39: =SUM(H39,J39,L39,N39) -> 0
A40: Due from Other Funds | B40: 144 | C40: =E40-F40 -> 0 | E40: =SUM(G40,I40,K40,M40) -> 0 | F40: =SUM(H40,J40,L40,N40) -> 0
A41: Receivables - Disallowances/Charges | B41: 146 | C41: =E41-F41 -> 0 | E41: =SUM(G41,I41,K41,M41) -> 0 | F41: =SUM(H41,J41,L41,N41) -> 0
A42: Advances to Officers and Employees | B42: 148 | C42: =E42-F42 -> 0 | E42: =SUM(G42,I42,K42,M42) -> 0 | F42: =SUM(H42,J42,L42,N42) -> 0
A43: Other Receivables | B43: 149 | C43: =E43-F43 -> 0 | E43: =SUM(G43,I43,K43,M43) -> 0 | F43: =SUM(H43,J43,L43,N43) -> 0
A44: Raw Materials Inventory | B44: 151 | C44: =E44-F44 -> 0 | E44: =SUM(G44,I44,K44,M44) -> 0 | F44: =SUM(H44,J44,L44,N44) -> 0
A45: Work-In-Process Inventory | B45: 152 | C45: =E45-F45 -> 0 | E45: =SUM(G45,I45,K45,M45) -> 0 | F45: =SUM(H45,J45,L45,N45) -> 0
A46: Finished Goods Inventory | B46: 153 | C46: =E46-F46 -> 0 | E46: =SUM(G46,I46,K46,M46) -> 0 | F46: =SUM(H46,J46,L46,N46) -> 0
A47: Merchandise Inventory | B47: 154 | C47: =E47-F47 -> 0 | E47: =SUM(G47,I47,K47,M47) -> 0 | F47: =SUM(H47,J47,L47,N47) -> 0
A48: Office Supplies Inventory | B48: 155 | C48: =E48-F48 -> 0 | E48: =SUM(G48,I48,K48,M48) -> 0 | F48: =SUM(H48,J48,L48,N48) -> 0
A49: Accountable Forms Inventory | B49: 156 | C49: =E49-F49 -> 0 | E49: =SUM(G49,I49,K49,M49) -> 0 | F49: =SUM(H49,J49,L49,N49) -> 0
A50: Animal/Zoological Supplies Inventory | B50: 157 | C50: =E50-F50 -> 0 | E50: =SUM(G50,I50,K50,M50) -> 0 | F50: =SUM(H50,J50,L50,N50) -> 0
A51: Food Supplies Inventory | B51: 158 | C51: =E51-F51 -> 0 | E51: =SUM(G51,I51,K51,M51) -> 0 | F51: =SUM(H51,J51,L51,N51) -> 0
A52: Drugs and Medicines Inventory | B52: 159 | C52: =E52-F52 -> 0 | E52: =SUM(G52,I52,K52,M52) -> 0 | F52: =SUM(H52,J52,L52,N52) -> 0
... A57: Military and Police Supplies Inventory | B57: 164 | C57: =E57-F57 -> 0 | E57: =SUM(G57,I57,K57,M57) -> 0 | F57: =SUM(H57,J57,L57,N57) -> 0
A58: Other Supplies Inventory | B58: 165 | C58: =E58-F58 -> 0 | E58: =SUM(G58,I58,K58,M58) -> 0 | F58: =SUM(H58,J58,L58,N58) -> 0
A59: Confiscated/Abandoned/Seized Goods Inventory | B59: 166 | C59: =E59-F59 -> 0 | E59: =SUM(G59,I59,K59,M59) -> 0 | F59: =SUM(H59,J59,L59,N59) -> 0
A60: Spare Parts Inventory | B60: 167 | C60: =E60-F60 -> 0 | E60: =SUM(G60,I60,K60,M60) -> 0 | F60: =SUM(H60,J60,L60,N60) -> 0
A61: Construction Materials Inventory | B61: 168 | C61: =E61-F61 -> 0 | E61: =SUM(G61,I61,K61,M61) -> 0 | F61: =SUM(H61,J61,L61,N61) -> 0
A62: Livestock Inventory | B62: 169 | C62: =E62-F62 -> 0 | E62: =SUM(G62,I62,K62,M62) -> 0 | F62: =SUM(H62,J62,L62,N62) -> 0
A63: Crops and Fruits Inventory | B63: 170 | C63: =E63-F63 -> 0 | E63: =SUM(G63,I63,K63,M63) -> 0 | F63: =SUM(H63,J63,L63,N63) -> 0
A64: Other Agricultural, Fishery and Forestry Products Inventory | B64: 176 | C64: =E64-F64 -> 0 | E64: =SUM(G64,I64,K64,M64) -> 0 | F64: =SUM(H64,J64,L64,N64) -> 0
A65: Prepaid Rent | B65: 177 | C65: =E65-F65 -> 0 | E65: =SUM(G65,I65,K65,M65) -> 0 | F65: =SUM(H65,J65,L65,N65) -> 0
A66: Prepaid Insurance | B66: 178 | C66: =E66-F66 -> 0 | E66: =SUM(G66,I66,K66,M66) -> 0 | F66: =SUM(H66,J66,L66,N66) -> 0
A67: Prepaid Interest | B67: 179 | C67: =E67-F67 -> 0 | E67: =SUM(G67,I67,K67,M67) -> 0 | F67: =SUM(H67,J67,L67,N67) -> 0
A68: Deposit on Letters of Credit | B68: 180 | C68: =E68-F68 -> 0 | E68: =SUM(G68,I68,K68,M68) -> 0 | F68: =SUM(H68,J68,L68,N68) -> 0
A69: Advances to Contractors | B69: 181 | C69: =E69-F69 -> 0 | E69: =SUM(G69,I69,K69,M69) -> 0 | F69: =SUM(H69,J69,L69,N69) -> 0
A70: Deferred Charges | B70: 182 | C70: =E70-F70 -> 0 | E70: =SUM(G70,I70,K70,M70) -> 0 | F70: =SUM(H70,J70,L70,N70) -> 0
A71: Other Prepaid Expenses | B71: 185 | C71: =E71-F71 -> 0 | E71: =SUM(G71,I71,K71,M71) -> 0 | F71: =SUM(H71,J71,L71,N71) -> 0
A72: Guaranty Deposits | B72: 186 | C72: =E72-F72 -> 0 | E72: =SUM(G72,I72,K72,M72) -> 0 | F72: =SUM(H72,J72,L72,N72) -> 0
A73: Other Current Assets | B73: 189 | C73: =E73-F73 -> 0 | E73: =SUM(G73,I73,K73,M73) -> 0 | F73: =SUM(H73,J73,L73,N73) -> 0
A74: Investments in Treasury Bills | B74: 191 | C74: =E74-F74 -> 0 | E74: =SUM(G74,I74,K74,M74) -> 0 | F74: =SUM(H74,J74,L74,N74) -> 0
A75: Investments in Stocks | B75: 192 | C75: =E75-F75 -> 0 | E75: =SUM(G75,I75,K75,M75) -> 0 | F75: =SUM(H75,J75,L75,N75) -> 0
A76: Investments in Bonds | B76: 193 | C76: =E76-F76 -> 0 | E76: =SUM(G76,I76,K76,M76) -> 0 | F76: =SUM(H76,J76,L76,N76) -> 0
A77: Other Investments and Marketable Securities | B77: 197 | C77: =E77-F77 -> 0 | E77: =SUM(G77,I77,K77,M77) -> 0 | F77: =SUM(H77,J77,L77,N77) -> 0
A78: Sinking Fund | B78: 198 | C78: =E78-F78 -> 0 | E78: =SUM(G78,I78,K78,M78) -> 0 | F78: =SUM(H78,J78,L78,N78) -> 0
A79: Land | B79: 201 | C79: =E79-F79 -> 0 | E79: =SUM(G79,I79,K79,M79) -> 0 | F79: =SUM(H79,J79,L79,N79) -> 0
A80: Land Improvements | B80: 202 | C80: =E80-F80 -> 0 | E80: =SUM(G80,I80,K80,M80) -> 0 | F80: =SUM(H80,J80,L80,N80) -> 0
A81: Accumulated Depreciation – Land Improvements | B81: 302 | D81: =F81-E81 -> 0 | E81: =SUM(G81,I81,K81,M81) -> 0 | F81: =SUM(H81,J81,L81,N81) -> 0
A82: Runways/Taxiways | B82: 203 | C82: =E82-F82 -> 0 | E82: =SUM(G82,I82,K82,M82) -> 0 | F82: =SUM(H82,J82,L82,N82) -> 0
A83: Accumulated Depreciation - Runways/Taxiways | B83: 303 | D83: =F83-E83 -> 0 | E83: =SUM(G83,I83,K83,M83) -> 0 | F83: =SUM(H83,J83,L83,N83) -> 0
A84: Railways | B84: 204 | C84: =E84-F84 -> 0 | E84: =SUM(G84,I84,K84,M84) -> 0 | F84: =SUM(H84,J84,L84,N84) -> 0
A85: Accumulated Depreciation - Railways | B85: 304 | D85: =F85-E85 -> 0 | E85: =SUM(G85,I85,K85,M85) -> 0 | F85: =SUM(H85,J85,L85,N85) -> 0
A86: Electrification, Power and Energy Structures | B86: 205 | C86: =E86-F86 -> 0 | E86: =SUM(G86,I86,K86,M86) -> 0 | F86: =SUM(H86,J86,L86,N86) -> 0
A87: Accumulated Depreciation - Electrification, Power and Energy | B87: 305 | D87: =F87-E87 -> 0 | E87: =SUM(G87,I87,K87,M87) -> 0 | F87: =SUM(H87,J87,L87,N87) -> 0
A88: Office Buildings | B88: 211 | C88: =E88-F88 -> 0 | E88: =SUM(G88,I88,K88,M88) -> 0 | F88: =SUM(H88,J88,L88,N88) -> 0
A89: Accumulated Depreciation - Office Buildings | B89: 311 | D89: =F89-E89 -> 0 | E89: =SUM(G89,I89,K89,M89) -> 0 | F89: =SUM(H89,J89,L89,N89) -> 0
A90: School Buildings | B90: 212 | C90: =E90-F90 -> 0 | E90: =SUM(G90,I90,K90,M90) -> 0 | F90: =SUM(H90,J90,L90,N90) -> 0
A91: Accumulated Depreciation - School Buildings | B91: 312 | D91: =F91-E91 -> 0 | E91: =SUM(G91,I91,K91,M91) -> 0 | F91: =SUM(H91,J91,L91,N91) -> 0
A92: Hospitals and Health Centers | B92: 213 | C92: =E92-F92 -> 0 | E92: =SUM(G92,I92,K92,M92) -> 0 | F92: =SUM(H92,J92,L92,N92) -> 0
A93: Accumulated Depreciation - Hospitals and Health Centers | B93: 313 | D93: =F93-E93 -> 0 | E93: =SUM(G93,I93,K93,M93) -> 0 | F93: =SUM(H93,J93,L93,N93) -> 0
A94: Markets and Slaughterhouses | B94: 214 | C94: =E94-F94 -> 0 | E94: =SUM(G94,I94,K94,M94) -> 0 | F94: =SUM(H94,J94,L94,N94) -> 0
A95: Accumulated Depreciation - Markets and Slaughterhouses | B95: 314 | D95: =F95-E95 -> 0 | E95: =SUM(G95,I95,K95,M95) -> 0 | F95: =SUM(H95,J95,L95,N95) -> 0
A96: Other Structures | B96: 215 | C96: =E96-F96 -> 0 | E96: =SUM(G96,I96,K96,M96) -> 0 | F96: =SUM(H96,J96,L96,N96) -> 0
A97: Accumulated Depreciation - Other Structures | B97: 315 | D97: =F97-E97 -> 0 | E97: =SUM(G97,I97,K97,M97) -> 0 | F97: =SUM(H97,J97,L97,N97) -> 0
A98: Leasehold Improvements, Land | B98: 218 | C98: =E98-F98 -> 0 | E98: =SUM(G98,I98,K98,M98) -> 0 | F98: =SUM(H98,J98,L98,N98) -> 0
A99: Accumulated Depreciation - Leasehold Improvements, Land | B99: 318 | D99: =F99-E99 -> 0 | E99: =SUM(G99,I99,K99,M99) -> 0 | F99: =SUM(H99,J99,L99,N99) -> 0
A100: Leasehold Improvements, Buildings | B100: 219 | C100: =E100-F100 -> 0 | E100: =SUM(G100,I100,K100,M100) -> 0 | F100: =SUM(H100,J100,L100,N100) -> 0
A101: Accumulated Depreciation - Leasehold Improvements, Buildings | B101: 319 | D101: =F101-E101 -> 0 | E101: =SUM(G101,I101,K101,M101) -> 0 | F101: =SUM(H101,J101,L101,N101) -> 0
A102: Other Leasehold Improvements | B102: 220 | C102: =E102-F102 -> 0 | E102: =SUM(G102,I102,K102,M102) -> 0 | F102: =SUM(H102,J102,L102,N102) -> 0
A103: Accumulated Depreciation - Other Leasehold Improvements | B103: 320 | D103: =F103-E103 -> 0 | E103: =SUM(G103,I103,K103,M103) -> 0 | F103: =SUM(H103,J103,L103,N103) -> 0
A104: Office Equipment | B104: 221 | C104: =E104-F104 -> 0 | E104: =SUM(G104,I104,K104,M104) -> 0 | F104: =SUM(H104,J104,L104,N104) -> 0
A105: Accumulated Depreciation - Office Equipment | B105: 321 | D105: =F105-E105 -> 0 | E105: =SUM(G105,I105,K105,M105) -> 0 | F105: =SUM(H105,J105,L105,N105) -> 0
A106: Furniture and Fixtures | B106: 222 | C106: =E106-F106 -> 0 | E106: =SUM(G106,I106,K106,M106) -> 0 | F106: =SUM(H106,J106,L106,N106) -> 0
A107: Accumulated Depreciation - Furniture and Fixtures | B107: 322 | D107: =F107-E107 -> 0 | E107: =SUM(G107,I107,K107,M107) -> 0 | F107: =SUM(H107,J107,L107,N107) -> 0
A108: IT Equipment and Software | B108: 223 | C108: =E108-F108 -> 0 | E108: =SUM(G108,I108,K108,M108) -> 0 | F108: =SUM(H108,J108,L108,N108) -> 0
A109: Accumulated Depreciation - IT Equipment | B109: 323 | D109: =F109-E109 -> 0 | E109: =SUM(G109,I109,K109,M109) -> 0 | F109: =SUM(H109,J109,L109,N109) -> 0
...

Sheet TB-Dec
A1: Republic of the Philippines
A2: PROVINCE OF AGUSAN DEL SUR
A3: Gov. Democrito O. Plaza Government Center, Prosperidad
A5: TRUST FUND
A6: TRIAL BALANCE
A7: As of December 31, 2011
E9: =A7 -> As of December 31, 2011 | G9: Check Disbursement | I9: Cash Disbursement | K9: Cash Receipts | M9: General Journal
A11: Account Title | B11: Account Code | C11: Debit | D11: Credit | E11: Debit | F11: Credit | G11: Debit | H11: Credit | I11: Debit | J11: Credit | K11: Debit | L11: Credit | M11: Debit | N11: Credit
A13: Cash in Vault | B13: 101 | C13: =E13-F13 -> 0 | E13: =SUM(G13,I13,K13,M13) -> 0 | F13: =SUM(H13,J13,L13,N13) -> 0
A14: Cash - Collecting Officers | B14: 102 | C14: =E14-F14 -> 0 | E14: =SUM(G14,I14,K14,M14) -> 0 | F14: =SUM(H14,J14,L14,N14) -> 0
A15: Cash Disbursing Officers | B15: 103 | C15: =E15-F15 -> 0 | E15: =SUM(G15,I15,K15,M15) -> 0 | F15: =SUM(H15,J15,L15,N15) -> 0
A16: Petty Cash Fund | B16: 104 | C16: =E16-F16 -> 0 | E16: =SUM(G16,I16,K16,M16) -> 0 | F16: =SUM(H16,J16,L16,N16) -> 0
A17: Payroll Fund | B17: 106 | C17: =E17-F17 -> 0 | E17: =SUM(G17,I17,K17,M17) -> 0 | F17: =SUM(H17,J17,L17,N17) -> 0
A18: Cash - Bangko Sentral ng Pilipinas | B18: 110 | C18: =E18-F18 -> 0 | E18: =SUM(G18,I18,K18,M18) -> 0 | F18: =SUM(H18,J18,L18,N18) -> 0
A19: Cash in Bank - Local Currency, Current Account | B19: 111 | C19: =E19-F19 -> 0 | E19: =SUM(G19,I19,K19,M19) -> 0 | F19: =SUM(H19,J19,L19,N19) -> 0
A20: Cash in Bank - Local Currency, SavingsAccount | B20: 112 | C20: =E20-F20 -> 0 | E20: =SUM(G20,I20,K20,M20) -> 0 | F20: =SUM(H20,J20,L20,N20) -> 0
A21: Cash in Bank - Local Currency, Time Deposits | B21: 113 | C21: =E21-F21 -> 0 | E21: =SUM(G21,I21,K21,M21) -> 0 | F21: =SUM(H21,J21,L21,N21) -> 0
A22: Cash - Bangko Sentral ng Pilipinas | B22: 114 | C22: =E22-F22 -> 0 | E22: =SUM(G22,I22,K22,M22) -> 0 | F22: =SUM(H22,J22,L22,N22) -> 0
A23: Cash in Bank - Foreign Currency, Current Account | B23: 115 | C23: =E23-F23 -> 0 | E23: =SUM(G23,I23,K23,M23) -> 0 | F23: =SUM(H23,J23,L23,N23) -> 0
A24: Cash in Bank - Foreign Currency, Savings Account | B24: 116 | C24: =E24-F24 -> 0 | E24: =SUM(G24,I24,K24,M24) -> 0 | F24: =SUM(H24,J24,L24,N24) -> 0
A25: Cash in Bank - Foreign Currency, Time Deposits | B25: 117 | C25: =E25-F25 -> 0 | E25: =SUM(G25,I25,K25,M25) -> 0 | F25: =SUM(H25,J25,L25,N25) -> 0
A26: Accounts Receivable | B26: 121 | C26: =E26-F26 -> 0 | E26: =SUM(G26,I26,K26,M26) -> 0 | F26: =SUM(H26,J26,L26,N26) -> 0
A27: Allowance for Doubtful Accounts | B27: 301 | C27: =E27-F27 -> 0 | E27: =SUM(G27,I27,K27,M27) -> 0 | F27: =SUM(H27,J27,L27,N27) -> 0
A28: Notes Receivable | B28: 122 | C28: =E28-F28 -> 0 | E28: =SUM(G28,I28,K28,M28) -> 0 | F28: =SUM(H28,J28,L28,N28) -> 0
A29: Due from Officers and Employees | B29: 123 | C29: =E29-F29 -> 0 | E29: =SUM(G29,I29,K29,M29) -> 0 | F29: =SUM(H29,J29,L29,N29) -> 0
A30: Loans Receivable - GOCCs | B30: 124 | C30: =E30-F30 -> 0 | E30: =SUM(G30,I30,K30,M30) -> 0 | F30: =SUM(H30,J30,L30,N30) -> 0
A31: Loans Receivable - LGUs | B31: 125 | C31: =E31-F31 -> 0 | E31: =SUM(G31,I31,K31,M31) -> 0 | F31: =SUM(H31,J31,L31,N31) -> 0
A32: Loans Receivable - Others | B32: 126 | C32: =E32-F32 -> 0 | E32: =SUM(G32,I32,K32,M32) -> 0 | F32: =SUM(H32,J32,L32,N32) -> 0
A33: Real Property Tax Receivable | B33: 127 | C33: =E33-F33 -> 0 | E33: =SUM(G33,I33,K33,M33) -> 0 | F33: =SUM(H33,J33,L33,N33) -> 0
A34: Special Education Tax Receivable | B34: 128 | C34: =E34-F34 -> 0 | E34: =SUM(G34,I34,K34,M34) -> 0 | F34: =SUM(H34,J34,L34,N34) -> 0
A35: Interests Receivable | B35: 129 | C35: =E35-F35 -> 0 | E35: =SUM(G35,I35,K35,M35) -> 0 | F35: =SUM(H35,J35,L35,N35) -> 0
... A37: Due from GOCCs | B37: 137 | C37: =E37-F37 -> 0 | E37: =SUM(G37,I37,K37,M37) -> 0 | F37: =SUM(H37,J37,L37,N37) -> 0
A38: Due from LGUs | B38: 138 | C38: =E38-F38 -> 0 | E38: =SUM(G38,I38,K38,M38) -> 0 | F38: =SUM(H38,J38,L38,N38) -> 0
A39: Due from NGOs/POs | B39: 139 | C39: =E39-F39 -> 0 | E39: =SUM(G39,I39,K39,M39) -> 0 | F39: =SUM(H39,J39,L39,N39) -> 0
A40: Due from Other Funds | B40: 144 | C40: =E40-F40 -> 0 | E40: =SUM(G40,I40,K40,M40) -> 0 | F40: =SUM(H40,J40,L40,N40) -> 0
A41: Receivables - Disallowances/Charges | B41: 146 | C41: =E41-F41 -> 0 | E41: =SUM(G41,I41,K41,M41) -> 0 | F41: =SUM(H41,J41,L41,N41) -> 0
A42: Advances to Officers and Employees | B42: 148 | C42: =E42-F42 -> 0 | E42: =SUM(G42,I42,K42,M42) -> 0 | F42: =SUM(H42,J42,L42,N42) -> 0
A43: Other Receivables | B43: 149 | C43: =E43-F43 -> 0 | E43: =SUM(G43,I43,K43,M43) -> 0 | F43: =SUM(H43,J43,L43,N43) -> 0
A44: Raw Materials Inventory | B44: 151 | C44: =E44-F44 -> 0 | E44: =SUM(G44,I44,K44,M44) -> 0 | F44: =SUM(H44,J44,L44,N44) -> 0
A45: Work-In-Process Inventory | B45: 152 | C45: =E45-F45 -> 0 | E45: =SUM(G45,I45,K45,M45) -> 0 | F45: =SUM(H45,J45,L45,N45) -> 0
A46: Finished Goods Inventory | B46: 153 | C46: =E46-F46 -> 0 | E46: =SUM(G46,I46,K46,M46) -> 0 | F46: =SUM(H46,J46,L46,N46) -> 0
A47: Merchandise Inventory | B47: 154 | C47: =E47-F47 -> 0 | E47: =SUM(G47,I47,K47,M47) -> 0 | F47: =SUM(H47,J47,L47,N47) -> 0
A48: Office Supplies Inventory | B48: 155 | C48: =E48-F48 -> 0 | E48: =SUM(G48,I48,K48,M48) -> 0 | F48: =SUM(H48,J48,L48,N48) -> 0
A49: Accountable Forms Inventory | B49: 156 | C49: =E49-F49 -> 0 | E49: =SUM(G49,I49,K49,M49) -> 0 | F49: =SUM(H49,J49,L49,N49) -> 0
A50: Animal/Zoological Supplies Inventory | B50: 157 | C50: =E50-F50 -> 0 | E50: =SUM(G50,I50,K50,M50) -> 0 | F50: =SUM(H50,J50,L50,N50) -> 0
A51: Food Supplies Inventory | B51: 158 | C51: =E51-F51 -> 0 | E51: =SUM(G51,I51,K51,M51) -> 0 | F51: =SUM(H51,J51,L51,N51) -> 0
A52: Drugs and Medicines Inventory | B52: 159 | C52: =E52-F52 -> 0 | E52: =SUM(G52,I52,K52,M52) -> 0 | F52: =SUM(H52,J52,L52,N52) -> 0
... A57: Military and Police Supplies Inventory | B57: 164 | C57: =E57-F57 -> 0 | E57: =SUM(G57,I57,K57,M57) -> 0 | F57: =SUM(H57,J57,L57,N57) -> 0
A58: Other Supplies Inventory | B58: 165 | C58: =E58-F58 -> 0 | E58: =SUM(G58,I58,K58,M58) -> 0 | F58: =SUM(H58,J58,L58,N58) -> 0
A59: Confiscated/Abandoned/Seized Goods Inventory | B59: 166 | C59: =E59-F59 -> 0 | E59: =SUM(G59,I59,K59,M59) -> 0 | F59: =SUM(H59,J59,L59,N59) -> 0
A60: Spare Parts Inventory | B60: 167 | C60: =E60-F60 -> 0 | E60: =SUM(G60,I60,K60,M60) -> 0 | F60: =SUM(H60,J60,L60,N60) -> 0
A61: Construction Materials Inventory | B61: 168 | C61: =E61-F61 -> 0 | E61: =SUM(G61,I61,K61,M61) -> 0 | F61: =SUM(H61,J61,L61,N61) -> 0
A62: Livestock Inventory | B62: 169 | C62: =E62-F62 -> 0 | E62: =SUM(G62,I62,K62,M62) -> 0 | F62: =SUM(H62,J62,L62,N62) -> 0
A63: Crops and Fruits Inventory | B63: 170 | C63: =E63-F63 -> 0 | E63: =SUM(G63,I63,K63,M63) -> 0 | F63: =SUM(H63,J63,L63,N63) -> 0
A64: Other Agricultural, Fishery and Forestry Products Inventory | B64: 176 | C64: =E64-F64 -> 0 | E64: =SUM(G64,I64,K64,M64) -> 0 | F64: =SUM(H64,J64,L64,N64) -> 0
A65: Prepaid Rent | B65: 177 | C65: =E65-F65 -> 0 | E65: =SUM(G65,I65,K65,M65) -> 0 | F65: =SUM(H65,J65,L65,N65) -> 0
A66: Prepaid Insurance | B66: 178 | C66: =E66-F66 -> 0 | E66: =SUM(G66,I66,K66,M66) -> 0 | F66: =SUM(H66,J66,L66,N66) -> 0
A67: Prepaid Interest | B67: 179 | C67: =E67-F67 -> 0 | E67: =SUM(G67,I67,K67,M67) -> 0 | F67: =SUM(H67,J67,L67,N67) -> 0
A68: Deposit on Letters of Credit | B68: 180 | C68: =E68-F68 -> 0 | E68: =SUM(G68,I68,K68,M68) -> 0 | F68: =SUM(H68,J68,L68,N68) -> 0
A69: Advances to Contractors | B69: 181 | C69: =E69-F69 -> 0 | E69: =SUM(G69,I69,K69,M69) -> 0 | F69: =SUM(H69,J69,L69,N69) -> 0
A70: Deferred Charges | B70: 182 | C70: =E70-F70 -> 0 | E70: =SUM(G70,I70,K70,M70) -> 0 | F70: =SUM(H70,J70,L70,N70) -> 0
A71: Other Prepaid Expenses | B71: 185 | C71: =E71-F71 -> 0 | E71: =SUM(G71,I71,K71,M71) -> 0 | F71: =SUM(H71,J71,L71,N71) -> 0
A72: Guaranty Deposits | B72: 186 | C72: =E72-F72 -> 0 | E72: =SUM(G72,I72,K72,M72) -> 0 | F72: =SUM(H72,J72,L72,N72) -> 0
A73: Other Current Assets | B73: 189 | C73: =E73-F73 -> 0 | E73: =SUM(G73,I73,K73,M73) -> 0 | F73: =SUM(H73,J73,L73,N73) -> 0
A74: Investments in Treasury Bills | B74: 191 | C74: =E74-F74 -> 0 | E74: =SUM(G74,I74,K74,M74) -> 0 | F74: =SUM(H74,J74,L74,N74) -> 0
A75: Investments in Stocks | B75: 192 | C75: =E75-F75 -> 0 | E75: =SUM(G75,I75,K75,M75) -> 0 | F75: =SUM(H75,J75,L75,N75) -> 0
A76: Investments in Bonds | B76: 193 | C76: =E76-F76 -> 0 | E76: =SUM(G76,I76,K76,M76) -> 0 | F76: =SUM(H76,J76,L76,N76) -> 0
A77: Other Investments and Marketable Securities | B77: 197 | C77: =E77-F77 -> 0 | E77: =SUM(G77,I77,K77,M77) -> 0 | F77: =SUM(H77,J77,L77,N77) -> 0
A78: Sinking Fund | B78: 198 | C78: =E78-F78 -> 0 | E78: =SUM(G78,I78,K78,M78) -> 0 | F78: =SUM(H78,J78,L78,N78) -> 0
A79: Land | B79: 201 | C79: =E79-F79 -> 0 | E79: =SUM(G79,I79,K79,M79) -> 0 | F79: =SUM(H79,J79,L79,N79) -> 0
A80: Land Improvements | B80: 202 | C80: =E80-F80 -> 0 | E80: =SUM(G80,I80,K80,M80) -> 0 | F80: =SUM(H80,J80,L80,N80) -> 0
A81: Accumulated Depreciation – Land Improvements | B81: 302 | D81: =F81-E81 -> 0 | E81: =SUM(G81,I81,K81,M81) -> 0 | F81: =SUM(H81,J81,L81,N81) -> 0
A82: Runways/Taxiways | B82: 203 | C82: =E82-F82 -> 0 | E82: =SUM(G82,I82,K82,M82) -> 0 | F82: =SUM(H82,J82,L82,N82) -> 0
A83: Accumulated Depreciation - Runways/Taxiways | B83: 303 | D83: =F83-E83 -> 0 | E83: =SUM(G83,I83,K83,M83) -> 0 | F83: =SUM(H83,J83,L83,N83) -> 0
A84: Railways | B84: 204 | C84: =E84-F84 -> 0 | E84: =SUM(G84,I84,K84,M84) -> 0 | F84: =SUM(H84,J84,L84,N84) -> 0
A85: Accumulated Depreciation - Railways | B85: 304 | D85: =F85-E85 -> 0 | E85: =SUM(G85,I85,K85,M85) -> 0 | F85: =SUM(H85,J85,L85,N85) -> 0
A86: Electrification, Power and Energy Structures | B86: 205 | C86: =E86-F86 -> 0 | E86: =SUM(G86,I86,K86,M86) -> 0 | F86: =SUM(H86,J86,L86,N86) -> 0
A87: Accumulated Depreciation - Electrification, Power and Energy | B87: 305 | D87: =F87-E87 -> 0 | E87: =SUM(G87,I87,K87,M87) -> 0 | F87: =SUM(H87,J87,L87,N87) -> 0
A88: Office Buildings | B88: 211 | C88: =E88-F88 -> 0 | E88: =SUM(G88,I88,K88,M88) -> 0 | F88: =SUM(H88,J88,L88,N88) -> 0
A89: Accumulated Depreciation - Office Buildings | B89: 311 | D89: =F89-E89 -> 0 | E89: =SUM(G89,I89,K89,M89) -> 0 | F89: =SUM(H89,J89,L89,N89) -> 0
A90: School Buildings | B90: 212 | C90: =E90-F90 -> 0 | E90: =SUM(G90,I90,K90,M90) -> 0 | F90: =SUM(H90,J90,L90,N90) -> 0
A91: Accumulated Depreciation - School Buildings | B91: 312 | D91: =F91-E91 -> 0 | E91: =SUM(G91,I91,K91,M91) -> 0 | F91: =SUM(H91,J91,L91,N91) -> 0
A92: Hospitals and Health Centers | B92: 213 | C92: =E92-F92 -> 0 | E92: =SUM(G92,I92,K92,M92) -> 0 | F92: =SUM(H92,J92,L92,N92) -> 0
A93: Accumulated Depreciation - Hospitals and Health Centers | B93: 313 | D93: =F93-E93 -> 0 | E93: =SUM(G93,I93,K93,M93) -> 0 | F93: =SUM(H93,J93,L93,N93) -> 0
A94: Markets and Slaughterhouses | B94: 214 | C94: =E94-F94 -> 0 | E94: =SUM(G94,I94,K94,M94) -> 0 | F94: =SUM(H94,J94,L94,N94) -> 0
A95: Accumulated Depreciation - Markets and Slaughterhouses | B95: 314 | D95: =F95-E95 -> 0 | E95: =SUM(G95,I95,K95,M95) -> 0 | F95: =SUM(H95,J95,L95,N95) -> 0
A96: Other Structures | B96: 215 | C96: =E96-F96 -> 0 | E96: =SUM(G96,I96,K96,M96) -> 0 | F96: =SUM(H96,J96,L96,N96) -> 0
A97: Accumulated Depreciation - Other Structures | B97: 315 | D97: =F97-E97 -> 0 | E97: =SUM(G97,I97,K97,M97) -> 0 | F97: =SUM(H97,J97,L97,N97) -> 0
A98: Leasehold Improvements, Land | B98: 218 | C98: =E98-F98 -> 0 | E98: =SUM(G98,I98,K98,M98) -> 0 | F98: =SUM(H98,J98,L98,N98) -> 0
A99: Accumulated Depreciation - Leasehold Improvements, Land | B99: 318 | D99: =F99-E99 -> 0 | E99: =SUM(G99,I99,K99,M99) -> 0 | F99: =SUM(H99,J99,L99,N99) -> 0
A100: Leasehold Improvements, Buildings | B100: 219 | C100: =E100-F100 -> 0 | E100: =SUM(G100,I100,K100,M100) -> 0 | F100: =SUM(H100,J100,L100,N100) -> 0
A101: Accumulated Depreciation - Leasehold Improvements, Buildings | B101: 319 | D101: =F101-E101 -> 0 | E101: =SUM(G101,I101,K101,M101) -> 0 | F101: =SUM(H101,J101,L101,N101) -> 0
A102: Other Leasehold Improvements | B102: 220 | C102: =E102-F102 -> 0 | E102: =SUM(G102,I102,K102,M102) -> 0 | F102: =SUM(H102,J102,L102,N102) -> 0
A103: Accumulated Depreciation - Other Leasehold Improvements | B103: 320 | D103: =F103-E103 -> 0 | E103: =SUM(G103,I103,K103,M103) -> 0 | F103: =SUM(H103,J103,L103,N103) -> 0
A104: Office Equipment | B104: 221 | C104: =E104-F104 -> 0 | E104: =SUM(G104,I104,K104,M104) -> 0 | F104: =SUM(H104,J104,L104,N104) -> 0
A105: Accumulated Depreciation - Office Equipment | B105: 321 | D105: =F105-E105 -> 0 | E105: =SUM(G105,I105,K105,M105) -> 0 | F105: =SUM(H105,J105,L105,N105) -> 0
A106: Furniture and Fixtures | B106: 222 | C106: =E106-F106 -> 0 | E106: =SUM(G106,I106,K106,M106) -> 0 | F106: =SUM(H106,J106,L106,N106) -> 0
A107: Accumulated Depreciation - Furniture and Fixtures | B107: 322 | D107: =F107-E107 -> 0 | E107: =SUM(G107,I107,K107,M107) -> 0 | F107: =SUM(H107,J107,L107,N107) -> 0
A108: IT Equipment and Software | B108: 223 | C108: =E108-F108 -> 0 | E108: =SUM(G108,I108,K108,M108) -> 0 | F108: =SUM(H108,J108,L108,N108) -> 0
A109: Accumulated Depreciation - IT Equipment | B109: 323 | D109: =F109-E109 -> 0 | E109: =SUM(G109,I109,K109,M109) -> 0 | F109: =SUM(H109,J109,L109,N109) -> 0
...

Sheet TB
A1: Republic of the Philippines
A2: PROVINCE OF AGUSAN DEL SUR
A3: Gov. Democrito O. Plaza Government Center, Prosperidad
A5: TRUST FUND
A6: TRIAL BALANCE
A7: As of August 31, 2011
G9: Check Disbursement | I9: Cash Disbursement | K9: Cash Receipts | M9: General Journal
A11: Account Title | B11: Account Code | C11: Debit | D11: Credit | E11: Debit | F11: Credit | G11: Debit | H11: Credit | I11: Debit | J11: Credit | K11: Debit | L11: Credit | M11: Debit | N11: Credit
A13: Cash in Vault | B13: 101 | C13: =E13-F13 -> 0 | E13: =SUM(G13,I13,K13,M13) -> 44928693 | F13: =SUM(H13,J13,L13,N13) -> 44928693 | G13: ='TB-Jan'!G13+'TB-Feb'!G13+'TB-Mar'!G13+'TB-Apr'!G13+'TB-May'!G13+'TB-Jun'!G13+'TB-Jul'!G13+'TB-Aug'!G13+'TB-Sep'!G13+'TB-Oct'!G13+'TB-Nov'!G13+'TB-Dec'!G13 -> 0 | H13: ='TB-Jan'!H13+'TB-Feb'!H13+'TB-Mar'!H13+'TB-Apr'!H13+'TB-May'!H13+'TB-Jun'!H13+'TB-Jul'!H13+'TB-Aug'!H13+'TB-Sep'!H13+'TB-Oct'!H13+'TB-Nov'!H13+'TB-Dec'!H13 -> 0 | I13: ='TB-Jan'!I13+'TB-Feb'!I13+'TB-Mar'!I13+'TB-Apr'!I13+'TB-May'!I13+'TB-Jun'!I13+'TB-Jul'!I13+'TB-Aug'!I13+'TB-Sep'!I13+'TB-Oct'!I13+'TB-Nov'!I13+'TB-Dec'!I13 -> 0 | J13: ='TB-Jan'!J13+'TB-Feb'!J13+'TB-Mar'!J13+'TB-Apr'!J13+'TB-May'!J13+'TB-Jun'!J13+'TB-Jul'!J13+'TB-Aug'!J13+'TB-Sep'!J13+'TB-Oct'!J13+'TB-Nov'!J13+'TB-Dec'!J13 -> 0 | K13: ='TB-Jan'!K13+'TB-Feb'!K13+'TB-Mar'!K13+'TB-Apr'!K13+'TB-May'!K13+'TB-Jun'!K13+'TB-Jul'!K13+'TB-Aug'!K13+'TB-Sep'!K13+'TB-Oct'!K13+'TB-Nov'!K13+'TB-Dec'!K13 -> 44928693 | L13: ='TB-Jan'!L13+'TB-Feb'!L13+'TB-Mar'!L13+'TB-Apr'!L13+'TB-May'!L13+'TB-Jun'!L13+'TB-Jul'!L13+'TB-Aug'!L13+'TB-Sep'!L13+'TB-Oct'!L13+'TB-Nov'!L13+'TB-Dec'!L13 -> 44928693 | M13: ='TB-Jan'!M13+'TB-Feb'!M13+'TB-Mar'!M13+'TB-Apr'!M13+'TB-May'!M13+'TB-Jun'!M13+'TB-Jul'!M13+'TB-Aug'!M13+'TB-Sep'!M13+'TB-Oct'!M13+'TB-Nov'!M13+'TB-Dec'!M13 -> 0 | N13: ='TB-Jan'!N13+'TB-Feb'!N13+'TB-Mar'!N13+'TB-Apr'!N13+'TB-May'!N13+'TB-Jun'!N13+'TB-Jul'!N13+'TB-Aug'!N13+'TB-Sep'!N13+'TB-Oct'!N13+'TB-Nov'!N13+'TB-Dec'!N13 -> 0
A14: Cash - Collecting Officers | B14: 102 | C14: =E14-F14 -> 0 | E14: =SUM(G14,I14,K14,M14) -> 0 | F14: =SUM(H14,J14,L14,N14) -> 0 | G14: ='TB-Jan'!G14+'TB-Feb'!G14+'TB-Mar'!G14+'TB-Apr'!G14+'TB-May'!G14+'TB-Jun'!G14+'TB-Jul'!G14+'TB-Aug'!G14+'TB-Sep'!G14+'TB-Oct'!G14+'TB-Nov'!G14+'TB-Dec'!G14 -> 0 | H14: ='TB-Jan'!H14+'TB-Feb'!H14+'TB-Mar'!H14+'TB-Apr'!H14+'TB-May'!H14+'TB-Jun'!H14+'TB-Jul'!H14+'TB-Aug'!H14+'TB-Sep'!H14+'TB-Oct'!H14+'TB-Nov'!H14+'TB-Dec'!H14 -> 0 | I14: ='TB-Jan'!I14+'TB-Feb'!I14+'TB-Mar'!I14+'TB-Apr'!I14+'TB-May'!I14+'TB-Jun'!I14+'TB-Jul'!I14+'TB-Aug'!I14+'TB-Sep'!I14+'TB-Oct'!I14+'TB-Nov'!I14+'TB-Dec'!I14 -> 0 | J14: ='TB-Jan'!J14+'TB-Feb'!J14+'TB-Mar'!J14+'TB-Apr'!J14+'TB-May'!J14+'TB-Jun'!J14+'TB-Jul'!J14+'TB-Aug'!J14+'TB-Sep'!J14+'TB-Oct'!J14+'TB-Nov'!J14+'TB-Dec'!J14 -> 0 | K14: ='TB-Jan'!K14+'TB-Feb'!K14+'TB-Mar'!K14+'TB-Apr'!K14+'TB-May'!K14+'TB-Jun'!K14+'TB-Jul'!K14+'TB-Aug'!K14+'TB-Sep'!K14+'TB-Oct'!K14+'TB-Nov'!K14+'TB-Dec'!K14 -> 0 | L14: ='TB-Jan'!L14+'TB-Feb'!L14+'TB-Mar'!L14+'TB-Apr'!L14+'TB-May'!L14+'TB-Jun'!L14+'TB-Jul'!L14+'TB-Aug'!L14+'TB-Sep'!L14+'TB-Oct'!L14+'TB-Nov'!L14+'TB-Dec'!L14 -> 0 | M14: ='TB-Jan'!M14+'TB-Feb'!M14+'TB-Mar'!M14+'TB-Apr'!M14+'TB-May'!M14+'TB-Jun'!M14+'TB-Jul'!M14+'TB-Aug'!M14+'TB-Sep'!M14+'TB-Oct'!M14+'TB-Nov'!M14+'TB-Dec'!M14 -> 0 | N14: ='TB-Jan'!N14+'TB-Feb'!N14+'TB-Mar'!N14+'TB-Apr'!N14+'TB-May'!N14+'TB-Jun'!N14+'TB-Jul'!N14+'TB-Aug'!N14+'TB-Sep'!N14+'TB-Oct'!N14+'TB-Nov'!N14+'TB-Dec'!N14 -> 0
A15: Cash Disbursing Officers | B15: 103 | C15: =E15-F15 -> 0 | E15: =SUM(G15,I15,K15,M15) -> 0 | F15: =SUM(H15,J15,L15,N15) -> 0 | G15: ='TB-Jan'!G15+'TB-Feb'!G15+'TB-Mar'!G15+'TB-Apr'!G15+'TB-May'!G15+'TB-Jun'!G15+'TB-Jul'!G15+'TB-Aug'!G15+'TB-Sep'!G15+'TB-Oct'!G15+'TB-Nov'!G15+'TB-Dec'!G15 -> 0 | H15: ='TB-Jan'!H15+'TB-Feb'!H15+'TB-Mar'!H15+'TB-Apr'!H15+'TB-May'!H15+'TB-Jun'!H15+'TB-Jul'!H15+'TB-Aug'!H15+'TB-Sep'!H15+'TB-Oct'!H15+'TB-Nov'!H15+'TB-Dec'!H15 -> 0 | I15: ='TB-Jan'!I15+'TB-Feb'!I15+'TB-Mar'!I15+'TB-Apr'!I15+'TB-May'!I15+'TB-Jun'!I15+'TB-Jul'!I15+'TB-Aug'!I15+'TB-Sep'!I15+'TB-Oct'!I15+'TB-Nov'!I15+'TB-Dec'!I15 -> 0 | J15: ='TB-Jan'!J15+'TB-Feb'!J15+'TB-Mar'!J15+'TB-Apr'!J15+'TB-May'!J15+'TB-Jun'!J15+'TB-Jul'!J15+'TB-Aug'!J15+'TB-Sep'!J15+'TB-Oct'!J15+'TB-Nov'!J15+'TB-Dec'!J15 -> 0 | K15: ='TB-Jan'!K15+'TB-Feb'!K15+'TB-Mar'!K15+'TB-Apr'!K15+'TB-May'!K15+'TB-Jun'!K15+'TB-Jul'!K15+'TB-Aug'!K15+'TB-Sep'!K15+'TB-Oct'!K15+'TB-Nov'!K15+'TB-Dec'!K15 -> 0 | L15: ='TB-Jan'!L15+'TB-Feb'!L15+'TB-Mar'!L15+'TB-Apr'!L15+'TB-May'!L15+'TB-Jun'!L15+'TB-Jul'!L15+'TB-Aug'!L15+'TB-Sep'!L15+'TB-Oct'!L15+'TB-Nov'!L15+'TB-Dec'!L15 -> 0 | M15: ='TB-Jan'!M15+'TB-Feb'!M15+'TB-Mar'!M15+'TB-Apr'!M15+'TB-May'!M15+'TB-Jun'!M15+'TB-Jul'!M15+'TB-Aug'!M15+'TB-Sep'!M15+'TB-Oct'!M15+'TB-Nov'!M15+'TB-Dec'!M15 -> 0 | N15: ='TB-Jan'!N15+'TB-Feb'!N15+'TB-Mar'!N15+'TB-Apr'!N15+'TB-May'!N15+'TB-Jun'!N15+'TB-Jul'!N15+'TB-Aug'!N15+'TB-Sep'!N15+'TB-Oct'!N15+'TB-Nov'!N15+'TB-Dec'!N15 -> 0
A16: Petty Cash Fund | B16: 104 | C16: =E16-F16 -> 50000 | E16: =SUM(G16,I16,K16,M16) -> 50000 | F16: =SUM(H16,J16,L16,N16) -> 0 | G16: ='TB-Jan'!G16+'TB-Feb'!G16+'TB-Mar'!G16+'TB-Apr'!G16+'TB-May'!G16+'TB-Jun'!G16+'TB-Jul'!G16+'TB-Aug'!G16+'TB-Sep'!G16+'TB-Oct'!G16+'TB-Nov'!G16+'TB-Dec'!G16 -> 50000 | H16: ='TB-Jan'!H16+'TB-Feb'!H16+'TB-Mar'!H16+'TB-Apr'!H16+'TB-May'!H16+'TB-Jun'!H16+'TB-Jul'!H16+'TB-Aug'!H16+'TB-Sep'!H16+'TB-Oct'!H16+'TB-Nov'!H16+'TB-Dec'!H16 -> 0 | I16: ='TB-Jan'!I16+'TB-Feb'!I16+'TB-Mar'!I16+'TB-Apr'!I16+'TB-May'!I16+'TB-Jun'!I16+'TB-Jul'!I16+'TB-Aug'!I16+'TB-Sep'!I16+'TB-Oct'!I16+'TB-Nov'!I16+'TB-Dec'!I16 -> 0 | J16: ='TB-Jan'!J16+'TB-Feb'!J16+'TB-Mar'!J16+'TB-Apr'!J16+'TB-May'!J16+'TB-Jun'!J16+'TB-Jul'!J16+'TB-Aug'!J16+'TB-Sep'!J16+'TB-Oct'!J16+'TB-Nov'!J16+'TB-Dec'!J16 -> 0 | K16: ='TB-Jan'!K16+'TB-Feb'!K16+'TB-Mar'!K16+'TB-Apr'!K16+'TB-May'!K16+'TB-Jun'!K16+'TB-Jul'!K16+'TB-Aug'!K16+'TB-Sep'!K16+'TB-Oct'!K16+'TB-Nov'!K16+'TB-Dec'!K16 -> 0 | L16: ='TB-Jan'!L16+'TB-Feb'!L16+'TB-Mar'!L16+'TB-Apr'!L16+'TB-May'!L16+'TB-Jun'!L16+'TB-Jul'!L16+'TB-Aug'!L16+'TB-Sep'!L16+'TB-Oct'!L16+'TB-Nov'!L16+'TB-Dec'!L16 -> 0 | M16: ='TB-Jan'!M16+'TB-Feb'!M16+'TB-Mar'!M16+'TB-Apr'!M16+'TB-May'!M16+'TB-Jun'!M16+'TB-Jul'!M16+'TB-Aug'!M16+'TB-Sep'!M16+'TB-Oct'!M16+'TB-Nov'!M16+'TB-Dec'!M16 -> 0 | N16: ='TB-Jan'!N16+'TB-Feb'!N16+'TB-Mar'!N16+'TB-Apr'!N16+'TB-May'!N16+'TB-Jun'!N16+'TB-Jul'!N16+'TB-Aug'!N16+'TB-Sep'!N16+'TB-Oct'!N16+'TB-Nov'!N16+'TB-Dec'!N16 -> 0
A17: Payroll Fund | B17: 106 | C17: =E17-F17 -> 8774.79 | E17: =SUM(G17,I17,K17,M17) -> 4661147.1 | F17: =SUM(H17,J17,L17,N17) -> 4652372.3 | G17: ='TB-Jan'!G17+'TB-Feb'!G17+'TB-Mar'!G17+'TB-Apr'!G17+'TB-May'!G17+'TB-Jun'!G17+'TB-Jul'!G17+'TB-Aug'!G17+'TB-Sep'!G17+'TB-Oct'!G17+'TB-Nov'!G17+'TB-Dec'!G17 -> 4661146.8 | H17: ='TB-Jan'!H17+'TB-Feb'!H17+'TB-Mar'!H17+'TB-Apr'!H17+'TB-May'!H17+'TB-Jun'!H17+'TB-Jul'!H17+'TB-Aug'!H17+'TB-Sep'!H17+'TB-Oct'!H17+'TB-Nov'!H17+'TB-Dec'!H17 -> 0 | I17: ='TB-Jan'!I17+'TB-Feb'!I17+'TB-Mar'!I17+'TB-Apr'!I17+'TB-May'!I17+'TB-Jun'!I17+'TB-Jul'!I17+'TB-Aug'!I17+'TB-Sep'!I17+'TB-Oct'!I17+'TB-Nov'!I17+'TB-Dec'!I17 -> 0 | J17: ='TB-Jan'!J17+'TB-Feb'!J17+'TB-Mar'!J17+'TB-Apr'!J17+'TB-May'!J17+'TB-Jun'!J17+'TB-Jul'!J17+'TB-Aug'!J17+'TB-Sep'!J17+'TB-Oct'!J17+'TB-Nov'!J17+'TB-Dec'!J17 -> 4648567.2 | K17: ='TB-Jan'!K17+'TB-Feb'!K17+'TB-Mar'!K17+'TB-Apr'!K17+'TB-May'!K17+'TB-Jun'!K17+'TB-Jul'!K17+'TB-Aug'!K17+'TB-Sep'!K17+'TB-Oct'!K17+'TB-Nov'!K17+'TB-Dec'!K17 -> 0 | L17: ='TB-Jan'!L17+'TB-Feb'!L17+'TB-Mar'!L17+'TB-Apr'!L17+'TB-May'!L17+'TB-Jun'!L17+'TB-Jul'!L17+'TB-Aug'!L17+'TB-Sep'!L17+'TB-Oct'!L17+'TB-Nov'!L17+'TB-Dec'!L17 -> 3804.84 | M17: ='TB-Jan'!M17+'TB-Feb'!M17+'TB-Mar'!M17+'TB-Apr'!M17+'TB-May'!M17+'TB-Jun'!M17+'TB-Jul'!M17+'TB-Aug'!M17+'TB-Sep'!M17+'TB-Oct'!M17+'TB-Nov'!M17+'TB-Dec'!M17 -> 0.3 | N17: ='TB-Jan'!N17+'TB-Feb'!N17+'TB-Mar'!N17+'TB-Apr'!N17+'TB-May'!N17+'TB-Jun'!N17+'TB-Jul'!N17+'TB-Aug'!N17+'TB-Sep'!N17+'TB-Oct'!N17+'TB-Nov'!N17+'TB-Dec'!N17 -> 0.3
A18: Cash - Bangko Sentral ng Pilipinas | B18: 110 | C18: =E18-F18 -> 0 | E18: =SUM(G18,I18,K18,M18) -> 0 | F18: =SUM(H18,J18,L18,N18) -> 0 | G18: ='TB-Jan'!G18+'TB-Feb'!G18+'TB-Mar'!G18+'TB-Apr'!G18+'TB-May'!G18+'TB-Jun'!G18+'TB-Jul'!G18+'TB-Aug'!G18+'TB-Sep'!G18+'TB-Oct'!G18+'TB-Nov'!G18+'TB-Dec'!G18 -> 0 | H18: ='TB-Jan'!H18+'TB-Feb'!H18+'TB-Mar'!H18+'TB-Apr'!H18+'TB-May'!H18+'TB-Jun'!H18+'TB-Jul'!H18+'TB-Aug'!H18+'TB-Sep'!H18+'TB-Oct'!H18+'TB-Nov'!H18+'TB-Dec'!H18 -> 0 | I18: ='TB-Jan'!I18+'TB-Feb'!I18+'TB-Mar'!I18+'TB-Apr'!I18+'TB-May'!I18+'TB-Jun'!I18+'TB-Jul'!I18+'TB-Aug'!I18+'TB-Sep'!I18+'TB-Oct'!I18+'TB-Nov'!I18+'TB-Dec'!I18 -> 0 | J18: ='TB-Jan'!J18+'TB-Feb'!J18+'TB-Mar'!J18+'TB-Apr'!J18+'TB-May'!J18+'TB-Jun'!J18+'TB-Jul'!J18+'TB-Aug'!J18+'TB-Sep'!J18+'TB-Oct'!J18+'TB-Nov'!J18+'TB-Dec'!J18 -> 0 | K18: ='TB-Jan'!K18+'TB-Feb'!K18+'TB-Mar'!K18+'TB-Apr'!K18+'TB-May'!K18+'TB-Jun'!K18+'TB-Jul'!K18+'TB-Aug'!K18+'TB-Sep'!K18+'TB-Oct'!K18+'TB-Nov'!K18+'TB-Dec'!K18 -> 0 | L18: ='TB-Jan'!L18+'TB-Feb'!L18+'TB-Mar'!L18+'TB-Apr'!L18+'TB-May'!L18+'TB-Jun'!L18+'TB-Jul'!L18+'TB-Aug'!L18+'TB-Sep'!L18+'TB-Oct'!L18+'TB-Nov'!L18+'TB-Dec'!L18 -> 0 | M18: ='TB-Jan'!M18+'TB-Feb'!M18+'TB-Mar'!M18+'TB-Apr'!M18+'TB-May'!M18+'TB-Jun'!M18+'TB-Jul'!M18+'TB-Aug'!M18+'TB-Sep'!M18+'TB-Oct'!M18+'TB-Nov'!M18+'TB-Dec'!M18 -> 0 | N18: ='TB-Jan'!N18+'TB-Feb'!N18+'TB-Mar'!N18+'TB-Apr'!N18+'TB-May'!N18+'TB-Jun'!N18+'TB-Jul'!N18+'TB-Aug'!N18+'TB-Sep'!N18+'TB-Oct'!N18+'TB-Nov'!N18+'TB-Dec'!N18 -> 0
A19: Cash in Bank - Local Currency, Current Account | B19: 111 | C19: =E19-F19 -> 1.0558268e+08 | E19: =SUM(G19,I19,K19,M19) -> 1.4010729e+08 | F19: =SUM(H19,J19,L19,N19) -> 34524614 | G19: ='TB-Jan'!G19+'TB-Feb'!G19+'TB-Mar'!G19+'TB-Apr'!G19+'TB-May'!G19+'TB-Jun'!G19+'TB-Jul'!G19+'TB-Aug'!G19+'TB-Sep'!G19+'TB-Oct'!G19+'TB-Nov'!G19+'TB-Dec'!G19 -> 75809618 | H19: ='TB-Jan'!H19+'TB-Feb'!H19+'TB-Mar'!H19+'TB-Apr'!H19+'TB-May'!H19+'TB-Jun'!H19+'TB-Jul'!H19+'TB-Aug'!H19+'TB-Sep'!H19+'TB-Oct'!H19+'TB-Nov'!H19+'TB-Dec'!H19 -> 34487154 | I19: ='TB-Jan'!I19+'TB-Feb'!I19+'TB-Mar'!I19+'TB-Apr'!I19+'TB-May'!I19+'TB-Jun'!I19+'TB-Jul'!I19+'TB-Aug'!I19+'TB-Sep'!I19+'TB-Oct'!I19+'TB-Nov'!I19+'TB-Dec'!I19 -> 0 | J19: ='TB-Jan'!J19+'TB-Feb'!J19+'TB-Mar'!J19+'TB-Apr'!J19+'TB-May'!J19+'TB-Jun'!J19+'TB-Jul'!J19+'TB-Aug'!J19+'TB-Sep'!J19+'TB-Oct'!J19+'TB-Nov'!J19+'TB-Dec'!J19 -> 0 | K19: ='TB-Jan'!K19+'TB-Feb'!K19+'TB-Mar'!K19+'TB-Apr'!K19+'TB-May'!K19+'TB-Jun'!K19+'TB-Jul'!K19+'TB-Aug'!K19+'TB-Sep'!K19+'TB-Oct'!K19+'TB-Nov'!K19+'TB-Dec'!K19 -> 44961659 | L19: ='TB-Jan'!L19+'TB-Feb'!L19+'TB-Mar'!L19+'TB-Apr'!L19+'TB-May'!L19+'TB-Jun'!L19+'TB-Jul'!L19+'TB-Aug'!L19+'TB-Sep'!L19+'TB-Oct'!L19+'TB-Nov'!L19+'TB-Dec'!L19 -> 0 | M19: ='TB-Jan'!M19+'TB-Feb'!M19+'TB-Mar'!M19+'TB-Apr'!M19+'TB-May'!M19+'TB-Jun'!M19+'TB-Jul'!M19+'TB-Aug'!M19+'TB-Sep'!M19+'TB-Oct'!M19+'TB-Nov'!M19+'TB-Dec'!M19 -> 19336018 | N19: ='TB-Jan'!N19+'TB-Feb'!N19+'TB-Mar'!N19+'TB-Apr'!N19+'TB-May'!N19+'TB-Jun'!N19+'TB-Jul'!N19+'TB-Aug'!N19+'TB-Sep'!N19+'TB-Oct'!N19+'TB-Nov'!N19+'TB-Dec'!N19 -> 37460.45
A20: Cash in Bank - Local Currency, SavingsAccount | B20: 112 | C20: =E20-F20 -> 4335118.1 | E20: =SUM(G20,I20,K20,M20) -> 4335118.1 | F20: =SUM(H20,J20,L20,N20) -> 0 | G20: ='TB-Jan'!G20+'TB-Feb'!G20+'TB-Mar'!G20+'TB-Apr'!G20+'TB-May'!G20+'TB-Jun'!G20+'TB-Jul'!G20+'TB-Aug'!G20+'TB-Sep'!G20+'TB-Oct'!G20+'TB-Nov'!G20+'TB-Dec'!G20 -> 4335118.1 | H20: ='TB-Jan'!H20+'TB-Feb'!H20+'TB-Mar'!H20+'TB-Apr'!H20+'TB-May'!H20+'TB-Jun'!H20+'TB-Jul'!H20+'TB-Aug'!H20+'TB-Sep'!H20+'TB-Oct'!H20+'TB-Nov'!H20+'TB-Dec'!H20 -> 0 | I20: ='TB-Jan'!I20+'TB-Feb'!I20+'TB-Mar'!I20+'TB-Apr'!I20+'TB-May'!I20+'TB-Jun'!I20+'TB-Jul'!I20+'TB-Aug'!I20+'TB-Sep'!I20+'TB-Oct'!I20+'TB-Nov'!I20+'TB-Dec'!I20 -> 0 | J20: ='TB-Jan'!J20+'TB-Feb'!J20+'TB-Mar'!J20+'TB-Apr'!J20+'TB-May'!J20+'TB-Jun'!J20+'TB-Jul'!J20+'TB-Aug'!J20+'TB-Sep'!J20+'TB-Oct'!J20+'TB-Nov'!J20+'TB-Dec'!J20 -> 0 | K20: ='TB-Jan'!K20+'TB-Feb'!K20+'TB-Mar'!K20+'TB-Apr'!K20+'TB-May'!K20+'TB-Jun'!K20+'TB-Jul'!K20+'TB-Aug'!K20+'TB-Sep'!K20+'TB-Oct'!K20+'TB-Nov'!K20+'TB-Dec'!K20 -> 0 | L20: ='TB-Jan'!L20+'TB-Feb'!L20+'TB-Mar'!L20+'TB-Apr'!L20+'TB-May'!L20+'TB-Jun'!L20+'TB-Jul'!L20+'TB-Aug'!L20+'TB-Sep'!L20+'TB-Oct'!L20+'TB-Nov'!L20+'TB-Dec'!L20 -> 0 | M20: ='TB-Jan'!M20+'TB-Feb'!M20+'TB-Mar'!M20+'TB-Apr'!M20+'TB-May'!M20+'TB-Jun'!M20+'TB-Jul'!M20+'TB-Aug'!M20+'TB-Sep'!M20+'TB-Oct'!M20+'TB-Nov'!M20+'TB-Dec'!M20 -> 0 | N20: ='TB-Jan'!N20+'TB-Feb'!N20+'TB-Mar'!N20+'TB-Apr'!N20+'TB-May'!N20+'TB-Jun'!N20+'TB-Jul'!N20+'TB-Aug'!N20+'TB-Sep'!N20+'TB-Oct'!N20+'TB-Nov'!N20+'TB-Dec'!N20 -> 0
A21: Cash in Bank - Local Currency, Time Deposits | B21: 113 | C21: =E21-F21 -> 0 | E21: =SUM(G21,I21,K21,M21) -> 0 | F21: =SUM(H21,J21,L21,N21) -> 0 | G21: ='TB-Jan'!G21+'TB-Feb'!G21+'TB-Mar'!G21+'TB-Apr'!G21+'TB-May'!G21+'TB-Jun'!G21+'TB-Jul'!G21+'TB-Aug'!G21+'TB-Sep'!G21+'TB-Oct'!G21+'TB-Nov'!G21+'TB-Dec'!G21 -> 0 | H21: ='TB-Jan'!H21+'TB-Feb'!H21+'TB-Mar'!H21+'TB-Apr'!H21+'TB-May'!H21+'TB-Jun'!H21+'TB-Jul'!H21+'TB-Aug'!H21+'TB-Sep'!H21+'TB-Oct'!H21+'TB-Nov'!H21+'TB-Dec'!H21 -> 0 | I21: ='TB-Jan'!I21+'TB-Feb'!I21+'TB-Mar'!I21+'TB-Apr'!I21+'TB-May'!I21+'TB-Jun'!I21+'TB-Jul'!I21+'TB-Aug'!I21+'TB-Sep'!I21+'TB-Oct'!I21+'TB-Nov'!I21+'TB-Dec'!I21 -> 0 | J21: ='TB-Jan'!J21+'TB-Feb'!J21+'TB-Mar'!J21+'TB-Apr'!J21+'TB-May'!J21+'TB-Jun'!J21+'TB-Jul'!J21+'TB-Aug'!J21+'TB-Sep'!J21+'TB-Oct'!J21+'TB-Nov'!J21+'TB-Dec'!J21 -> 0 | K21: ='TB-Jan'!K21+'TB-Feb'!K21+'TB-Mar'!K21+'TB-Apr'!K21+'TB-May'!K21+'TB-Jun'!K21+'TB-Jul'!K21+'TB-Aug'!K21+'TB-Sep'!K21+'TB-Oct'!K21+'TB-Nov'!K21+'TB-Dec'!K21 -> 0 | L21: ='TB-Jan'!L21+'TB-Feb'!L21+'TB-Mar'!L21+'TB-Apr'!L21+'TB-May'!L21+'TB-Jun'!L21+'TB-Jul'!L21+'TB-Aug'!L21+'TB-Sep'!L21+'TB-Oct'!L21+'TB-Nov'!L21+'TB-Dec'!L21 -> 0 | M21: ='TB-Jan'!M21+'TB-Feb'!M21+'TB-Mar'!M21+'TB-Apr'!M21+'TB-May'!M21+'TB-Jun'!M21+'TB-Jul'!M21+'TB-Aug'!M21+'TB-Sep'!M21+'TB-Oct'!M21+'TB-Nov'!M21+'TB-Dec'!M21 -> 0 | N21: ='TB-Jan'!N21+'TB-Feb'!N21+'TB-Mar'!N21+'TB-Apr'!N21+'TB-May'!N21+'TB-Jun'!N21+'TB-Jul'!N21+'TB-Aug'!N21+'TB-Sep'!N21+'TB-Oct'!N21+'TB-Nov'!N21+'TB-Dec'!N21 -> 0
A22: Cash - Bangko Sentral ng Pilipinas | B22: 114 | C22: =E22-F22 -> 0 | E22: =SUM(G22,I22,K22,M22) -> 0 | F22: =SUM(H22,J22,L22,N22) -> 0 | G22: ='TB-Jan'!G22+'TB-Feb'!G22+'TB-Mar'!G22+'TB-Apr'!G22+'TB-May'!G22+'TB-Jun'!G22+'TB-Jul'!G22+'TB-Aug'!G22+'TB-Sep'!G22+'TB-Oct'!G22+'TB-Nov'!G22+'TB-Dec'!G22 -> 0 | H22: ='TB-Jan'!H22+'TB-Feb'!H22+'TB-Mar'!H22+'TB-Apr'!H22+'TB-May'!H22+'TB-Jun'!H22+'TB-Jul'!H22+'TB-Aug'!H22+'TB-Sep'!H22+'TB-Oct'!H22+'TB-Nov'!H22+'TB-Dec'!H22 -> 0 | I22: ='TB-Jan'!I22+'TB-Feb'!I22+'TB-Mar'!I22+'TB-Apr'!I22+'TB-May'!I22+'TB-Jun'!I22+'TB-Jul'!I22+'TB-Aug'!I22+'TB-Sep'!I22+'TB-Oct'!I22+'TB-Nov'!I22+'TB-Dec'!I22 -> 0 | J22: ='TB-Jan'!J22+'TB-Feb'!J22+'TB-Mar'!J22+'TB-Apr'!J22+'TB-May'!J22+'TB-Jun'!J22+'TB-Jul'!J22+'TB-Aug'!J22+'TB-Sep'!J22+'TB-Oct'!J22+'TB-Nov'!J22+'TB-Dec'!J22 -> 0 | K22: ='TB-Jan'!K22+'TB-Feb'!K22+'TB-Mar'!K22+'TB-Apr'!K22+'TB-May'!K22+'TB-Jun'!K22+'TB-Jul'!K22+'TB-Aug'!K22+'TB-Sep'!K22+'TB-Oct'!K22+'TB-Nov'!K22+'TB-Dec'!K22 -> 0 | L22: ='TB-Jan'!L22+'TB-Feb'!L22+'TB-Mar'!L22+'TB-Apr'!L22+'TB-May'!L22+'TB-Jun'!L22+'TB-Jul'!L22+'TB-Aug'!L22+'TB-Sep'!L22+'TB-Oct'!L22+'TB-Nov'!L22+'TB-Dec'!L22 -> 0 | M22: ='TB-Jan'!M22+'TB-Feb'!M22+'TB-Mar'!M22+'TB-Apr'!M22+'TB-May'!M22+'TB-Jun'!M22+'TB-Jul'!M22+'TB-Aug'!M22+'TB-Sep'!M22+'TB-Oct'!M22+'TB-Nov'!M22+'TB-Dec'!M22 -> 0 | N22: ='TB-Jan'!N22+'TB-Feb'!N22+'TB-Mar'!N22+'TB-Apr'!N22+'TB-May'!N22+'TB-Jun'!N22+'TB-Jul'!N22+'TB-Aug'!N22+'TB-Sep'!N22+'TB-Oct'!N22+'TB-Nov'!N22+'TB-Dec'!N22 -> 0
A23: Cash in Bank - Foreign Currency, Current Account | B23: 115 | C23: =E23-F23 -> 0 | E23: =SUM(G23,I23,K23,M23) -> 0 | F23: =SUM(H23,J23,L23,N23) -> 0 | G23: ='TB-Jan'!G23+'TB-Feb'!G23+'TB-Mar'!G23+'TB-Apr'!G23+'TB-May'!G23+'TB-Jun'!G23+'TB-Jul'!G23+'TB-Aug'!G23+'TB-Sep'!G23+'TB-Oct'!G23+'TB-Nov'!G23+'TB-Dec'!G23 -> 0 | H23: ='TB-Jan'!H23+'TB-Feb'!H23+'TB-Mar'!H23+'TB-Apr'!H23+'TB-May'!H23+'TB-Jun'!H23+'TB-Jul'!H23+'TB-Aug'!H23+'TB-Sep'!H23+'TB-Oct'!H23+'TB-Nov'!H23+'TB-Dec'!H23 -> 0 | I23: ='TB-Jan'!I23+'TB-Feb'!I23+'TB-Mar'!I23+'TB-Apr'!I23+'TB-May'!I23+'TB-Jun'!I23+'TB-Jul'!I23+'TB-Aug'!I23+'TB-Sep'!I23+'TB-Oct'!I23+'TB-Nov'!I23+'TB-Dec'!I23 -> 0 | J23: ='TB-Jan'!J23+'TB-Feb'!J23+'TB-Mar'!J23+'TB-Apr'!J23+'TB-May'!J23+'TB-Jun'!J23+'TB-Jul'!J23+'TB-Aug'!J23+'TB-Sep'!J23+'TB-Oct'!J23+'TB-Nov'!J23+'TB-Dec'!J23 -> 0 | K23: ='TB-Jan'!K23+'TB-Feb'!K23+'TB-Mar'!K23+'TB-Apr'!K23+'TB-May'!K23+'TB-Jun'!K23+'TB-Jul'!K23+'TB-Aug'!K23+'TB-Sep'!K23+'TB-Oct'!K23+'TB-Nov'!K23+'TB-Dec'!K23 -> 0 | L23: ='TB-Jan'!L23+'TB-Feb'!L23+'TB-Mar'!L23+'TB-Apr'!L23+'TB-May'!L23+'TB-Jun'!L23+'TB-Jul'!L23+'TB-Aug'!L23+'TB-Sep'!L23+'TB-Oct'!L23+'TB-Nov'!L23+'TB-Dec'!L23 -> 0 | M23: ='TB-Jan'!M23+'TB-Feb'!M23+'TB-Mar'!M23+'TB-Apr'!M23+'TB-May'!M23+'TB-Jun'!M23+'TB-Jul'!M23+'TB-Aug'!M23+'TB-Sep'!M23+'TB-Oct'!M23+'TB-Nov'!M23+'TB-Dec'!M23 -> 0 | N23: ='TB-Jan'!N23+'TB-Feb'!N23+'TB-Mar'!N23+'TB-Apr'!N23+'TB-May'!N23+'TB-Jun'!N23+'TB-Jul'!N23+'TB-Aug'!N23+'TB-Sep'!N23+'TB-Oct'!N23+'TB-Nov'!N23+'TB-Dec'!N23 -> 0
A24: Cash in Bank - Foreign Currency, Savings Account | B24: 116 | C24: =E24-F24 -> 0 | E24: =SUM(G24,I24,K24,M24) -> 0 | F24: =SUM(H24,J24,L24,N24) -> 0 | G24: ='TB-Jan'!G24+'TB-Feb'!G24+'TB-Mar'!G24+'TB-Apr'!G24+'TB-May'!G24+'TB-Jun'!G24+'TB-Jul'!G24+'TB-Aug'!G24+'TB-Sep'!G24+'TB-Oct'!G24+'TB-Nov'!G24+'TB-Dec'!G24 -> 0 | H24: ='TB-Jan'!H24+'TB-Feb'!H24+'TB-Mar'!H24+'TB-Apr'!H24+'TB-May'!H24+'TB-Jun'!H24+'TB-Jul'!H24+'TB-Aug'!H24+'TB-Sep'!H24+'TB-Oct'!H24+'TB-Nov'!H24+'TB-Dec'!H24 -> 0 | I24: ='TB-Jan'!I24+'TB-Feb'!I24+'TB-Mar'!I24+'TB-Apr'!I24+'TB-May'!I24+'TB-Jun'!I24+'TB-Jul'!I24+'TB-Aug'!I24+'TB-Sep'!I24+'TB-Oct'!I24+'TB-Nov'!I24+'TB-Dec'!I24 -> 0 | J24: ='TB-Jan'!J24+'TB-Feb'!J24+'TB-Mar'!J24+'TB-Apr'!J24+'TB-May'!J24+'TB-Jun'!J24+'TB-Jul'!J24+'TB-Aug'!J24+'TB-Sep'!J24+'TB-Oct'!J24+'TB-Nov'!J24+'TB-Dec'!J24 -> 0 | K24: ='TB-Jan'!K24+'TB-Feb'!K24+'TB-Mar'!K24+'TB-Apr'!K24+'TB-May'!K24+'TB-Jun'!K24+'TB-Jul'!K24+'TB-Aug'!K24+'TB-Sep'!K24+'TB-Oct'!K24+'TB-Nov'!K24+'TB-Dec'!K24 -> 0 | L24: ='TB-Jan'!L24+'TB-Feb'!L24+'TB-Mar'!L24+'TB-Apr'!L24+'TB-May'!L24+'TB-Jun'!L24+'TB-Jul'!L24+'TB-Aug'!L24+'TB-Sep'!L24+'TB-Oct'!L24+'TB-Nov'!L24+'TB-Dec'!L24 -> 0 | M24: ='TB-Jan'!M24+'TB-Feb'!M24+'TB-Mar'!M24+'TB-Apr'!M24+'TB-May'!M24+'TB-Jun'!M24+'TB-Jul'!M24+'TB-Aug'!M24+'TB-Sep'!M24+'TB-Oct'!M24+'TB-Nov'!M24+'TB-Dec'!M24 -> 0 | N24: ='TB-Jan'!N24+'TB-Feb'!N24+'TB-Mar'!N24+'TB-Apr'!N24+'TB-May'!N24+'TB-Jun'!N24+'TB-Jul'!N24+'TB-Aug'!N24+'TB-Sep'!N24+'TB-Oct'!N24+'TB-Nov'!N24+'TB-Dec'!N24 -> 0
A25: Cash in Bank - Foreign Currency, Time Deposits | B25: 117 | C25: =E25-F25 -> 0 | E25: =SUM(G25,I25,K25,M25) -> 0 | F25: =SUM(H25,J25,L25,N25) -> 0 | G25: ='TB-Jan'!G25+'TB-Feb'!G25+'TB-Mar'!G25+'TB-Apr'!G25+'TB-May'!G25+'TB-Jun'!G25+'TB-Jul'!G25+'TB-Aug'!G25+'TB-Sep'!G25+'TB-Oct'!G25+'TB-Nov'!G25+'TB-Dec'!G25 -> 0 | H25: ='TB-Jan'!H25+'TB-Feb'!H25+'TB-Mar'!H25+'TB-Apr'!H25+'TB-May'!H25+'TB-Jun'!H25+'TB-Jul'!H25+'TB-Aug'!H25+'TB-Sep'!H25+'TB-Oct'!H25+'TB-Nov'!H25+'TB-Dec'!H25 -> 0 | I25: ='TB-Jan'!I25+'TB-Feb'!I25+'TB-Mar'!I25+'TB-Apr'!I25+'TB-May'!I25+'TB-Jun'!I25+'TB-Jul'!I25+'TB-Aug'!I25+'TB-Sep'!I25+'TB-Oct'!I25+'TB-Nov'!I25+'TB-Dec'!I25 -> 0 | J25: ='TB-Jan'!J25+'TB-Feb'!J25+'TB-Mar'!J25+'TB-Apr'!J25+'TB-May'!J25+'TB-Jun'!J25+'TB-Jul'!J25+'TB-Aug'!J25+'TB-Sep'!J25+'TB-Oct'!J25+'TB-Nov'!J25+'TB-Dec'!J25 -> 0 | K25: ='TB-Jan'!K25+'TB-Feb'!K25+'TB-Mar'!K25+'TB-Apr'!K25+'TB-May'!K25+'TB-Jun'!K25+'TB-Jul'!K25+'TB-Aug'!K25+'TB-Sep'!K25+'TB-Oct'!K25+'TB-Nov'!K25+'TB-Dec'!K25 -> 0 | L25: ='TB-Jan'!L25+'TB-Feb'!L25+'TB-Mar'!L25+'TB-Apr'!L25+'TB-May'!L25+'TB-Jun'!L25+'TB-Jul'!L25+'TB-Aug'!L25+'TB-Sep'!L25+'TB-Oct'!L25+'TB-Nov'!L25+'TB-Dec'!L25 -> 0 | M25: ='TB-Jan'!M25+'TB-Feb'!M25+'TB-Mar'!M25+'TB-Apr'!M25+'TB-May'!M25+'TB-Jun'!M25+'TB-Jul'!M25+'TB-Aug'!M25+'TB-Sep'!M25+'TB-Oct'!M25+'TB-Nov'!M25+'TB-Dec'!M25 -> 0 | N25: ='TB-Jan'!N25+'TB-Feb'!N25+'TB-Mar'!N25+'TB-Apr'!N25+'TB-May'!N25+'TB-Jun'!N25+'TB-Jul'!N25+'TB-Aug'!N25+'TB-Sep'!N25+'TB-Oct'!N25+'TB-Nov'!N25+'TB-Dec'!N25 -> 0
A26: Accounts Receivable | B26: 121 | C26: =E26-F26 -> 0 | E26: =SUM(G26,I26,K26,M26) -> 0 | F26: =SUM(H26,J26,L26,N26) -> 0 | G26: ='TB-Jan'!G26+'TB-Feb'!G26+'TB-Mar'!G26+'TB-Apr'!G26+'TB-May'!G26+'TB-Jun'!G26+'TB-Jul'!G26+'TB-Aug'!G26+'TB-Sep'!G26+'TB-Oct'!G26+'TB-Nov'!G26+'TB-Dec'!G26 -> 0 | H26: ='TB-Jan'!H26+'TB-Feb'!H26+'TB-Mar'!H26+'TB-Apr'!H26+'TB-May'!H26+'TB-Jun'!H26+'TB-Jul'!H26+'TB-Aug'!H26+'TB-Sep'!H26+'TB-Oct'!H26+'TB-Nov'!H26+'TB-Dec'!H26 -> 0 | I26: ='TB-Jan'!I26+'TB-Feb'!I26+'TB-Mar'!I26+'TB-Apr'!I26+'TB-May'!I26+'TB-Jun'!I26+'TB-Jul'!I26+'TB-Aug'!I26+'TB-Sep'!I26+'TB-Oct'!I26+'TB-Nov'!I26+'TB-Dec'!I26 -> 0 | J26: ='TB-Jan'!J26+'TB-Feb'!J26+'TB-Mar'!J26+'TB-Apr'!J26+'TB-May'!J26+'TB-Jun'!J26+'TB-Jul'!J26+'TB-Aug'!J26+'TB-Sep'!J26+'TB-Oct'!J26+'TB-Nov'!J26+'TB-Dec'!J26 -> 0 | K26: ='TB-Jan'!K26+'TB-Feb'!K26+'TB-Mar'!K26+'TB-Apr'!K26+'TB-May'!K26+'TB-Jun'!K26+'TB-Jul'!K26+'TB-Aug'!K26+'TB-Sep'!K26+'TB-Oct'!K26+'TB-Nov'!K26+'TB-Dec'!K26 -> 0 | L26: ='TB-Jan'!L26+'TB-Feb'!L26+'TB-Mar'!L26+'TB-Apr'!L26+'TB-May'!L26+'TB-Jun'!L26+'TB-Jul'!L26+'TB-Aug'!L26+'TB-Sep'!L26+'TB-Oct'!L26+'TB-Nov'!L26+'TB-Dec'!L26 -> 0 | M26: ='TB-Jan'!M26+'TB-Feb'!M26+'TB-Mar'!M26+'TB-Apr'!M26+'TB-May'!M26+'TB-Jun'!M26+'TB-Jul'!M26+'TB-Aug'!M26+'TB-Sep'!M26+'TB-Oct'!M26+'TB-Nov'!M26+'TB-Dec'!M26 -> 0 | N26: ='TB-Jan'!N26+'TB-Feb'!N26+'TB-Mar'!N26+'TB-Apr'!N26+'TB-May'!N26+'TB-Jun'!N26+'TB-Jul'!N26+'TB-Aug'!N26+'TB-Sep'!N26+'TB-Oct'!N26+'TB-Nov'!N26+'TB-Dec'!N26 -> 0
A27: Allowance for Doubtful Accounts | B27: 301 | C27: =E27-F27 -> 0 | E27: =SUM(G27,I27,K27,M27) -> 0 | F27: =SUM(H27,J27,L27,N27) -> 0 | G27: ='TB-Jan'!G27+'TB-Feb'!G27+'TB-Mar'!G27+'TB-Apr'!G27+'TB-May'!G27+'TB-Jun'!G27+'TB-Jul'!G27+'TB-Aug'!G27+'TB-Sep'!G27+'TB-Oct'!G27+'TB-Nov'!G27+'TB-Dec'!G27 -> 0 | H27: ='TB-Jan'!H27+'TB-Feb'!H27+'TB-Mar'!H27+'TB-Apr'!H27+'TB-May'!H27+'TB-Jun'!H27+'TB-Jul'!H27+'TB-Aug'!H27+'TB-Sep'!H27+'TB-Oct'!H27+'TB-Nov'!H27+'TB-Dec'!H27 -> 0 | I27: ='TB-Jan'!I27+'TB-Feb'!I27+'TB-Mar'!I27+'TB-Apr'!I27+'TB-May'!I27+'TB-Jun'!I27+'TB-Jul'!I27+'TB-Aug'!I27+'TB-Sep'!I27+'TB-Oct'!I27+'TB-Nov'!I27+'TB-Dec'!I27 -> 0 | J27: ='TB-Jan'!J27+'TB-Feb'!J27+'TB-Mar'!J27+'TB-Apr'!J27+'TB-May'!J27+'TB-Jun'!J27+'TB-Jul'!J27+'TB-Aug'!J27+'TB-Sep'!J27+'TB-Oct'!J27+'TB-Nov'!J27+'TB-Dec'!J27 -> 0 | K27: ='TB-Jan'!K27+'TB-Feb'!K27+'TB-Mar'!K27+'TB-Apr'!K27+'TB-May'!K27+'TB-Jun'!K27+'TB-Jul'!K27+'TB-Aug'!K27+'TB-Sep'!K27+'TB-Oct'!K27+'TB-Nov'!K27+'TB-Dec'!K27 -> 0 | L27: ='TB-Jan'!L27+'TB-Feb'!L27+'TB-Mar'!L27+'TB-Apr'!L27+'TB-May'!L27+'TB-Jun'!L27+'TB-Jul'!L27+'TB-Aug'!L27+'TB-Sep'!L27+'TB-Oct'!L27+'TB-Nov'!L27+'TB-Dec'!L27 -> 0 | M27: ='TB-Jan'!M27+'TB-Feb'!M27+'TB-Mar'!M27+'TB-Apr'!M27+'TB-May'!M27+'TB-Jun'!M27+'TB-Jul'!M27+'TB-Aug'!M27+'TB-Sep'!M27+'TB-Oct'!M27+'TB-Nov'!M27+'TB-Dec'!M27 -> 0 | N27: ='TB-Jan'!N27+'TB-Feb'!N27+'TB-Mar'!N27+'TB-Apr'!N27+'TB-May'!N27+'TB-Jun'!N27+'TB-Jul'!N27+'TB-Aug'!N27+'TB-Sep'!N27+'TB-Oct'!N27+'TB-Nov'!N27+'TB-Dec'!N27 -> 0
A28: Notes Receivable | B28: 122 | C28: =E28-F28 -> 0 | E28: =SUM(G28,I28,K28,M28) -> 0 | F28: =SUM(H28,J28,L28,N28) -> 0 | G28: ='TB-Jan'!G28+'TB-Feb'!G28+'TB-Mar'!G28+'TB-Apr'!G28+'TB-May'!G28+'TB-Jun'!G28+'TB-Jul'!G28+'TB-Aug'!G28+'TB-Sep'!G28+'TB-Oct'!G28+'TB-Nov'!G28+'TB-Dec'!G28 -> 0 | H28: ='TB-Jan'!H28+'TB-Feb'!H28+'TB-Mar'!H28+'TB-Apr'!H28+'TB-May'!H28+'TB-Jun'!H28+'TB-Jul'!H28+'TB-Aug'!H28+'TB-Sep'!H28+'TB-Oct'!H28+'TB-Nov'!H28+'TB-Dec'!H28 -> 0 | I28: ='TB-Jan'!I28+'TB-Feb'!I28+'TB-Mar'!I28+'TB-Apr'!I28+'TB-May'!I28+'TB-Jun'!I28+'TB-Jul'!I28+'TB-Aug'!I28+'TB-Sep'!I28+'TB-Oct'!I28+'TB-Nov'!I28+'TB-Dec'!I28 -> 0 | J28: ='TB-Jan'!J28+'TB-Feb'!J28+'TB-Mar'!J28+'TB-Apr'!J28+'TB-May'!J28+'TB-Jun'!J28+'TB-Jul'!J28+'TB-Aug'!J28+'TB-Sep'!J28+'TB-Oct'!J28+'TB-Nov'!J28+'TB-Dec'!J28 -> 0 | K28: ='TB-Jan'!K28+'TB-Feb'!K28+'TB-Mar'!K28+'TB-Apr'!K28+'TB-May'!K28+'TB-Jun'!K28+'TB-Jul'!K28+'TB-Aug'!K28+'TB-Sep'!K28+'TB-Oct'!K28+'TB-Nov'!K28+'TB-Dec'!K28 -> 0 | L28: ='TB-Jan'!L28+'TB-Feb'!L28+'TB-Mar'!L28+'TB-Apr'!L28+'TB-May'!L28+'TB-Jun'!L28+'TB-Jul'!L28+'TB-Aug'!L28+'TB-Sep'!L28+'TB-Oct'!L28+'TB-Nov'!L28+'TB-Dec'!L28 -> 0 | M28: ='TB-Jan'!M28+'TB-Feb'!M28+'TB-Mar'!M28+'TB-Apr'!M28+'TB-May'!M28+'TB-Jun'!M28+'TB-Jul'!M28+'TB-Aug'!M28+'TB-Sep'!M28+'TB-Oct'!M28+'TB-Nov'!M28+'TB-Dec'!M28 -> 0 | N28: ='TB-Jan'!N28+'TB-Feb'!N28+'TB-Mar'!N28+'TB-Apr'!N28+'TB-May'!N28+'TB-Jun'!N28+'TB-Jul'!N28+'TB-Aug'!N28+'TB-Sep'!N28+'TB-Oct'!N28+'TB-Nov'!N28+'TB-Dec'!N28 -> 0
A29: Due from Officers and Employees | B29: 123 | C29: =E29-F29 -> 0 | E29: =SUM(G29,I29,K29,M29) -> 0 | F29: =SUM(H29,J29,L29,N29) -> 0 | G29: ='TB-Jan'!G29+'TB-Feb'!G29+'TB-Mar'!G29+'TB-Apr'!G29+'TB-May'!G29+'TB-Jun'!G29+'TB-Jul'!G29+'TB-Aug'!G29+'TB-Sep'!G29+'TB-Oct'!G29+'TB-Nov'!G29+'TB-Dec'!G29 -> 0 | H29: ='TB-Jan'!H29+'TB-Feb'!H29+'TB-Mar'!H29+'TB-Apr'!H29+'TB-May'!H29+'TB-Jun'!H29+'TB-Jul'!H29+'TB-Aug'!H29+'TB-Sep'!H29+'TB-Oct'!H29+'TB-Nov'!H29+'TB-Dec'!H29 -> 0 | I29: ='TB-Jan'!I29+'TB-Feb'!I29+'TB-Mar'!I29+'TB-Apr'!I29+'TB-May'!I29+'TB-Jun'!I29+'TB-Jul'!I29+'TB-Aug'!I29+'TB-Sep'!I29+'TB-Oct'!I29+'TB-Nov'!I29+'TB-Dec'!I29 -> 0 | J29: ='TB-Jan'!J29+'TB-Feb'!J29+'TB-Mar'!J29+'TB-Apr'!J29+'TB-May'!J29+'TB-Jun'!J29+'TB-Jul'!J29+'TB-Aug'!J29+'TB-Sep'!J29+'TB-Oct'!J29+'TB-Nov'!J29+'TB-Dec'!J29 -> 0 | K29: ='TB-Jan'!K29+'TB-Feb'!K29+'TB-Mar'!K29+'TB-Apr'!K29+'TB-May'!K29+'TB-Jun'!K29+'TB-Jul'!K29+'TB-Aug'!K29+'TB-Sep'!K29+'TB-Oct'!K29+'TB-Nov'!K29+'TB-Dec'!K29 -> 0 | L29: ='TB-Jan'!L29+'TB-Feb'!L29+'TB-Mar'!L29+'TB-Apr'!L29+'TB-May'!L29+'TB-Jun'!L29+'TB-Jul'!L29+'TB-Aug'!L29+'TB-Sep'!L29+'TB-Oct'!L29+'TB-Nov'!L29+'TB-Dec'!L29 -> 0 | M29: ='TB-Jan'!M29+'TB-Feb'!M29+'TB-Mar'!M29+'TB-Apr'!M29+'TB-May'!M29+'TB-Jun'!M29+'TB-Jul'!M29+'TB-Aug'!M29+'TB-Sep'!M29+'TB-Oct'!M29+'TB-Nov'!M29+'TB-Dec'!M29 -> 0 | N29: ='TB-Jan'!N29+'TB-Feb'!N29+'TB-Mar'!N29+'TB-Apr'!N29+'TB-May'!N29+'TB-Jun'!N29+'TB-Jul'!N29+'TB-Aug'!N29+'TB-Sep'!N29+'TB-Oct'!N29+'TB-Nov'!N29+'TB-Dec'!N29 -> 0
A30: Loans Receivable - GOCCs | B30: 124 | C30: =E30-F30 -> 0 | E30: =SUM(G30,I30,K30,M30) -> 0 | F30: =SUM(H30,J30,L30,N30) -> 0 | G30: ='TB-Jan'!G30+'TB-Feb'!G30+'TB-Mar'!G30+'TB-Apr'!G30+'TB-May'!G30+'TB-Jun'!G30+'TB-Jul'!G30+'TB-Aug'!G30+'TB-Sep'!G30+'TB-Oct'!G30+'TB-Nov'!G30+'TB-Dec'!G30 -> 0 | H30: ='TB-Jan'!H30+'TB-Feb'!H30+'TB-Mar'!H30+'TB-Apr'!H30+'TB-May'!H30+'TB-Jun'!H30+'TB-Jul'!H30+'TB-Aug'!H30+'TB-Sep'!H30+'TB-Oct'!H30+'TB-Nov'!H30+'TB-Dec'!H30 -> 0 | I30: ='TB-Jan'!I30+'TB-Feb'!I30+'TB-Mar'!I30+'TB-Apr'!I30+'TB-May'!I30+'TB-Jun'!I30+'TB-Jul'!I30+'TB-Aug'!I30+'TB-Sep'!I30+'TB-Oct'!I30+'TB-Nov'!I30+'TB-Dec'!I30 -> 0 | J30: ='TB-Jan'!J30+'TB-Feb'!J30+'TB-Mar'!J30+'TB-Apr'!J30+'TB-May'!J30+'TB-Jun'!J30+'TB-Jul'!J30+'TB-Aug'!J30+'TB-Sep'!J30+'TB-Oct'!J30+'TB-Nov'!J30+'TB-Dec'!J30 -> 0 | K30: ='TB-Jan'!K30+'TB-Feb'!K30+'TB-Mar'!K30+'TB-Apr'!K30+'TB-May'!K30+'TB-Jun'!K30+'TB-Jul'!K30+'TB-Aug'!K30+'TB-Sep'!K30+'TB-Oct'!K30+'TB-Nov'!K30+'TB-Dec'!K30 -> 0 | L30: ='TB-Jan'!L30+'TB-Feb'!L30+'TB-Mar'!L30+'TB-Apr'!L30+'TB-May'!L30+'TB-Jun'!L30+'TB-Jul'!L30+'TB-Aug'!L30+'TB-Sep'!L30+'TB-Oct'!L30+'TB-Nov'!L30+'TB-Dec'!L30 -> 0 | M30: ='TB-Jan'!M30+'TB-Feb'!M30+'TB-Mar'!M30+'TB-Apr'!M30+'TB-May'!M30+'TB-Jun'!M30+'TB-Jul'!M30+'TB-Aug'!M30+'TB-Sep'!M30+'TB-Oct'!M30+'TB-Nov'!M30+'TB-Dec'!M30 -> 0 | N30: ='TB-Jan'!N30+'TB-Feb'!N30+'TB-Mar'!N30+'TB-Apr'!N30+'TB-May'!N30+'TB-Jun'!N30+'TB-Jul'!N30+'TB-Aug'!N30+'TB-Sep'!N30+'TB-Oct'!N30+'TB-Nov'!N30+'TB-Dec'!N30 -> 0
A31: Loans Receivable - LGUs | B31: 125 | C31: =E31-F31 -> 0 | E31: =SUM(G31,I31,K31,M31) -> 0 | F31: =SUM(H31,J31,L31,N31) -> 0 | G31: ='TB-Jan'!G31+'TB-Feb'!G31+'TB-Mar'!G31+'TB-Apr'!G31+'TB-May'!G31+'TB-Jun'!G31+'TB-Jul'!G31+'TB-Aug'!G31+'TB-Sep'!G31+'TB-Oct'!G31+'TB-Nov'!G31+'TB-Dec'!G31 -> 0 | H31: ='TB-Jan'!H31+'TB-Feb'!H31+'TB-Mar'!H31+'TB-Apr'!H31+'TB-May'!H31+'TB-Jun'!H31+'TB-Jul'!H31+'TB-Aug'!H31+'TB-Sep'!H31+'TB-Oct'!H31+'TB-Nov'!H31+'TB-Dec'!H31 -> 0 | I31: ='TB-Jan'!I31+'TB-Feb'!I31+'TB-Mar'!I31+'TB-Apr'!I31+'TB-May'!I31+'TB-Jun'!I31+'TB-Jul'!I31+'TB-Aug'!I31+'TB-Sep'!I31+'TB-Oct'!I31+'TB-Nov'!I31+'TB-Dec'!I31 -> 0 | J31: ='TB-Jan'!J31+'TB-Feb'!J31+'TB-Mar'!J31+'TB-Apr'!J31+'TB-May'!J31+'TB-Jun'!J31+'TB-Jul'!J31+'TB-Aug'!J31+'TB-Sep'!J31+'TB-Oct'!J31+'TB-Nov'!J31+'TB-Dec'!J31 -> 0 | K31: ='TB-Jan'!K31+'TB-Feb'!K31+'TB-Mar'!K31+'TB-Apr'!K31+'TB-May'!K31+'TB-Jun'!K31+'TB-Jul'!K31+'TB-Aug'!K31+'TB-Sep'!K31+'TB-Oct'!K31+'TB-Nov'!K31+'TB-Dec'!K31 -> 0 | L31: ='TB-Jan'!L31+'TB-Feb'!L31+'TB-Mar'!L31+'TB-Apr'!L31+'TB-May'!L31+'TB-Jun'!L31+'TB-Jul'!L31+'TB-Aug'!L31+'TB-Sep'!L31+'TB-Oct'!L31+'TB-Nov'!L31+'TB-Dec'!L31 -> 0 | M31: ='TB-Jan'!M31+'TB-Feb'!M31+'TB-Mar'!M31+'TB-Apr'!M31+'TB-May'!M31+'TB-Jun'!M31+'TB-Jul'!M31+'TB-Aug'!M31+'TB-Sep'!M31+'TB-Oct'!M31+'TB-Nov'!M31+'TB-Dec'!M31 -> 0 | N31: ='TB-Jan'!N31+'TB-Feb'!N31+'TB-Mar'!N31+'TB-Apr'!N31+'TB-May'!N31+'TB-Jun'!N31+'TB-Jul'!N31+'TB-Aug'!N31+'TB-Sep'!N31+'TB-Oct'!N31+'TB-Nov'!N31+'TB-Dec'!N31 -> 0
A32: Loans Receivable - Others | B32: 126 | C32: =E32-F32 -> 0 | E32: =SUM(G32,I32,K32,M32) -> 0 | F32: =SUM(H32,J32,L32,N32) -> 0 | G32: ='TB-Jan'!G32+'TB-Feb'!G32+'TB-Mar'!G32+'TB-Apr'!G32+'TB-May'!G32+'TB-Jun'!G32+'TB-Jul'!G32+'TB-Aug'!G32+'TB-Sep'!G32+'TB-Oct'!G32+'TB-Nov'!G32+'TB-Dec'!G32 -> 0 | H32: ='TB-Jan'!H32+'TB-Feb'!H32+'TB-Mar'!H32+'TB-Apr'!H32+'TB-May'!H32+'TB-Jun'!H32+'TB-Jul'!H32+'TB-Aug'!H32+'TB-Sep'!H32+'TB-Oct'!H32+'TB-Nov'!H32+'TB-Dec'!H32 -> 0 | I32: ='TB-Jan'!I32+'TB-Feb'!I32+'TB-Mar'!I32+'TB-Apr'!I32+'TB-May'!I32+'TB-Jun'!I32+'TB-Jul'!I32+'TB-Aug'!I32+'TB-Sep'!I32+'TB-Oct'!I32+'TB-Nov'!I32+'TB-Dec'!I32 -> 0 | J32: ='TB-Jan'!J32+'TB-Feb'!J32+'TB-Mar'!J32+'TB-Apr'!J32+'TB-May'!J32+'TB-Jun'!J32+'TB-Jul'!J32+'TB-Aug'!J32+'TB-Sep'!J32+'TB-Oct'!J32+'TB-Nov'!J32+'TB-Dec'!J32 -> 0 | K32: ='TB-Jan'!K32+'TB-Feb'!K32+'TB-Mar'!K32+'TB-Apr'!K32+'TB-May'!K32+'TB-Jun'!K32+'TB-Jul'!K32+'TB-Aug'!K32+'TB-Sep'!K32+'TB-Oct'!K32+'TB-Nov'!K32+'TB-Dec'!K32 -> 0 | L32: ='TB-Jan'!L32+'TB-Feb'!L32+'TB-Mar'!L32+'TB-Apr'!L32+'TB-May'!L32+'TB-Jun'!L32+'TB-Jul'!L32+'TB-Aug'!L32+'TB-Sep'!L32+'TB-Oct'!L32+'TB-Nov'!L32+'TB-Dec'!L32 -> 0 | M32: ='TB-Jan'!M32+'TB-Feb'!M32+'TB-Mar'!M32+'TB-Apr'!M32+'TB-May'!M32+'TB-Jun'!M32+'TB-Jul'!M32+'TB-Aug'!M32+'TB-Sep'!M32+'TB-Oct'!M32+'TB-Nov'!M32+'TB-Dec'!M32 -> 0 | N32: ='TB-Jan'!N32+'TB-Feb'!N32+'TB-Mar'!N32+'TB-Apr'!N32+'TB-May'!N32+'TB-Jun'!N32+'TB-Jul'!N32+'TB-Aug'!N32+'TB-Sep'!N32+'TB-Oct'!N32+'TB-Nov'!N32+'TB-Dec'!N32 -> 0
A33: Real Property Tax Receivable | B33: 127 | C33: =E33-F33 -> 0 | E33: =SUM(G33,I33,K33,M33) -> 0 | F33: =SUM(H33,J33,L33,N33) -> 0 | G33: ='TB-Jan'!G33+'TB-Feb'!G33+'TB-Mar'!G33+'TB-Apr'!G33+'TB-May'!G33+'TB-Jun'!G33+'TB-Jul'!G33+'TB-Aug'!G33+'TB-Sep'!G33+'TB-Oct'!G33+'TB-Nov'!G33+'TB-Dec'!G33 -> 0 | H33: ='TB-Jan'!H33+'TB-Feb'!H33+'TB-Mar'!H33+'TB-Apr'!H33+'TB-May'!H33+'TB-Jun'!H33+'TB-Jul'!H33+'TB-Aug'!H33+'TB-Sep'!H33+'TB-Oct'!H33+'TB-Nov'!H33+'TB-Dec'!H33 -> 0 | I33: ='TB-Jan'!I33+'TB-Feb'!I33+'TB-Mar'!I33+'TB-Apr'!I33+'TB-May'!I33+'TB-Jun'!I33+'TB-Jul'!I33+'TB-Aug'!I33+'TB-Sep'!I33+'TB-Oct'!I33+'TB-Nov'!I33+'TB-Dec'!I33 -> 0 | J33: ='TB-Jan'!J33+'TB-Feb'!J33+'TB-Mar'!J33+'TB-Apr'!J33+'TB-May'!J33+'TB-Jun'!J33+'TB-Jul'!J33+'TB-Aug'!J33+'TB-Sep'!J33+'TB-Oct'!J33+'TB-Nov'!J33+'TB-Dec'!J33 -> 0 | K33: ='TB-Jan'!K33+'TB-Feb'!K33+'TB-Mar'!K33+'TB-Apr'!K33+'TB-May'!K33+'TB-Jun'!K33+'TB-Jul'!K33+'TB-Aug'!K33+'TB-Sep'!K33+'TB-Oct'!K33+'TB-Nov'!K33+'TB-Dec'!K33 -> 0 | L33: ='TB-Jan'!L33+'TB-Feb'!L33+'TB-Mar'!L33+'TB-Apr'!L33+'TB-May'!L33+'TB-Jun'!L33+'TB-Jul'!L33+'TB-Aug'!L33+'TB-Sep'!L33+'TB-Oct'!L33+'TB-Nov'!L33+'TB-Dec'!L33 -> 0 | M33: ='TB-Jan'!M33+'TB-Feb'!M33+'TB-Mar'!M33+'TB-Apr'!M33+'TB-May'!M33+'TB-Jun'!M33+'TB-Jul'!M33+'TB-Aug'!M33+'TB-Sep'!M33+'TB-Oct'!M33+'TB-Nov'!M33+'TB-Dec'!M33 -> 0 | N33: ='TB-Jan'!N33+'TB-Feb'!N33+'TB-Mar'!N33+'TB-Apr'!N33+'TB-May'!N33+'TB-Jun'!N33+'TB-Jul'!N33+'TB-Aug'!N33+'TB-Sep'!N33+'TB-Oct'!N33+'TB-Nov'!N33+'TB-Dec'!N33 -> 0
A34: Special Education Tax Receivable | B34: 128 | C34: =E34-F34 -> 0 | E34: =SUM(G34,I34,K34,M34) -> 0 | F34: =SUM(H34,J34,L34,N34) -> 0 | G34: ='TB-Jan'!G34+'TB-Feb'!G34+'TB-Mar'!G34+'TB-Apr'!G34+'TB-May'!G34+'TB-Jun'!G34+'TB-Jul'!G34+'TB-Aug'!G34+'TB-Sep'!G34+'TB-Oct'!G34+'TB-Nov'!G34+'TB-Dec'!G34 -> 0 | H34: ='TB-Jan'!H34+'TB-Feb'!H34+'TB-Mar'!H34+'TB-Apr'!H34+'TB-May'!H34+'TB-Jun'!H34+'TB-Jul'!H34+'TB-Aug'!H34+'TB-Sep'!H34+'TB-Oct'!H34+'TB-Nov'!H34+'TB-Dec'!H34 -> 0 | I34: ='TB-Jan'!I34+'TB-Feb'!I34+'TB-Mar'!I34+'TB-Apr'!I34+'TB-May'!I34+'TB-Jun'!I34+'TB-Jul'!I34+'TB-Aug'!I34+'TB-Sep'!I34+'TB-Oct'!I34+'TB-Nov'!I34+'TB-Dec'!I34 -> 0 | J34: ='TB-Jan'!J34+'TB-Feb'!J34+'TB-Mar'!J34+'TB-Apr'!J34+'TB-May'!J34+'TB-Jun'!J34+'TB-Jul'!J34+'TB-Aug'!J34+'TB-Sep'!J34+'TB-Oct'!J34+'TB-Nov'!J34+'TB-Dec'!J34 -> 0 | K34: ='TB-Jan'!K34+'TB-Feb'!K34+'TB-Mar'!K34+'TB-Apr'!K34+'TB-May'!K34+'TB-Jun'!K34+'TB-Jul'!K34+'TB-Aug'!K34+'TB-Sep'!K34+'TB-Oct'!K34+'TB-Nov'!K34+'TB-Dec'!K34 -> 0 | L34: ='TB-Jan'!L34+'TB-Feb'!L34+'TB-Mar'!L34+'TB-Apr'!L34+'TB-May'!L34+'TB-Jun'!L34+'TB-Jul'!L34+'TB-Aug'!L34+'TB-Sep'!L34+'TB-Oct'!L34+'TB-Nov'!L34+'TB-Dec'!L34 -> 0 | M34: ='TB-Jan'!M34+'TB-Feb'!M34+'TB-Mar'!M34+'TB-Apr'!M34+'TB-May'!M34+'TB-Jun'!M34+'TB-Jul'!M34+'TB-Aug'!M34+'TB-Sep'!M34+'TB-Oct'!M34+'TB-Nov'!M34+'TB-Dec'!M34 -> 0 | N34: ='TB-Jan'!N34+'TB-Feb'!N34+'TB-Mar'!N34+'TB-Apr'!N34+'TB-May'!N34+'TB-Jun'!N34+'TB-Jul'!N34+'TB-Aug'!N34+'TB-Sep'!N34+'TB-Oct'!N34+'TB-Nov'!N34+'TB-Dec'!N34 -> 0
A35: Interests Receivable | B35: 129 | C35: =E35-F35 -> 0 | E35: =SUM(G35,I35,K35,M35) -> 0 | F35: =SUM(H35,J35,L35,N35) -> 0 | G35: ='TB-Jan'!G35+'TB-Feb'!G35+'TB-Mar'!G35+'TB-Apr'!G35+'TB-May'!G35+'TB-Jun'!G35+'TB-Jul'!G35+'TB-Aug'!G35+'TB-Sep'!G35+'TB-Oct'!G35+'TB-Nov'!G35+'TB-Dec'!G35 -> 0 | H35: ='TB-Jan'!H35+'TB-Feb'!H35+'TB-Mar'!H35+'TB-Apr'!H35+'TB-May'!H35+'TB-Jun'!H35+'TB-Jul'!H35+'TB-Aug'!H35+'TB-Sep'!H35+'TB-Oct'!H35+'TB-Nov'!H35+'TB-Dec'!H35 -> 0 | I35: ='TB-Jan'!I35+'TB-Feb'!I35+'TB-Mar'!I35+'TB-Apr'!I35+'TB-May'!I35+'TB-Jun'!I35+'TB-Jul'!I35+'TB-Aug'!I35+'TB-Sep'!I35+'TB-Oct'!I35+'TB-Nov'!I35+'TB-Dec'!I35 -> 0 | J35: ='TB-Jan'!J35+'TB-Feb'!J35+'TB-Mar'!J35+'TB-Apr'!J35+'TB-May'!J35+'TB-Jun'!J35+'TB-Jul'!J35+'TB-Aug'!J35+'TB-Sep'!J35+'TB-Oct'!J35+'TB-Nov'!J35+'TB-Dec'!J35 -> 0 | K35: ='TB-Jan'!K35+'TB-Feb'!K35+'TB-Mar'!K35+'TB-Apr'!K35+'TB-May'!K35+'TB-Jun'!K35+'TB-Jul'!K35+'TB-Aug'!K35+'TB-Sep'!K35+'TB-Oct'!K35+'TB-Nov'!K35+'TB-Dec'!K35 -> 0 | L35: ='TB-Jan'!L35+'TB-Feb'!L35+'TB-Mar'!L35+'TB-Apr'!L35+'TB-May'!L35+'TB-Jun'!L35+'TB-Jul'!L35+'TB-Aug'!L35+'TB-Sep'!L35+'TB-Oct'!L35+'TB-Nov'!L35+'TB-Dec'!L35 -> 0 | M35: ='TB-Jan'!M35+'TB-Feb'!M35+'TB-Mar'!M35+'TB-Apr'!M35+'TB-May'!M35+'TB-Jun'!M35+'TB-Jul'!M35+'TB-Aug'!M35+'TB-Sep'!M35+'TB-Oct'!M35+'TB-Nov'!M35+'TB-Dec'!M35 -> 0 | N35: ='TB-Jan'!N35+'TB-Feb'!N35+'TB-Mar'!N35+'TB-Apr'!N35+'TB-May'!N35+'TB-Jun'!N35+'TB-Jul'!N35+'TB-Aug'!N35+'TB-Sep'!N35+'TB-Oct'!N35+'TB-Nov'!N35+'TB-Dec'!N35 -> 0
... A37: Due from GOCCs | B37: 137 | C37: =E37-F37 -> 0 | E37: =SUM(G37,I37,K37,M37) -> 0 | F37: =SUM(H37,J37,L37,N37) -> 0 | G37: ='TB-Jan'!G37+'TB-Feb'!G37+'TB-Mar'!G37+'TB-Apr'!G37+'TB-May'!G37+'TB-Jun'!G37+'TB-Jul'!G37+'TB-Aug'!G37+'TB-Sep'!G37+'TB-Oct'!G37+'TB-Nov'!G37+'TB-Dec'!G37 -> 0 | H37: ='TB-Jan'!H37+'TB-Feb'!H37+'TB-Mar'!H37+'TB-Apr'!H37+'TB-May'!H37+'TB-Jun'!H37+'TB-Jul'!H37+'TB-Aug'!H37+'TB-Sep'!H37+'TB-Oct'!H37+'TB-Nov'!H37+'TB-Dec'!H37 -> 0 | I37: ='TB-Jan'!I37+'TB-Feb'!I37+'TB-Mar'!I37+'TB-Apr'!I37+'TB-May'!I37+'TB-Jun'!I37+'TB-Jul'!I37+'TB-Aug'!I37+'TB-Sep'!I37+'TB-Oct'!I37+'TB-Nov'!I37+'TB-Dec'!I37 -> 0 | J37: ='TB-Jan'!J37+'TB-Feb'!J37+'TB-Mar'!J37+'TB-Apr'!J37+'TB-May'!J37+'TB-Jun'!J37+'TB-Jul'!J37+'TB-Aug'!J37+'TB-Sep'!J37+'TB-Oct'!J37+'TB-Nov'!J37+'TB-Dec'!J37 -> 0 | K37: ='TB-Jan'!K37+'TB-Feb'!K37+'TB-Mar'!K37+'TB-Apr'!K37+'TB-May'!K37+'TB-Jun'!K37+'TB-Jul'!K37+'TB-Aug'!K37+'TB-Sep'!K37+'TB-Oct'!K37+'TB-Nov'!K37+'TB-Dec'!K37 -> 0 | L37: ='TB-Jan'!L37+'TB-Feb'!L37+'TB-Mar'!L37+'TB-Apr'!L37+'TB-May'!L37+'TB-Jun'!L37+'TB-Jul'!L37+'TB-Aug'!L37+'TB-Sep'!L37+'TB-Oct'!L37+'TB-Nov'!L37+'TB-Dec'!L37 -> 0 | M37: ='TB-Jan'!M37+'TB-Feb'!M37+'TB-Mar'!M37+'TB-Apr'!M37+'TB-May'!M37+'TB-Jun'!M37+'TB-Jul'!M37+'TB-Aug'!M37+'TB-Sep'!M37+'TB-Oct'!M37+'TB-Nov'!M37+'TB-Dec'!M37 -> 0 | N37: ='TB-Jan'!N37+'TB-Feb'!N37+'TB-Mar'!N37+'TB-Apr'!N37+'TB-May'!N37+'TB-Jun'!N37+'TB-Jul'!N37+'TB-Aug'!N37+'TB-Sep'!N37+'TB-Oct'!N37+'TB-Nov'!N37+'TB-Dec'!N37 -> 0
A38: Due from LGUs | B38: 138 | C38: =E38-F38 -> 1183464.4 | E38: =SUM(G38,I38,K38,M38) -> 1183464.4 | F38: =SUM(H38,J38,L38,N38) -> 0 | G38: ='TB-Jan'!G38+'TB-Feb'!G38+'TB-Mar'!G38+'TB-Apr'!G38+'TB-May'!G38+'TB-Jun'!G38+'TB-Jul'!G38+'TB-Aug'!G38+'TB-Sep'!G38+'TB-Oct'!G38+'TB-Nov'!G38+'TB-Dec'!G38 -> 1183464.4 | H38: ='TB-Jan'!H38+'TB-Feb'!H38+'TB-Mar'!H38+'TB-Apr'!H38+'TB-May'!H38+'TB-Jun'!H38+'TB-Jul'!H38+'TB-Aug'!H38+'TB-Sep'!H38+'TB-Oct'!H38+'TB-Nov'!H38+'TB-Dec'!H38 -> 0 | I38: ='TB-Jan'!I38+'TB-Feb'!I38+'TB-Mar'!I38+'TB-Apr'!I38+'TB-May'!I38+'TB-Jun'!I38+'TB-Jul'!I38+'TB-Aug'!I38+'TB-Sep'!I38+'TB-Oct'!I38+'TB-Nov'!I38+'TB-Dec'!I38 -> 0 | J38: ='TB-Jan'!J38+'TB-Feb'!J38+'TB-Mar'!J38+'TB-Apr'!J38+'TB-May'!J38+'TB-Jun'!J38+'TB-Jul'!J38+'TB-Aug'!J38+'TB-Sep'!J38+'TB-Oct'!J38+'TB-Nov'!J38+'TB-Dec'!J38 -> 0 | K38: ='TB-Jan'!K38+'TB-Feb'!K38+'TB-Mar'!K38+'TB-Apr'!K38+'TB-May'!K38+'TB-Jun'!K38+'TB-Jul'!K38+'TB-Aug'!K38+'TB-Sep'!K38+'TB-Oct'!K38+'TB-Nov'!K38+'TB-Dec'!K38 -> 0 | L38: ='TB-Jan'!L38+'TB-Feb'!L38+'TB-Mar'!L38+'TB-Apr'!L38+'TB-May'!L38+'TB-Jun'!L38+'TB-Jul'!L38+'TB-Aug'!L38+'TB-Sep'!L38+'TB-Oct'!L38+'TB-Nov'!L38+'TB-Dec'!L38 -> 0 | M38: ='TB-Jan'!M38+'TB-Feb'!M38+'TB-Mar'!M38+'TB-Apr'!M38+'TB-May'!M38+'TB-Jun'!M38+'TB-Jul'!M38+'TB-Aug'!M38+'TB-Sep'!M38+'TB-Oct'!M38+'TB-Nov'!M38+'TB-Dec'!M38 -> 0 | N38: ='TB-Jan'!N38+'TB-Feb'!N38+'TB-Mar'!N38+'TB-Apr'!N38+'TB-May'!N38+'TB-Jun'!N38+'TB-Jul'!N38+'TB-Aug'!N38+'TB-Sep'!N38+'TB-Oct'!N38+'TB-Nov'!N38+'TB-Dec'!N38 -> 0
A39: Due from NGOs/POs | B39: 139 | C39: =E39-F39 -> 1897625 | E39: =SUM(G39,I39,K39,M39) -> 1897625 | F39: =SUM(H39,J39,L39,N39) -> 0 | G39: ='TB-Jan'!G39+'TB-Feb'!G39+'TB-Mar'!G39+'TB-Apr'!G39+'TB-May'!G39+'TB-Jun'!G39+'TB-Jul'!G39+'TB-Aug'!G39+'TB-Sep'!G39+'TB-Oct'!G39+'TB-Nov'!G39+'TB-Dec'!G39 -> 1897625 | H39: ='TB-Jan'!H39+'TB-Feb'!H39+'TB-Mar'!H39+'TB-Apr'!H39+'TB-May'!H39+'TB-Jun'!H39+'TB-Jul'!H39+'TB-Aug'!H39+'TB-Sep'!H39+'TB-Oct'!H39+'TB-Nov'!H39+'TB-Dec'!H39 -> 0 | I39: ='TB-Jan'!I39+'TB-Feb'!I39+'TB-Mar'!I39+'TB-Apr'!I39+'TB-May'!I39+'TB-Jun'!I39+'TB-Jul'!I39+'TB-Aug'!I39+'TB-Sep'!I39+'TB-Oct'!I39+'TB-Nov'!I39+'TB-Dec'!I39 -> 0 | J39: ='TB-Jan'!J39+'TB-Feb'!J39+'TB-Mar'!J39+'TB-Apr'!J39+'TB-May'!J39+'TB-Jun'!J39+'TB-Jul'!J39+'TB-Aug'!J39+'TB-Sep'!J39+'TB-Oct'!J39+'TB-Nov'!J39+'TB-Dec'!J39 -> 0 | K39: ='TB-Jan'!K39+'TB-Feb'!K39+'TB-Mar'!K39+'TB-Apr'!K39+'TB-May'!K39+'TB-Jun'!K39+'TB-Jul'!K39+'TB-Aug'!K39+'TB-Sep'!K39+'TB-Oct'!K39+'TB-Nov'!K39+'TB-Dec'!K39 -> 0 | L39: ='TB-Jan'!L39+'TB-Feb'!L39+'TB-Mar'!L39+'TB-Apr'!L39+'TB-May'!L39+'TB-Jun'!L39+'TB-Jul'!L39+'TB-Aug'!L39+'TB-Sep'!L39+'TB-Oct'!L39+'TB-Nov'!L39+'TB-Dec'!L39 -> 0 | M39: ='TB-Jan'!M39+'TB-Feb'!M39+'TB-Mar'!M39+'TB-Apr'!M39+'TB-May'!M39+'TB-Jun'!M39+'TB-Jul'!M39+'TB-Aug'!M39+'TB-Sep'!M39+'TB-Oct'!M39+'TB-Nov'!M39+'TB-Dec'!M39 -> 0 | N39: ='TB-Jan'!N39+'TB-Feb'!N39+'TB-Mar'!N39+'TB-Apr'!N39+'TB-May'!N39+'TB-Jun'!N39+'TB-Jul'!N39+'TB-Aug'!N39+'TB-Sep'!N39+'TB-Oct'!N39+'TB-Nov'!N39+'TB-Dec'!N39 -> 0
A40: Due from Other Funds | B40: 144 | C40: =E40-F40 -> 0 | E40: =SUM(G40,I40,K40,M40) -> 0 | F40: =SUM(H40,J40,L40,N40) -> 0 | G40: ='TB-Jan'!G40+'TB-Feb'!G40+'TB-Mar'!G40+'TB-Apr'!G40+'TB-May'!G40+'TB-Jun'!G40+'TB-Jul'!G40+'TB-Aug'!G40+'TB-Sep'!G40+'TB-Oct'!G40+'TB-Nov'!G40+'TB-Dec'!G40 -> 0 | H40: ='TB-Jan'!H40+'TB-Feb'!H40+'TB-Mar'!H40+'TB-Apr'!H40+'TB-May'!H40+'TB-Jun'!H40+'TB-Jul'!H40+'TB-Aug'!H40+'TB-Sep'!H40+'TB-Oct'!H40+'TB-Nov'!H40+'TB-Dec'!H40 -> 0 | I40: ='TB-Jan'!I40+'TB-Feb'!I40+'TB-Mar'!I40+'TB-Apr'!I40+'TB-May'!I40+'TB-Jun'!I40+'TB-Jul'!I40+'TB-Aug'!I40+'TB-Sep'!I40+'TB-Oct'!I40+'TB-Nov'!I40+'TB-Dec'!I40 -> 0 | J40: ='TB-Jan'!J40+'TB-Feb'!J40+'TB-Mar'!J40+'TB-Apr'!J40+'TB-May'!J40+'TB-Jun'!J40+'TB-Jul'!J40+'TB-Aug'!J40+'TB-Sep'!J40+'TB-Oct'!J40+'TB-Nov'!J40+'TB-Dec'!J40 -> 0 | K40: ='TB-Jan'!K40+'TB-Feb'!K40+'TB-Mar'!K40+'TB-Apr'!K40+'TB-May'!K40+'TB-Jun'!K40+'TB-Jul'!K40+'TB-Aug'!K40+'TB-Sep'!K40+'TB-Oct'!K40+'TB-Nov'!K40+'TB-Dec'!K40 -> 0 | L40: ='TB-Jan'!L40+'TB-Feb'!L40+'TB-Mar'!L40+'TB-Apr'!L40+'TB-May'!L40+'TB-Jun'!L40+'TB-Jul'!L40+'TB-Aug'!L40+'TB-Sep'!L40+'TB-Oct'!L40+'TB-Nov'!L40+'TB-Dec'!L40 -> 0 | M40: ='TB-Jan'!M40+'TB-Feb'!M40+'TB-Mar'!M40+'TB-Apr'!M40+'TB-May'!M40+'TB-Jun'!M40+'TB-Jul'!M40+'TB-Aug'!M40+'TB-Sep'!M40+'TB-Oct'!M40+'TB-Nov'!M40+'TB-Dec'!M40 -> 0 | N40: ='TB-Jan'!N40+'TB-Feb'!N40+'TB-Mar'!N40+'TB-Apr'!N40+'TB-May'!N40+'TB-Jun'!N40+'TB-Jul'!N40+'TB-Aug'!N40+'TB-Sep'!N40+'TB-Oct'!N40+'TB-Nov'!N40+'TB-Dec'!N40 -> 0
