Workbook

Sheet TB
A1: Republic of the Philippines
A2: PROVINCE OF AGUSAN DEL SUR
A3: Gov. Democrito O. Plaza Government Center, Prosperidad
A5: TRUST FUND
A6: TRIAL BALANCE
A7: As of January 31, 2011
L9: cash trnsactions
A10: Account Title | B10: Account Code | C10: Total | E10: GENERAL FUND | G10: Debit | H10: Debit Totals | I10: Credit Totals | J10: Credit | L10: Debit | M10: Credit
C11: Debit | D11: Credit | E11: Debit | F11: Credit
A12: Cash in Vault | B12: 101 | C12: =E12+G12+#REF! -> #REF! | G12: =H12-I12 -> 0
A13: Cash - Collecting Officers | B13: 102 | G13: =H13-I13 -> 0
A14: Cash Disbursing Officers | B14: 103 | C14: =E14+G16+#REF! -> #REF! | G14: =H14-I14 -> 0
A15: Petty Cash Fund | B15: 104 | C15: =E15+G15+#REF! -> #REF! | G15: =H15-I15 -> 0
A16: Payroll Fund | B16: 106 | G16: =H16-I16 -> -0.8 | H16: =527771.6 -> 527771.6 | I16: =527771.6+0.8 -> 527772.4 | L16: 527771.6 | M16: =0.8+527771.6 -> 527772.4
A17: Cash - Bangko Sentral ng Pilipinas | B17: 110 | C17: =E17+G17+#REF! -> #REF! | G17: =H17-I17 -> 0
A18: Cash in Bank - Local Currency, Current Account | B18: 111 | C18: =E18+G18+#REF! -> #REF! | G18: =H18-I18 -> 14332535 | H18: =8793653.96+15352900 -> 24146554 | I18: 9814018.6 | L18: =8793653.96+15352900 -> 24146554 | M18: 9814018.6
A19: Cash in Bank - Local Currency, SavingsAccount | B19: 112 | C19: =E19+G19+#REF! -> #REF! | G19: =H19-I19 -> 0
A20: Cash in Bank - Local Currency, Time Deposits | B20: 113 | C20: =E20+G20+#REF! -> #REF! | G20: =H20-I20 -> 0
A21: Cash - Bangko Sentral ng Pilipinas | B21: 114 | C21: =E21+G21+#REF! -> #REF! | G21: =H21-I21 -> 0
A22: Cash in Bank - Foreign Currency, Current Account | B22: 115 | C22: =E22+G22+#REF! -> #REF! | G22: =H22-I22 -> 0
A23: Cash in Bank - Foreign Currency, Savings Account | B23: 116 | C23: =E23+G23+#REF! -> #REF! | G23: =H23-I23 -> 0
A24: Cash in Bank - Foreign Currency, Time Deposits | B24: 117 | C24: =E24+G24+#REF! -> #REF! | G24: =H24-I24 -> 0
A25: Accounts Receivable | B25: 121 | C25: =E25+G25+#REF! -> #REF! | G25: =H25-I25 -> 0
A26: Allowance for Doubtful Accounts | B26: 301 | D26: =F26+J26+#REF! -> #REF! | G26: =H26-I26 -> 0
A27: Notes Receivable | B27: 122 | C27: =E27+G27+#REF! -> #REF! | G27: =H27-I27 -> 0
A28: Due from Officers and Employees | B28: 123 | C28: =E28+G41+#REF! -> #REF! | G28: =H28-I28 -> 0
A29: Loans Receivable - GOCCs | B29: 124 | C29: =E29+G29+#REF! -> #REF! | G29: =H29-I29 -> 0
A30: Loans Receivable - LGUs | B30: 125 | C30: =E30+G30+#REF! -> #REF! | G30: =H30-I30 -> 0
A31: Loans Receivable - Others | B31: 126 | C31: =E31+G31+#REF! -> #REF! | G31: =H31-I31 -> 0
A32: Real Property Tax Receivable | B32: 127 | C32: =E32+G32+#REF! -> #REF! | G32: =H32-I32 -> 0
A33: Special Education Tax Receivable | B33: 128 | C33: =E33+G33+#REF! -> #REF! | G33: =H33-I33 -> 0
A34: Interests Receivable | B34: 129 | C34: =E34+G34+#REF! -> #REF! | G34: =H34-I34 -> 0
A35: Due from NGAs | B35: 136 | C35: =E35+G35+#REF! -> #REF! | G35: =H35-I35 -> 0
A36: Due from GOCCs | B36: 137 | C36: =E36+G36+#REF! -> #REF! | G36: =H36-I36 -> 0
A37: Due from LGUs | B37: 138 | C37: =E37+G37+#REF! -> #REF! | G37: =H37-I37 -> 0
A38: Due from NGOs/POs | B38: 139 | C38: =E38+G38+#REF! -> #REF! | G38: =H38-I38 -> -280000 | I38: =200000+80000 -> 280000 | M38: 200000
A39: Due from Other Funds | B39: 144 | C39: =E39+G39+#REF! -> #REF! | G39: =H39-I39 -> 0
A40: Receivables - Disallowances/Charges | B40: 146 | C40: =E40+G40+#REF! -> #REF! | G40: =H40-I40 -> 0
A41: Advances to Officers and Employees | B41: 148 | G41: =H41-I41 -> 189984.6 | H41: =758250.92 -> 758250.92 | I41: =1608.72+566657.6 -> 568266.32 | L41: 758250.92 | M41: 1608.72
A42: Other Receivables | B42: 149 | C42: =E42+G42+#REF! -> #REF! | G42: =H42-I42 -> 0
A43: Raw Materials Inventory | B43: 151 | C43: =E43+G43+#REF! -> #REF! | G43: =H43-I43 -> 0
A44: Work-In-Process Inventory | B44: 152 | C44: =E44+G44+#REF! -> #REF! | G44: =H44-I44 -> 0
A45: Finished Goods Inventory | B45: 153 | C45: =E45+G45+#REF! -> #REF! | G45: =H45-I45 -> 0
A46: Merchandise Inventory | B46: 154 | C46: =E46+G46+#REF! -> #REF! | G46: =H46-I46 -> 0
A47: Office Supplies Inventory | B47: 155 | C47: =E47+G47+#REF! -> #REF! | G47: =H47-I47 -> 0
A48: Accountable Forms Inventory | B48: 156 | C48: =E48+G48+#REF! -> #REF! | G48: =H48-I48 -> 0
A49: Animal/Zoological Supplies Inventory | B49: 157 | C49: =E49+G49+#REF! -> #REF! | G49: =H49-I49 -> 0
A50: Food Supplies Inventory | B50: 158 | C50: =E50+G50+#REF! -> #REF! | G50: =H50-I50 -> 0
A51: Drugs and Medicines Inventory | B51: 159 | C51: =E51+G51+#REF! -> #REF! | G51: =H51-I51 -> 518992 | H51: 518992 | L51: 491188.85
A52: Medical, Dental and Laboratory Supplies Inventory | B52: 160 | C52: =E52+G52+#REF! -> #REF! | G52: =H52-I52 -> 0
A53: Gasoline, Oil and Lubricants Inventory | B53: 161 | C53: =E53+G53+#REF! -> #REF! | G53: =H53-I53 -> 1798400 | H53: 1798400 | L53: 1702057.1
A54: Agricultural Supplies Inventory | B54: 162 | C54: =E54+G54+#REF! -> #REF! | G54: =H54-I54 -> 0
A55: Textbooks and Instructional Materials Inventory | B55: 163 | C55: =E55+G55+#REF! -> #REF! | G55: =H55-I55 -> 0
A56: Military and Police Supplies Inventory | B56: 164 | C56: =E56+G56+#REF! -> #REF! | G56: =H56-I56 -> 0
A57: Other Supplies Inventory | B57: 165 | C57: =E57+G57+#REF! -> #REF! | G57: =H57-I57 -> 0
A58: Confiscated/Abandoned/Seized Goods Inventory | B58: 166 | C58: =E58+G58+#REF! -> #REF! | G58: =H58-I58 -> 0
A59: Spare Parts Inventory | B59: 167 | C59: =E59+G59+#REF! -> #REF! | G59: =H59-I59 -> 0
A60: Construction Materials Inventory | B60: 168 | C60: =E60+G60+#REF! -> #REF! | G60: =H60-I60 -> 0
A61: Livestock Inventory | B61: 169 | C61: =E61+G61+#REF! -> #REF! | G61: =H61-I61 -> 0
A62: Crops and Fruits Inventory | B62: 170 | C62: =E62+G62+#REF! -> #REF! | G62: =H62-I62 -> 0
A63: Other Agricultural, Fishery and Forestry Products Inventory | B63: 176 | C63: =E63+G63+#REF! -> #REF! | G63: =H63-I63 -> 0
A64: Prepaid Rent | B64: 177 | C64: =E64+G64+#REF! -> #REF! | G64: =H64-I64 -> 0
A65: Prepaid Insurance | B65: 178 | C65: =E65+G65+#REF! -> #REF! | G65: =H65-I65 -> 0
A66: Prepaid Interest | B66: 179 | C66: =E66+G66+#REF! -> #REF! | G66: =H66-I66 -> 0
A67: Deposit on Letters of Credit | B67: 180 | C67: =E67+G67+#REF! -> #REF! | G67: =H67-I67 -> 0
A68: Advances to Contractors | B68: 181 | C68: =E68+G68+#REF! -> #REF! | G68: =H68-I68 -> 0
A69: Deferred Charges | B69: 182 | C69: =E69+G69+#REF! -> #REF! | G69: =H69-I69 -> 0
A70: Other Prepaid Expenses | B70: 185 | C70: =E70+G70+#REF! -> #REF! | G70: =H70-I70 -> 0
A71: Guaranty Deposits | B71: 186 | C71: =E71+G71+#REF! -> #REF! | G71: =H71-I71 -> 0
A72: Other Current Assets | B72: 189 | C72: =E72+G72+#REF! -> #REF! | G72: =H72-I72 -> 0
A73: Investments in Treasury Bills | B73: 191 | C73: =E73+G73+#REF! -> #REF! | G73: =H73-I73 -> 0
A74: Investments in Stocks | B74: 192 | C74: =E74+G74+#REF! -> #REF! | G74: =H74-I74 -> 0
A75: Investments in Bonds | B75: 193 | C75: =E75+G75+#REF! -> #REF! | G75: =H75-I75 -> 0
A76: Other Investments and Marketable Securities | B76: 197 | C76: =E76+G76+#REF! -> #REF! | G76: =H76-I76 -> 0
A77: Sinking Fund | B77: 198 | C77: =E77+G77+#REF! -> #REF! | G77: =H77-I77 -> 0
A78: Land | B78: 201 | C78: =E78+G78+#REF! -> #REF! | G78: =H78-I78 -> 0
A79: Land Improvements | B79: 202 | C79: =E79+G79+#REF! -> #REF! | G79: =H79-I79 -> 0
A80: Accumulated Depreciation – Land Improvements | B80: 302 | D80: =F80+J80+#REF! -> #REF! | J80: =I80-H80 -> 0
A81: Runways/Taxiways | B81: 203 | C81: =E81+G81+#REF! -> #REF! | G81: =H81-I81 -> 0 | J81: =I81-H81 -> 0
A82: Accumulated Depreciation - Runways/Taxiways | B82: 303 | D82: =F82+J82+#REF! -> #REF! | G82: =H82-I82 -> 0 | J82: =I82-H82 -> 0
A83: Railways | B83: 204 | C83: =E83+G83+#REF! -> #REF! | G83: =H83-I83 -> 0 | J83: =I83-H83 -> 0
A84: Accumulated Depreciation - Railways | B84: 304 | D84: =F84+J84+#REF! -> #REF! | G84: =H84-I84 -> 0 | J84: =I84-H84 -> 0
A85: Electrification, Power and Energy Structures | B85: 205 | C85: =E85+G85+#REF! -> #REF! | G85: =H85-I85 -> 0
A86: Accumulated Depreciation - Electrification, Power and Energy | B86: 305 | D86: =F86+J86+#REF! -> #REF! | J86: =I86-H86 -> 0
A87: Office Buildings | B87: 211 | C87: =E87+G87+#REF! -> #REF! | G87: =H87-I87 -> 0
A88: Accumulated Depreciation - Office Buildings | B88: 311 | D88: =F88+J88+#REF! -> #REF! | J88: =I88-H88 -> 0
A89: School Buildings | B89: 212 | C89: =E89+G89+#REF! -> #REF! | G89: =H89-I89 -> 0 | J89: =I89-H89 -> 0
A90: Accumulated Depreciation - School Buildings | B90: 312 | D90: =F90+J90+#REF! -> #REF! | G90: =H90-I90 -> 0 | J90: =I90-H90 -> 0
A91: Hospitals and Health Centers | B91: 213 | C91: =E91+G91+#REF! -> #REF! | G91: =H91-I91 -> 0
A92: Accumulated Depreciation - Hospitals and Health Centers | B92: 313 | D92: =F92+J92+#REF! -> #REF! | J92: =I92-H92 -> 0
A93: Markets and Slaughterhouses | B93: 214 | C93: =E93+G93+#REF! -> #REF! | G93: =H93-I93 -> 0
A94: Accumulated Depreciation - Markets and Slaughterhouses | B94: 314 | D94: =F94+J94+#REF! -> #REF! | G94: =H94-I94 -> 0 | J94: =I94-H94 -> 0
A95: Other Structures | B95: 215 | C95: =E95+G95+#REF! -> #REF! | G95: =H95-I95 -> 0
A96: Accumulated Depreciation - Other Structures | B96: 315 | D96: =F96+J96+#REF! -> #REF! | J96: =I96-H96 -> 0
A97: Leasehold Improvements, Land | B97: 218 | C97: =E97+G97+#REF! -> #REF! | G97: =H97-I97 -> 0
A98: Accumulated Depreciation - Leasehold Improvements, Land | B98: 318 | D98: =F98+J98+#REF! -> #REF! | J98: =I98-H98 -> 0
A99: Leasehold Improvements, Buildings | B99: 219 | C99: =E99+G99+#REF! -> #REF! | G99: =H99-I99 -> 0 | J99: =I99-H99 -> 0
A100: Accumulated Depreciation - Leasehold Improvements, Buildings | B100: 319 | D100: =F100+J100+#REF! -> #REF! | G100: =H100-I100 -> 0 | J100: =I100-H100 -> 0
A101: Other Leasehold Improvements | B101: 220 | C101: =E101+G101+#REF! -> #REF! | G101: =H101-I101 -> 0 | J101: =I101-H101 -> 0
A102: Accumulated Depreciation - Other Leasehold Improvements | B102: 320 | D102: =F102+J102+#REF! -> #REF! | G102: =H102-I102 -> 0 | J102: =I102-H102 -> 0
...

Sheet CASH FLOWS
A1: Republic of the Philippines
A2: PROVINCE OF AGUSAN DEL SUR
A3: Gov. Democrito O. Plaza Government Center, Prosperidad
A6: STATEMENT OF CASH FLOWS
A7: For the Year Ended December 31, 2010
F9: as of | G9: for
F10: 40513 | G10: 40544 | H10: notes
A11: Cash Flows From Operating Activities
B12: Cash Inflows
C13: Share from Internal Revenue Allotment | H13: CR | I13: 665
C14: Collection from Taxpayers | H14: CR | I14: 581-593, 598-599, 127-128, 129,
C15: Receipts from sale of goods and services | H15: CR | I15: 611-624, 628, 629, 631-644, 648, 649, 666,
C16: Interest Income | E16: =F16+G16 -> 171088.46 | F16: 171088.46 | H16: CR | I16: 664
C17: Dividend Income | E17: =F17+G17 -> 0 | H17: CR | I17: 661
C18: Other Receipts | E18: =F18+G18 -> 2.23816e+08 | F18: 1.9966944e+08 | G18: =TB!M38+TB!M41+TB!M181+TB!M184+TB!M186+TB!M189 -> 24146553 | H18: CR | I18: 601-603, 605, 606, 608-609, 662, 663, 667-671, 678, 679, 652, 656, 657, 121-123, 136-139, 144, 146, 148, 149, 413-418, 424, 426, 427, 439, 451, 452, 455, 403
C19: Total Cash Inflows | E19: =SUM(E16:E18) -> 2.2398709e+08 | F19: 1.9984053e+08 | G19: =G18+G16 -> 24146553
B20: Cash Outflows
C21: Payments to -
D22: Suppliers/Creditors | E22: =F22+G22 -> 7235118.3 | F22: 5041872.3 | G22: =TB!L51+TB!L53 -> 2193246 | H22: DR | I22: 755-765, 151, 154, 155-165, 167-170, 176
D23: Employees | E23: =F23+G23 -> 12955183 | F23: 12196932 | G23: =TB!L41 -> 758250.92 | H23: DR | I23: 701-707, 711-725, 731-734, 738-743, 749, 403, 148
C24: Interest Expense | E24: =F24+G24 -> 0 | H24: DR | I24: 975, 409
C25: Other Disbursements | E25: =F25+G25 -> 1.2439496e+08 | F25: 1.1759165e+08 | G25: =TB!L177+TB!L178+TB!L179+TB!L180+TB!L181+TB!L184+TB!L186+TB!L189 -> 6803305.6 | H25: DR | I25: 751-754, 766-768, 771-775, 778-788, 791-797, 799, 802, 805, 811-815, 818-820, 821-823, 826-827, 829-836, 840-841, 848, 850, 851-857, 860-862, 871-878, 881-884, 891-893, 969, 971, 972, 974, 979, 177-182, 185, 186, 189, 401, 402, 412-418, 424, 426, 427, 429, 439, 138, 139,149
C26: Total Cash Outflows | E26: =SUM(E22:E25) -> 1.4458526e+08 | F26: 1.3483045e+08 | G26: =SUM(G22:G25) -> 9754802.5
B27: Cash Provided by (Used In) | E27: =E19-E26 -> 79401830 | F27: 65010079 | G27: =G19-G26 -> 14391751
A28: Cash Flows From Investing Activities
B29: Cash Inflows
C30: Sale of Property, Plant and Equipment | H30: CR | I30: ALL PPEs disposed net of accu. Depn. Plus gainon sale
C31: Sale of Debt Securities of Other Entities
C32: Collection of Principal on Loans to Other Entities | H32: CR | I32: 124-126
C33: Total Cash Inflows
B34: Cash Outflows
C35: Purchase of Property, Plant and Equipment and Public Infrastructures | E35: =F35+G35 -> 97141070 | F35: 97081854 | G35: =TB!L107 -> 59216.15 | I35: ALL PPEs
C36: Purchase of Debt Securities of the Other Entities | H36: DR | I36: 191, 193, 192, 197, 198
C37: Grant/Loans to other Entities
C38: Total Cash Outflows | E38: =SUM(E35:E37) -> 97141070 | F38: 97081854 | G38: =SUM(G35:G37) -> 59216.15
B39: Cash Provided by (Used In) | E39: =E33-E38 -> -97141070 | F39: -97081854 | G39: =G33-G38 -> -59216.15
A40: Cash Flows From Financing Activities
B41: Cash Inflows
C42: Issuance of Debt Securities | H42: CR | I42: 441-443
C43: Acquisition of Loan | H43: CR | I43: 444-445, 450
C44: Total Cash Inflows
B45: Cash Outflows
C46: Retirement/Redemption of Debt Securities | H46: DR | I46: 441-443
C47: Payment of Loan Amortization | H47: DR | I47: 444-445, 450
C48: Total Cash Outflows
B49: Cash Provided by (Used In)
A50: Net Cash Provided By (Used in) | E50: =E27+E39 -> -17739240 | F50: -32071775 | G50: =G27+G39 -> 14332535
A51: Cash at the Beginning of the Period | E51: 1.065559e+08 | F51: 1.065559e+08 | G51: 74484122
A52: Cash at the End of the Period | E52: =E51+E50 -> 88816657 | F52: 74484122 | G52: =G51+G50 -> 88816657
I53: balance sheet balance
D54: 74484122 | E54: 0
A59: Certified Correct:
A63: JOY D. LAGAT, CPA
A64: OIC- Provincial Accountant

Sheet BS
A1: Republic of the Philippines
A2: PROVINCE OF AGUSAN DEL SUR
A3: Gov. Democrito O. Plaza Government Center, Prosperidad
A5: TRUST FUND
A6: BALANCE SHEET
A7: =+TB!A7 -> As of January 31, 2011
A9: ASSETS
A10: CURRENT ASSETS
B11: CASH | E11: =+E12+E17+E22 -> #REF! | F11: =+F12+F17+F22 -> 14332535 | G11: =+G12+G17+G22 -> #REF! | H11: =+H12+H17+H22 -> #REF!
C12: Cash on Hand | E12: =SUM(E13:E16) -> #REF! | F12: =SUM(F13:F16) -> -0.8 | G12: =SUM(G13:G16) -> #REF! | H12: =SUM(H13:H16) -> #REF!
D13: Cash in Vault | E13: =SUM(F13:H13) -> #REF! | F13: =TB!G12 -> 0 | G13: =[1]Sheet1!K13 -> #REF! | H13: =[1]Sheet1!M13 -> #REF!
D14: Cash - Collecting Officers | E14: =SUM(F14:H14) -> 0 | F14: =TB!G13 -> 0
D15: Cash - Disbursing Officers | E15: =SUM(F15:H15) -> #REF! | F15: =TB!G14 -> 0 | G15: =[1]Sheet1!K15 -> #REF! | H15: =[1]Sheet1!M15 -> #REF!
D16: Payroll Fund | E16: =SUM(F16:H16) -> #REF! | F16: =TB!G16 -> -0.8 | G16: =[1]Sheet1!K16 -> #REF! | H16: =[1]Sheet1!M16 -> #REF!
C17: Cash in Bank - Local Currency | E17: =SUM(E18:E21) -> #REF! | F17: =SUM(F18:F21) -> 14332535 | G17: =SUM(G18:G21) -> #REF! | H17: =SUM(H18:H21) -> #REF!
D18: Cash - Bangko Sentral ng Pilipinas | E18: =SUM(F18:H18) -> #REF! | F18: =TB!G17 -> 0 | G18: =[1]Sheet1!K17 -> #REF! | H18: =[1]Sheet1!M17 -> #REF!
D19: Cash in Bank - Local Currency, Current Account | E19: =SUM(F19:H19) -> #REF! | F19: =TB!G18 -> 14332535 | G19: =[1]Sheet1!K18 -> #REF! | H19: =[1]Sheet1!M18 -> #REF!
D20: Cash in Bank - Local Currency, Savings Account | E20: =SUM(F20:H20) -> #REF! | F20: =TB!G19 -> 0 | G20: =[1]Sheet1!K19 -> #REF! | H20: =[1]Sheet1!M19 -> #REF!
D21: Cash in Bank - Local Currency, Time Deposits | E21: =SUM(F21:H21) -> #REF! | F21: =TB!G20 -> 0 | G21: =[1]Sheet1!K20 -> #REF! | H21: =[1]Sheet1!M20 -> #REF!
C22: Cash in Bank - Foreign Currency | E22: =SUM(E23:E26) -> #REF! | F22: =SUM(F23:F26) -> 0 | G22: =SUM(G23:G26) -> #REF! | H22: =SUM(H23:H26) -> #REF!
D23: Cash - Bangko Sentral ng Pilipinas | E23: =SUM(F23:H23) -> #REF! | F23: =TB!G21 -> 0 | G23: =[1]Sheet1!K21 -> #REF! | H23: =[1]Sheet1!M21 -> #REF!
D24: Cash in Bank - Foreign Currency, Current Account | E24: =SUM(F24:H24) -> #REF! | F24: =TB!G22 -> 0 | G24: =[1]Sheet1!K22 -> #REF! | H24: =[1]Sheet1!M22 -> #REF!
D25: Cash in Bank - Foreign Currency, Savings Account | E25: =SUM(F25:H25) -> #REF! | F25: =TB!G23 -> 0 | G25: =[1]Sheet1!K23 -> #REF! | H25: =[1]Sheet1!M23 -> #REF!
D26: Cash in Bank - Foreign Currency, Time Deposits | E26: =SUM(F26:H26) -> #REF! | F26: =TB!G24 -> 0 | G26: =[1]Sheet1!K24 -> #REF! | H26: =[1]Sheet1!M24 -> #REF!
B27: RECEIVABLES | E27: =+E28+E39+E44+E46 -> #REF! | F27: =+F28+F39+F44+F46 -> -90015.4 | G27: =+G28+G39+G44+G46 -> #REF! | H27: =+H28+H39+H44+H46 -> #REF!
C28: Receivable Accounts | E28: =SUM(E31:E38)+E29-E30 -> #REF! | F28: =SUM(F31:F38)+F29-F30 -> 189984.6 | G28: =SUM(G31:G38)+G29-G30 -> #REF! | H28: =SUM(H31:H38)+H29-H30 -> #REF!
D29: Accounts Receivable | E29: =SUM(F29:H29) -> #REF! | F29: =TB!G25 -> 0 | G29: =[1]Sheet1!K25 -> #REF! | H29: =[1]Sheet1!M25 -> #REF!
D30: Allowance for Doubtful Accounts | E30: =SUM(F30:H30) -> #REF! | F30: =TB!G26 -> 0 | G30: =[1]Sheet1!L26 -> #REF! | H30: =[1]Sheet1!N26 -> #REF!
D31: Notes Receivable | E31: =SUM(F31:H31) -> #REF! | F31: =TB!G27 -> 0 | G31: =[1]Sheet1!K27 -> #REF! | H31: =[1]Sheet1!M27 -> #REF!
D32: Advances to Officers & Employees | E32: =SUM(F32:H32) -> #REF! | F32: =TB!G41 -> 189984.6 | G32: =[1]Sheet1!K28 -> #REF! | H32: =[1]Sheet1!M28 -> #REF!
D33: Loans Receivable - GOCCs | E33: =SUM(F33:H33) -> #REF! | F33: =TB!G29 -> 0 | G33: =[1]Sheet1!K29 -> #REF! | H33: =[1]Sheet1!M29 -> #REF!
D34: Loans Receivable - LGUs | E34: =SUM(F34:H34) -> #REF! | F34: =TB!G30 -> 0 | G34: =[1]Sheet1!K30 -> #REF! | H34: =[1]Sheet1!M30 -> #REF!
D35: Loans Receivable - Others | E35: =SUM(F35:H35) -> #REF! | F35: =TB!G31 -> 0 | G35: =[1]Sheet1!K31 -> #REF! | H35: =[1]Sheet1!M31 -> #REF!
D36: Real Property Tax Receivable | E36: =SUM(F36:H36) -> #REF! | F36: =TB!G32 -> 0 | G36: =[1]Sheet1!K32 -> #REF! | H36: =[1]Sheet1!M32 -> #REF!
D37: Special Education Tax Receivable | E37: =SUM(F37:H37) -> #REF! | F37: =TB!G33 -> 0 | G37: =[1]Sheet1!K33 -> #REF! | H37: =[1]Sheet1!M33 -> #REF!
D38: Interests Receivable | E38: =SUM(F38:H38) -> #REF! | F38: =TB!G34 -> 0 | G38: =[1]Sheet1!K34 -> #REF! | H38: =[1]Sheet1!M34 -> #REF!
C39: Inter-Agency Receivables | E39: =SUM(E40:E43) -> #REF! | F39: =SUM(F40:F43) -> -280000 | G39: =SUM(G40:G43) -> #REF! | H39: =SUM(H40:H43) -> #REF!
D40: Due from NGAs | E40: =SUM(F40:H40) -> #REF! | F40: =TB!G35 -> 0 | G40: =[1]Sheet1!K35 -> #REF! | H40: =[1]Sheet1!M35 -> #REF!
D41: Due from GOCCs | E41: =SUM(F41:H41) -> #REF! | F41: =TB!G36 -> 0 | G41: =[1]Sheet1!K36 -> #REF! | H41: =[1]Sheet1!M36 -> #REF!
D42: Due from LGUs | E42: =SUM(F42:H42) -> #REF! | F42: =TB!G37 -> 0 | G42: =[1]Sheet1!K37 -> #REF! | H42: =[1]Sheet1!M37 -> #REF!
D43: Due from NGOs/POs | E43: =SUM(F43:H43) -> #REF! | F43: =TB!G38 -> -280000 | G43: =[1]Sheet1!K38 -> #REF! | H43: =[1]Sheet1!M38 -> #REF!
C44: Intra-Agency Receivables | E44: =+E45 -> #REF! | F44: =+F45 -> 0 | G44: =+G45 -> #REF! | H44: =+H45 -> #REF!
D45: Due from Other Funds | E45: =SUM(F45:H45) -> #REF! | F45: =TB!G39 -> 0 | G45: =[1]Sheet1!K39 -> #REF! | H45: =[1]Sheet1!M39 -> #REF!
C46: Other Receivables | E46: =SUM(E47:E48) -> #REF! | F46: =SUM(F47:F48) -> 0 | G46: =SUM(G47:G48) -> #REF! | H46: =SUM(H47:H48) -> #REF!
D47: Receivables - Disallowances/Charges | E47: =SUM(F47:H47) -> #REF! | F47: =TB!G40 -> 0 | G47: =[1]Sheet1!K40 -> #REF! | H47: =[1]Sheet1!M40 -> #REF!
D48: Other Receivables | E48: =SUM(F48:H48) -> #REF! | F48: =TB!G42 -> 0 | G48: =[1]Sheet1!K41 -> #REF! | H48: =[1]Sheet1!M41 -> #REF!
B49: INVENTORIES | E49: =+E50+E55+E70 -> #REF! | F49: =+F50+F55+F70 -> 2317392 | G49: =+G50+G55+G70 -> #REF! | H49: =+H50+H55+H70 -> #REF!
C50: Materials | E50: =SUM(E51:E54) -> #REF! | F50: =SUM(F51:F54) -> 0 | G50: =SUM(G51:G54) -> #REF! | H50: =SUM(H51:H54) -> #REF!
D51: Raw Materials Inventory | E51: =SUM(F51:H51) -> #REF! | F51: =TB!G43 -> 0 | G51: =[1]Sheet1!K42 -> #REF! | H51: =[1]Sheet1!M42 -> #REF!
D52: Work-In-Process Inventory | E52: =SUM(F52:H52) -> #REF! | F52: =TB!G44 -> 0 | G52: =[1]Sheet1!K43 -> #REF! | H52: =[1]Sheet1!M43 -> #REF!
D53: Finished Goods Inventory | E53: =SUM(F53:H53) -> #REF! | F53: =TB!G45 -> 0 | G53: =[1]Sheet1!K44 -> #REF! | H53: =[1]Sheet1!M44 -> #REF!
D54: Merchandise Inventory | E54: =SUM(F54:H54) -> #REF! | F54: =TB!G46 -> 0 | G54: =[1]Sheet1!K45 -> #REF! | H54: =[1]Sheet1!M45 -> #REF!
C55: Supplies | E55: =SUM(E56:E69) -> #REF! | F55: =SUM(F56:F69) -> 2317392 | G55: =SUM(G56:G69) -> #REF! | H55: =SUM(H56:H69) -> #REF!
D56: Office Supplies Inventory | E56: =SUM(F56:H56) -> #REF! | F56: =TB!G47 -> 0 | G56: =[1]Sheet1!K46 -> #REF! | H56: =[1]Sheet1!M46 -> #REF!
D57: Accountable Forms Inventory | E57: =SUM(F57:H57) -> #REF! | F57: =TB!G48 -> 0 | G57: =[1]Sheet1!K47 -> #REF! | H57: =[1]Sheet1!M47 -> #REF!
D58: Animal/Zoological Supplies Inventory | E58: =SUM(F58:H58) -> #REF! | F58: =TB!G49 -> 0 | G58: =[1]Sheet1!K48 -> #REF! | H58: =[1]Sheet1!M48 -> #REF!
D59: Food Supplies Inventory | E59: =SUM(F59:H59) -> #REF! | F59: =TB!G50 -> 0 | G59: =[1]Sheet1!K49 -> #REF! | H59: =[1]Sheet1!M49 -> #REF!
D60: Drugs and Medicines Inventory | E60: =SUM(F60:H60) -> #REF! | F60: =TB!G51 -> 518992 | G60: =[1]Sheet1!K50 -> #REF! | H60: =[1]Sheet1!M50 -> #REF!
D61: Medical, Dental and Laboratory Supplies Inventory | E61: =SUM(F61:H61) -> #REF! | F61: =TB!G52 -> 0 | G61: =[1]Sheet1!K51 -> #REF! | H61: =[1]Sheet1!M51 -> #REF!
D62: Gasoline, Oil and Lubricants Inventory | E62: =SUM(F62:H62) -> #REF! | F62: =TB!G53 -> 1798400 | G62: =[1]Sheet1!K52 -> #REF! | H62: =[1]Sheet1!M52 -> #REF!
D63: Agricultural Supplies Inventory | E63: =SUM(F63:H63) -> #REF! | F63: =TB!G54 -> 0 | G63: =[1]Sheet1!K53 -> #REF! | H63: =[1]Sheet1!M53 -> #REF!
D64: Textbooks and Instructional Materials Inventory | E64: =SUM(F64:H64) -> #REF! | F64: =TB!G55 -> 0 | G64: =[1]Sheet1!K54 -> #REF! | H64: =[1]Sheet1!M54 -> #REF!
D65: Military and Police Supplies Inventory | E65: =SUM(F65:H65) -> #REF! | F65: =TB!G56 -> 0 | G65: =[1]Sheet1!K55 -> #REF! | H65: =[1]Sheet1!M55 -> #REF!
D66: Other Supplies Inventory | E66: =SUM(F66:H66) -> #REF! | F66: =TB!G57 -> 0 | G66: =[1]Sheet1!K56 -> #REF! | H66: =[1]Sheet1!M56 -> #REF!
D67: Confiscated/Abandoned/Seized Goods Inventory | E67: =SUM(F67:H67) -> #REF! | F67: =TB!G58 -> 0 | G67: =[1]Sheet1!K57 -> #REF! | H67: =[1]Sheet1!M57 -> #REF!
... D69: Construction Materials Inventory | E69: =SUM(F69:H69) -> #REF! | F69: =TB!G60 -> 0 | G69: =[1]Sheet1!K59 -> #REF! | H69: =[1]Sheet1!M59 -> #REF!
C70: Agricultural, Fishery and Forestry Products | E70: =SUM(E71:E73) -> #REF! | F70: =SUM(F71:F73) -> 0 | G70: =SUM(G71:G73) -> #REF! | H70: =SUM(H71:H73) -> #REF!
D71: Livestock Inventory | E71: =SUM(F71:H71) -> #REF! | F71: =TB!G61 -> 0 | G71: =[1]Sheet1!K60 -> #REF! | H71: =[1]Sheet1!M60 -> #REF!
D72: Crops and Fruits Inventory | E72: =SUM(F72:H72) -> #REF! | F72: =TB!G62 -> 0 | G72: =[1]Sheet1!K61 -> #REF! | H72: =[1]Sheet1!M61 -> #REF!
D73: Other Agricultural, Fishery and Forestry Products Inventory | E73: =SUM(F73:H73) -> #REF! | F73: =TB!G63 -> 0 | G73: =[1]Sheet1!K62 -> #REF! | H73: =[1]Sheet1!M62 -> #REF!
B74: PREPAYMENTS | E74: =SUM(E75:E81) -> #REF! | F74: =SUM(F75:F81) -> 0 | G74: =SUM(G75:G81) -> #REF! | H74: =SUM(H75:H81) -> #REF!
C75: Prepaid Rent | E75: =SUM(F75:H75) -> #REF! | F75: =TB!G64 -> 0 | G75: =[1]Sheet1!K63 -> #REF! | H75: =[1]Sheet1!M63 -> #REF!
C76: Prepaid Insurance | E76: =SUM(F76:H76) -> #REF! | F76: =TB!G65 -> 0 | G76: =[1]Sheet1!K64 -> #REF! | H76: =[1]Sheet1!M64 -> #REF!
C77: Prepaid Interest | E77: =SUM(F77:H77) -> #REF! | F77: =TB!G66 -> 0 | G77: =[1]Sheet1!K65 -> #REF! | H77: =[1]Sheet1!M65 -> #REF!
C78: Deposit on Letters of Credit | E78: =SUM(F78:H78) -> #REF! | F78: =TB!G67 -> 0 | G78: =[1]Sheet1!K66 -> #REF! | H78: =[1]Sheet1!M66 -> #REF!
C79: Advances to Contractors | E79: =SUM(F79:H79) -> #REF! | F79: =TB!G68 -> 0 | G79: =[1]Sheet1!K67 -> #REF! | H79: =[1]Sheet1!M67 -> #REF!
C80: Deferred Charges | E80: =SUM(F80:H80) -> #REF! | F80: =TB!G69 -> 0 | G80: =[1]Sheet1!K68 -> #REF! | H80: =[1]Sheet1!M68 -> #REF!
C81: Other Prepaid Expenses | E81: =SUM(F81:H81) -> #REF! | F81: =TB!G70 -> 0 | G81: =[1]Sheet1!K69 -> #REF! | H81: =[1]Sheet1!M69 -> #REF!
B82: OTHER CURRENT ASSETS | E82: =SUM(E83:E84) -> #REF! | F82: =SUM(F83:F84) -> 0 | G82: =SUM(G83:G84) -> #REF! | H82: =SUM(H83:H84) -> #REF!
D83: Guaranty Deposits | E83: =SUM(F83:H83) -> #REF! | F83: =TB!G71 -> 0 | G83: =[1]Sheet1!K70 -> #REF! | H83: =[1]Sheet1!M70 -> #REF!
D84: Other Current Assets | E84: =SUM(F84:H84) -> #REF! | F84: =TB!G72 -> 0 | G84: =[1]Sheet1!K71 -> #REF! | H84: =[1]Sheet1!M71 -> #REF!
D85: Total Current Assets | E85: =+E82+E74+E49+E27+E11 -> #REF! | F85: =+F82+F74+F49+F27+F11 -> 16559911 | G85: =+G82+G74+G49+G27+G11 -> #REF! | H85: =+H82+H74+H49+H27+H11 -> #REF!
A86: INVESTMENTS
B87: INVESTMENT IN SECURITIES | E87: =SUM(E88:E91) -> #REF! | F87: =SUM(F88:F91) -> 0 | G87: =SUM(G88:G91) -> #REF! | H87: =SUM(H88:H91) -> #REF!
C88: Investments in Treasury Bills | E88: =SUM(F88:H88) -> #REF! | F88: =TB!G73 -> 0 | G88: =[1]Sheet1!K72 -> #REF! | H88: =[1]Sheet1!M72 -> #REF!
C89: Investments in Stocks | E89: =SUM(F89:H89) -> #REF! | F89: =TB!G74 -> 0 | G89: =[1]Sheet1!K73 -> #REF! | H89: =[1]Sheet1!M73 -> #REF!
C90: Investments in Bonds | E90: =SUM(F90:H90) -> #REF! | F90: =TB!G75 -> 0 | G90: =[1]Sheet1!K74 -> #REF! | H90: =[1]Sheet1!M74 -> #REF!
C91: Other Investments and Marketable Securities | E91: =SUM(F91:H91) -> #REF! | F91: =TB!G76 -> 0 | G91: =[1]Sheet1!K75 -> #REF! | H91: =[1]Sheet1!M75 -> #REF!
B92: SINKING FUND | E92: =+E93 -> #REF! | F92: =+F93 -> 0 | G92: =+G93 -> #REF! | H92: =+H93 -> #REF!
C93: Sinking Fund | E93: =SUM(F93:H93) -> #REF! | F93: =TB!G77 -> 0 | G93: =[1]Sheet1!K76 -> #REF! | H93: =[1]Sheet1!M76 -> #REF!
D94: Total Investments | E94: =+E92+E87 -> #REF! | F94: =+F92+F87 -> 0 | G94: =+G92+G87 -> #REF! | H94: =+H92+H87 -> #REF!
A95: PROPERTY, PLANT AND EQUIPMENT
B96: LAND AND LAND IMPROVEMENTS | E96: =+E97+E98+E101+E104+E107 -> #REF! | F96: =+F97+F98+F101+F104+F107 -> 0 | G96: =+G97+G98+G101+G104+G107 -> #REF! | H96: =+H97+H98+H101+H104+H107 -> #REF!
C97: Land | E97: =SUM(F97:H97) -> #REF! | F97: =TB!G78 -> 0 | G97: =[1]Sheet1!K77 -> #REF! | H97: =[1]Sheet1!M77 -> #REF!
C98: Land Improvements (net) | E98: =SUM(F98:H98) -> #REF! | F98: =+F99-F100 -> 0 | G98: =+G99-G100 -> #REF! | H98: =+H99-H100 -> #REF!
D99: Land Improvements | E99: =SUM(F99:H99) -> #REF! | F99: =TB!G79 -> 0 | G99: =[1]Sheet1!K78 -> #REF! | H99: =[1]Sheet1!M78 -> #REF!
D100: Accumulated Depreciation – Land Improvements | E100: =SUM(F100:H100) -> #REF! | F100: =TB!J80 -> 0 | G100: =[1]Sheet1!L79 -> #REF! | H100: =[1]Sheet1!N79 -> #REF!
C101: Runways/Taxiways (net) | E101: =SUM(F101:H101) -> #REF! | F101: =+F102-F103 -> 0 | G101: =+G102-G103 -> #REF! | H101: =+H102-H103 -> #REF!
D102: Runways/Taxiways | E102: =SUM(F102:H102) -> #REF! | F102: =TB!G81 -> 0 | G102: =[1]Sheet1!K80 -> #REF! | H102: =[1]Sheet1!M80 -> #REF!
D103: Accumulated Depreciation - Runways/Taxiways | E103: =SUM(F103:H103) -> #REF! | F103: =TB!J82 -> 0 | G103: =[1]Sheet1!L81 -> #REF! | H103: =[1]Sheet1!N81 -> #REF!
...

Sheet Comparative BS
A1: Republic of the Philippines
A2: PROVINCE OF AGUSAN DEL SUR
A3: Gov. Democrito O. Plaza Government Center, Prosperidad
A5: BALANCE SHEET
A6: TRUST FUND
A7: =+TB!A7 -> As of January 31, 2011
A8: (With Comparative Figures for CY 2009)
F10: 2010 | G10: 2009
A11: ASSETS
A12: CURRENT ASSETS
B13: CASH | E13: =+E14+E19+E24 -> #REF! | F13: =+F14+F19+F24 -> 14332535 | G13: =+G14+G19+G24 -> 1.065559e+08 | H13: =+H14+H19+H24 -> #REF! | I13: =+G13-[2]BS!$F$11 -> 0
C14: Cash on Hand | E14: =SUM(E15:E18) -> #REF! | F14: =SUM(F15:F18) -> -0.8 | G14: =SUM(G15:G18) -> 11756.52 | H14: =SUM(H15:H18) -> #REF! | I14: =+G14-[2]BS!$F$12 -> 0
D15: Cash in Vault | E15: =SUM(F15:H15) -> #REF! | F15: =TB!G12 -> 0 | G15: =[2]TB!G12 -> 0 | H15: =[1]Sheet1!M13 -> #REF! | I15: =+G15-[2]BS!$F$11 -> -1.065559e+08
D16: Cash - Collecting Officers | E16: =SUM(F16:H16) -> 0 | F16: =TB!G13 -> 0 | G16: =[2]TB!G13 -> 0 | I16: =+G16-[2]BS!$F$11 -> -1.065559e+08
D17: Cash - Disbursing Officers | E17: =SUM(F17:H17) -> #REF! | F17: =TB!G14 -> 0 | G17: =[2]TB!G14 -> 0 | H17: =[1]Sheet1!M15 -> #REF! | I17: =+G17-[2]BS!$F$11 -> -1.065559e+08
D18: Payroll Fund | E18: =SUM(F18:H18) -> #REF! | F18: =TB!G16 -> -0.8 | G18: =[2]TB!G16 -> 11756.52 | H18: =[1]Sheet1!M16 -> #REF! | I18: =+G18-[2]BS!$F$16 -> 0
C19: Cash in Bank - Local Currency | E19: =SUM(E20:E23) -> #REF! | F19: =SUM(F20:F23) -> 14332535 | G19: =SUM(G20:G23) -> 1.0654414e+08 | H19: =SUM(H20:H23) -> #REF! | I19: =+G19-[2]BS!$F$17 -> 0
D20: Cash - Bangko Sentral ng Pilipinas | E20: =SUM(F20:H20) -> #REF! | F20: =TB!G17 -> 0 | G20: =[2]TB!G17 -> 0 | H20: =[1]Sheet1!M17 -> #REF! | I20: =+G20-[2]BS!$F$11 -> -1.065559e+08
D21: Cash in Bank - Local Currency, Current Account | E21: =SUM(F21:H21) -> #REF! | F21: =TB!G18 -> 14332535 | G21: =[2]TB!G18 -> 1.0220902e+08 | H21: =[1]Sheet1!M18 -> #REF! | I21: =+G21-[2]BS!$F$19 -> 0
D22: Cash in Bank - Local Currency, Savings Account | E22: =SUM(F22:H22) -> #REF! | F22: =TB!G19 -> 0 | G22: =[2]TB!G19 -> 4335118.1 | H22: =[1]Sheet1!M19 -> #REF! | I22: =+G22-[2]BS!$F$20 -> 0
D23: Cash in Bank - Local Currency, Time Deposits | E23: =SUM(F23:H23) -> #REF! | F23: =TB!G20 -> 0 | G23: =[2]TB!G20 -> 0 | H23: =[1]Sheet1!M20 -> #REF! | I23: =+G23-[2]BS!$F$11 -> -1.065559e+08
C24: Cash in Bank - Foreign Currency | E24: =SUM(E25:E28) -> #REF! | F24: =SUM(F25:F28) -> 0 | G24: =SUM(G25:G28) -> 0 | H24: =SUM(H25:H28) -> #REF! | I24: =+G24-[2]BS!$F$11 -> -1.065559e+08
D25: Cash - Bangko Sentral ng Pilipinas | E25: =SUM(F25:H25) -> #REF! | F25: =TB!G21 -> 0 | G25: =[2]TB!G21 -> 0 | H25: =[1]Sheet1!M21 -> #REF! | I25: =+G25-[2]BS!$F$11 -> -1.065559e+08
D26: Cash in Bank - Foreign Currency, Current Account | E26: =SUM(F26:H26) -> #REF! | F26: =TB!G22 -> 0 | G26: =[2]TB!G22 -> 0 | H26: =[1]Sheet1!M22 -> #REF! | I26: =+G26-[2]BS!$F$11 -> -1.065559e+08
D27: Cash in Bank - Foreign Currency, Savings Account | E27: =SUM(F27:H27) -> #REF! | F27: =TB!G23 -> 0 | G27: =[2]TB!G23 -> 0 | H27: =[1]Sheet1!M23 -> #REF! | I27: =+G27-[2]BS!$F$11 -> -1.065559e+08
D28: Cash in Bank - Foreign Currency, Time Deposits | E28: =SUM(F28:H28) -> #REF! | F28: =TB!G24 -> 0 | G28: =[2]TB!G24 -> 0 | H28: =[1]Sheet1!M24 -> #REF! | I28: =+G28-[2]BS!$F$11 -> -1.065559e+08
B29: RECEIVABLES | E29: =+E30+E41+E46+E48 -> #REF! | F29: =+F30+F41+F46+F48 -> -90015.4 | G29: =+G30+G41+G46+G48 -> 35446067 | H29: =+H30+H41+H46+H48 -> #REF! | I29: =+G29-[2]BS!$F$27 -> 0
C30: Receivable Accounts | E30: =SUM(E33:E40)+E31-E32 -> #REF! | F30: =SUM(F33:F40)+F31-F32 -> 189984.6 | G30: =SUM(G33:G40)+G31-G32 -> 31847669 | H30: =SUM(H33:H40)+H31-H32 -> #REF! | I30: =+G30-[2]BS!$F$28 -> 0
D31: Accounts Receivable | E31: =SUM(F31:H31) -> #REF! | F31: =TB!G25 -> 0 | G31: =[2]TB!G25 -> 0 | H31: =[1]Sheet1!M25 -> #REF! | I31: =+G31-[2]BS!$F$11 -> -1.065559e+08
D32: Allowance for Doubtful Accounts | E32: =SUM(F32:H32) -> #REF! | F32: =TB!G26 -> 0 | G32: =[2]TB!G26 -> 0 | H32: =[1]Sheet1!N26 -> #REF! | I32: =+G32-[2]BS!$F$11 -> -1.065559e+08
D33: Notes Receivable | E33: =SUM(F33:H33) -> #REF! | F33: =TB!G27 -> 0 | G33: =[2]TB!G27 -> 0 | H33: =[1]Sheet1!M27 -> #REF! | I33: =+G33-[2]BS!$F$11 -> -1.065559e+08
D34: Advances to Officers & Employees | E34: =SUM(F34:H34) -> #REF! | F34: =TB!G41 -> 189984.6 | G34: =[2]TB!G41 -> 31847669 | H34: =[1]Sheet1!M28 -> #REF! | I34: =+G34-[2]BS!$F$32 -> 0
D35: Loans Receivable - GOCCs | E35: =SUM(F35:H35) -> #REF! | F35: =TB!G29 -> 0 | G35: =[2]TB!G29 -> 0 | H35: =[1]Sheet1!M29 -> #REF! | I35: =+G35-[2]BS!$F$11 -> -1.065559e+08
D36: Loans Receivable - LGUs | E36: =SUM(F36:H36) -> #REF! | F36: =TB!G30 -> 0 | G36: =[2]TB!G30 -> 0 | H36: =[1]Sheet1!M30 -> #REF! | I36: =+G36-[2]BS!$F$11 -> -1.065559e+08
D37: Loans Receivable - Others | E37: =SUM(F37:H37) -> #REF! | F37: =TB!G31 -> 0 | G37: =[2]TB!G31 -> 0 | H37: =[1]Sheet1!M31 -> #REF! | I37: =+G37-[2]BS!$F$11 -> -1.065559e+08
D38: Real Property Tax Receivable | E38: =SUM(F38:H38) -> #REF! | F38: =TB!G32 -> 0 | G38: =[2]TB!G32 -> 0 | H38: =[1]Sheet1!M32 -> #REF! | I38: =+G38-[2]BS!$F$11 -> -1.065559e+08
D39: Special Education Tax Receivable | E39: =SUM(F39:H39) -> #REF! | F39: =TB!G33 -> 0 | G39: =[2]TB!G33 -> 0 | H39: =[1]Sheet1!M33 -> #REF! | I39: =+G39-[2]BS!$F$11 -> -1.065559e+08
D40: Interests Receivable | E40: =SUM(F40:H40) -> #REF! | F40: =TB!G34 -> 0 | G40: =[2]TB!G34 -> 0 | H40: =[1]Sheet1!M34 -> #REF! | I40: =+G40-[2]BS!$F$11 -> -1.065559e+08
C41: Inter-Agency Receivables | E41: =SUM(E42:E45) -> #REF! | F41: =SUM(F42:F45) -> -280000 | G41: =SUM(G42:G45) -> 3285964.4 | H41: =SUM(H42:H45) -> #REF! | I41: =+G41-[2]BS!$F$39 -> 0
D42: Due from NGAs | E42: =SUM(F42:H42) -> #REF! | F42: =TB!G35 -> 0 | G42: =[2]TB!G35 -> 0 | H42: =[1]Sheet1!M35 -> #REF! | I42: =+G42-[2]BS!$F$11 -> -1.065559e+08
D43: Due from GOCCs | E43: =SUM(F43:H43) -> #REF! | F43: =TB!G36 -> 0 | G43: =[2]TB!G36 -> 0 | H43: =[1]Sheet1!M36 -> #REF! | I43: =+G43-[2]BS!$F$11 -> -1.065559e+08
D44: Due from LGUs | E44: =SUM(F44:H44) -> #REF! | F44: =TB!G37 -> 0 | G44: =[2]TB!G37 -> 1183464.4 | H44: =[1]Sheet1!M37 -> #REF! | I44: =+G44-[2]BS!$F$42 -> 0
D45: Due from NGOs/POs | E45: =SUM(F45:H45) -> #REF! | F45: =TB!G38 -> -280000 | G45: =[2]TB!G38 -> 2102500 | H45: =[1]Sheet1!M38 -> #REF! | I45: =+G45-[2]BS!$F$43 -> 0
C46: Intra-Agency Receivables | E46: =+E47 -> #REF! | F46: =+F47 -> 0 | G46: =+G47 -> 0 | H46: =+H47 -> #REF! | I46: =+G46-[2]BS!$F$11 -> -1.065559e+08
D47: Due from Other Funds | E47: =SUM(F47:H47) -> #REF! | F47: =TB!G39 -> 0 | G47: =[2]TB!G39 -> 0 | H47: =[1]Sheet1!M39 -> #REF! | I47: =+G47-[2]BS!$F$11 -> -1.065559e+08
C48: Other Receivables | E48: =SUM(E49:E50) -> #REF! | F48: =SUM(F49:F50) -> 0 | G48: =SUM(G49:G50) -> 312433.89 | H48: =SUM(H49:H50) -> #REF! | I48: =+G48-[2]BS!$F$46 -> 0
D49: Receivables - Disallowances/Charges | E49: =SUM(F49:H49) -> #REF! | F49: =TB!G40 -> 0 | G49: =[2]TB!G40 -> 0 | H49: =[1]Sheet1!M40 -> #REF! | I49: =+G49-[2]BS!$F$11 -> -1.065559e+08
D50: Other Receivables | E50: =SUM(F50:H50) -> #REF! | F50: =TB!G42 -> 0 | G50: =[2]TB!G42 -> 312433.89 | H50: =[1]Sheet1!M41 -> #REF! | I50: =+G50-[2]BS!$F$48 -> 0
B51: INVENTORIES | E51: =+E52+E57+E72 -> #REF! | F51: =+F52+F57+F72 -> 2317392 | G51: =+G52+G57+G72 -> 0 | H51: =+H52+H57+H72 -> #REF! | I51: =+G51-[2]BS!$F$11 -> -1.065559e+08
C52: Materials | E52: =SUM(E53:E56) -> #REF! | F52: =SUM(F53:F56) -> 0 | G52: =SUM(G53:G56) -> 0 | H52: =SUM(H53:H56) -> #REF! | I52: =+G52-[2]BS!$F$11 -> -1.065559e+08
D53: Raw Materials Inventory | E53: =SUM(F53:H53) -> #REF! | F53: =TB!G43 -> 0 | G53: =[2]TB!G43 -> 0 | H53: =[1]Sheet1!M42 -> #REF! | I53: =+G53-[2]BS!$F$11 -> -1.065559e+08
D54: Work-In-Process Inventory | E54: =SUM(F54:H54) -> #REF! | F54: =TB!G44 -> 0 | G54: =[2]TB!G44 -> 0 | H54: =[1]Sheet1!M43 -> #REF! | I54: =+G54-[2]BS!$F$11 -> -1.065559e+08
D55: Finished Goods Inventory | E55: =SUM(F55:H55) -> #REF! | F55: =TB!G45 -> 0 | G55: =[2]TB!G45 -> 0 | H55: =[1]Sheet1!M44 -> #REF! | I55: =+G55-[2]BS!$F$11 -> -1.065559e+08
D56: Merchandise Inventory | E56: =SUM(F56:H56) -> #REF! | F56: =TB!G46 -> 0 | G56: =[2]TB!G46 -> 0 | H56: =[1]Sheet1!M45 -> #REF! | I56: =+G56-[2]BS!$F$11 -> -1.065559e+08
C57: Supplies | E57: =SUM(E58:E71) -> #REF! | F57: =SUM(F58:F71) -> 2317392 | G57: =SUM(G58:G71) -> 0 | H57: =SUM(H58:H71) -> #REF! | I57: =+G57-[2]BS!$F$11 -> -1.065559e+08
D58: Office Supplies Inventory | E58: =SUM(F58:H58) -> #REF! | F58: =TB!G47 -> 0 | G58: =[2]TB!G47 -> 0 | H58: =[1]Sheet1!M46 -> #REF! | I58: =+G58-[2]BS!$F$11 -> -1.065559e+08
D59: Accountable Forms Inventory | E59: =SUM(F59:H59) -> #REF! | F59: =TB!G48 -> 0 | G59: =[2]TB!G48 -> 0 | H59: =[1]Sheet1!M47 -> #REF! | I59: =+G59-[2]BS!$F$11 -> -1.065559e+08
D60: Animal/Zoological Supplies Inventory | E60: =SUM(F60:H60) -> #REF! | F60: =TB!G49 -> 0 | G60: =[2]TB!G49 -> 0 | H60: =[1]Sheet1!M48 -> #REF! | I60: =+G60-[2]BS!$F$11 -> -1.065559e+08
D61: Food Supplies Inventory | E61: =SUM(F61:H61) -> #REF! | F61: =TB!G50 -> 0 | G61: =[2]TB!G50 -> 0 | H61: =[1]Sheet1!M49 -> #REF! | I61: =+G61-[2]BS!$F$11 -> -1.065559e+08
D62: Drugs and Medicines Inventory | E62: =SUM(F62:H62) -> #REF! | F62: =TB!G51 -> 518992 | G62: =[2]TB!G51 -> 0 | H62: =[1]Sheet1!M50 -> #REF! | I62: =+G62-[2]BS!$F$11 -> -1.065559e+08
D63: Medical, Dental and Laboratory Supplies Inventory | E63: =SUM(F63:H63) -> #REF! | F63: =TB!G52 -> 0 | G63: =[2]TB!G52 -> 0 | H63: =[1]Sheet1!M51 -> #REF! | I63: =+G63-[2]BS!$F$11 -> -1.065559e+08
D64: Gasoline, Oil and Lubricants Inventory | E64: =SUM(F64:H64) -> #REF! | F64: =TB!G53 -> 1798400 | G64: =[2]TB!G53 -> 0 | H64: =[1]Sheet1!M52 -> #REF! | I64: =+G64-[2]BS!$F$11 -> -1.065559e+08
D65: Agricultural Supplies Inventory | E65: =SUM(F65:H65) -> #REF! | F65: =TB!G54 -> 0 | G65: =[2]TB!G54 -> 0 | H65: =[1]Sheet1!M53 -> #REF! | I65: =+G65-[2]BS!$F$11 -> -1.065559e+08
D66: Textbooks and Instructional Materials Inventory | E66: =SUM(F66:H66) -> #REF! | F66: =TB!G55 -> 0 | G66: =[2]TB!G55 -> 0 | H66: =[1]Sheet1!M54 -> #REF! | I66: =+G66-[2]BS!$F$11 -> -1.065559e+08
D67: Military and Police Supplies Inventory | E67: =SUM(F67:H67) -> #REF! | F67: =TB!G56 -> 0 | G67: =[2]TB!G56 -> 0 | H67: =[1]Sheet1!M55 -> #REF! | I67: =+G67-[2]BS!$F$11 -> -1.065559e+08
D68: Other Supplies Inventory | E68: =SUM(F68:H68) -> #REF! | F68: =TB!G57 -> 0 | G68: =[2]TB!G57 -> 0 | H68: =[1]Sheet1!M56 -> #REF! | I68: =+G68-[2]BS!$F$11 -> -1.065559e+08
D69: Confiscated/Abandoned/Seized Goods Inventory | E69: =SUM(F69:H69) -> #REF! | F69: =TB!G58 -> 0 | G69: =[2]TB!G58 -> 0 | H69: =[1]Sheet1!M57 -> #REF! | I69: =+G69-[2]BS!$F$11 -> -1.065559e+08
... D71: Construction Materials Inventory | E71: =SUM(F71:H71) -> #REF! | F71: =TB!G60 -> 0 | G71: =[2]TB!G60 -> 0 | H71: =[1]Sheet1!M59 -> #REF! | I71: =+G71-[2]BS!$F$11 -> -1.065559e+08
C72: Agricultural, Fishery and Forestry Products | E72: =SUM(E73:E75) -> #REF! | F72: =SUM(F73:F75) -> 0 | G72: =SUM(G73:G75) -> 0 | H72: =SUM(H73:H75) -> #REF! | I72: =+G72-[2]BS!$F$11 -> -1.065559e+08
D73: Livestock Inventory | E73: =SUM(F73:H73) -> #REF! | F73: =TB!G61 -> 0 | G73: =[2]TB!G61 -> 0 | H73: =[1]Sheet1!M60 -> #REF! | I73: =+G73-[2]BS!$F$11 -> -1.065559e+08
D74: Crops and Fruits Inventory | E74: =SUM(F74:H74) -> #REF! | F74: =TB!G62 -> 0 | G74: =[2]TB!G62 -> 0 | H74: =[1]Sheet1!M61 -> #REF! | I74: =+G74-[2]BS!$F$11 -> -1.065559e+08
D75: Other Agricultural, Fishery and Forestry Products Inventory | E75: =SUM(F75:H75) -> #REF! | F75: =TB!G63 -> 0 | G75: =[2]TB!G63 -> 0 | H75: =[1]Sheet1!M62 -> #REF! | I75: =+G75-[2]BS!$F$11 -> -1.065559e+08
B76: PREPAYMENTS | E76: =SUM(E77:E83) -> #REF! | F76: =SUM(F77:F83) -> 0 | G76: =SUM(G77:G83) -> 0 | H76: =SUM(H77:H83) -> #REF! | I76: =+G76-[2]BS!$F$11 -> -1.065559e+08
C77: Prepaid Rent | E77: =SUM(F77:H77) -> #REF! | F77: =TB!G64 -> 0 | G77: =[2]TB!G64 -> 0 | H77: =[1]Sheet1!M63 -> #REF! | I77: =+G77-[2]BS!$F$11 -> -1.065559e+08
C78: Prepaid Insurance | E78: =SUM(F78:H78) -> #REF! | F78: =TB!G65 -> 0 | G78: =[2]TB!G65 -> 0 | H78: =[1]Sheet1!M64 -> #REF! | I78: =+G78-[2]BS!$F$11 -> -1.065559e+08
C79: Prepaid Interest | E79: =SUM(F79:H79) -> #REF! | F79: =TB!G66 -> 0 | G79: =[2]TB!G66 -> 0 | H79: =[1]Sheet1!M65 -> #REF! | I79: =+G79-[2]BS!$F$11 -> -1.065559e+08
C80: Deposit on Letters of Credit | E80: =SUM(F80:H80) -> #REF! | F80: =TB!G67 -> 0 | G80: =[2]TB!G67 -> 0 | H80: =[1]Sheet1!M66 -> #REF! | I80: =+G80-[2]BS!$F$11 -> -1.065559e+08
C81: Advances to Contractors | E81: =SUM(F81:H81) -> #REF! | F81: =TB!G68 -> 0 | G81: =[2]TB!G68 -> 0 | H81: =[1]Sheet1!M67 -> #REF! | I81: =+G81-[2]BS!$F$11 -> -1.065559e+08
C82: Deferred Charges | E82: =SUM(F82:H82) -> #REF! | F82: =TB!G69 -> 0 | G82: =[2]TB!G69 -> 0 | H82: =[1]Sheet1!M68 -> #REF! | I82: =+G82-[2]BS!$F$11 -> -1.065559e+08
C83: Other Prepaid Expenses | E83: =SUM(F83:H83) -> #REF! | F83: =TB!G70 -> 0 | G83: =[2]TB!G70 -> 0 | H83: =[1]Sheet1!M69 -> #REF! | I83: =+G83-[2]BS!$F$11 -> -1.065559e+08
B84: OTHER CURRENT ASSETS | E84: =SUM(E85:E86) -> #REF! | F84: =SUM(F85:F86) -> 0 | G84: =SUM(G85:G86) -> 0 | H84: =SUM(H85:H86) -> #REF! | I84: =+G84-[2]BS!$F$11 -> -1.065559e+08
D85: Guaranty Deposits | E85: =SUM(F85:H85) -> #REF! | F85: =TB!G71 -> 0 | G85: =[2]TB!G71 -> 0 | H85: =[1]Sheet1!M70 -> #REF! | I85: =+G85-[2]BS!$F$11 -> -1.065559e+08
D86: Other Current Assets | E86: =SUM(F86:H86) -> #REF! | F86: =TB!G72 -> 0 | G86: =[2]TB!G72 -> 0 | H86: =[1]Sheet1!M71 -> #REF! | I86: =+G86-[2]BS!$F$11 -> -1.065559e+08
D87: Total Current Assets | E87: =+E84+E76+E51+E29+E13 -> #REF! | F87: =+F84+F76+F51+F29+F13 -> 16559911 | G87: =+G84+G76+G51+G29+G13 -> 1.4200196e+08 | H87: =+H84+H76+H51+H29+H13 -> #REF! | I87: =+G87-[2]BS!$F$85 -> 0
A88: INVESTMENTS | I88: =+G88-[2]BS!$F$11 -> -1.065559e+08
B89: INVESTMENT IN SECURITIES | E89: =SUM(E90:E93) -> #REF! | F89: =SUM(F90:F93) -> 0 | G89: =SUM(G90:G93) -> 0 | H89: =SUM(H90:H93) -> #REF! | I89: =+G89-[2]BS!$F$11 -> -1.065559e+08
C90: Investments in Treasury Bills | E90: =SUM(F90:H90) -> #REF! | F90: =TB!G73 -> 0 | G90: =[2]TB!G73 -> 0 | H90: =[1]Sheet1!M72 -> #REF! | I90: =+G90-[2]BS!$F$11 -> -1.065559e+08
C91: Investments in Stocks | E91: =SUM(F91:H91) -> #REF! | F91: =TB!G74 -> 0 | G91: =[2]TB!G74 -> 0 | H91: =[1]Sheet1!M73 -> #REF! | I91: =+G91-[2]BS!$F$11 -> -1.065559e+08
C92: Investments in Bonds | E92: =SUM(F92:H92) -> #REF! | F92: =TB!G75 -> 0 | G92: =[2]TB!G75 -> 0 | H92: =[1]Sheet1!M74 -> #REF! | I92: =+G92-[2]BS!$F$11 -> -1.065559e+08
C93: Other Investments and Marketable Securities | E93: =SUM(F93:H93) -> #REF! | F93: =TB!G76 -> 0 | G93: =[2]TB!G76 -> 0 | H93: =[1]Sheet1!M75 -> #REF! | I93: =+G93-[2]BS!$F$11 -> -1.065559e+08
B94: SINKING FUND | E94: =+E95 -> #REF! | F94: =+F95 -> 0 | G94: =+G95 -> 0 | H94: =+H95 -> #REF! | I94: =+G94-[2]BS!$F$11 -> -1.065559e+08
C95: Sinking Fund | E95: =SUM(F95:H95) -> #REF! | F95: =TB!G77 -> 0 | G95: =[2]TB!G77 -> 0 | H95: =[1]Sheet1!M76 -> #REF! | I95: =+G95-[2]BS!$F$11 -> -1.065559e+08
D96: Total Investments | E96: =+E94+E89 -> #REF! | F96: =+F94+F89 -> 0 | G96: =+G94+G89 -> 0 | H96: =+H94+H89 -> #REF! | I96: =+G96-[2]BS!$F$11 -> -1.065559e+08
A97: PROPERTY, PLANT AND EQUIPMENT | I97: =+G97-[2]BS!$F$11 -> -1.065559e+08
B98: LAND AND LAND IMPROVEMENTS | E98: =+E99+E100+E103+E106+E109 -> #REF! | F98: =+F99+F100+F103+F106+F109 -> 0 | G98: =+G99+G100+G103+G106+G109 -> 0 | H98: =+H99+H100+H103+H106+H109 -> #REF! | I98: =+G98-[2]BS!$F$11 -> -1.065559e+08
C99: Land | E99: =SUM(F99:H99) -> #REF! | F99: =TB!G78 -> 0 | G99: =[2]TB!G78 -> 0 | H99: =[1]Sheet1!M77 -> #REF! | I99: =+G99-[2]BS!$F$11 -> -1.065559e+08
C100: Land Improvements (net) | E100: =SUM(F100:H100) -> #REF! | F100: =+F101-F102 -> 0 | G100: =+G101-G102 -> 0 | H100: =+H101-H102 -> #REF! | I100: =+G100-[2]BS!$F$11 -> -1.065559e+08
D101: Land Improvements | E101: =SUM(F101:H101) -> #REF! | F101: =TB!G79 -> 0 | G101: =[2]TB!G79 -> 0 | H101: =[1]Sheet1!M78 -> #REF! | I101: =+G101-[2]BS!$F$11 -> -1.065559e+08
D102: Accumulated Depreciation – Land Improvements | E102: =SUM(F102:H102) -> #REF! | F102: =TB!J80 -> 0 | G102: =[2]TB!J80 -> 0 | H102: =[1]Sheet1!N79 -> #REF! | I102: =+G102-[2]BS!$F$11 -> -1.065559e+08
C103: Runways/Taxiways (net) | E103: =SUM(F103:H103) -> #REF! | F103: =+F104-F105 -> 0 | G103: =+G104-G105 -> 0 | H103: =+H104-H105 -> #REF! | I103: =+G103-[2]BS!$F$11 -> -1.065559e+08
...

Sheet SIE
A1: Republic of the Philippines
A2: PROVINCE OF AGUSAN DEL SUR
A3: Gov. Democrito O. Plaza Government Center, Prosperidad
A5: GENERAL FUND PROPER
A6: STATEMENT OF INCOME AND EXPENSES
A7: For the quarter ended June 30, 2009
A10: TAX REVENUE
B11: Local Taxes | G11: =SUM(G12:G27) -> #REF! | H11: =SUM(H12:H27) -> 0 | I11: =SUM(I12:I27) -> #REF! | J11: =SUM(J12:J27) -> #REF!
C12: Professional Tax | G12: =SUM(H12:J12) -> #REF! | H12: =TB!J204 -> 0 | I12: =[1]Sheet1!L204 -> #REF! | J12: =[1]Sheet1!N204 -> #REF!
C13: Amusement Tax | G13: =SUM(H13:J13) -> 0 | H13: =TB!J205 -> 0
C14: Business Tax | G14: =SUM(H14:J14) -> #REF! | H14: =TB!J206 -> 0 | I14: =[1]Sheet1!L205 -> #REF! | J14: =[1]Sheet1!N205 -> #REF!
C15: Community Tax | G15: =SUM(H15:J15) -> #REF! | H15: =TB!J207 -> 0 | I15: =[1]Sheet1!L206 -> #REF! | J15: =[1]Sheet1!N206 -> #REF!
C16: Franchise Tax | G16: =SUM(H16:J16) -> #REF! | H16: =TB!J208 -> 0 | I16: =[1]Sheet1!L207 -> #REF! | J16: =[1]Sheet1!N207 -> #REF!
C17: Occupation Tax ** | G17: =SUM(H17:J17) -> #REF! | H17: =TB!J209 -> 0 | I17: =[1]Sheet1!L208 -> #REF! | J17: =[1]Sheet1!N208 -> #REF!
C18: Printing and Publication Tax | G18: =SUM(H18:J18) -> #REF! | H18: =TB!J210 -> 0 | I18: =[1]Sheet1!L209 -> #REF! | J18: =[1]Sheet1!N209 -> #REF!
C19: Property Transfer Tax | G19: =SUM(H19:J19) -> #REF! | H19: =TB!J211 -> 0 | I19: =[1]Sheet1!L210 -> #REF! | J19: =[1]Sheet1!N210 -> #REF!
C20: Real Property Tax | G20: =SUM(H20:J20) -> #REF! | H20: =TB!J212 -> 0 | I20: =[1]Sheet1!L211 -> #REF! | J20: =[1]Sheet1!N211 -> #REF!
C21: Real Property Tax on Idle Lands | G21: =SUM(H21:J21) -> #REF! | H21: =TB!J213 -> 0 | I21: =[1]Sheet1!L212 -> #REF! | J21: =[1]Sheet1!N212 -> #REF!
C22: Special Assessment Tax | G22: =SUM(H22:J22) -> #REF! | H22: =TB!J214 -> 0 | I22: =[1]Sheet1!L213 -> #REF! | J22: =[1]Sheet1!N213 -> #REF!
C23: Special Education Tax | G23: =SUM(H23:J23) -> #REF! | H23: =TB!J215 -> 0 | I23: =[1]Sheet1!L214 -> #REF! | J23: =[1]Sheet1!N214 -> #REF!
C24: Tax on Delivery Trucks and Vans | G24: =SUM(H24:J24) -> #REF! | H24: =TB!J216 -> 0 | I24: =[1]Sheet1!L215 -> #REF! | J24: =[1]Sheet1!N215 -> #REF!
C25: Tax on Sand, Gravel and Other Quarry Products | G25: =SUM(H25:J25) -> #REF! | H25: =TB!J217 -> 0 | I25: =[1]Sheet1!L216 -> #REF! | J25: =[1]Sheet1!N216 -> #REF!
... C27: Fines and Penalties - Local Taxes | G27: =SUM(H27:J27) -> #REF! | H27: =TB!J219 -> 0 | I27: =[1]Sheet1!L218 -> #REF! | J27: =[1]Sheet1!N218 -> #REF!
A28: GENERAL INCOME ACCOUNTS | G28: =+G29+G38+G55+G76 -> #REF! | H28: =+H29+H38+H55+H76 -> 0 | I28: =+I29+I38+I55+I76 -> #REF! | J28: =+J29+J38+J55+J76 -> #REF!
B29: Permits and Licenses | G29: =SUM(G30:G37) -> #REF! | H29: =SUM(H30:H37) -> 0 | I29: =SUM(I30:I37) -> #REF! | J29: =SUM(J30:J37) -> #REF!
C30: Fees on Weights and Measures | G30: =SUM(H30:J30) -> #REF! | H30: =TB!J220 -> 0 | I30: =[1]Sheet1!L219 -> #REF! | J30: =[1]Sheet1!N219 -> #REF!
C31: Fishery Rental Fees | G31: =SUM(H31:J31) -> #REF! | H31: =TB!J221 -> 0 | I31: =[1]Sheet1!L220 -> #REF! | J31: =[1]Sheet1!N220 -> #REF!
C32: Franchising and Licensing Fees | G32: =SUM(H32:J32) -> #REF! | H32: =TB!J222 -> 0 | I32: =[1]Sheet1!L221 -> #REF! | J32: =[1]Sheet1!N221 -> #REF!
C33: Motor Vehicles Users Charge | G33: =SUM(H33:J33) -> #REF! | H33: =TB!J223 -> 0 | I33: =[1]Sheet1!L222 -> #REF! | J33: =[1]Sheet1!N222 -> #REF!
C34: Permit Fees | G34: =SUM(H34:J34) -> #REF! | H34: =TB!J224 -> 0 | I34: =[1]Sheet1!L223 -> #REF! | J34: =[1]Sheet1!N223 -> #REF!
C35: Registration Fees | G35: =SUM(H35:J35) -> #REF! | H35: =TB!J225 -> 0 | I35: =[1]Sheet1!L224 -> #REF! | J35: =[1]Sheet1!N224 -> #REF!
C36: Other Permits and Licenses | G36: =SUM(H36:J36) -> #REF! | H36: =TB!J226 -> 0 | I36: =[1]Sheet1!L225 -> #REF! | J36: =[1]Sheet1!N225 -> #REF!
C37: Fines and Penalties - Permits and Licenses | G37: =SUM(H37:J37) -> #REF! | H37: =TB!J227 -> 0 | I37: =[1]Sheet1!L226 -> #REF! | J37: =[1]Sheet1!N226 -> #REF!
B38: Service Income | G38: =SUM(G39:G54) -> #REF! | H38: =SUM(H39:H54) -> 0 | I38: =SUM(I39:I54) -> #REF! | J38: =SUM(J39:J54) -> #REF!
C39: Affiliation Fees | G39: =SUM(H39:J39) -> #REF! | H39: =TB!J228 -> 0 | I39: =[1]Sheet1!L227 -> #REF! | J39: =[1]Sheet1!N227 -> #REF!
C40: Athletic and Cultural Fees | G40: =SUM(H40:J40) -> #REF! | H40: =TB!J229 -> 0 | I40: =[1]Sheet1!L228 -> #REF! | J40: =[1]Sheet1!N228 -> #REF!
C41: Clearance and Certification Fees | G41: =SUM(H41:J41) -> #REF! | H41: =TB!J230 -> 0 | I41: =[1]Sheet1!L229 -> #REF! | J41: =[1]Sheet1!N229 -> #REF!
C42: Comprehensive Examination Fees | G42: =SUM(H42:J42) -> #REF! | H42: =TB!J231 -> 0 | I42: =[1]Sheet1!L230 -> #REF! | J42: =[1]Sheet1!N230 -> #REF!
C43: Diploma and Graduation Fees | G43: =SUM(H43:J43) -> #REF! | H43: =TB!J232 -> 0 | I43: =[1]Sheet1!L231 -> #REF! | J43: =[1]Sheet1!N231 -> #REF!
C44: Garbage Fees | G44: =SUM(H44:J44) -> #REF! | H44: =TB!J233 -> 0 | I44: =[1]Sheet1!L232 -> #REF! | J44: =[1]Sheet1!N232 -> #REF!
C45: Inspection Fees | G45: =SUM(H45:J45) -> #REF! | H45: =TB!J234 -> 0 | I45: =[1]Sheet1!L233 -> #REF! | J45: =[1]Sheet1!N233 -> #REF!
C46: Library Fees | G46: =SUM(H46:J46) -> #REF! | H46: =TB!J235 -> 0 | I46: =[1]Sheet1!L234 -> #REF! | J46: =[1]Sheet1!N234 -> #REF!
C47: Medical, Dental and Laboratory Fees | G47: =SUM(H47:J47) -> #REF! | H47: =TB!J236 -> 0 | I47: =[1]Sheet1!L235 -> #REF! | J47: =[1]Sheet1!N235 -> #REF!
C48: Passport and Visa Fees | G48: =SUM(H48:J48) -> #REF! | H48: =TB!J237 -> 0 | I48: =[1]Sheet1!L236 -> #REF! | J48: =[1]Sheet1!N236 -> #REF!
C49: Processing Fees | G49: =SUM(H49:J49) -> #REF! | H49: =TB!J238 -> 0 | I49: =[1]Sheet1!L237 -> #REF! | J49: =[1]Sheet1!N237 -> #REF!
C50: Seminar Fees | G50: =SUM(H50:J50) -> #REF! | H50: =TB!J239 -> 0 | I50: =[1]Sheet1!L238 -> #REF! | J50: =[1]Sheet1!N238 -> #REF!
... C53: Other Service Income | G53: =SUM(H53:J53) -> #REF! | H53: =TB!J242 -> 0 | I53: =[1]Sheet1!L241 -> #REF! | J53: =[1]Sheet1!N241 -> #REF!
C54: Fines and Penalties - Service Income | G54: =SUM(H54:J54) -> #REF! | H54: =TB!J244 -> 0 | I54: =[1]Sheet1!L242 -> #REF! | J54: =[1]Sheet1!N242 -> #REF!
B55: Business Income | G55: =SUM(G56:G72)+G75 -> #REF! | H55: =SUM(H56:H72)+H75 -> 0 | I55: =SUM(I56:I72)+I75 -> #REF! | J55: =SUM(J56:J72)+J75 -> #REF!
C56: Hospital Fees | G56: =SUM(H56:J56) -> #REF! | H56: =TB!J245 -> 0 | I56: =[1]Sheet1!L243 -> #REF! | J56: =[1]Sheet1!N243 -> #REF!
C57: Income from Canteen Operations | G57: =SUM(H57:J57) -> #REF! | H57: =TB!J246 -> 0 | I57: =[1]Sheet1!L244 -> #REF! | J57: =[1]Sheet1!N244 -> #REF!
C58: Income from Cemetery Operations | G58: =SUM(H58:J58) -> #REF! | H58: =TB!J247 -> 0 | I58: =[1]Sheet1!L245 -> #REF! | J58: =[1]Sheet1!N245 -> #REF!
C59: Income from Communication Facilities | G59: =SUM(H59:J59) -> #REF! | H59: =TB!J248 -> 0 | I59: =[1]Sheet1!L246 -> #REF! | J59: =[1]Sheet1!N246 -> #REF!
C60: Income from Dormitory Operations | G60: =SUM(H60:J60) -> #REF! | H60: =TB!J249 -> 0 | I60: =[1]Sheet1!L247 -> #REF! | J60: =[1]Sheet1!N247 -> #REF!
C61: Income from Markets | G61: =SUM(H61:J61) -> #REF! | H61: =TB!J250 -> 0 | I61: =[1]Sheet1!L248 -> #REF! | J61: =[1]Sheet1!N248 -> #REF!
C62: Income from Slaughterhouses | G62: =SUM(H62:J62) -> #REF! | H62: =TB!J251 -> 0 | I62: =[1]Sheet1!L249 -> #REF! | J62: =[1]Sheet1!N249 -> #REF!
C63: Income from Transportation Systems | G63: =SUM(H63:J63) -> #REF! | H63: =TB!J252 -> 0 | I63: =[1]Sheet1!L250 -> #REF! | J63: =[1]Sheet1!N250 -> #REF!
C64: Income from Waterworks Systems | G64: =SUM(H64:J64) -> #REF! | H64: =TB!J253 -> 0 | I64: =[1]Sheet1!L251 -> #REF! | J64: =[1]Sheet1!N251 -> #REF!
C65: Landing and Parking Fees | G65: =SUM(H65:J65) -> #REF! | H65: =TB!J254 -> 0 | I65: =[1]Sheet1!L252 -> #REF! | J65: =[1]Sheet1!N252 -> #REF!
C66: Printing and Publication Income | G66: =SUM(H66:J66) -> #REF! | H66: =TB!J255 -> 0 | I66: =[1]Sheet1!L253 -> #REF! | J66: =[1]Sheet1!N253 -> #REF!
C67: Rent Income | G67: =SUM(H67:J67) -> #REF! | H67: =TB!J256 -> 0 | I67: =[1]Sheet1!L254 -> #REF! | J67: =[1]Sheet1!N254 -> #REF!
C68: Sales Revenue | H68: =TB!J257 -> 0
C69: Tuition Fees | G69: =SUM(H69:J69) -> #REF! | H69: =TB!J258 -> 0 | I69: =[1]Sheet1!L256 -> #REF! | J69: =[1]Sheet1!N256 -> #REF!
C70: Subsidy from National Government Agencies | H70: =TB!J261 -> 0
C71: Other Business Income | G71: =SUM(H71:J71) -> #REF! | H71: =TB!J259 -> 0 | I71: =[1]Sheet1!L257 -> #REF! | J71: =[1]Sheet1!N257 -> #REF!
C72: Fines and Penalties - Business Income | G72: =SUM(H72:J72) -> #REF! | H72: =TB!J260 -> 0 | I72: =[1]Sheet1!L258 -> #REF! | J72: =[1]Sheet1!N258 -> #REF!
C73: Sales Revenue | G73: =SUM(H73:J73) -> #REF! | H73: =TB!J257 -> 0 | I73: =[1]Sheet1!L255 -> #REF! | J73: =[1]Sheet1!N255 -> #REF!
C74: Less: Cost of Goods Sold | G74: =SUM(H74:J74) -> #REF! | H74: =TB!J200 -> 0 | I74: =[1]Sheet1!L199 -> #REF! | J74: =[1]Sheet1!N199 -> #REF!
C75: Gross Profit | G75: =SUM(H75:J75) -> #REF! | H75: =+H73-H74 -> 0 | I75: =+I73-I74 -> #REF! | J75: =+J73-J74 -> #REF!
B76: Other Income | G76: =SUM(G77:G89) -> #REF! | H76: =SUM(H77:H89) -> 0 | I76: =SUM(I77:I89) -> #REF! | J76: =SUM(J77:J89) -> #REF!
C77: Dividend Income | G77: =SUM(H77:J77) -> #REF! | H77: =TB!J264 -> 0 | I77: =[1]Sheet1!L262 -> #REF! | J77: =[1]Sheet1!N262 -> #REF!
C78: Income from Grants and Donations | G78: =SUM(H78:J78) -> #REF! | H78: =TB!J265 -> 0 | I78: =[1]Sheet1!L263 -> #REF! | J78: =[1]Sheet1!N263 -> #REF!
C79: Insurance Income | G79: =SUM(H79:J79) -> #REF! | H79: =TB!J266 -> 0 | I79: =[1]Sheet1!L264 -> #REF! | J79: =[1]Sheet1!N264 -> #REF!
C80: Interest Income | G80: =SUM(H80:J80) -> #REF! | H80: =TB!J267 -> 0 | I80: =[1]Sheet1!L265 -> #REF! | J80: =[1]Sheet1!N265 -> #REF!
C81: Internal Revenue Allotment | G81: =SUM(H81:J81) -> #REF! | H81: =TB!J268 -> 0 | I81: =[1]Sheet1!L266 -> #REF! | J81: =[1]Sheet1!N266 -> #REF!
C82: Sale of Confiscated/Abandoned/Seized Goods and Properties | G82: =SUM(H82:J82) -> #REF! | H82: =TB!J269 -> 0 | I82: =[1]Sheet1!L267 -> #REF! | J82: =[1]Sheet1!N267 -> #REF!
C83: Share from Economic Zones | G83: =SUM(H83:J83) -> #REF! | H83: =TB!J270 -> 0 | I83: =[1]Sheet1!L268 -> #REF! | J83: =[1]Sheet1!N268 -> #REF!
C84: Share from Expanded Value Added Tax (EVAT) | G84: =SUM(H84:J84) -> #REF! | H84: =TB!J271 -> 0 | I84: =[1]Sheet1!L269 -> #REF! | J84: =[1]Sheet1!N269 -> #REF!
C85: Share from National Wealth | G85: =SUM(H85:J85) -> #REF! | H85: =TB!J272 -> 0 | I85: =[1]Sheet1!L270 -> #REF! | J85: =[1]Sheet1!N270 -> #REF!
C86: Share from PAGCOR/PCSO | G86: =SUM(H86:J86) -> #REF! | H86: =TB!J273 -> 0 | I86: =[1]Sheet1!L271 -> #REF! | J86: =[1]Sheet1!N271 -> #REF!
C87: Share from Tobacco Excise Tax | G87: =SUM(H87:J87) -> #REF! | H87: =TB!J274 -> 0 | I87: =[1]Sheet1!L272 -> #REF! | J87: =[1]Sheet1!N272 -> #REF!
C88: Miscellaneous Income | G88: =SUM(H88:J88) -> #REF! | H88: =TB!J275 -> 0 | I88: =[1]Sheet1!L273 -> #REF! | J88: =[1]Sheet1!N273 -> #REF!
C89: Other Fines and Penalties | G89: =SUM(H89:J89) -> #REF! | H89: =TB!J276 -> 0 | I89: =[1]Sheet1!L274 -> #REF! | J89: =[1]Sheet1!N274 -> #REF!
A90: TOTAL INCOME | G90: =+G28+G11 -> #REF! | H90: =+H28+H11 -> 0 | I90: =+I28+I11 -> #REF! | J90: =+J28+J11 -> #REF!
A91: EXPENSES
B92: PERSONAL SERVICES | G92: =+G93+G101+G117+G122 -> #REF! | H92: =+H93+H101+H117+H122 -> 0 | I92: =+I93+I101+I117+I122 -> #REF! | J92: =+J93+J101+J117+J122 -> #REF!
C93: Salaries and Wages | G93: =SUM(G94:G100) -> #REF! | H93: =SUM(H94:H100) -> 0 | I93: =SUM(I94:I100) -> #REF! | J93: =SUM(J94:J100) -> #REF!
D94: Salaries and Wages - Regular | G94: =SUM(H94:J94) -> #REF! | H94: =TB!G281 -> 0 | I94: =[1]Sheet1!K279 -> #REF! | J94: =[1]Sheet1!M279 -> #REF!
D95: Salaries and Wages - Military/Uniformed | G95: =SUM(H95:J95) -> #REF! | H95: =TB!G282 -> 0 | I95: =[1]Sheet1!K280 -> #REF! | J95: =[1]Sheet1!M280 -> #REF!
D96: Salaries and Wages - Part-time | G96: =SUM(H96:J96) -> #REF! | H96: =TB!G283 -> 0 | I96: =[1]Sheet1!K281 -> #REF! | J96: =[1]Sheet1!M281 -> #REF!
D97: Salaries and Wages - Substitute | G97: =SUM(H97:J97) -> #REF! | H97: =TB!G284 -> 0 | I97: =[1]Sheet1!K282 -> #REF! | J97: =[1]Sheet1!M282 -> #REF!
D98: Salaries and Wages - Casual | G98: =SUM(H98:J98) -> #REF! | H98: =TB!G285 -> 0 | I98: =[1]Sheet1!K283 -> #REF! | J98: =[1]Sheet1!M283 -> #REF!
D99: Salaries and Wages - Contractual | G99: =SUM(H99:J99) -> #REF! | H99: =TB!G286 -> 0 | I99: =[1]Sheet1!K284 -> #REF! | J99: =[1]Sheet1!M284 -> #REF!
D100: Salaries and Wages - Emergency | G100: =SUM(H100:J100) -> #REF! | H100: =TB!G287 -> 0 | I100: =[1]Sheet1!K285 -> #REF! | J100: =[1]Sheet1!M285 -> #REF!
C101: Other Compensation | G101: =SUM(G102:G116) -> #REF! | H101: =SUM(H102:H116) -> 0 | I101: =SUM(I102:I116) -> #REF! | J101: =SUM(J102:J116) -> #REF!
D102: Personnel Economic Relief Allowance ( PERA) | G102: =SUM(H102:J102) -> #REF! | H102: =TB!G288 -> 0 | I102: =[1]Sheet1!K286 -> #REF! | J102: =[1]Sheet1!M286 -> #REF!
D103: Additional Compensation ( ADCOM) | G103: =SUM(H103:J103) -> #REF! | H103: =TB!G289 -> 0 | I103: =[1]Sheet1!K287 -> #REF! | J103: =[1]Sheet1!M287 -> #REF!
D104: Representation Allowance (RA) | G104: =SUM(H104:J104) -> #REF! | H104: =TB!G290 -> 0 | I104: =[1]Sheet1!K288 -> #REF! | J104: =[1]Sheet1!M288 -> #REF!
D105: Transportation Allowance (TA) | G105: =SUM(H105:J105) -> #REF! | H105: =TB!G291 -> 0 | I105: =[1]Sheet1!K289 -> #REF! | J105: =[1]Sheet1!M289 -> #REF!
D106: Clothing/Uniform Allowance | G106: =SUM(H106:J106) -> #REF! | H106: =TB!G292 -> 0 | I106: =[1]Sheet1!K290 -> #REF! | J106: =[1]Sheet1!M290 -> #REF!
...

Sheet SGE
A1: Republic of the Philippines
A2: PROVINCE OF AGUSAN DEL SUR
A3: Gov. Democrito O. Plaza Government Center, Prosperidad
A5: GENERAL FUND PROPER
A6: STATEMENT OF GOVERNMENT EQUITY
A7: For the year ended 2009
A12: Government Equity, Beginning Balance | B12: =SUM(C12:E12) -> #REF! | D12: =D40 -> #REF! | E12: =E40 -> #REF!
A13: (per BS, as of December 31, 2007)
A14: Add Retained Operating Surplus: | B14: =SUM(B15:B16) -> #REF! | D14: =SUM(D15:D16) -> #REF! | E14: =SUM(E15:E16) -> #REF!
A15: Current Operations (Net Income/Loss per SIE) | B15: =SUM(C15:E15) -> #REF! | C15: =SIE!H321 -> 0 | D15: =[1]Sheet1!I320 -> #REF! | E15: =[1]Sheet1!J320 -> #REF!
A16: Prior Years’ Adjustments (Bal.per Pre-closing Trial Balance) | B16: =SUM(C16:E16) -> #REF! | C16: =-TB!G280 -> 0 | D16: =+D36 -> #REF! | E16: =+E36 -> #REF! | F16: =C15+C16 -> 0
A17: Less: Transfer of Public Infrastructure | B17: =SUM(C17:E17) -> #REF! | C17: =SUM([3]PRE!G183) -> 0 | D17: =SUM([1]Sheet1!J146:J155) -> #REF! | E17: =SUM([1]Sheet1!K146:K155) -> #REF!
A18: TOTAL | F18: =F12+F16 -> 0
A19: Add/Deduct: Transfer from( to)
A20: Transfer of PPE/Completed projects from Trust
A21: Fund/General Fund/Other Fund
A22: Transfer of PPE/Completed projects to General Fund/Other Fund
A23: Transfer of completed Projects to Registry:
A24: Public Infrastructure | C24: 0
A25: Reforestation Projects
A26: Transfer of PPE/completed projects from Other LGU
A27: Transfer of PPE/completed projects to Other LGUs
A28: Other Adjustments | F28: =SUM(C20:C24) -> 0
A29: Government Equity, Ending Balance
A30: (per BS as of December 31, 2008 ) | F30: =F18+F28 -> 0
A35: Computations:
A36: 1) Prior Years' Adjustments | B36: =+B38-B37 -> #REF! | C36: =+C38-C37 -> 14987551 | D36: =+D38-D37 -> #REF! | E36: =+E38-E37 -> #REF!
A37: Debit Balance | B37: =SUM(C37:E37) -> #REF! | C37: 0 | D37: =+[1]Sheet1!K278 -> #REF! | E37: =+[1]Sheet1!M278 -> #REF!
A38: Credit Balance | B38: =SUM(C38:E38) -> #REF! | C38: =[3]PRE!J203 -> 14987551 | D38: =+[1]Sheet1!L278 -> #REF! | E38: =+[1]Sheet1!N278 -> #REF!
A40: 2) Government Equity, Jan. 1 | B40: =+B42-B41 -> #REF! | C40: =+C42-C41 -> 2.5351169e+08 | D40: =+D42-D41 -> #REF! | E40: =+E42-E41 -> #REF!
A41: Debit Balance | B41: =SUM(C41:E41) -> #REF! | C41: =[4]tb!$J$198 -> 4.9353478e+08 | D41: =+[1]Sheet1!K198 -> #REF! | E41: =+[1]Sheet1!M198 -> #REF!
A42: Credit Balance | B42: =SUM(C42:E42) -> #REF! | C42: =[3]PRE!J194 -> 7.4704647e+08 | D42: =+[1]Sheet1!L198 -> #REF! | E42: =+[1]Sheet1!N198 -> #REF!
A45: Certified Correct:
A49: JOY D. LAGAT, CPA
A50: Accountant-IV
A51: Officer in charge

Sheet schedule
A1: Republic of the Philippines
A2: PROVINCE OF AGUSAN DEL SUR
A3: Gov. Democrito O. Plaza Government Center, Prosperidad
A5: TRUST FUND
A6: SCHEDULE
A7: =+TB!A7 -> As of January 31, 2011
A9: Schedule 1 - 106- Payroll Fund
C10: Corazon Canda | E10: =92515.04-92515.04 -> 0
C11: Evangeline Cabalan | E11: =19911.05-370154.28+357554.28-735562.83+735464.31+671055.63-670356.58+502907.22+0.4-502932.43+278954.03-278954.03+350636.97-350636.97+61826.69-61761.69+276593.53-276593.62+121469.22-121469.22-60869.63+60869.63+99114.14-99114.14+442158.01-442158.01+253268.81-253268.81+373409.17-373409.17+199934.06-199934.06+151582.91-151582.91+113162.43-113162.43 -> 7951.68
C12: Josefina Tado | E12: =3804.84-166413.19+156413.19+10000-247864.3+322435.3+416530.57-491101.57+117942.65-117942.65+153319.07-153319.07+108071.63-106071.63-2000 -> 3804.84
C13: Corazon Canda | E13: =216876.22-216896.22+197933.2-197933.2+466695.11-466695.11+637006.02-637006.02+396756.51-396756.51-978711.86+978712.66+522640.6-522520.6-464+1281293.05-1280629.05-0.8+527771.6-527771.6 -> 300
E14: =SUM(E10:E13) -> 12056.52 | F14: =+E14-TB!G16 -> 12057.32
A16: Schedule 2 - 111- CASH IN BANK-LCCA
C17: (1) LBP | D17: -UNICEF | E17: =209901.89+539600-566506.88-10000+18268+767093-246754.32+806.46-301097.08-229320.48+1025+3090-91733.08-10481.18+667600-205673.82+48-80000-25500+1723420-459126.25+663690-296475-148808.8+4958.8-565020-0.5-504386.22+5301.82+8400-397345.6-306591.5+150000+17035.72-35610-8200-67556.5+498400-5700-32200-35170.4+164-218603.04-119.6+5980-43769.96+852900 -> 1245932.5
C18: PNB | D18: -Proper | E18: 37145.34
C19: (3) PNB | D19: -PCSO Funds | E19: =10152.77+13119.82+20133.47+33458.78+5+45600+79455.31 -> 201925.15
C20: (4) LBP | D20: -UNDP | E20: 466.98
C21: (5) LBP | D21: -LDAP-RPT | E21: 1160.35
C22: (7) LBP | D22: -PREMIUMED RPTA MDP 3 | E22: =6792.07-5542.07 -> 1250
C23: (8) LBP | D23: -LPP | E23: =1579.09+30 -> 1609.09
C24: (9) LBP | D24: -LBP Trust Fund Proper | E24: =13100299.14-4122238.07+15415636.1-5412381.29+15862220+5615874.14-15171078.7-4092088.17+4672519.54-165+14808997.18-4485716.44+8850438.88-5675295.86+8907588.89-13749045.72+3134796.33-4622382.41+8404100.29-6720-5223788.81+4906262.2-5306885.4+9423901+800-6595818.57-30000+13037923.57-11361377.98-4958.8+4129799.43-4941365.85-4372.3-36800.09+2643606.66-10041120.25-5301.82+3933853.16-5907264.55+2134584.64-2650921.76+1603047.37-2000-4537984.21+3465788.98-5096720.47-1922+5579782.03-4339072+3712813.19-2693499.26+5770917.83+24228.34-3337331.18+1404510.83-13336+1658.51-3111842.9+1475989.49-1573791.15+3338649.54-5468466.22+3097009.23-4025968.85+14500000 -> 39308574
C25: (10) LBP | D25: -President's Social Fund | E25: =40917.91-7857-243-32500 -> 317.91 | G25: PSF- | H25: PR 20 pcs. Plywood 4x8 | I25: 8100
C26: (11) LBP | D26: -Rural Water Supply | E26: =42649.47-0.4-40500 -> 2149.07 | H26: Cash Adv., >S. Calonzo | I26: 82500
C27: (13) LBP | D27: -BWSA - DPWH | E27: =15647.51-4034.78 -> 11612.73
C28: (12) DBP | D28: -Rural Water Supply | E28: =3067.29 -> 3067.29 | H28: For transfer to TF PROPER | I28: 274885.98
C29: (17) DBP | D29: -Department of Energy | E29: =224470.19 -> 224470.19 | H29: 11/27/08 Adolph Edward Plaza - reimb of TEV | I29: 42693.75
C30: (18) LBP | D30: -Malaria Resource Center | E30: =41048.48+39430-18086.4+4500+3500-15360.41-298.88+13030+6500+3500-2440.2-49.8+1600+1100+1500-3743.6+1000-4510.9+750-90.5+1500+3750-1708+4500-7737.1+250-10187.02+2500-417.88+1750+6500+1000+7000+1950+150-5423.8 -> 78253.99 | H30: 11/27/2008 Joselito S. Aala - reimb of TEV | I30: 10495
C31: (21) DBP | D31: -Malaria Control Project | E31: =1322860.75-28443.5-15506.5-600+45785.41+10876.05+2673.94 -> 1337646.1 | H31: 11/27/2008 Christopher H. Lindo -C/A travel | I31: 49120
C32: (22) LBP | D32: -LGU Support to Malaria for Revolving Fund | E32: =261221.26-40992-34560-1440-24192-1008 -> 159029.26 | I32: 63700 | J32: 12/11/08 | K32: Gov. MA.V.G.PLAZA | M32: travel manila
C33: (23) LBP | D33: -Hospital Revolving Fund | E33: =4981332.63+0.6-1209340.04+766814.05-503404.01+691367.5+738878.15-107861.11-663534.38+717390.81+30643.8+957589.32-518902.43+15270+1607.13+678843.5-849490.65+778966.5-1365899.62+648626.21-886973.92+843319.8-686352.5+1133171.16-2765755.83+833608.49-823050+666554.09-90+0.1-580899.05+1056163.24-583291.34+4372.3+36800.09+654912.49-1195917.63+1575+598574.52-451426.85+647170.55-1423797.21-17035.72+991.07+489714.1-261193.28+812821.7-525356.06+877154.65-870495.89+739516.42-369379.99+818804.85-727862.23+551442.61-0.4-402076.29+728376.5-125195.71+796947.7-162053.98+585193.55-689576.3 -> 5118302.8 | I33: 32500 | J33: 4/07/09 | K33: Sherwin Calonzo - cash advance of 13 packs PVC Plastic
C34: (25) LBP | D34: -DOPMH Revolving Fund | E34: =4092402.61-29640-1405016.22+963423.25-907489.12+922711.86+1658941.6-10872.5-239792.37+1399956.31+1076013.86-1706740.69+1209922.36-1098580.69+1350094.88-2122363.94+1061442.43-2126461.68+1103125.81-45387.45+1540347.9-2054080.03+1248687-1793241.91+983986.49-530035.5+1902921.03-1244111.01+1101808.93-1080903.66+867896.65-931026.88+824262.55-1231533.85+3039.5+955997-335050.85+1073501.4-21323.01+1505553.31-1014419.66+998890.25-393118.05+1178892.38-2079140.08+1286959.27-757139.77+1041088.9-385221.79+1096232.76-1004399.17+1844511.32-2878387.18 -> 6867134.6 | H34: Total | I34: =SUM(I25:I33) -> 563994.73
C35: (26)DBP | D35: -Material Testing | E35: =18542.12-18542.12 -> 0 | F35: 11/12/2009 - close and transfer to GF | H35: Actual Cash Bal. | I35: =E25-I34 -> -563676.82 | J35: 08/08
C36: (28)LBP | D36: -DAR-IFAD-LP | E36: =1008210.21-4718.92-16759.11-58082.1-14605.6-18791.4-9798.66-14413.21-5751.98-4550.08-350+6020.76+4550.08+4550.08-57888 -> 817622.07 | F36: 67,000 IP Balance
C37: (29)LBP | D37: -DAR-IFAD-GOP | E37: =174996.78-112.56-20556+90000-7920-9360-25780-21994.7-6455.65-27029.73-350-6020.76-42374.24-31808.26+13.5-6572.45-6666.4-2613-28484.31-3067.84-795.06-24.59-1650 -> 15374.73
C38: (30)LBP | D38: -Mutual Fund | E38: =459272.31-94500+75321-126000+131049+73498-105000-110160+29767.33+14943-263910+331813-75710+66397-56000+70307-94500+66403-42000+16179-42000+65469+58547-29500-63072+134408-73500+16225-84000+71762-127760+56283-47776+80464-52500+86635-344615.52+188196-108361.48+45188+143496-146801.37+66016.5-10500-61338.66+73586-88000+101532-82000+298391 -> 491643.11
C39: (31)DBP | D39: -PSF-Governor's Guest House | E39: =1156.39 -> 1156.39
C40: (32)DBP | D40: -Blood Screening Fee | E40: =502987.89+29640-222559.07+27400-236.79+39100+240160-2822.12-14973+54600+25500-14977.6+46800-15109.48+52000-15000-17508.93+43100-310027.59+34200-1822.31+190000-326868.15+48400-1863+148750-162294.85+72300-14982.24+63815-15015+47500+57700-9577.87-16259.65-7320.52-991.07+49200-259204.56+260600-204351.83+150700-115745.52+106100-30020.5+38150+39600-567720.5+151500+75900-75000+63150 -> 236600.74
C41: (33)DBP | D41: -MINSSAD | E41: =14803798.86-6861128.87+2545656.29-3006751.37+952089.3+11744516.72-16783233.05-2645608.7+1526866.97-0.4+6693817.8-3556666.12-3063963.75+2241181.97-1768361.05+2844365.78-1215311.07+7870149.5-8799796.61+687849.5+10927288.48-12643272.72+982612.76-575816.71+913075.2-2487538.77+1669444.98+2582821.24-1895838.43+3763454.24-1203620.8+4929193-7003369.09-2854098.99+5206616.49-1180047.58+799410.84-3178116.73+5529592.23-2988096.08-996610.7+4664473.36-1708466.93-19.8+87762.67-3416072.07-897647.3+6619248.78-6571673.94-665528.87+2554699.56-1779097.16 -> 3394232.9
C42: (34)LBP | D42: -SELAP | E42: =3430887.47-282980.06-4533.14+8100000-130471.58-1400412.35-137047.22+2180000-926901.21-2671549.16-1895967.17-1402883.92-226273.73-115493.09+63072-1823297.85+18944.5-442609.37-337486.09+457596.09-1682454.46-60884.11-11850.28-2346.55+120-28134.38-183.91-22544.32-8747.68-5080-2360 -> 628128.43
C43: (35)DBP | D43: DOPMH AFFILIATION | E43: =266284+41700+21820-187500+13235-60+10270+1560+32120+340+19400+2760+18420+26520+23180+6100-55176.8+1020-33587.22+16400+35160-16846.43+7530-953.57+5760 -> 255454.98
C44: (36)LBP | D44: -ECCD | E44: =837399.71-5000+892843+14000-376998.5-7462.5-225+1500-64241+500-500+500+23480-2400+1000+5250+500+500+2000+90207.94 -> 1412853.6
C45: (37)DBP | D45: -DBP TF-Proper | E45: =5540000+9410000-686032.96+8400000-701062.47-6385113.84+1491087.56-1241876.3+50000000+1800000-50195961+3080000-666246.33+32000000-12277427.96+4370532.59+7955.37+33985.83-18576905.38+47537.87-2245279.28+42711359.55-7501383.7+520000-34385658.71-3374544.53+1019589.07-2564193.85+1040000-4095188.5+300.3+1455000+59478.98-1735131.15+18257817.17-5099101.78+1066358.56-13662335.15+4850000-5845392.63+1970000-2245023.17-179303.22 -> 15467841
C46: (38)LBP | D46: -MRDP LP | E46: =10000+3000000-3000000-1500+0.39 -> 8500.39
C47: (39)LBP | D47: -MRDP GOP | E47: =10000+3000000+4061.34-1500-1718084.96-126217.62-39257.08+4518.69 -> 1133520.4
C48: (40)LBP | D48: -Provl Road Maintenance Facility | E48: 5280000
C49: (41)DBP | D49: -DOPMH EC Revolving Fund | E49: =364572.2+121423.05+26310.6+58454+23668.75+344569.3-212492.15 -> 726505.75
E50: =SUM(E16:E49) -> 84469482 | F50: =+E50-TB!G18 -> 70136947
H51: =+F50/2 -> 35068473
A52: Schedule 3 - 112- CASH IN BANK-Savings Deposit
D53: PNB-KKK | E53: 335118.08
D54: PNB- | E54: 3000000
D55: LBP | E55: 1000000
D56: DBP | E56: =50000000-50000000+32000000-32000000 -> 0 | F56: Calamity Fund
C57: TOTAL | E57: =SUM(E53:E56) -> 4335118.1 | F57: =+E57-TB!G19 -> 4335118.1
A60: Schedule 4-138-DUE FROM LGU'S
C61: Bayugan | E61: 79500
C62: Bunawan | E62: 73224.85 | G62: .
C63: Esperanza | E63: 90965.68
C64: La Paz | E64: 57400
C65: Loreto | E65: 87900
C66: Prosperidad | E66: 90901.89
C67: Rosario | E67: 96000.01
C68: San Francisco | E68: 74009
C69: San Luis | E69: 86650
C70: Sibagat | E70: 100000
C71: Sta. Josefa | E71: 80528
C72: Talacogon | E72: 96270
C73: Trento | E73: 72115
C74: Veruela | E74: 98000
C75: TOTAL | E75: =SUM(E61:E74) -> 1183464.4 | F75: =+E75-TB!G37 -> 1183464.4
A78: Schedule 5- 139-DUE FROM NGO'S/PO'S
C80: ADSEMCO-MUTUAL FUND | E80: =80000+200000-200000-80000 -> 0
C81: ADSEMCO-MUTUAL FUND | E81: =200000-200000 -> 0
C82: AGUSAN PEOPLES HEALTH DEV'T. FOUNDATION-111(22) | E82: 500000
C83: AMELITA C. BAHIAN | E83: 200000
C84: ANNA LIZA AMAMA-ID | E84: 10000
C85: ANTITOQUIA DEVELOPMENT MPC/Rodrigo Sesdosyo | E85: 135000
C86: BEAWAN MPC(SELAP) VEG. PROGRAM-ESPERANZA, ADS | E86: 60000
C87: CROSABICON IRRIGATION ASSOCIATION/Fernando Meñoza | E87: 135000
C88: EDWARD WOOD FURNITURE/Ms. Lanie Chua | E88: =200000-34000-51000-60775-16000 -> 38225
C89: Irrigation Association - BALIK/Eugenio Alamillo | E89: 135000
C90: JOEMARK OSTOS | E90: 100000
C91: JOSEPHINE TUDTUD | E91: =50000-10000 -> 40000
C92: MARYJANE CATON | E92: =20000-4000 -> 16000
C93: MILDA C. GASATAN | E93: 100000
C94: NELMA DE GUZMAN, Enterprise Dev. Loan Assistance | E94: 50000
C95: NOREY'S CRIB & SWING PRODUCTS/NOEL JASO | E95: =100000-65000-5000-30000 -> 0
C96: NOVELYN D. ARCHE | E96: 10000
C97: RUTCHEL MORALES/ RJL CAKES & PASTRIES | E97: =50000-10000-9000-3000 -> 28000
C98: RUDY AGUILAR | E98: =30000-5600-11200-8200-2000-6600 -> -3600
C99: SAFRA-ADAP, SAN FRANCISCO | E99: =200000-150000 -> 50000
C100: SERGIO SANCHEZ | E100: 200000
C101: ROMANA BAGTILAY (OFW) | E101: 50000
C102: CHERRY VEE YTAC (OFW) | E102: 50000
C103: WILD TRENDS WOODCRAFT | E103: =50000-8500-8500-33000+100000-8500-20000-71500 -> 0
C104: TOTAL | E104: =SUM(E80:E103) -> 1903625 | F104: =+E104-TB!G38 -> 2183625
A107: Schedule 6 -148- ADVANCES TO OFFICERS AND EMPLOYEES
G108: PSF-
C109: Adolph Edward G. Plaza-PSF-Operational | E109: =6769960 -> 6769960 | G109: =E109 -> 6769960
C110: Amparo Prochina | E110: =30000+30000-29834.27-165.73 -> 30000 | G110: 285000
...
